Workbook

Sheet Inputs
A1: FASTENAL CO: model inputs
A2: $ in millions unless noted; rates as decimals
M3: FY2027E | N3: FY2028E | O3: FY2029E | P3: FY2030E
A4: Last reported quarter of FY2026 | C4: 1
A5: Shares outstanding, latest 10-Q/10-K cover (millions) | C5: 1148.0351
A7: Revenue growth, FY2026 quarters vs. same quarter of FY2025 | C7: 0.087
A8: Revenue growth by forecast year | M8: 0.087 | N8: 0.074 | O8: 0.061 | P8: 0.048
A9: Gross margin | C9: 0.4519
A10: SG&A, % of revenue | C10: 0.2479
A11: Other operating expenses, % of revenue | C11: 0
A12: Depreciation and amortization, % of revenue | C12: 0.0219
A13: Capital expenditures, % of revenue | C13: 0.0299
A14: Tax rate | C14: 0.24
A15: Days sales outstanding (on revenue) | C15: 55.4
A16: Days inventory outstanding (on cost of revenue) | C16: 141.5
A17: Days payables outstanding (on cost of revenue) | C17: 25.6
A18: Shareholder payouts and other financing, % of net income | C18: 0.84
A19: Interest expense, net, per year ($ in millions) | C19: 6.2
A20: Other non-operating income, per quarter ($ in millions) | C20: 0
... A26: Terminal growth rate | C26: 0.025

Sheet IS
A1: FASTENAL CO: income statement
A2: $ in millions
C3: Q1 FY2025 | D3: Q2 FY2025 | E3: Q3 FY2025 | F3: Q4 FY2025 | G3: FY2025 | H3: Q1 FY2026 | I3: Q2 FY2026 | J3: Q3 FY2026 | K3: Q4 FY2026 | L3: FY2026 | M3: FY2027E | N3: FY2028E | O3: FY2029E | P3: FY2030E
C4: A | D4: A | E4: A | F4: A | G4: A | H4: =IF(1<=Inputs!$C$4,"A","E") | I4: =IF(2<=Inputs!$C$4,"A","E") | J4: =IF(3<=Inputs!$C$4,"A","E") | K4: =IF(4<=Inputs!$C$4,"A","E") | M4: E | N4: E | O4: E | P4: E
A6: Revenue | C6: 1959.4 | D6: 2080.3 | E6: 2133.3 | F6: =G6-C6-D6-E6 | G6: 8200.5 | H6: 2201.7 | I6: =D6*(1+Inputs!$C$7) | J6: =E6*(1+Inputs!$C$7) | K6: =F6*(1+Inputs!$C$7) | L6: =SUM(H6:K6) | M6: =L6*(1+Inputs!M8) | N6: =M6*(1+Inputs!N8) | O6: =N6*(1+Inputs!O8) | P6: =O6*(1+Inputs!P8)
A7: Cost of revenue | C7: 1075.5 | D7: 1137.5 | E7: 1167.5 | F7: =G7-C7-D7-E7 | G7: 4509.3 | H7: 1218.8 | I7: =I6*(1-Inputs!$C$9) | J7: =J6*(1-Inputs!$C$9) | K7: =K6*(1-Inputs!$C$9) | L7: =SUM(H7:K7) | M7: =M6*(1-Inputs!$C$9) | N7: =N6*(1-Inputs!$C$9) | O7: =O6*(1-Inputs!$C$9) | P7: =P6*(1-Inputs!$C$9)
A8: Gross profit | C8: =C6-C7 | D8: =D6-D7 | E8: =E6-E7 | F8: =F6-F7 | G8: =G6-G7 | H8: =H6-H7 | I8: =I6-I7 | J8: =J6-J7 | ... P8: =P6-P7
A9: Selling, general and administrative | C9: 490 | D9: 506.7 | E9: 524.3 | F9: =G9-C9-D9-E9 | G9: 2035.5 | H9: 535.3 | I9: =I6*Inputs!$C$10 | J9: =J6*Inputs!$C$10 | K9: =K6*Inputs!$C$10 | L9: =SUM(H9:K9) | M9: =M6*Inputs!$C$10 | N9: =N6*Inputs!$C$10 | O9: =O6*Inputs!$C$10 | P9: =P6*Inputs!$C$10
A10: Other operating expenses, net | C10: =C8-C9-C11 | D10: =D8-D9-D11 | E10: =E8-E9-E11 | F10: =F8-F9-F11 | G10: =G8-G9-G11 | H10: =H8-H9-H11 | I10: =I6*Inputs!$C$11 | J10: =J6*Inputs!$C$11 | K10: =K6*Inputs!$C$11 | L10: =L8-L9-L11 | M10: =M6*Inputs!$C$11 | N10: =N6*Inputs!$C$11 | O10: =O6*Inputs!$C$11 | P10: =P6*Inputs!$C$11
A11: Operating income | C11: 393.9 | D11: 436.1 | E11: 441.5 | F11: =G11-C11-D11-E11 | G11: 1655.7 | H11: 447.6 | I11: =I8-I9-I10 | J11: =J8-J9-J10 | K11: =K8-K9-K10 | L11: =SUM(H11:K11) | M11: =M8-M9-M10 | N11: =N8-N9-N10 | O11: =O8-O9-O10 | P11: =P8-P9-P10
A12: Interest expense | C12: 1.7 | D12: 2.2 | E12: 1.6 | F12: =G12-C12-D12-E12 | G12: 6.2 | H12: 0.8 | I12: =Inputs!$C$19/4 | J12: =Inputs!$C$19/4 | K12: =Inputs!$C$19/4 | L12: =SUM(H12:K12) | M12: =Inputs!$C$19 | N12: =Inputs!$C$19 | O12: =Inputs!$C$19 | P12: =Inputs!$C$19
A13: Other non-operating income (expense), net | C13: =C14-C11+C12 | D13: =D14-D11+D12 | E13: =E14-E11+E12 | F13: =F14-F11+F12 | G13: =G14-G11+G12 | H13: =H14-H11+H12 | I13: =Inputs!$C$20 | J13: =Inputs!$C$20 | K13: =Inputs!$C$20 | L13: =L14-L11+L12 | M13: =Inputs!$C$20*4 | N13: =Inputs!$C$20*4 | O13: =Inputs!$C$20*4 | P13: =Inputs!$C$20*4
A14: Income before income taxes | C14: 393.1 | D14: 436.6 | E14: 440.6 | F14: =G14-C14-D14-E14 | G14: 1655 | H14: 448.3 | I14: =I11-I12+I13 | J14: =J11-J12+J13 | K14: =K11-K12+K13 | L14: =SUM(H14:K14) | M14: =M11-M12+M13 | N14: =N11-N12+N13 | O14: =O11-O12+O13 | P14: =P11-P12+P13
A15: Income tax expense | C15: 94.4 | D15: 106.3 | E15: 105.1 | F15: =G15-C15-D15-E15 | G15: 396.6 | H15: 108.6 | I15: =I14*Inputs!$C$14 | J15: =J14*Inputs!$C$14 | K15: =K14*Inputs!$C$14 | L15: =SUM(H15:K15) | M15: =M14*Inputs!$C$14 | N15: =N14*Inputs!$C$14 | O15: =O14*Inputs!$C$14 | P15: =P14*Inputs!$C$14
A16: Other items after tax, incl. non-controlling interests | C16: =C17-(C14-C15) | D16: =D17-(D14-D15) | E16: =E17-(E14-E15) | F16: =F17-(F14-F15) | G16: =G17-(G14-G15) | H16: =H17-(H14-H15) | I16: =Inputs!$C$21 | J16: =Inputs!$C$21 | K16: =Inputs!$C$21 | L16: =L17-(L14-L15) | M16: =Inputs!$C$21*4 | N16: =Inputs!$C$21*4 | O16: =Inputs!$C$21*4 | P16: =Inputs!$C$21*4
A17: Net income attributable to the company | C17: 298.7 | D17: 330.3 | E17: 335.5 | F17: =G17-C17-D17-E17 | G17: 1258.4 | H17: 339.8 | I17: =I14-I15+I16 | J17: =J14-J15+J16 | K17: =K14-K15+K16 | L17: =SUM(H17:K17) | M17: =M14-M15+M16 | N17: =N14-N15+N16 | O17: =O14-O15+O16 | P17: =P14-P15+P16
A18: Memo: depreciation and amortization (cash flow statement) | C18: =CF!C25 | D18: =CF!D25-CF!C25 | E18: =CF!E25-CF!D25 | F18: =CF!G25-CF!E25 | G18: =CF!G25 | H18: =CF!H25 | I18: =I6*Inputs!$C$12 | J18: =J6*Inputs!$C$12 | K18: =K6*Inputs!$C$12 | L18: =SUM(H18:K18) | M18: =M6*Inputs!$C$12 | N18: =N6*Inputs!$C$12 | O18: =O6*Inputs!$C$12 | P18: =P6*Inputs!$C$12
A19: EBITDA (operating income + D&A) | C19: =C11+C18 | D19: =D11+D18 | E19: =E11+E18 | F19: =F11+F18 | G19: =G11+G18 | H19: =H11+H18 | I19: =I11+I18 | J19: =J11+J18 | ... P19: =P11+P18

Sheet BS
A1: FASTENAL CO: balance sheet
A2: $ in millions
G3: FY2025 | H3: Q1 FY2026 | I3: Q2 FY2026 | J3: Q3 FY2026 | K3: Q4 FY2026 | M3: FY2027E | N3: FY2028E | O3: FY2029E | P3: FY2030E
G4: A | H4: =IF(1<=Inputs!$C$4,"A","E") | I4: =IF(2<=Inputs!$C$4,"A","E") | J4: =IF(3<=Inputs!$C$4,"A","E") | K4: =IF(4<=Inputs!$C$4,"A","E") | M4: E | N4: E | O4: E | P4: E
A6: Cash and cash equivalents | G6: 276.8 | H6: 308.6 | I6: =CF!I17 | J6: =CF!J17 | K6: =CF!K17 | M6: =CF!M17 | N6: =CF!N17 | O6: =CF!O17 | P6: =CF!P17
A7: Accounts receivable, net | G7: 1245.3 | H7: 1445.2 | I7: =IS!I6*Inputs!$C$15/91.25 | J7: =IS!J6*Inputs!$C$15/91.25 | K7: =IS!K6*Inputs!$C$15/91.25 | M7: =IS!M6*Inputs!$C$15/365 | N7: =IS!N6*Inputs!$C$15/365 | O7: =IS!O6*Inputs!$C$15/365 | P7: =IS!P6*Inputs!$C$15/365
A8: Inventories | G8: 1748 | H8: 1692.5 | I8: =IS!I7*Inputs!$C$16/91.25 | J8: =IS!J7*Inputs!$C$16/91.25 | K8: =IS!K7*Inputs!$C$16/91.25 | M8: =IS!M7*Inputs!$C$16/365 | N8: =IS!N7*Inputs!$C$16/365 | O8: =IS!O7*Inputs!$C$16/365 | P8: =IS!P7*Inputs!$C$16/365
A9: Other current assets | G9: =G10-G6-G7-G8 | H9: =H10-H6-H7-H8 | I9: =H9 | J9: =I9 | K9: =J9 | M9: =K9 | N9: =M9 | O9: =N9 | P9: =O9
A10: Total current assets | G10: 3472.1 | H10: 3619.8 | I10: =I6+I7+I8+I9 | J10: =J6+J7+J8+J9 | K10: =K6+K7+K8+K9 | M10: =M6+M7+M8+M9 | N10: =N6+N7+N8+N9 | O10: =O6+O7+O8+O9 | P10: =P6+P7+P8+P9
A11: Property and equipment, net | G11: 1131.6 | H11: 1140.3 | I11: =H11-CF!I10-IS!I18 | J11: =I11-CF!J10-IS!J18 | K11: =J11-CF!K10-IS!K18 | M11: =K11-CF!M10-IS!M18 | N11: =M11-CF!N10-IS!N18 | O11: =N11-CF!O10-IS!O18 | P11: =O11-CF!P10-IS!P18
A12: Goodwill | G12: 0 | H12: 0 | I12: =H12 | J12: =I12 | K12: =J12 | M12: =K12 | N12: =M12 | O12: =N12 | P12: =O12
A13: Intangible assets, net | G13: 0 | H13: 0 | I13: =H13 | J13: =I13 | K13: =J13 | M13: =K13 | N13: =M13 | O13: =N13 | P13: =O13
A14: Other non-current assets | G14: =G15-G10-G11-G12-G13 | H14: =H15-H10-H11-H12-H13 | I14: =H14 | J14: =I14 | K14: =J14 | M14: =K14 | N14: =M14 | O14: =N14 | P14: =O14
A15: Total assets | G15: 5052.9 | H15: 5209.8 | I15: =I10+I11+I12+I13+I14 | J15: =J10+J11+J12+J13+J14 | K15: =K10+K11+K12+K13+K14 | M15: =M10+M11+M12+M13+M14 | N15: =N10+N11+N12+N13+N14 | O15: =O10+O11+O12+O13+O14 | P15: =P10+P11+P12+P13+P14
A16: Accounts payable | G16: 316.8 | H16: 363.2 | I16: =IS!I7*Inputs!$C$17/91.25 | J16: =IS!J7*Inputs!$C$17/91.25 | K16: =IS!K7*Inputs!$C$17/91.25 | M16: =IS!M7*Inputs!$C$17/365 | N16: =IS!N7*Inputs!$C$17/365 | O16: =IS!O7*Inputs!$C$17/365 | P16: =IS!P7*Inputs!$C$17/365
A17: Short-term borrowings | G17: 0 | H17: 0 | I17: =H17 | J17: =I17 | K17: =J17 | M17: =K17 | N17: =M17 | O17: =N17 | P17: =O17
A18: Current portion of long-term debt | G18: 25 | H18: 25 | I18: =H18 | J18: =I18 | K18: =J18 | M18: =K18 | N18: =M18 | O18: =N18 | P18: =O18
A19: Other current liabilities | G19: =G20-G16-G17-G18 | H19: =H20-H16-H17-H18 | I19: =H19 | J19: =I19 | K19: =J19 | M19: =K19 | N19: =M19 | O19: =N19 | P19: =O19
A20: Total current liabilities | G20: 715.6 | H20: 824.1 | I20: =I16+I17+I18+I19 | J20: =J16+J17+J18+J19 | K20: =K16+K17+K18+K19 | M20: =M16+M17+M18+M19 | N20: =N16+N17+N18+N19 | O20: =O16+O17+O18+O19 | P20: =P16+P17+P18+P19
A21: Long-term debt | G21: 100 | H21: 100 | I21: =H21 | J21: =I21 | K21: =J21 | M21: =K21 | N21: =M21 | O21: =N21 | P21: =O21
A22: Other non-current liabilities | G22: =G28-G20-G21-G24-G25-G26 | H22: =H28-H20-H21-H24-H25-H26 | I22: =H22 | J22: =I22 | K22: =J22 | M22: =K22 | N22: =M22 | O22: =N22 | P22: =O22
A23: Total liabilities | G23: =G28-G24-G25-G26 | H23: =H28-H24-H25-H26 | I23: =I28-I24-I25-I26 | J23: =J28-J24-J25-J26 | K23: =K28-K24-K25-K26 | M23: =M28-M24-M25-M26 | N23: =N28-N24-N25-N26 | O23: =O28-O24-O25-O26 | P23: =P28-P24-P25-P26
A24: Redeemable non-controlling interests | G24: 0 | H24: 0 | I24: =H24 | J24: =I24 | K24: =J24 | M24: =K24 | N24: =M24 | O24: =N24 | P24: =O24
A25: Shareholders' equity (company) | G25: 3943.6 | H25: 3989.5 | I25: =H25+IS!I17+CF!I13 | J25: =I25+IS!J17+CF!J13 | K25: =J25+IS!K17+CF!K13 | M25: =K25+IS!M17+CF!M13 | N25: =M25+IS!N17+CF!N13 | O25: =N25+IS!O17+CF!O13 | P25: =O25+IS!P17+CF!P13
A26: Non-controlling interests | G26: 0 | H26: 0 | I26: =H26 | J26: =I26 | K26: =J26 | M26: =K26 | N26: =M26 | O26: =N26 | P26: =O26
A27: Total equity | G27: =G25+G26 | H27: =H25+H26 | I27: =I25+I26 | J27: =J25+J26 | K27: =K25+K26 | M27: =M25+M26 | N27: =N25+N26 | O27: =O25+O26 | P27: =P25+P26
A28: Total liabilities and equity | G28: 5052.9 | H28: 5209.8 | I28: =I20+I21+I22+I24+I25+I26 | J28: =J20+J21+J22+J24+J25+J26 | K28: =K20+K21+K22+K24+K25+K26 | M28: =M20+M21+M22+M24+M25+M26 | N28: =N20+N21+N22+N24+N25+N26 | O28: =O20+O21+O22+O24+O25+O26 | P28: =P20+P21+P22+P24+P25+P26
A29: Check: total assets - total liabilities and equity (should be 0) | G29: =G15-G28 | H29: =H15-H28 | I29: =I15-I28 | J29: =J15-J28 | K29: =K15-K28 | M29: =M15-M28 | N29: =N15-N28 | O29: =O15-O28 | P29: =P15-P28

Sheet CF
A1: FASTENAL CO: cash flow statement
A2: $ in millions
G3: FY2025 | H3: Q1 FY2026 | I3: Q2 FY2026 | J3: Q3 FY2026 | K3: Q4 FY2026 | L3: FY2026 | M3: FY2027E | N3: FY2028E | O3: FY2029E | P3: FY2030E
G4: A | H4: =IF(1<=Inputs!$C$4,"A","E") | I4: =IF(2<=Inputs!$C$4,"A","E") | J4: =IF(3<=Inputs!$C$4,"A","E") | K4: =IF(4<=Inputs!$C$4,"A","E") | M4: E | N4: E | O4: E | P4: E
A6: Net income | G6: =IS!G17 | H6: =IS!H17 | I6: =IS!I17 | J6: =IS!J17 | K6: =IS!K17 | L6: =IS!L17 | M6: =IS!M17 | N6: =IS!N17 | ... P6: =IS!P17
A7: Depreciation and amortization | G7: =IS!G18 | H7: =IS!H18 | I7: =IS!I18 | J7: =IS!J18 | K7: =IS!K18 | L7: =IS!L18 | M7: =IS!M18 | N7: =IS!N18 | ... P7: =IS!P18
A8: Working capital and other operating items | G8: =G9-G6-G7 | H8: =H9-H6-H7 | I8: =BS!H7-BS!I7+BS!H8-BS!I8+BS!I16-BS!H16 | J8: =BS!I7-BS!J7+BS!I8-BS!J8+BS!J16-BS!I16 | K8: =BS!J7-BS!K7+BS!J8-BS!K8+BS!K16-BS!J16 | L8: =SUM(H8:K8) | M8: =BS!K7-BS!M7+BS!K8-BS!M8+BS!M16-BS!K16 | N8: =BS!M7-BS!N7+BS!M8-BS!N8+BS!N16-BS!M16 | O8: =BS!N7-BS!O7+BS!N8-BS!O8+BS!O16-BS!N16 | P8: =BS!O7-BS!P7+BS!O8-BS!P8+BS!P16-BS!O16
A9: Cash from operating activities | G9: =G21 | H9: =H21 | I9: =I6+I7+I8 | J9: =J6+J7+J8 | K9: =K6+K7+K8 | L9: =SUM(H9:K9) | M9: =M6+M7+M8 | N9: =N6+N7+N8 | O9: =O6+O7+O8 | P9: =P6+P7+P8
A10: Capital expenditures | G10: =G22 | H10: =H22 | I10: =-IS!I6*Inputs!$C$13 | J10: =-IS!J6*Inputs!$C$13 | K10: =-IS!K6*Inputs!$C$13 | L10: =SUM(H10:K10) | M10: =-IS!M6*Inputs!$C$13 | N10: =-IS!N6*Inputs!$C$13 | O10: =-IS!O6*Inputs!$C$13 | P10: =-IS!P6*Inputs!$C$13
A11: Other investing activities | G11: =G12-G10 | H11: =H12-H10 | I11: =Inputs!$C$22 | J11: =Inputs!$C$22 | K11: =Inputs!$C$22 | L11: =SUM(H11:K11) | M11: =Inputs!$C$22*4 | N11: =Inputs!$C$22*4 | O11: =Inputs!$C$22*4 | P11: =Inputs!$C$22*4
A12: Cash from investing activities | G12: =G23 | H12: =H23 | I12: =I10+I11 | J12: =J10+J11 | K12: =K10+K11 | L12: =SUM(H12:K12) | M12: =M10+M11 | N12: =N10+N11 | O12: =O10+O11 | P12: =P10+P11
A13: Cash from financing activities | G13: =G24 | H13: =H24 | I13: =-IS!I17*Inputs!$C$18 | J13: =-IS!J17*Inputs!$C$18 | K13: =-IS!K17*Inputs!$C$18 | L13: =SUM(H13:K13) | M13: =-IS!M17*Inputs!$C$18 | N13: =-IS!N17*Inputs!$C$18 | O13: =-IS!O17*Inputs!$C$18 | P13: =-IS!P17*Inputs!$C$18
A14: Exchange rate effect, restricted cash and other | H14: =BS!H6-BS!G6-H9-H12-H13 | I14: =Inputs!$C$23 | J14: =Inputs!$C$23 | K14: =Inputs!$C$23 | L14: =SUM(H14:K14) | M14: =Inputs!$C$23*4 | N14: =Inputs!$C$23*4 | O14: =Inputs!$C$23*4 | P14: =Inputs!$C$23*4
A15: Net change in cash | H15: =H9+H12+H13+H14 | I15: =I9+I12+I13+I14 | J15: =J9+J12+J13+J14 | K15: =K9+K12+K13+K14 | L15: =SUM(H15:K15) | M15: =M9+M12+M13+M14 | N15: =N9+N12+N13+N14 | O15: =O9+O12+O13+O14 | P15: =P9+P12+P13+P14
A16: Cash at beginning of period | H16: =BS!G6 | I16: =BS!H6 | J16: =BS!I6 | K16: =BS!J6 | L16: =BS!G6 | M16: =BS!K6 | N16: =BS!M6 | O16: =BS!N6 | P16: =BS!O6
A17: Cash at end of period | H17: =H16+H15 | I17: =I16+I15 | J17: =J16+J15 | K17: =K16+K15 | L17: =L16+L15 | M17: =M16+M15 | N17: =N16+N15 | O17: =O16+O15 | P17: =P16+P15
A18: Free cash flow (operating cash flow + capital expenditures) | G18: =G9+G10 | H18: =H9+H10 | I18: =I9+I10 | J18: =J9+J10 | K18: =K9+K10 | L18: =L9+L10 | M18: =M9+M10 | N18: =N9+N10 | ... P18: =P9+P10
A20: As reported in each filing (year to date)
A21: Cash from operating activities, year to date (as reported) | G21: 1295.9 | H21: 378.4
A22: Capital expenditures, year to date (as reported) | G22: -245.3 | H22: -58.9
A23: Cash from investing activities, year to date (as reported) | G23: -231 | H23: -57.6
A24: Cash from financing activities, year to date (as reported) | G24: -1054.9 | H24: -288.3
A25: Depreciation and amortization, year to date (as reported) | C25: 44.7 | D25: 89.8 | E25: 134.7 | G25: 179.2 | H25: 44.6

Sheet DCF
A1: FASTENAL CO: unlevered DCF and valuation
A2: $ in millions
H3: Q1 FY2026 | I3: Q2 FY2026 | J3: Q3 FY2026 | K3: Q4 FY2026 | M3: FY2027E | N3: FY2028E | O3: FY2029E | P3: FY2030E
H4: =IF(1<=Inputs!$C$4,"A","E") | I4: =IF(2<=Inputs!$C$4,"A","E") | J4: =IF(3<=Inputs!$C$4,"A","E") | K4: =IF(4<=Inputs!$C$4,"A","E") | M4: E | N4: E | O4: E | P4: E
A6: Fiscal quarter | H6: 1 | I6: 2 | J6: 3 | K6: 4
A7: EBIT | H7: =IS!H11 | I7: =IS!I11 | J7: =IS!J11 | K7: =IS!K11 | M7: =IS!M11 | N7: =IS!N11 | O7: =IS!O11 | P7: =IS!P11
A8: Tax on EBIT | H8: =-H7*Inputs!$C$14 | I8: =-I7*Inputs!$C$14 | J8: =-J7*Inputs!$C$14 | K8: =-K7*Inputs!$C$14 | M8: =-M7*Inputs!$C$14 | N8: =-N7*Inputs!$C$14 | O8: =-O7*Inputs!$C$14 | P8: =-P7*Inputs!$C$14
A9: NOPAT | H9: =H7+H8 | I9: =I7+I8 | J9: =J7+J8 | K9: =K7+K8 | M9: =M7+M8 | N9: =N7+N8 | O9: =O7+O8 | P9: =P7+P8
A10: Depreciation and amortization | H10: =IS!H18 | I10: =IS!I18 | J10: =IS!J18 | K10: =IS!K18 | M10: =IS!M18 | N10: =IS!N18 | O10: =IS!O18 | P10: =IS!P18
A11: Capital expenditures | H11: =CF!H10 | I11: =CF!I10 | J11: =CF!J10 | K11: =CF!K10 | M11: =CF!M10 | N11: =CF!N10 | O11: =CF!O10 | P11: =CF!P10
A12: Working capital and other | H12: =CF!H8 | I12: =CF!I8 | J12: =CF!J8 | K12: =CF!K8 | M12: =CF!M8 | N12: =CF!N8 | O12: =CF!O8 | P12: =CF!P8
A13: Unlevered free cash flow | H13: =H9+H10+H11+H12 | I13: =I9+I10+I11+I12 | J13: =J9+J10+J11+J12 | K13: =K9+K10+K11+K12 | M13: =M9+M10+M11+M12 | N13: =N9+N10+N11+N12 | O13: =O9+O10+O11+O12 | P13: =P9+P10+P11+P12
A14: Discount period (years from the balance sheet date) | M14: =C20+1 | N14: =C20+2 | O14: =C20+3 | P14: =C20+4
A15: Discount factor | M15: =1/(1+Inputs!$C$25)^M14 | N15: =1/(1+Inputs!$C$25)^N14 | O15: =1/(1+Inputs!$C$25)^O14 | P15: =1/(1+Inputs!$C$25)^P14
A16: PV of unlevered free cash flow | M16: =M13*M15 | N16: =N13*N15 | O16: =O13*O15 | P16: =P13*P15
A18: Revenue, last four reported quarters | C18: =SUM(IS!D6:F6)+SUM(IS!H6:H6)
A19: EBITDA, last four reported quarters | C19: =SUM(IS!D19:F19)+SUM(IS!H19:H19)
A20: Rest of the current fiscal year (years) | C20: =(4-Inputs!$C$4)/4
A21: Unlevered free cash flow, rest of the current fiscal year | C21: =SUMPRODUCT((H6:K6>Inputs!$C$4)*H13:K13)
A22: Discount factor, rest of the current fiscal year | C22: =1/(1+Inputs!$C$25)^C20
A23: PV, rest of the current fiscal year | C23: =C21*C22
A24: Terminal value (Gordon growth, end of last forecast year) | C24: =P13*(1+Inputs!$C$26)/(Inputs!$C$25-Inputs!$C$26)
A25: PV of terminal value | C25: =C24*P15
A26: Enterprise value | C26: =C23+SUM(M16:P16)+C25
A27: Less: cash and cash equivalents (latest reported balance sheet) | C27: =BS!H6
A28: Short-term borrowings (latest reported balance sheet) | C28: =BS!H17
A29: Current portion of long-term debt (latest reported balance sheet) | C29: =BS!H18
A30: Long-term debt (latest reported balance sheet) | C30: =BS!H21
A31: Net debt | C31: =C28+C29+C30-C27
A32: Non-controlling interests, incl. redeemable (latest reported balance sheet) | C32: =BS!H26+BS!H24
A33: Equity value | C33: =C26-C31-C32
A34: Shares outstanding | C34: =Inputs!$C$5
A35: Equity value per share ($) | C35: =C33/C34
A36: Enterprise value / EBITDA, last four reported quarters (x) | C36: =C26/C19

Sheet Scratch
