Workbook

Sheet Cover
B1: APPLE INC. (NASDAQ: AAPL)
B2: Investment Analyst Model | 3-Statement Forecast + DCF Valuation
B5: MODEL OVERVIEW
B7: Issuer | C7: Apple Inc. (NASDAQ: AAPL)
B8: Sector | C8: Technology: Consumer Electronics & Services
B9: Reporting period | C9: Fiscal years ending last Saturday of September
B10: Historicals | C10: FY2021 – FY2025 (5 years actuals from 10-K filings)
B11: Projections | C11: FY2026E – FY2029E (4 years forecast)
B12: Methodology | C12: Top-down driver-based: segment revenue → gross margin → OpEx → BS roll-forwards
B13: Valuation | C13: ="Unlevered DCF at WACC "&TEXT(Assumptions!B54,"0.00%")&", terminal growth "&TEXT(Assumptions!B55,"0.0%")&"; FY27E to FY29E discounted from the "&TEXT(Assumptions!B60,"d mmm yyyy")&" valuation date, Gordon terminal value at FY29E" -> Unlevered DCF at WACC 9.34%, terminal growth 2.5%; FY27E to FY29E discounted from the 28 Sep 2026 valuation date, Gordon terminal value at FY29E
B14: Tax assumption | C14: Scenario tax rate (Base 15%: the FY21 to FY25 average excluding FY24's EU State Aid charge)
B15: Capital return | C15: ~95% of FCF returned to shareholders via buybacks + dividends (Apple stated policy)
B17: WORKBOOK STRUCTURE
B19: Cover | C19: This page
B20: Assumptions | C20: All forecast drivers: segment growth rates, margins, tax, WACC inputs (BLUE = editable)
B21: IS | C21: Income Statement FY21A–FY29E: top-down build from segment revenue
B22: BS | C22: Balance Sheet FY21A–FY29E: working capital days-based, full roll-forwards
B23: CFS | C23: Cash Flow Statement FY21A–FY29E: indirect method, ties to BS change in cash
B24: Ratios | C24: Profitability, returns, leverage, working capital ratios
B25: DCF | C25: Enterprise value, equity value, implied share price + WACC × g sensitivity
B26: Dashboard | C26: Executive view: KPIs, valuation summary, key charts
B27: Validation | C27: 10-K line-by-line audit, structural checks and forecast sanity bands
B28: Pivots | C28: Pivot summaries of the statements
B29: COLOR CONVENTIONS (IB STANDARD)
B31: BLUE | C31: Hardcoded inputs (historicals from 10-K + assumption drivers)
B32: BLACK | C32: Formulas (calculated from inputs and other formulas)
B33: GREEN | C33: Cross-sheet links (pulled from another sheet)
B34: TICKS | C34: Audit checks: a green tick when a check passes, a red cross when it fails
B36: DATA SOURCES
B38: 10-K FY2025 | C38: Filed Oct 31, 2025: covers FY2023A, FY2024A, FY2025A
B39: 10-K FY2022 | C39: Filed Oct 28, 2022: covers FY2021A and FY2022A
B40: SEC EDGAR | C40: https://www.sec.gov/cgi-bin/browse-edgar?action=getcompany&CIK=0000320193
B43: PREPARED BY
B44: Alven Yuka | CPA Finalist | Nairobi, Kenya
B45: linkedin.com/in/alven-yuka-610b78174 | github.com/alvenyuka

Sheet Dashboard
B2: APPLE INC. (AAPL) FINANCIAL DASHBOARD
B3: OVERVIEW OF REVENUE, COSTS, PROFITABILITY & KEY INVESTOR METRICS
C7: 💲 TOTAL REVENUE FY26E | G7: 📊 NET INCOME FY26E | K7: 💰 FREE CASH FLOW FY26E | O7: 🏆 TOP SEGMENT FY25A | S7: 📈 DILUTED EPS FY26E
C8: ="$"&TEXT(IS!H14/1000,"0.0")&"B" -> $436.9B | G8: ="$"&TEXT(IS!H39/1000,"0.0")&"B" -> $121.3B | K8: ="$"&TEXT(CFS!G21/1000,"0.0")&"B" -> $153.6B | O8: =INDEX(B80:B84,MATCH(MAX(G80:G84),G80:G84,0)) -> iPhone | S8: ="$"&TEXT(IS!H44,"0.00") -> $8.29
C9: =IF(IS!H14/IS!F14-1>=0,"▲ ","▼ ")&TEXT(IS!H14/IS!F14-1,"+0.0%;-0.0%")&" vs FY25A" -> ▲ +5.0% vs FY25A | G9: =IF(IS!H39/IS!F39-1>=0,"▲ ","▼ ")&TEXT(IS!H39/IS!F39-1,"+0.0%;-0.0%")&" vs FY25A" -> ▲ +8.3% vs FY25A | K9: =IF(CFS!G21/CFS!F21-1>=0,"▲ ","▼ ")&TEXT(CFS!G21/CFS!F21-1,"+0.0%;-0.0%")&" vs FY25A" -> ▲ +55.6% vs FY25A | O9: ="$"&TEXT(G80/1000,"0.0")&"B ("&TEXT(G80/G$90,"0.0%")&" of mix)" -> $209.6B (50.4% of mix) | S9: =IF(IS!H44/IS!F44-1>=0,"▲ ","▼ ")&TEXT(IS!H44/IS!F44-1,"+0.0%;-0.0%")&" vs FY25A" -> ▲ +11.1% vs FY25A
B12: FILTERS & CONTROLS | D12: REVENUE TREND & GROWTH % | M12: $M, FY21A–FY29E | N12: REVENUE BY GEOGRAPHY FY25A | U12: ="$"&TEXT(IS!F14/1000,"0")&"B" -> $416B
B14: SCENARIO
B15: =Assumptions!B62 -> Base
D28: REVENUE BY SEGMENT FY25A | H28: REVENUE BY GEOGRAPHY FY25A | M28: $B / % mix | N28: TOP 5 PRODUCT LINES BY REVENUE FY25A
H30: REGION | L30: REVENUE | M30: MIX
H31: Americas | K31: =REPT("█",ROUND(M31*40,0)) -> █████████████████ | L31: =IS!F66/1000 -> 178.353 | M31: =IS!F66/IS!F71 -> 0.42856731
H32: Europe | K32: =REPT("█",ROUND(M32*40,0)) -> ███████████ | L32: =IS!F67/1000 -> 111.032 | M32: =IS!F67/IS!F71 -> 0.26680059
H33: Greater China | K33: =REPT("█",ROUND(M33*40,0)) -> ██████ | L33: =IS!F68/1000 -> 64.377 | M33: =IS!F68/IS!F71 -> 0.15469253
H34: Rest of APAC | K34: =REPT("█",ROUND(M34*40,0)) -> ███ | L34: =IS!F70/1000 -> 33.696 | M34: =IS!F70/IS!F71 -> 0.080968664
H35: Japan | K35: =REPT("█",ROUND(M35*40,0)) -> ███ | L35: =IS!F69/1000 -> 28.703 | M35: =IS!F69/IS!F71 -> 0.068970903
H37: Total | L37: =IS!F71/1000 -> 416.161 | M37: =L37/L37 -> 1
D45: P&L CASCADE BY FISCAL YEAR | M45: $M | N45: PROFITABILITY MARGINS TREND | U45: % by FY
D47: LINE ITEM | G47: FY23A | H47: FY24A | I47: FY25A | J47: FY26E | K47: FY27E | L47: FY28E | M47: FY29E
D48: Total Revenue | G48: =IS!D14 -> 383285 | H48: =IS!E14 -> 391035 | I48: =IS!F14 -> 416161 | J48: =IS!H14 -> 436869.75 | K48: =IS!I14 -> 459080.35 | L48: =IS!J14 -> 482929.54 | M48: =IS!K14 -> 508567.73
D49: (-) Cost of Sales | G49: =-(IS!D19+IS!D20) -> -214137 | H49: =-(IS!E19+IS!E20) -> -210352 | I49: =-(IS!F19+IS!F20) -> -220960 | J49: =-(IS!H19+IS!H20) -> -228186.3 | K49: =-(IS!I19+IS!I20) -> -237239.61 | L49: =-(IS!J19+IS!J20) -> -246806.59 | M49: =-(IS!K19+IS!K20) -> -256927.55
D50: Gross Profit | G50: =IS!D22 -> 169148 | H50: =IS!E22 -> 180683 | I50: =IS!F22 -> 195201 | J50: =IS!H22 -> 208683.45 | K50: =IS!I22 -> 221840.74 | L50: =IS!J22 -> 236122.95 | M50: =IS!K22 -> 251640.18
D51: (-) R&D Expense | G51: =-IS!D26 -> -29915 | H51: =-IS!E26 -> -31370 | I51: =-IS!F26 -> -34550 | J51: =-IS!H26 -> -37141.25 | K51: =-IS!I26 -> -39926.844 | L51: =-IS!J26 -> -42921.357 | M51: =-IS!K26 -> -46140.459
D52: (-) SG&A Expense | G52: =-IS!D27 -> -24932 | H52: =-IS!E27 -> -26097 | I52: =-IS!F27 -> -27601 | J52: =-IS!H27 -> -28843.045 | K52: =-IS!I27 -> -30140.982 | L52: =-IS!J27 -> -31497.326 | M52: =-IS!K27 -> -32914.706
D53: Operating Income | G53: =IS!D29 -> 114301 | H53: =IS!E29 -> 123216 | I53: =IS!F29 -> 133050 | J53: =IS!H29 -> 142699.15 | K53: =IS!I29 -> 151772.92 | L53: =IS!J29 -> 161704.27 | M53: =IS!K29 -> 172585.01
D54: (-) Income Tax | G54: =-IS!D37 -> -16741 | H54: =-IS!E37 -> -29749 | I54: =-IS!F37 -> -20719 | J54: =-IS!H37 -> -21404.873 | K54: =-IS!I37 -> -22765.937 | L54: =-IS!J37 -> -24255.64 | M54: =-IS!K37 -> -25887.752
D55: Net Income | G55: =IS!D39 -> 96995 | H55: =IS!E39 -> 93736 | I55: =IS!F39 -> 112010 | J55: =IS!H39 -> 121294.28 | K55: =IS!I39 -> 129006.98 | L55: =IS!J39 -> 137448.63 | M55: =IS!K39 -> 146697.26
D56: Diluted EPS ($) | G56: =IS!D44 -> 6.13 | H56: =IS!E44 -> 6.08 | I56: =IS!F44 -> 7.46 | J56: =IS!H44 -> 8.2866058 | K56: =IS!I44 -> 9.0266273 | L56: =IS!J44 -> 9.8713057 | M56: =IS!K44 -> 10.840767
D57: Free Cash Flow | G57: =CFS!D21 -> 99584 | H57: =CFS!E21 -> 108807 | I57: =CFS!F21 -> 98767 | J57: =CFS!G21 -> 153635.75 | K57: =CFS!H21 -> 144816.26 | L57: =CFS!I21 -> 154120.94 | M57: =CFS!J21 -> 164299.73
D62: REVENUE BY PRODUCT LINE FY25A | J62: FREE CASH FLOW BY FY | O62: $B | P62: KEY INVESTOR INSIGHTS
B64: Chart data, linked to the income statement | P64: 🟢 | Q64: ="Gross margin expanding "&TEXT(Ratios!B7,"0.0%")&" → "&TEXT(Ratios!J7,"0.0%") -> Gross margin expanding 41.8% → 49.5%
B65: Region | C65: FY21A | D65: FY22A | E65: FY23A | F65: FY24A | G65: FY25A | H65: FY26E | I65: FY27E | J65: FY28E | Q65: Services mix shift and own-silicon advantage compounding.
B66: Americas | C66: =IS!B66 -> 153306 | D66: =IS!C66 -> 169658 | E66: =IS!D66 -> 162560 | F66: =IS!E66 -> 167045 | G66: =IS!F66 -> 178353 | H66: =IS!H66 -> 187912.11 | I66: =IS!I66 -> 198053.16 | J66: =IS!J66 -> 208827.05
B67: Europe | C67: =IS!B67 -> 89307 | D67: =IS!C67 -> 95118 | E67: =IS!D67 -> 94294 | F67: =IS!E67 -> 101328 | G67: =IS!F67 -> 111032 | H67: =IS!H67 -> 118662.12 | I67: =IS!I67 -> 126861.16 | J67: =IS!J67 -> 135682.31 | P67: 💡 | Q67: ="Services revenue "&TEXT(IS!K13/IS!B13,"0.0")&"x, FY21 to FY29: $"&TEXT(IS!B13/1000,"0")&"B to $"&TEXT(IS!K13/1000,"0")&"B" -> Services revenue 2.4x, FY21 to FY29: $68B to $163B
B68: Greater China | C68: =IS!B68 -> 68366 | D68: =IS!C68 -> 74200 | E68: =IS!D68 -> 72559 | F68: =IS!E68 -> 66952 | G68: =IS!F68 -> 64377 | H68: =IS!H68 -> 63608.46 | I68: =IS!I68 -> 62871.187 | J68: =IS!J68 -> 62167.932 | Q68: =TEXT((IS!K13/IS!B13)^(1/8)-1,"0.0%")&" CAGR, "&TEXT(IS!K13/IS!K14,"0.0%")&" of FY29E revenue" -> 11.4% CAGR, 32.0% of FY29E revenue
B69: Japan | C69: =IS!B69 -> 28482 | D69: =IS!C69 -> 25977 | E69: =IS!D69 -> 24257 | F69: =IS!E69 -> 25052 | G69: =IS!F69 -> 28703 | H69: =IS!H69 -> 30675.47 | I69: =IS!I69 -> 32795.012 | J69: =IS!J69 -> 35075.377
B70: Rest of APAC | C70: =IS!B70 -> 26356 | D70: =IS!C70 -> 29375 | E70: =IS!D70 -> 29615 | F70: =IS!E70 -> 30658 | G70: =IS!F70 -> 33696 | H70: =IS!H70 -> 36011.589 | I70: =IS!I70 -> 38499.834 | J70: =IS!J70 -> 41176.877 | P70: 🟢 | Q70: ="Free cash flow of $"&TEXT(CFS!G21/1000,"0")&"B in FY26E" -> Free cash flow of $154B in FY26E
Q71: =TEXT(CFS!G21/IS!H14,"0.0%")&" FCF margin, against "&TEXT(CFS!F21/IS!F14,"0.0%")&" in FY25A" -> 35.2% FCF margin, against 23.7% in FY25A
P73: ⚠️ | Q73: ="Greater China revenue softening" -> Greater China revenue softening
Q74: ="from $"&TEXT(D68/1000,"0")&"B (FY22A) to $"&TEXT(G68/1000,"0")&"B (FY25A), -"&TEXT(1-G68/D68,"0%")&" decline." -> from $74B (FY22A) to $64B (FY25A), -13% decline.
B76: Total | C76: =SUM(C66:C70) -> 365817 | D76: =SUM(D66:D70) -> 394328 | E76: =SUM(E66:E70) -> 383285 | F76: =SUM(F66:F70) -> 391035 | G76: =SUM(G66:G70) -> 416161 | H76: =SUM(H66:H70) -> 436869.75 | I76: =SUM(I66:I70) -> 459080.35 | J76: =SUM(J66:J70) -> 482929.54
B79: Product Line | C79: FY21A | D79: FY22A | E79: FY23A | F79: FY24A | G79: FY25A | H79: FY26E | I79: FY27E | J79: FY28E | K79: FY29E
B80: iPhone | C80: =IS!B9 -> 191973 | D80: =IS!C9 -> 205489 | E80: =IS!D9 -> 200583 | F80: =IS!E9 -> 201183 | G80: =IS!F9 -> 209586 | H80: =IS!H9 -> 215873.58 | I80: =IS!I9 -> 222349.79 | J80: =IS!J9 -> 229020.28 | K80: =IS!K9 -> 235890.89
B81: Mac | C81: =IS!B10 -> 35190 | D81: =IS!C10 -> 40177 | E81: =IS!D10 -> 29357 | F81: =IS!E10 -> 29984 | G81: =IS!F10 -> 33708 | H81: =IS!H10 -> 35393.4 | I81: =IS!I10 -> 37163.07 | J81: =IS!J10 -> 39021.224 | K81: =IS!K10 -> 40972.285
B82: iPad | C82: =IS!B11 -> 31862 | D82: =IS!C11 -> 29292 | E82: =IS!D11 -> 28300 | F82: =IS!E11 -> 26694 | G82: =IS!F11 -> 28023 | H82: =IS!H11 -> 28583.46 | I82: =IS!I11 -> 29155.129 | J82: =IS!J11 -> 29738.232 | K82: =IS!K11 -> 30332.996
B83: Wearables | C83: =IS!B12 -> 38367 | D83: =IS!C12 -> 41241 | E83: =IS!D12 -> 39845 | F83: =IS!E12 -> 37005 | G83: =IS!F12 -> 35686 | H83: =IS!H12 -> 36399.72 | I83: =IS!I12 -> 37127.714 | J83: =IS!J12 -> 37870.269 | K83: =IS!K12 -> 38627.674
B84: Services | C84: =IS!B13 -> 68425 | D84: =IS!C13 -> 78129 | E84: =IS!D13 -> 85200 | F84: =IS!E13 -> 96169 | G84: =IS!F13 -> 109158 | H84: =IS!H13 -> 120619.59 | I84: =IS!I13 -> 133284.65 | J84: =IS!J13 -> 147279.53 | K84: =IS!K13 -> 162743.89
B90: Total | C90: =SUM(C80:C84) -> 365817 | D90: =SUM(D80:D84) -> 394328 | E90: =SUM(E80:E84) -> 383285 | F90: =SUM(F80:F84) -> 391035 | G90: =SUM(G80:G84) -> 416161 | H90: =SUM(H80:H84) -> 436869.75 | I90: =SUM(I80:I84) -> 459080.35 | J90: =SUM(J80:J84) -> 482929.54 | K90: =SUM(K80:K84) -> 508567.73
C92: FY21A | D92: FY22A | E92: FY23A | F92: FY24A | G92: FY25A | H92: FY26E | I92: FY27E | J92: FY28E | K92: FY29E
B93: Products ($B) | C93: =IS!B8/1000 -> 297.392 | D93: =IS!C8/1000 -> 316.199 | E93: =IS!D8/1000 -> 298.085 | F93: =IS!E8/1000 -> 294.866 | G93: =IS!F8/1000 -> 307.003 | H93: =IS!H8/1000 -> 316.25016 | I93: =IS!I8/1000 -> 325.7957 | J93: =IS!J8/1000 -> 335.65 | K93: =IS!K8/1000 -> 345.82384
B94: Services ($B) | C94: =IS!B13/1000 -> 68.425 | D94: =IS!C13/1000 -> 78.129 | E94: =IS!D13/1000 -> 85.2 | F94: =IS!E13/1000 -> 96.169 | G94: =IS!F13/1000 -> 109.158 | H94: =IS!H13/1000 -> 120.61959 | I94: =IS!I13/1000 -> 133.28465 | J94: =IS!J13/1000 -> 147.27953 | K94: =IS!K13/1000 -> 162.74389
B95: Growth % | D95: =IS!C14/IS!B14-1 -> 0.077937876 | E95: =IS!D14/IS!C14-1 -> -0.028004605 | F95: =IS!E14/IS!D14-1 -> 0.020219941 | G95: =IS!F14/IS!E14-1 -> 0.064255118 | H95: =IS!H14/IS!F14-1 -> 0.04976139 | I95: =IS!I14/IS!H14-1 -> 0.05084032 | J95: =IS!J14/IS!I14-1 -> 0.05194993 | K95: =IS!K14/IS!J14-1 -> 0.053088885
B97: Region | C97: FY25A ($B)
B98: Americas | C98: =G66/1000 -> 178.353
B99: Europe | C99: =G67/1000 -> 111.032
B100: Greater China | C100: =G68/1000 -> 64.377
B101: Japan | C101: =G69/1000 -> 28.703
B102: Rest of APAC | C102: =G70/1000 -> 33.696
B104: Segment | C104: FY25A ($B)
B105: Products | C105: =IS!F8/1000 -> 307.003
B106: Services | C106: =IS!F13/1000 -> 109.158
B108: Product | C108: FY25A ($B)
B109: iPad | C109: =G82/1000 -> 28.023
B110: Mac | C110: =G81/1000 -> 33.708
B111: Wearables | C111: =G83/1000 -> 35.686
B112: Services | C112: =G84/1000 -> 109.158
B113: iPhone | C113: =G80/1000 -> 209.586
C115: FY21A | D115: FY22A | E115: FY23A | F115: FY24A | G115: FY25A | H115: FY26E | I115: FY27E | J115: FY28E | K115: FY29E
B116: Gross % | C116: =Ratios!B7 -> 0.4177936 | D116: =Ratios!C7 -> 0.43309631 | E116: =Ratios!D7 -> 0.4413113 | F116: =Ratios!E7 -> 0.4620635 | G116: =Ratios!F7 -> 0.46905164 | H116: =Ratios!G7 -> 0.47767887 | I116: =Ratios!H7 -> 0.48322857 | J116: =Ratios!I7 -> 0.48893871 | K116: =Ratios!J7 -> 0.4948017
B117: Operating % | C117: =Ratios!B8 -> 0.29782378 | D117: =Ratios!C8 -> 0.30288744 | E117: =Ratios!D8 -> 0.29821412 | F117: =Ratios!E8 -> 0.31510223 | G117: =Ratios!F8 -> 0.319708 | H117: =Ratios!G8 -> 0.32664004 | I117: =Ratios!H8 -> 0.33060207 | J117: =Ratios!I8 -> 0.33484029 | K117: =Ratios!J8 -> 0.33935502
B118: Net % | C118: =Ratios!B9 -> 0.25881793 | D118: =Ratios!C9 -> 0.25309641 | E118: =Ratios!D9 -> 0.25306234 | F118: =Ratios!E9 -> 0.23971256 | G118: =Ratios!F9 -> 0.26915064 | H118: =Ratios!G9 -> 0.27764403 | I118: =Ratios!H9 -> 0.28101176 | J118: =Ratios!I9 -> 0.28461424 | K118: =Ratios!J9 -> 0.28845176
B119: FCF % | C119: =Ratios!B31 -> 0.25409699 | D119: =Ratios!C31 -> 0.28261498 | E119: =Ratios!D31 -> 0.25981711 | F119: =Ratios!E31 -> 0.27825386 | G119: =Ratios!F31 -> 0.23732882 | H119: =Ratios!G31 -> 0.35167404 | I119: =Ratios!H31 -> 0.31544862 | J119: =Ratios!I31 -> 0.31913752 | K119: =Ratios!J31 -> 0.32306363
B121: Product | C121: FY23A | D121: FY24A | E121: FY25A
B122: iPhone | C122: =E80/1000 -> 200.583 | D122: =F80/1000 -> 201.183 | E122: =G80/1000 -> 209.586
B123: Services | C123: =E84/1000 -> 85.2 | D123: =F84/1000 -> 96.169 | E123: =G84/1000 -> 109.158
B124: Wearables | C124: =E83/1000 -> 39.845 | D124: =F83/1000 -> 37.005 | E124: =G83/1000 -> 35.686
B125: Mac | C125: =E81/1000 -> 29.357 | D125: =F81/1000 -> 29.984 | E125: =G81/1000 -> 33.708
B126: iPad | C126: =E82/1000 -> 28.3 | D126: =F82/1000 -> 26.694 | E126: =G82/1000 -> 28.023
C128: FY21A | D128: FY22A | E128: FY23A | F128: FY24A | G128: FY25A | H128: FY26E | I128: FY27E | J128: FY28E | K128: FY29E
B129: FCF ($B) | C129: =CFS!B21/1000 -> 92.953 | D129: =CFS!C21/1000 -> 111.443 | E129: =CFS!D21/1000 -> 99.584 | F129: =CFS!E21/1000 -> 108.807 | G129: =CFS!F21/1000 -> 98.767 | H129: =CFS!G21/1000 -> 153.63575 | I129: =CFS!H21/1000 -> 144.81626 | J129: =CFS!I21/1000 -> 154.12094 | K129: =CFS!J21/1000 -> 164.29973

Sheet Assumptions
A1: ASSUMPTIONS | Forecast Drivers
A4: USD Millions | B4: FY2021A | C4: FY2022A | D4: FY2023A | E4: FY2024A | F4: FY2025A | G4: FY2026E | H4: FY2027E | I4: FY2028E | J4: FY2029E
B5: Sep 25, 2021 | C5: Sep 24, 2022 | D5: Sep 30, 2023 | E5: Sep 28, 2024 | F5: Sep 27, 2025 | G5: Sep 26, 2026 | H5: Sep 25, 2027 | I5: Sep 30, 2028 | J5: Sep 30, 2029
A7: REVENUE GROWTH DRIVERS | Segment-Level
A8: Products revenue YoY growth | B8: ="" | C8: =IS!C8/IS!B8-1 -> 0.063239764 | D8: =IS!D8/IS!C8-1 -> -0.057286709 | E8: =IS!E8/IS!D8-1 -> -0.010798933 | F8: =IS!F8/IS!E8-1 -> 0.04116107 | G8: =CHOOSE(MATCH(Scenario,{"Bear","Base","Bull"},0),$B$65,$C$65,$D$65) -> 0.030120748 | H8: =CHOOSE(MATCH(Scenario,{"Bear","Base","Bull"},0),$B$65,$C$65,$D$65) -> 0.030120748 | I8: =CHOOSE(MATCH(Scenario,{"Bear","Base","Bull"},0),$B$65,$C$65,$D$65) -> 0.030120748 | J8: =CHOOSE(MATCH(Scenario,{"Bear","Base","Bull"},0),$B$65,$C$65,$D$65) -> 0.030120748
A9: iPhone | C9: =IS!C9/IS!B9-1 -> 0.070405734 | D9: =IS!D9/IS!C9-1 -> -0.023874757 | E9: =IS!E9/IS!D9-1 -> 0.0029912804 | F9: =IS!F9/IS!E9-1 -> 0.041767943 | G9: =CHOOSE(MATCH(Scenario,{"Bear","Base","Bull"},0),$B$66,$C$66,$D$66) -> 0.03 | H9: =CHOOSE(MATCH(Scenario,{"Bear","Base","Bull"},0),$B$66,$C$66,$D$66) -> 0.03 | I9: =CHOOSE(MATCH(Scenario,{"Bear","Base","Bull"},0),$B$66,$C$66,$D$66) -> 0.03 | J9: =CHOOSE(MATCH(Scenario,{"Bear","Base","Bull"},0),$B$66,$C$66,$D$66) -> 0.03
A10: Mac | C10: =IS!C10/IS!B10-1 -> 0.1417164 | D10: =IS!D10/IS!C10-1 -> -0.26930831 | E10: =IS!E10/IS!D10-1 -> 0.021357768 | F10: =IS!F10/IS!E10-1 -> 0.12419957 | G10: =CHOOSE(MATCH(Scenario,{"Bear","Base","Bull"},0),$B$67,$C$67,$D$67) -> 0.05 | H10: =CHOOSE(MATCH(Scenario,{"Bear","Base","Bull"},0),$B$67,$C$67,$D$67) -> 0.05 | I10: =CHOOSE(MATCH(Scenario,{"Bear","Base","Bull"},0),$B$67,$C$67,$D$67) -> 0.05 | J10: =CHOOSE(MATCH(Scenario,{"Bear","Base","Bull"},0),$B$67,$C$67,$D$67) -> 0.05
A11: iPad | C11: =IS!C11/IS!B11-1 -> -0.080660348 | D11: =IS!D11/IS!C11-1 -> -0.033865902 | E11: =IS!E11/IS!D11-1 -> -0.056749117 | F11: =IS!F11/IS!E11-1 -> 0.049786469 | G11: =CHOOSE(MATCH(Scenario,{"Bear","Base","Bull"},0),$B$68,$C$68,$D$68) -> 0.02 | H11: =CHOOSE(MATCH(Scenario,{"Bear","Base","Bull"},0),$B$68,$C$68,$D$68) -> 0.02 | I11: =CHOOSE(MATCH(Scenario,{"Bear","Base","Bull"},0),$B$68,$C$68,$D$68) -> 0.02 | J11: =CHOOSE(MATCH(Scenario,{"Bear","Base","Bull"},0),$B$68,$C$68,$D$68) -> 0.02
A12: Wearables, Home & Accessories | C12: =IS!C12/IS!B12-1 -> 0.074908124 | D12: =IS!D12/IS!C12-1 -> -0.03384981 | E12: =IS!E12/IS!D12-1 -> -0.071276195 | F12: =IS!F12/IS!E12-1 -> -0.035643832 | G12: =CHOOSE(MATCH(Scenario,{"Bear","Base","Bull"},0),$B$69,$C$69,$D$69) -> 0.02 | H12: =CHOOSE(MATCH(Scenario,{"Bear","Base","Bull"},0),$B$69,$C$69,$D$69) -> 0.02 | I12: =CHOOSE(MATCH(Scenario,{"Bear","Base","Bull"},0),$B$69,$C$69,$D$69) -> 0.02 | J12: =CHOOSE(MATCH(Scenario,{"Bear","Base","Bull"},0),$B$69,$C$69,$D$69) -> 0.02
A13: Services revenue YoY growth | B13: ="" | C13: =IS!C13/IS!B13-1 -> 0.14181951 | D13: =IS!D13/IS!C13-1 -> 0.090504166 | E13: =IS!E13/IS!D13-1 -> 0.12874413 | F13: =IS!F13/IS!E13-1 -> 0.13506431 | G13: =CHOOSE(MATCH(Scenario,{"Bear","Base","Bull"},0),$B$70,$C$70,$D$70) -> 0.105 | H13: =CHOOSE(MATCH(Scenario,{"Bear","Base","Bull"},0),$B$70,$C$70,$D$70) -> 0.105 | I13: =CHOOSE(MATCH(Scenario,{"Bear","Base","Bull"},0),$B$70,$C$70,$D$70) -> 0.105 | J13: =CHOOSE(MATCH(Scenario,{"Bear","Base","Bull"},0),$B$70,$C$70,$D$70) -> 0.105
A15: MARGIN DRIVERS | Segment-Level Gross Margins
A16: Products gross margin % | B16: =(IS!B8-IS!B19)/IS!B8 -> 0.35349303 | C16: =(IS!C8-IS!C19)/IS!C8 -> 0.3628348 | D16: =(IS!D8-IS!D19)/IS!D8 -> 0.36500663 | E16: =(IS!E8-IS!E19)/IS!E8 -> 0.37180618 | F16: =(IS!F8-IS!F19)/IS!F8 -> 0.3677065 | G16: =CHOOSE(MATCH(Scenario,{"Bear","Base","Bull"},0),$B$71,$C$71,$D$71) -> 0.37 | H16: =CHOOSE(MATCH(Scenario,{"Bear","Base","Bull"},0),$B$71,$C$71,$D$71) -> 0.37 | I16: =CHOOSE(MATCH(Scenario,{"Bear","Base","Bull"},0),$B$71,$C$71,$D$71) -> 0.37 | J16: =CHOOSE(MATCH(Scenario,{"Bear","Base","Bull"},0),$B$71,$C$71,$D$71) -> 0.37
A17: Services gross margin % | B17: =(IS!B13-IS!B20)/IS!B13 -> 0.69725977 | C17: =(IS!C13-IS!C20)/IS!C13 -> 0.71745447 | D17: =(IS!D13-IS!D20)/IS!D13 -> 0.70827465 | E17: =(IS!E13-IS!E20)/IS!E13 -> 0.73880356 | F17: =(IS!F13-IS!F20)/IS!F13 -> 0.75408124 | G17: =CHOOSE(MATCH(Scenario,{"Bear","Base","Bull"},0),$B$72,$C$72,$D$72) -> 0.76 | H17: =CHOOSE(MATCH(Scenario,{"Bear","Base","Bull"},0),$B$72,$C$72,$D$72) -> 0.76 | I17: =CHOOSE(MATCH(Scenario,{"Bear","Base","Bull"},0),$B$72,$C$72,$D$72) -> 0.76 | J17: =CHOOSE(MATCH(Scenario,{"Bear","Base","Bull"},0),$B$72,$C$72,$D$72) -> 0.76
A19: OPERATING EXPENSE DRIVERS | R&D + SG&A YoY Growth
A20: R&D expense YoY growth | B20: ="" | C20: =IS!C26/IS!B26-1 -> 0.19791001 | D20: =IS!D26/IS!C26-1 -> 0.13957564 | E20: =IS!E26/IS!D26-1 -> 0.048637807 | F20: =IS!F26/IS!E26-1 -> 0.10137074 | G20: =CHOOSE(MATCH(Scenario,{"Bear","Base","Bull"},0),$B$73,$C$73,$D$73) -> 0.075 | H20: =CHOOSE(MATCH(Scenario,{"Bear","Base","Bull"},0),$B$73,$C$73,$D$73) -> 0.075 | I20: =CHOOSE(MATCH(Scenario,{"Bear","Base","Bull"},0),$B$73,$C$73,$D$73) -> 0.075 | J20: =CHOOSE(MATCH(Scenario,{"Bear","Base","Bull"},0),$B$73,$C$73,$D$73) -> 0.075
A21: SG&A expense YoY growth | B21: ="" | C21: =IS!C27/IS!B27-1 -> 0.14203796 | D21: =IS!D27/IS!C27-1 -> -0.0064557265 | E21: =IS!E27/IS!D27-1 -> 0.046727098 | F21: =IS!F27/IS!E27-1 -> 0.057631145 | G21: =CHOOSE(MATCH(Scenario,{"Bear","Base","Bull"},0),$B$74,$C$74,$D$74) -> 0.045 | H21: =CHOOSE(MATCH(Scenario,{"Bear","Base","Bull"},0),$B$74,$C$74,$D$74) -> 0.045 | I21: =CHOOSE(MATCH(Scenario,{"Bear","Base","Bull"},0),$B$74,$C$74,$D$74) -> 0.045 | J21: =CHOOSE(MATCH(Scenario,{"Bear","Base","Bull"},0),$B$74,$C$74,$D$74) -> 0.045
A23: OTHER INCOME STATEMENT DRIVERS
A24: Other income / (expense), $M | B24: =IS!B35 -> 258 | C24: =IS!C35 -> -334 | D24: =IS!D35 -> -565 | E24: =IS!E35 -> 269 | F24: =IS!F35 -> -321 | G24: =CHOOSE(MATCH(Scenario,{"Bear","Base","Bull"},0),$B$83,$C$83,$D$83) -> 0 | H24: =CHOOSE(MATCH(Scenario,{"Bear","Base","Bull"},0),$B$83,$C$83,$D$83) -> 0 | I24: =CHOOSE(MATCH(Scenario,{"Bear","Base","Bull"},0),$B$83,$C$83,$D$83) -> 0 | J24: =CHOOSE(MATCH(Scenario,{"Bear","Base","Bull"},0),$B$83,$C$83,$D$83) -> 0
A25: Effective tax rate | B25: =IS!B37/IS!B36 -> 0.13302261 | C25: =IS!C37/IS!C36 -> 0.16204462 | D25: =IS!D37/IS!D36 -> 0.14719174 | E25: =IS!E37/IS!E36 -> 0.24091185 | F25: =IS!F37/IS!F36 -> 0.15610002 | G25: =CHOOSE(MATCH(Scenario,{"Bear","Base","Bull"},0),$B$75,$C$75,$D$75) -> 0.15 | H25: =CHOOSE(MATCH(Scenario,{"Bear","Base","Bull"},0),$B$75,$C$75,$D$75) -> 0.15 | I25: =CHOOSE(MATCH(Scenario,{"Bear","Base","Bull"},0),$B$75,$C$75,$D$75) -> 0.15 | J25: =CHOOSE(MATCH(Scenario,{"Bear","Base","Bull"},0),$B$75,$C$75,$D$75) -> 0.15
A27: BALANCE SHEET DRIVERS | Working Capital Days
A28: Days sales outstanding (DSO) | B28: =BS!C7/IS!B14*365 -> 26.219312 | C28: =BS!D7/IS!C14*365 -> 26.087825 | D28: =BS!E7/IS!D14*365 -> 28.100291 | E28: =BS!F7/IS!E14*365 -> 31.185572 | F28: =BS!G7/IS!F14*365 -> 34.886991 | G28: 30 | H28: 30 | I28: 30 | J28: 30
A29: Days inventory outstanding (DIO) | B29: =BS!C8/IS!B21*365 -> 11.276593 | C29: =BS!D8/IS!C21*365 -> 8.0756981 | D29: =BS!E8/IS!D21*365 -> 10.791292 | E29: =BS!F8/IS!E21*365 -> 12.642571 | F29: =BS!G8/IS!F21*365 -> 9.4454652 | G29: 10 | H29: 10 | I29: 10 | J29: 10
A30: Days payable outstanding (DPO) | B30: =BS!C21/IS!B21*365 -> 93.851071 | C30: =BS!D21/IS!C21*365 -> 104.68528 | D30: =BS!E21/IS!D21*365 -> 106.72147 | E30: =BS!F21/IS!E21*365 -> 119.65848 | F30: =BS!G21/IS!F21*365 -> 115.40052 | G30: 115 | H30: 115 | I30: 115 | J30: 115
A32: Share-based compensation as % of revenue | B32: =CFS!B12/IS!B14 -> 0.021611899 | C32: =CFS!C12/IS!C14 -> 0.022920006 | D32: =CFS!D12/IS!D14 -> 0.028263564 | E32: =CFS!E12/IS!E14 -> 0.029889908 | F32: =CFS!F12/IS!F14 -> 0.030908711 | G32: 0.031 | H32: 0.031 | I32: 0.031 | J32: 0.031
A33: Other current liabilities as % of revenue | B33: =BS!C22/IS!B14 -> 0.12982721 | C33: =BS!D22/IS!C14 -> 0.15430048 | D33: =BS!E22/IS!D14 -> 0.15348631 | E33: =BS!F22/IS!E14 -> 0.20024806 | F33: =BS!G22/IS!F14 -> 0.1595224 | G33: 0.17 | H33: 0.17 | I33: 0.17 | J33: 0.17
A34: Deferred revenue as % of services revenue | B34: =BS!C23/IS!B13 -> 0.11124589 | C34: =BS!D23/IS!C13 -> 0.10126842 | D34: =BS!E23/IS!D13 -> 0.094612676 | E34: =BS!F23/IS!E13 -> 0.085776082 | F34: =BS!G23/IS!F13 -> 0.08295315 | G34: 0.078 | H34: 0.078 | I34: 0.078 | J34: 0.078
A35: Vendor non-trade receivables as % of COGS | B35: =BS!C9/IS!B21 -> 0.11845188 | C35: =BS!D9/IS!C21 -> 0.14649334 | D35: =BS!E9/IS!D21 -> 0.14699468 | E35: =BS!F9/IS!E21 -> 0.15608599 | F35: =BS!G9/IS!F21 -> 0.15016293 | G35: 0.135 | H35: 0.135 | I35: 0.135 | J35: 0.135
A36: CAPEX & DEPRECIATION DRIVERS
A37: CapEx as % of revenue | B37: =-CFS!B19/IS!B14 -> 0.030302036 | C37: =-CFS!C19/IS!C14 -> 0.027155059 | D37: =-CFS!D19/IS!D14 -> 0.028592301 | E37: =-CFS!E19/IS!E14 -> 0.024158963 | F37: =-CFS!F19/IS!F14 -> 0.030553079 | G37: =CHOOSE(MATCH(Scenario,{"Bear","Base","Bull"},0),$B$76,$C$76,$D$76) -> 0.028 | H37: =CHOOSE(MATCH(Scenario,{"Bear","Base","Bull"},0),$B$76,$C$76,$D$76) -> 0.028 | I37: =CHOOSE(MATCH(Scenario,{"Bear","Base","Bull"},0),$B$76,$C$76,$D$76) -> 0.028 | J37: =CHOOSE(MATCH(Scenario,{"Bear","Base","Bull"},0),$B$76,$C$76,$D$76) -> 0.028
A38: Depreciation & amortization, $M | B38: =CFS!B10 -> 11284 | C38: =CFS!C10 -> 11104 | D38: =CFS!D10 -> 11519 | E38: =CFS!E10 -> 11445 | F38: =CFS!F10 -> 11698 | G38: =CHOOSE(MATCH(Scenario,{"Bear","Base","Bull"},0),$B$84,$C$84,$D$84)*IS!H14 -> 12232.353 | H38: =CHOOSE(MATCH(Scenario,{"Bear","Base","Bull"},0),$B$84,$C$84,$D$84)*IS!I14 -> 12854.25 | I38: =CHOOSE(MATCH(Scenario,{"Bear","Base","Bull"},0),$B$84,$C$84,$D$84)*IS!J14 -> 13522.027 | J38: =CHOOSE(MATCH(Scenario,{"Bear","Base","Bull"},0),$B$84,$C$84,$D$84)*IS!K14 -> 14239.896
A40: CAPITAL RETURN POLICY | Per Apple's Stated Plan
A41: Capital return as % of FCF | B41: =(-CFS!B24-CFS!B25)/CFS!B21 -> 1.0805246 | C41: =(-CFS!C24-CFS!C25)/CFS!C21 -> 0.93539298 | D41: =(-CFS!D24-CFS!D25)/CFS!D21 -> 0.92961721 | E41: =(-CFS!E24-CFS!E25)/CFS!E21 -> 1.0126462 | F41: =(-CFS!F24-CFS!F25)/CFS!F21 -> 1.0745694 | G41: =CHOOSE(MATCH(Scenario,{"Bear","Base","Bull"},0),$B$81,$C$81,$D$81) -> 0.95 | H41: =CHOOSE(MATCH(Scenario,{"Bear","Base","Bull"},0),$B$81,$C$81,$D$81) -> 0.95 | I41: =CHOOSE(MATCH(Scenario,{"Bear","Base","Bull"},0),$B$81,$C$81,$D$81) -> 0.95 | J41: =CHOOSE(MATCH(Scenario,{"Bear","Base","Bull"},0),$B$81,$C$81,$D$81) -> 0.95 | N41: Buybacks retire shares at the Assumptions!B59 price in every forecast year (a simplification)
A42: Dividends as % of capital return | B42: =-CFS!B24/(-CFS!B24-CFS!B25) -> 0.14403911 | C42: =-CFS!C24/(-CFS!C24-CFS!C25) -> 0.14236927 | D42: =-CFS!D24/(-CFS!D24-CFS!D25) -> 0.16230084 | E42: =-CFS!E24/(-CFS!E24-CFS!E25) -> 0.13826089 | F42: =-CFS!F24/(-CFS!F24-CFS!F25) -> 0.14530019 | G42: =CHOOSE(MATCH(Scenario,{"Bear","Base","Bull"},0),$B$82,$C$82,$D$82) -> 0.15 | H42: =CHOOSE(MATCH(Scenario,{"Bear","Base","Bull"},0),$B$82,$C$82,$D$82) -> 0.15 | I42: =CHOOSE(MATCH(Scenario,{"Bear","Base","Bull"},0),$B$82,$C$82,$D$82) -> 0.15 | J42: =CHOOSE(MATCH(Scenario,{"Bear","Base","Bull"},0),$B$82,$C$82,$D$82) -> 0.15
A44: WACC & DCF VALUATION INPUTS
A45: Risk-free rate | B45: =CHOOSE(MATCH(Scenario,{"Bear","Base","Bull"},0),$B$79,$C$79,$D$79) -> 0.045
A46: Equity risk premium | B46: =CHOOSE(MATCH(Scenario,{"Bear","Base","Bull"},0),$B$80,$C$80,$D$80) -> 0.05
A47: Beta (Apple) | B47: =CHOOSE(MATCH(Scenario,{"Bear","Base","Bull"},0),$B$77,$C$77,$D$77) -> 1.1
A48: Cost of equity | B48: =B45+B47*B46 -> 0.1
A49: Pre-tax cost of debt | B49: 0.04
A50: Tax rate (for WACC) | B50: =G25 -> 0.15
A51: After-tax cost of debt | B51: =B49*(1-B50) -> 0.034
A52: Target debt / capital | B52: 0.1
A53: Target equity / capital | B53: =1-B52 -> 0.9
A54: WACC | B54: =B48*B53+B51*B52 -> 0.0934
A55: Terminal growth rate (g) | B55: =CHOOSE(MATCH(Scenario,{"Bear","Base","Bull"},0),$B$78,$C$78,$D$78) -> 0.025
A57: VALUATION INPUTS
A58: Diluted shares outstanding (M) | B58: 15004.7
A59: Current share price (USD) | B59: 338.4 | C59: Close on 28 Sep 2026 (Excel STOCKHISTORY)
A60: Valuation date | B60: =DATE(2026,9,28) -> 46293 | C60: Date of the B59 close. FY2026 ended 26 Sep 2026, before this date, so FY26E cash sits in net cash.
A61: SCENARIO ENGINE | Forecast Case Toggle
A62: Active scenario → | B62: Base | C62: ← Change this dropdown. All FY26–FY29 drivers update; IS/BS/CFS/DCF/Dashboard re-flow.
A64: Driver | B64: Bear | C64: Base | D64: Bull | E64: Unit | F64: Notes
A65: Products revenue growth (avg) | B65: =(IS!$F$9*(1+B66)+IS!$F$10*(1+B67)+IS!$F$11*(1+B68)+IS!$F$12*(1+B69))/IS!$F$8-1 -> -0.0042792416 | C65: =(IS!$F$9*(1+C66)+IS!$F$10*(1+C67)+IS!$F$11*(1+C68)+IS!$F$12*(1+C69))/IS!$F$8-1 -> 0.030120748 | D65: =(IS!$F$9*(1+D66)+IS!$F$10*(1+D67)+IS!$F$11*(1+D68)+IS!$F$12*(1+D69))/IS!$F$8-1 -> 0.061283147 | E65: % | F65: Applied to G8:J8
A66: iPhone YoY growth | B66: 0 | C66: 0.03 | D66: 0.06 | E66: %
A67: Mac YoY growth | B67: 0.02 | C67: 0.05 | D67: 0.08 | E67: %
A68: iPad YoY growth | B68: -0.02 | C68: 0.02 | D68: 0.05 | E68: %
A69: Wearables YoY growth | B69: -0.04 | C69: 0.02 | D69: 0.06 | E69: %
A70: Services revenue growth (avg) | B70: 0.06 | C70: 0.105 | D70: 0.14 | E70: % | F70: Applied to G13:J13
A71: Products gross margin (avg) | B71: 0.36 | C71: 0.37 | D71: 0.405 | E71: % | F71: Applied to G16:J16. Base 37.0% = FY24-FY25 average (37.2%, 36.8%)
A72: Services gross margin (avg) | B72: 0.74 | C72: 0.76 | D72: 0.78 | E72: % | F72: Applied to G17:J17. Base 76% sits just above FY25's 75.4% on a trend rising about 1.4 pts a year since FY21
A73: R&D expense growth | B73: 0.1 | C73: 0.075 | D73: 0.05 | E73: % | F73: Applied to G20:J20 (Bear = higher spend)
A74: SG&A expense growth | B74: 0.07 | C74: 0.045 | D74: 0.03 | E74: % | F74: Applied to G21:J21
A75: Effective tax rate | B75: 0.18 | C75: 0.15 | D75: 0.13 | E75: % | F75: Applied to G25:J25. Base 15% = FY21-FY25 average excluding FY24's one-off EU State Aid charge (14.9%), and matches the 15% in B50
A76: CapEx % of revenue | B76: 0.035 | C76: 0.028 | D76: 0.022 | E76: % | F76: Applied to G37:J37
A77: Beta | B77: 1.25 | C77: 1.1 | D77: 0.95 | E77: x | F77: Drives beta at B47
A78: Terminal growth rate (g) | B78: 0.02 | C78: 0.025 | D78: 0.03 | E78: % | F78: Drives terminal growth at B55
A79: Risk-free rate | B79: 0.05 | C79: 0.045 | D79: 0.04 | E79: % | F79: Drives risk-free rate at B45
A80: Equity risk premium | B80: 0.055 | C80: 0.05 | D80: 0.045 | E80: % | F80: Drives equity risk premium at B46
A81: Capital return as % of FCF | B81: 0.85 | C81: 0.95 | D81: 1.05 | E81: %
A82: Dividends as % of capital return | B82: 0.18 | C82: 0.15 | D82: 0.12 | E82: %
A83: Other income $M | B83: -500 | C83: 0 | D83: 500 | E83: $M
A84: D&A as % of revenue | B84: 0.032 | C84: 0.028 | D84: 0.025 | E84: %
A86: BS STRUCTURAL & DEBT SCHEDULE | Scenario-Flexed Inputs
A87: Driver | B87: FY26E Bear | C87: FY26E Base | D87: FY26E Bull | E87: FY27E Bear | F87: FY27E Base | G87: FY27E Bull | H87: FY28E Bear | I87: FY28E Base | J87: FY28E Bull | K87: FY29E Bear | L87: FY29E Base | M87: FY29E Bull | N87: Basis
A88: Short-term marketable securities, annual change | B88: 0 | N88: 0% holds short-term securities at the FY25 balance; long-term securities fund the minimum-cash rule (row 96)
A89: Other current assets, % of revenue | B89: =AVERAGE(BS!F10/IS!E14,BS!G10/IS!F14) -> 0.035791452 | N89: FY24 to FY25 average of the 10-K balance over revenue
A90: Other non-current assets, % of revenue | B90: =AVERAGE(BS!F16/IS!E14,BS!G16/IS!F14) -> 0.19628157 | N90: FY24 to FY25 average of the 10-K balance over revenue
A91: Commercial paper, annual change | B91: 0 | N91: 0% holds commercial paper at the FY25 balance
A92: Current portion of LT debt | B92: 2500 | C92: 2000 | D92: 1500 | E92: 500 | F92: 0 | G92: 0 | H92: 500 | I92: 0 | J92: 0 | K92: 500 | L92: 0 | M92: 0 | N92: Scenario inputs: scheduled repayment of the current portion of term debt
A93: Long-term debt | B93: 70000 | C93: 65000 | D93: 60000 | E93: 60000 | F93: 55000 | G93: 50000 | H93: 50000 | I93: 45000 | J93: 40000 | K93: 50000 | L93: 45000 | M93: 40000 | N93: Scenario inputs: long-term debt balance after scheduled maturities
A94: Other non-current liabilities, % of revenue | B94: =AVERAGE(BS!F30/IS!E14,BS!G30/IS!F14) -> 0.10859444 | N94: FY24 to FY25 average of the 10-K balance over revenue
A95: Accumulated other comprehensive income, annual change ($M) | B95: 0 | N95: Held at FY25: market-value movements are not forecast
A96: Minimum operating cash ($M) | B96: =MIN(BS!C5:G5) -> 23646 | N96: Lowest FY21 to FY25 year-end cash. Long-term securities are sold to keep forecast cash at or above it.
A97: P/E multiples, low / mid / high (football field) | B97: 22 | C97: 26 | D97: 30 | N97: Bracket Apple's trading range on forward earnings; applied to FY29E and discounted
A98: EV/EBITDA multiples, low / mid / high (football field) | B98: 16 | C98: 19 | D98: 22

Sheet IS
A1: INCOME STATEMENT | FY2021A – FY2029E
A2: Top-down build: segment revenue × segment GM → gross profit → OpEx → operating income → net income
A4: USD Millions | B4: FY2021A | C4: FY2022A | D4: FY2023A | E4: FY2024A | F4: FY2025A | G4: Q1 FY26A | H4: FY2026E | I4: FY2027E | J4: FY2028E | K4: FY2029E
B5: Sep 25, 2021 | C5: Sep 24, 2022 | D5: Sep 30, 2023 | E5: Sep 28, 2024 | F5: Sep 27, 2025 | G5: Dec 27, 2025 | H5: Sep 26, 2026 | I5: Sep 25, 2027 | J5: Sep 30, 2028 | K5: Sep 30, 2029
A7: REVENUE
A8: Products revenue | B8: =SUM(B9:B12) -> 297392 | C8: =SUM(C9:C12) -> 316199 | D8: =SUM(D9:D12) -> 298085 | E8: =SUM(E9:E12) -> 294866 | F8: =SUM(F9:F12) -> 307003 | G8: =SUM(G9:G12) -> 113743 | H8: =SUM(H9:H12) -> 316250.16 | I8: =SUM(I9:I12) -> 325795.7 | ... K8: =SUM(K9:K12) -> 345823.84
A9: iPhone | B9: 191973 | C9: 205489 | D9: 200583 | E9: 201183 | F9: 209586 | G9: 85269 | H9: =F9*(1+Assumptions!G9) -> 215873.58 | I9: =H9*(1+Assumptions!H9) -> 222349.79 | J9: =I9*(1+Assumptions!I9) -> 229020.28 | K9: =J9*(1+Assumptions!J9) -> 235890.89
A10: Mac | B10: 35190 | C10: 40177 | D10: 29357 | E10: 29984 | F10: 33708 | G10: 8386 | H10: =F10*(1+Assumptions!G10) -> 35393.4 | I10: =H10*(1+Assumptions!H10) -> 37163.07 | J10: =I10*(1+Assumptions!I10) -> 39021.224 | K10: =J10*(1+Assumptions!J10) -> 40972.285
A11: iPad | B11: 31862 | C11: 29292 | D11: 28300 | E11: 26694 | F11: 28023 | G11: 8595 | H11: =F11*(1+Assumptions!G11) -> 28583.46 | I11: =H11*(1+Assumptions!H11) -> 29155.129 | J11: =I11*(1+Assumptions!I11) -> 29738.232 | K11: =J11*(1+Assumptions!J11) -> 30332.996
A12: Wearables, Home & Accessories | B12: 38367 | C12: 41241 | D12: 39845 | E12: 37005 | F12: 35686 | G12: 11493 | H12: =F12*(1+Assumptions!G12) -> 36399.72 | I12: =H12*(1+Assumptions!H12) -> 37127.714 | J12: =I12*(1+Assumptions!I12) -> 37870.269 | K12: =J12*(1+Assumptions!J12) -> 38627.674
A13: Services net sales | B13: 68425 | C13: 78129 | D13: 85200 | E13: 96169 | F13: 109158 | G13: 30013 | H13: =F13*(1+Assumptions!G13) -> 120619.59 | I13: =H13*(1+Assumptions!H13) -> 133284.65 | J13: =I13*(1+Assumptions!I13) -> 147279.53 | K13: =J13*(1+Assumptions!J13) -> 162743.89
A14: Total revenue | B14: =SUM(B9:B13) -> 365817 | C14: =SUM(C9:C13) -> 394328 | D14: =SUM(D9:D13) -> 383285 | E14: =SUM(E9:E13) -> 391035 | F14: =SUM(F9:F13) -> 416161 | G14: =SUM(G9:G13) -> 143756 | H14: =SUM(H9:H13) -> 436869.75 | I14: =SUM(I9:I13) -> 459080.35 | ... K14: =SUM(K9:K13) -> 508567.73
A15: YoY Revenue Growth | B15: - | C15: =(C14-B14)/B14 -> 0.077937876 | D15: =(D14-C14)/C14 -> -0.028004605 | E15: =(E14-D14)/D14 -> 0.020219941 | F15: =(F14-E14)/E14 -> 0.064255118 | H15: =(H14-F14)/F14 -> 0.04976139 | I15: =(I14-H14)/H14 -> 0.05084032 | J15: =(J14-I14)/I14 -> 0.05194993 | K15: =(K14-J14)/J14 -> 0.053088885
A16: Services % of revenue | B16: =B13/B14 -> 0.18704708 | C16: =C13/C14 -> 0.19813201 | D16: =D13/D14 -> 0.2222889 | E16: =E13/E14 -> 0.24593451 | F16: =F13/F14 -> 0.26229752 | G16: =G13/G14 -> 0.20877737 | H16: =H13/H14 -> 0.27609966 | I16: =I13/I14 -> 0.29032967 | ... K16: =K13/K14 -> 0.32000435
A18: COST OF SALES
A19: Cost of products | B19: 192266 | C19: 201471 | D19: 189282 | E19: 185233 | F19: 194116 | G19: 67478 | H19: =H8*(1-Assumptions!G16) -> 199237.6 | I19: =I8*(1-Assumptions!H16) -> 205251.29 | J19: =J8*(1-Assumptions!I16) -> 211459.5 | K19: =K8*(1-Assumptions!J16) -> 217869.02
A20: Cost of services | B20: 20715 | C20: 22075 | D20: 24855 | E20: 25119 | F20: 26844 | G20: 7047 | H20: =H13*(1-Assumptions!G17) -> 28948.702 | I20: =I13*(1-Assumptions!H17) -> 31988.315 | J20: =J13*(1-Assumptions!I17) -> 35347.088 | K20: =K13*(1-Assumptions!J17) -> 39058.533
A21: Total cost of sales | B21: =SUM(B19:B20) -> 212981 | C21: =SUM(C19:C20) -> 223546 | D21: =SUM(D19:D20) -> 214137 | E21: =SUM(E19:E20) -> 210352 | F21: =SUM(F19:F20) -> 220960 | G21: =SUM(G19:G20) -> 74525 | H21: =SUM(H19:H20) -> 228186.3 | I21: =SUM(I19:I20) -> 237239.61 | ... K21: =SUM(K19:K20) -> 256927.55
A22: Gross profit | B22: =B14-B21 -> 152836 | C22: =C14-C21 -> 170782 | D22: =D14-D21 -> 169148 | E22: =E14-E21 -> 180683 | F22: =F14-F21 -> 195201 | G22: =G14-G21 -> 69231 | H22: =H14-H21 -> 208683.45 | I22: =I14-I21 -> 221840.74 | ... K22: =K14-K21 -> 251640.18
A23: Gross margin % | B23: =B22/B14 -> 0.4177936 | C23: =C22/C14 -> 0.43309631 | D23: =D22/D14 -> 0.4413113 | E23: =E22/E14 -> 0.4620635 | F23: =F22/F14 -> 0.46905164 | G23: =G22/G14 -> 0.48158686 | H23: =H22/H14 -> 0.47767887 | I23: =I22/I14 -> 0.48322857 | ... K23: =K22/K14 -> 0.4948017
A25: OPERATING EXPENSES
A26: Research & development | B26: 21914 | C26: 26251 | D26: 29915 | E26: 31370 | F26: 34550 | G26: 10887 | H26: =F26*(1+Assumptions!G20) -> 37141.25 | I26: =H26*(1+Assumptions!H20) -> 39926.844 | J26: =I26*(1+Assumptions!I20) -> 42921.357 | K26: =J26*(1+Assumptions!J20) -> 46140.459
A27: Selling, general & administrative | B27: 21973 | C27: 25094 | D27: 24932 | E27: 26097 | F27: 27601 | G27: 7492 | H27: =F27*(1+Assumptions!G21) -> 28843.045 | I27: =H27*(1+Assumptions!H21) -> 30140.982 | J27: =I27*(1+Assumptions!I21) -> 31497.326 | K27: =J27*(1+Assumptions!J21) -> 32914.706
A28: Total operating expenses | B28: =SUM(B26:B27) -> 43887 | C28: =SUM(C26:C27) -> 51345 | D28: =SUM(D26:D27) -> 54847 | E28: =SUM(E26:E27) -> 57467 | F28: =SUM(F26:F27) -> 62151 | G28: =SUM(G26:G27) -> 18379 | H28: =SUM(H26:H27) -> 65984.295 | I28: =SUM(I26:I27) -> 70067.826 | ... K28: =SUM(K26:K27) -> 79055.165
A29: Operating income | B29: =B22-B28 -> 108949 | C29: =C22-C28 -> 119437 | D29: =D22-D28 -> 114301 | E29: =E22-E28 -> 123216 | F29: =F22-F28 -> 133050 | G29: =G22-G28 -> 50852 | H29: =H22-H28 -> 142699.15 | I29: =I22-I28 -> 151772.92 | ... K29: =K22-K28 -> 172585.01
A30: Operating margin % | B30: =B29/B14 -> 0.29782378 | C30: =C29/C14 -> 0.30288744 | D30: =D29/D14 -> 0.29821412 | E30: =E29/E14 -> 0.31510223 | F30: =F29/F14 -> 0.319708 | G30: =G29/G14 -> 0.35373828 | H30: =H29/H14 -> 0.32664004 | I30: =I29/I14 -> 0.33060207 | ... K30: =K29/K14 -> 0.33935502
A31: (+) Depreciation & Amortization | B31: 11284 | C31: 11104 | D31: 11519 | E31: 11445 | F31: 11698 | G31: 3214 | H31: =Assumptions!G38 -> 12232.353 | I31: =Assumptions!H38 -> 12854.25 | J31: =Assumptions!I38 -> 13522.027 | K31: =Assumptions!J38 -> 14239.896
A32: EBITDA | B32: =B29+B31 -> 120233 | C32: =C29+C31 -> 130541 | D32: =D29+D31 -> 125820 | E32: =E29+E31 -> 134661 | F32: =F29+F31 -> 144748 | G32: =G29+G31 -> 54066 | H32: =H29+H31 -> 154931.51 | I32: =I29+I31 -> 164627.17 | ... K32: =K29+K31 -> 186824.91
A33: EBITDA Margin % | B33: =B32/B14 -> 0.3286698 | C33: =C32/C14 -> 0.33104674 | D33: =D32/D14 -> 0.32826748 | E33: =E32/E14 -> 0.34437071 | F33: =F32/F14 -> 0.34781731 | G33: =G32/G14 -> 0.37609561 | H33: =H32/H14 -> 0.35464004 | I33: =I32/I14 -> 0.35860207 | ... K33: =K32/K14 -> 0.36735502
A34: NON-OPERATING & TAXES
A35: Other income / (expense), net | B35: 258 | C35: -334 | D35: -565 | E35: 269 | F35: -321 | G35: 150 | H35: =Assumptions!G24 -> 0 | I35: =Assumptions!H24 -> 0 | J35: =Assumptions!I24 -> 0 | K35: =Assumptions!J24 -> 0
A36: Pre-tax income | B36: =B29+B35 -> 109207 | C36: =C29+C35 -> 119103 | D36: =D29+D35 -> 113736 | E36: =E29+E35 -> 123485 | F36: =F29+F35 -> 132729 | G36: =G29+G35 -> 51002 | H36: =H29+H35 -> 142699.15 | I36: =I29+I35 -> 151772.92 | ... K36: =K29+K35 -> 172585.01
A37: Income tax expense | B37: 14527 | C37: 19300 | D37: 16741 | E37: 29749 | F37: 20719 | G37: 8905 | H37: =H36*Assumptions!G25 -> 21404.873 | I37: =I36*Assumptions!H25 -> 22765.937 | J37: =J36*Assumptions!I25 -> 24255.64 | K37: =K36*Assumptions!J25 -> 25887.752
A38: Effective tax rate | B38: =B37/B36 -> 0.13302261 | C38: =C37/C36 -> 0.16204462 | D38: =D37/D36 -> 0.14719174 | E38: =E37/E36 -> 0.24091185 | F38: =F37/F36 -> 0.15610002 | G38: =G37/G36 -> 0.174601 | H38: =H37/H36 -> 0.15 | I38: =I37/I36 -> 0.15 | ... K38: =K37/K36 -> 0.15
A39: NET INCOME | B39: =B36-B37 -> 94680 | C39: =C36-C37 -> 99803 | D39: =D36-D37 -> 96995 | E39: =E36-E37 -> 93736 | F39: =F36-F37 -> 112010 | G39: =G36-G37 -> 42097 | H39: =H36-H37 -> 121294.28 | I39: =I36-I37 -> 129006.98 | ... K39: =K36-K37 -> 146697.26
A40: Net margin % | B40: =B39/B14 -> 0.25881793 | C40: =C39/C14 -> 0.25309641 | D40: =D39/D14 -> 0.25306234 | E40: =E39/E14 -> 0.23971256 | F40: =F39/F14 -> 0.26915064 | G40: =G39/G14 -> 0.29283647 | H40: =H39/H14 -> 0.27764403 | I40: =I39/I14 -> 0.28101176 | ... K40: =K39/K14 -> 0.28845176
A42: PER SHARE DATA
A43: Basic EPS ($) | B43: 5.67 | C43: 6.15 | D43: 6.16 | E43: 6.11 | F43: 7.5 | G43: 2.85 | H43: =H39/H45 -> 8.2866058 | I43: =I39/I45 -> 9.0266273 | J43: =J39/J45 -> 9.8713057 | K43: =K39/K45 -> 10.840767
A44: Diluted EPS ($) | B44: 5.61 | C44: 6.11 | D44: 6.13 | E44: 6.08 | F44: 7.46 | G44: 2.84 | H44: =H39/H45 -> 8.2866058 | I44: =I39/I45 -> 9.0266273 | J44: =J39/J45 -> 9.8713057 | K44: =K39/K45 -> 10.840767
A45: Diluted shares outstanding (M) | B45: 16864 | C45: 16326 | D45: 15813 | E45: 15409 | F45: 15004 | G45: 14810 | H45: =F45+CFS!G25/Assumptions!$B$59 -> 14637.39 | I45: =H45+CFS!H25/Assumptions!$B$59 -> 14291.825 | J45: =I45+CFS!I25/Assumptions!$B$59 -> 13924.057 | K45: =J45+CFS!J25/Assumptions!$B$59 -> 13532
A46: Dividend per share ($) | B46: 0.85 | C46: 0.91 | D46: 0.95 | E46: 0.99 | F46: 1.06 | H46: =-CFS!G24/H45 -> 1.4956966 | I46: =-CFS!H24/I45 -> 1.4439246 | J46: =-CFS!I24/J45 -> 1.5772869 | K46: =-CFS!J24/K45 -> 1.7301738
A52: GROSS MARGIN DETAIL | By Segment
A54: Products gross profit | B54: =B8-B19 -> 105126 | C54: =C8-C19 -> 114728 | D54: =D8-D19 -> 108803 | E54: =E8-E19 -> 109633 | F54: =F8-F19 -> 112887 | G54: =G8-G19 -> 46265 | H54: =H8-H19 -> 117012.56 | I54: =I8-I19 -> 120544.41 | ... K54: =K8-K19 -> 127954.82
A55: Products gross margin % | B55: =B54/B8 -> 0.35349303 | C55: =C54/C8 -> 0.3628348 | D55: =D54/D8 -> 0.36500663 | E55: =E54/E8 -> 0.37180618 | F55: =F54/F8 -> 0.3677065 | G55: =G54/G8 -> 0.40675031 | H55: =H54/H8 -> 0.37 | I55: =I54/I8 -> 0.37 | ... K55: =K54/K8 -> 0.37
A56: Services gross profit | B56: =B13-B20 -> 47710 | C56: =C13-C20 -> 56054 | D56: =D13-D20 -> 60345 | E56: =E13-E20 -> 71050 | F56: =F13-F20 -> 82314 | G56: =G13-G20 -> 22966 | H56: =H13-H20 -> 91670.888 | I56: =I13-I20 -> 101296.33 | ... K56: =K13-K20 -> 123685.35
A57: Services gross margin % | B57: =B56/B13 -> 0.69725977 | C57: =C56/C13 -> 0.71745447 | D57: =D56/D13 -> 0.70827465 | E57: =E56/E13 -> 0.73880356 | F57: =F56/F13 -> 0.75408124 | G57: =G56/G13 -> 0.76520175 | H57: =H56/H13 -> 0.76 | I57: =I56/I13 -> 0.76 | ... K57: =K56/K13 -> 0.76
A58: Total gross profit | B58: =B54+B56 -> 152836 | C58: =C54+C56 -> 170782 | D58: =D54+D56 -> 169148 | E58: =E54+E56 -> 180683 | F58: =F54+F56 -> 195201 | G58: =G54+G56 -> 69231 | H58: =H54+H56 -> 208683.45 | I58: =I54+I56 -> 221840.74 | ... K58: =K54+K56 -> 251640.18
A59: Blended gross margin % | B59: =B58/B14 -> 0.4177936 | C59: =C58/C14 -> 0.43309631 | D59: =D58/D14 -> 0.4413113 | E59: =E58/E14 -> 0.4620635 | F59: =F58/F14 -> 0.46905164 | G59: =G58/G14 -> 0.48158686 | H59: =H58/H14 -> 0.47767887 | I59: =I58/I14 -> 0.48322857 | ... K59: =K58/K14 -> 0.4948017
A61: Source: Apple 10-K (FY22 + FY25). Geographic + product splits per SEC EDGAR filings. Forecast growth rates (column L) are editable inputs (blue): change to flex the model.
A64: REVENUE BY GEOGRAPHIC SEGMENT | M64: Fcst growth
A66: Americas | B66: 153306 | C66: 169658 | D66: 162560 | E66: 167045 | F66: 178353 | G66: 58529 | H66: =$F66*(1+$M66)*IS!H$14/($F66*(1+$M66)+$F67*(1+$M67)+$F68*(1+$M68)+$F69*(1+$M69)+$F70*(1+$M70)) -> 187912.11 | I66: =H66*(1+$M66)*IS!I$14/(H66*(1+$M66)+H67*(1+$M67)+H68*(1+$M68)+H69*(1+$M69)+H70*(1+$M70)) -> 198053.16 | J66: =I66*(1+$M66)*IS!J$14/(I66*(1+$M66)+I67*(1+$M67)+I68*(1+$M68)+I69*(1+$M69)+I70*(1+$M70)) -> 208827.05 | K66: =J66*(1+$M66)*IS!K$14/(J66*(1+$M66)+J67*(1+$M67)+J68*(1+$M68)+J69*(1+$M69)+J70*(1+$M70)) -> 220289.67 | M66: 0.045
A67: Europe | B67: 89307 | C67: 95118 | D67: 94294 | E67: 101328 | F67: 111032 | G67: 38146 | H67: =$F67*(1+$M67)*IS!H$14/($F66*(1+$M66)+$F67*(1+$M67)+$F68*(1+$M68)+$F69*(1+$M69)+$F70*(1+$M70)) -> 118662.12 | I67: =H67*(1+$M67)*IS!I$14/(H66*(1+$M66)+H67*(1+$M67)+H68*(1+$M68)+H69*(1+$M69)+H70*(1+$M70)) -> 126861.16 | J67: =I67*(1+$M67)*IS!J$14/(I66*(1+$M66)+I67*(1+$M67)+I68*(1+$M68)+I69*(1+$M69)+I70*(1+$M70)) -> 135682.31 | K67: =J67*(1+$M67)*IS!K$14/(J66*(1+$M66)+J67*(1+$M67)+J68*(1+$M68)+J69*(1+$M69)+J70*(1+$M70)) -> 145184.47 | M67: 0.06
A68: Greater China | B68: 68366 | C68: 74200 | D68: 72559 | E68: 66952 | F68: 64377 | G68: 25526 | H68: =$F68*(1+$M68)*IS!H$14/($F66*(1+$M66)+$F67*(1+$M67)+$F68*(1+$M68)+$F69*(1+$M69)+$F70*(1+$M70)) -> 63608.46 | I68: =H68*(1+$M68)*IS!I$14/(H66*(1+$M66)+H67*(1+$M67)+H68*(1+$M68)+H69*(1+$M69)+H70*(1+$M70)) -> 62871.187 | J68: =I68*(1+$M68)*IS!J$14/(I66*(1+$M66)+I67*(1+$M67)+I68*(1+$M68)+I69*(1+$M69)+I70*(1+$M70)) -> 62167.932 | K68: =J68*(1+$M68)*IS!K$14/(J66*(1+$M66)+J67*(1+$M67)+J68*(1+$M68)+J69*(1+$M69)+J70*(1+$M70)) -> 61501.2 | M68: -0.02
A69: Japan | B69: 28482 | C69: 25977 | D69: 24257 | E69: 25052 | F69: 28703 | G69: 9413 | H69: =$F69*(1+$M69)*IS!H$14/($F66*(1+$M66)+$F67*(1+$M67)+$F68*(1+$M68)+$F69*(1+$M69)+$F70*(1+$M70)) -> 30675.47 | I69: =H69*(1+$M69)*IS!I$14/(H66*(1+$M66)+H67*(1+$M67)+H68*(1+$M68)+H69*(1+$M69)+H70*(1+$M70)) -> 32795.012 | J69: =I69*(1+$M69)*IS!J$14/(I66*(1+$M66)+I67*(1+$M67)+I68*(1+$M68)+I69*(1+$M69)+I70*(1+$M70)) -> 35075.377 | K69: =J69*(1+$M69)*IS!K$14/(J66*(1+$M66)+J67*(1+$M67)+J68*(1+$M68)+J69*(1+$M69)+J70*(1+$M70)) -> 37531.792 | M69: 0.06
A70: Rest of Asia Pacific | B70: 26356 | C70: 29375 | D70: 29615 | E70: 30658 | F70: 33696 | G70: 12142 | H70: =$F70*(1+$M70)*IS!H$14/($F66*(1+$M66)+$F67*(1+$M67)+$F68*(1+$M68)+$F69*(1+$M69)+$F70*(1+$M70)) -> 36011.589 | I70: =H70*(1+$M70)*IS!I$14/(H66*(1+$M66)+H67*(1+$M67)+H68*(1+$M68)+H69*(1+$M69)+H70*(1+$M70)) -> 38499.834 | J70: =I70*(1+$M70)*IS!J$14/(I66*(1+$M66)+I67*(1+$M67)+I68*(1+$M68)+I69*(1+$M69)+I70*(1+$M70)) -> 41176.877 | K70: =J70*(1+$M70)*IS!K$14/(J66*(1+$M66)+J67*(1+$M67)+J68*(1+$M68)+J69*(1+$M69)+J70*(1+$M70)) -> 44060.595 | M70: 0.06
A71: Total revenue | B71: =SUM(B66:B70) -> 365817 | C71: =SUM(C66:C70) -> 394328 | D71: =SUM(D66:D70) -> 383285 | E71: =SUM(E66:E70) -> 391035 | F71: =SUM(F66:F70) -> 416161 | G71: =SUM(G66:G70) -> 143756 | H71: =SUM(H66:H70) -> 436869.75 | I71: =SUM(I66:I70) -> 459080.35 | ... K71: =SUM(K66:K70) -> 508567.73
A72: Check vs Total revenue (row 14) | B72: =B71-B14 -> 0 | C72: =C71-C14 -> 0 | D72: =D71-D14 -> 0 | E72: =E71-E14 -> 0 | F72: =F71-F14 -> 0 | G72: =G71-G14 -> 0 | H72: =H71-H14 -> 0 | I72: =I71-I14 -> 0 | ... K72: =K71-K14 -> 0
A74: % of total revenue
A75: Americas | B75: =B66/B71 -> 0.41907839 | C75: =C66/C71 -> 0.43024589 | D75: =D66/D71 -> 0.42412304 | E75: =E66/E71 -> 0.42718682 | F75: =F66/F71 -> 0.42856731 | G75: =G66/G71 -> 0.40714127 | H75: =H66/H71 -> 0.43013304 | I75: =I66/I71 -> 0.43141284 | ... K75: =K66/K71 -> 0.43315699
A76: Europe | B76: =B67/B71 -> 0.24413026 | C76: =C67/C71 -> 0.24121543 | D76: =D67/D71 -> 0.24601537 | E76: =E67/E71 -> 0.2591277 | F76: =F67/F71 -> 0.26680059 | G76: =G67/G71 -> 0.2653524 | H76: =H67/H71 -> 0.27161899 | I76: =I67/I71 -> 0.27633759 | ... K76: =K67/K71 -> 0.28547716
A77: Greater China | B77: =B68/B71 -> 0.18688579 | C77: =C68/C71 -> 0.18816823 | D77: =D68/D71 -> 0.18930822 | E77: =E68/E71 -> 0.17121741 | F77: =F68/F71 -> 0.15469253 | G77: =G68/G71 -> 0.17756476 | H77: =H68/H71 -> 0.14560051 | I77: =I68/I71 -> 0.13695029 | ... K77: =K68/K71 -> 0.1209302
A78: Japan | B78: =B69/B71 -> 0.077858601 | C78: =C69/C71 -> 0.065876631 | D78: =D69/D71 -> 0.06328711 | E78: =E69/E71 -> 0.064065876 | F78: =F69/F71 -> 0.068970903 | G78: =G69/G71 -> 0.065479006 | H78: =H69/H71 -> 0.070216512 | I78: =I69/I71 -> 0.071436323 | ... K78: =K69/K71 -> 0.073799004
A79: Rest of Asia Pacific | B79: =B70/B71 -> 0.072046952 | C79: =C70/C71 -> 0.074493822 | D79: =D70/D71 -> 0.077266264 | E79: =E70/E71 -> 0.078402189 | F79: =F70/F71 -> 0.080968664 | G79: =G70/G71 -> 0.084462562 | H79: =H70/H71 -> 0.082430951 | I79: =I70/I71 -> 0.083862953 | ... K79: =K70/K71 -> 0.086636632
A81: Revenue YoY growth
A82: Americas | C82: =C66/B66-1 -> 0.10666249 | D82: =D66/C66-1 -> -0.041837108 | E82: =E66/D66-1 -> 0.027589813 | F82: =F66/E66-1 -> 0.067694334 | H82: =H66/F66-1 -> 0.053596595 | I82: =I66/H66-1 -> 0.053966958 | J82: =J66/I66-1 -> 0.054398977 | K82: =K66/J66-1 -> 0.054890503
A83: Europe | C83: =C67/B67-1 -> 0.065067688 | D83: =D67/C67-1 -> -0.0086629239 | E83: =E67/D67-1 -> 0.074596475 | F83: =F67/E67-1 -> 0.095768198 | H83: =H67/F67-1 -> 0.068719991 | I83: =I67/H67-1 -> 0.06909567 | J83: =J67/I67-1 -> 0.06953389 | K83: =K67/J67-1 -> 0.070032472
A84: Greater China | C84: =C68/B68-1 -> 0.085334816 | D84: =D68/C68-1 -> -0.022115903 | E84: =E68/D68-1 -> -0.077275045 | F84: =F68/E68-1 -> -0.03846039 | H84: =H68/F68-1 -> -0.011938121 | I84: =I68/H68-1 -> -0.011590796 | J84: =J68/I68-1 -> -0.011185649 | K84: =K68/J68-1 -> -0.010724696
A85: Japan | C85: =C69/B69-1 -> -0.087950284 | D85: =D69/C69-1 -> -0.066212419 | E85: =E69/D69-1 -> 0.032774045 | F85: =F69/E69-1 -> 0.14573687 | H85: =H69/F69-1 -> 0.068719991 | I85: =I69/H69-1 -> 0.06909567 | J85: =J69/I69-1 -> 0.06953389 | K85: =K69/J69-1 -> 0.070032472
A86: Rest of Asia Pacific | C86: =C70/B70-1 -> 0.11454697 | D86: =D70/C70-1 -> 0.0081702128 | E86: =E70/D70-1 -> 0.035218639 | F86: =F70/E70-1 -> 0.099093222 | H86: =H70/F70-1 -> 0.068719991 | I86: =I70/H70-1 -> 0.06909567 | J86: =J70/I70-1 -> 0.06953389 | K86: =K70/J70-1 -> 0.070032472

Sheet BS
B1: APPLE INC.: BALANCE SHEET (FY2021A-FY2029E)
B3: Line Item | C3: FY21A | D3: FY22A | E3: FY23A | F3: FY24A | G3: FY25A | H3: FY26E | I3: FY27E | J3: FY28E | K3: FY29E
B4: CURRENT ASSETS
B5: Cash & cash equivalents | C5: 34940 | D5: 23646 | E5: 29965 | F5: 29943 | G5: 35934 | H5: =CFS!G30 -> 23646 | I5: =CFS!H30 -> 23646 | J5: =CFS!I30 -> 23646 | K5: =CFS!J30 -> 31860.987
B6: Short-term marketable securities | C6: 27699 | D6: 24658 | E6: 31590 | F6: 35228 | G6: 18763 | H6: =G6*(1+Assumptions!$B$88) -> 18763 | I6: =H6*(1+Assumptions!$B$88) -> 18763 | J6: =I6*(1+Assumptions!$B$88) -> 18763 | K6: =J6*(1+Assumptions!$B$88) -> 18763
B7: Accounts receivable, net | C7: 26278 | D7: 28184 | E7: 29508 | F7: 33410 | G7: 39777 | H7: =Assumptions!G28*IS!H14/365 -> 35907.103 | I7: =Assumptions!H28*IS!I14/365 -> 37732.631 | J7: =Assumptions!I28*IS!J14/365 -> 39692.839 | K7: =Assumptions!J28*IS!K14/365 -> 41800.087
B8: Inventory | C8: 6580 | D8: 4946 | E8: 6331 | F8: 7286 | G8: 5718 | H8: =Assumptions!G29*IS!H21/365 -> 6251.6795 | I8: =Assumptions!H29*IS!I21/365 -> 6499.7153 | J8: =Assumptions!I29*IS!J21/365 -> 6761.8244 | K8: =Assumptions!J29*IS!K21/365 -> 7039.1111
B9: Vendor non-trade receivables | C9: 25228 | D9: 32748 | E9: 31477 | F9: 32833 | G9: 33180 | H9: =Assumptions!G35*IS!H21 -> 30805.151 | I9: =Assumptions!H35*IS!I21 -> 32027.347 | J9: =Assumptions!I35*IS!J21 -> 33318.89 | K9: =Assumptions!J35*IS!K21 -> 34685.22
B10: Other current assets | C10: 14111 | D10: 21223 | E10: 14695 | F10: 14287 | G10: 14585 | H10: =Assumptions!$B$89*IS!H14 -> 15636.203 | I10: =Assumptions!$B$89*IS!I14 -> 16431.152 | J10: =Assumptions!$B$89*IS!J14 -> 17284.749 | K10: =Assumptions!$B$89*IS!K14 -> 18202.377
B11: Total Current Assets | C11: =SUM(C5:C10) -> 134836 | D11: =SUM(D5:D10) -> 135405 | E11: =SUM(E5:E10) -> 143566 | F11: =SUM(F5:F10) -> 152987 | G11: =SUM(G5:G10) -> 147957 | H11: =SUM(H5:H10) -> 131009.14 | I11: =SUM(I5:I10) -> 135099.85 | J11: =SUM(J5:J10) -> 139467.3 | K11: =SUM(K5:K10) -> 152350.78
B13: NON-CURRENT ASSETS
B14: Property, plant & equipment, net | C14: 39440 | D14: 42117 | E14: 43715 | F14: 45680 | G14: 49834 | H14: =G14+Assumptions!G37*IS!H14-Assumptions!G38 -> 49834 | I14: =H14+Assumptions!H37*IS!I14-Assumptions!H38 -> 49834 | J14: =I14+Assumptions!I37*IS!J14-Assumptions!I38 -> 49834 | K14: =J14+Assumptions!J37*IS!K14-Assumptions!J38 -> 49834
B15: Long-term marketable securities | C15: 127877 | D15: 120805 | E15: 100544 | F15: 91479 | G15: 77723 | H15: =G15*(1+Assumptions!$B$88)-MAX(0,Assumptions!$B$96-(CFS!G7+CFS!G14+CFS!G19+CFS!G27)) -> 74014.788 | I15: =H15*(1+Assumptions!$B$88)-MAX(0,Assumptions!$B$96-(CFS!H7+CFS!H14+CFS!H19+CFS!H27)) -> 69255.601 | J15: =I15*(1+Assumptions!$B$88)-MAX(0,Assumptions!$B$96-(CFS!I7+CFS!I14+CFS!I19+CFS!I27)) -> 66961.647 | K15: =J15*(1+Assumptions!$B$88)-MAX(0,Assumptions!$B$96-(CFS!J7+CFS!J14+CFS!J19+CFS!J27)) -> 66961.647
B16: Other non-current assets | C16: 48849 | D16: 54428 | E16: 64758 | F16: 74834 | G16: 83727 | H16: =Assumptions!$B$90*IS!H14 -> 85749.48 | I16: =Assumptions!$B$90*IS!I14 -> 90109.011 | J16: =Assumptions!$B$90*IS!J14 -> 94790.167 | K16: =Assumptions!$B$90*IS!K14 -> 99822.472
B17: Total Non-Current Assets | C17: =SUM(C14:C16) -> 216166 | D17: =SUM(D14:D16) -> 217350 | E17: =SUM(E14:E16) -> 209017 | F17: =SUM(F14:F16) -> 211993 | G17: =SUM(G14:G16) -> 211284 | H17: =SUM(H14:H16) -> 209598.27 | I17: =SUM(I14:I16) -> 209198.61 | J17: =SUM(J14:J16) -> 211585.81 | K17: =SUM(K14:K16) -> 216618.12
B18: TOTAL ASSETS | C18: =C11+C17 -> 351002 | D18: =D11+D17 -> 352755 | E18: =E11+E17 -> 352583 | F18: =F11+F17 -> 364980 | G18: =G11+G17 -> 359241 | H18: =H11+H17 -> 340607.4 | I18: =I11+I17 -> 344298.46 | J18: =J11+J17 -> 351053.12 | K18: =K11+K17 -> 368968.9
B20: CURRENT LIABILITIES
B21: Accounts payable | C21: 54763 | D21: 64115 | E21: 62611 | F21: 68960 | G21: 69860 | H21: =Assumptions!G30*IS!H21/365 -> 71894.314 | I21: =Assumptions!H30*IS!I21/365 -> 74746.725 | J21: =Assumptions!I30*IS!J21/365 -> 77760.981 | K21: =Assumptions!J30*IS!K21/365 -> 80949.778
B22: Other current liabilities | C22: 47493 | D22: 60845 | E22: 58829 | F22: 78304 | G22: 66387 | H22: =Assumptions!G33*IS!H14 -> 74267.857 | I22: =Assumptions!H33*IS!I14 -> 78043.659 | J22: =Assumptions!I33*IS!J14 -> 82098.022 | K22: =Assumptions!J33*IS!K14 -> 86456.514
B23: Deferred revenue | C23: 7612 | D23: 7912 | E23: 8061 | F23: 8249 | G23: 9055 | H23: =Assumptions!G34*IS!H13 -> 9408.328 | I23: =Assumptions!H34*IS!I13 -> 10396.202 | J23: =Assumptions!I34*IS!J13 -> 11487.804 | K23: =Assumptions!J34*IS!K13 -> 12694.023
B24: Commercial paper | C24: 6000 | D24: 9982 | E24: 5985 | F24: 9967 | G24: 7979 | H24: =G24*(1+Assumptions!$B$91) -> 7979 | I24: =H24*(1+Assumptions!$B$91) -> 7979 | J24: =I24*(1+Assumptions!$B$91) -> 7979 | K24: =J24*(1+Assumptions!$B$91) -> 7979
B25: Current portion of LT debt | C25: 9613 | D25: 11128 | E25: 9822 | F25: 10912 | G25: 12350 | H25: =CHOOSE(MATCH(Scenario,{"Bear","Base","Bull"},0),Assumptions!$B$92,Assumptions!$C$92,Assumptions!$D$92) -> 2000 | I25: =CHOOSE(MATCH(Scenario,{"Bear","Base","Bull"},0),Assumptions!$E$92,Assumptions!$F$92,Assumptions!$G$92) -> 0 | J25: =CHOOSE(MATCH(Scenario,{"Bear","Base","Bull"},0),Assumptions!$H$92,Assumptions!$I$92,Assumptions!$J$92) -> 0 | K25: =CHOOSE(MATCH(Scenario,{"Bear","Base","Bull"},0),Assumptions!$K$92,Assumptions!$L$92,Assumptions!$M$92) -> 0
B26: Total Current Liabilities | C26: =SUM(C21:C25) -> 125481 | D26: =SUM(D21:D25) -> 153982 | E26: =SUM(E21:E25) -> 145308 | F26: =SUM(F21:F25) -> 176392 | G26: =SUM(G21:G25) -> 165631 | H26: =SUM(H21:H25) -> 165549.5 | I26: =SUM(I21:I25) -> 171165.59 | J26: =SUM(J21:J25) -> 179325.81 | K26: =SUM(K21:K25) -> 188079.31
B28: NON-CURRENT LIABILITIES
B29: Long-term debt | C29: 109106 | D29: 98959 | E29: 95281 | F29: 85750 | G29: 78328 | H29: =CHOOSE(MATCH(Scenario,{"Bear","Base","Bull"},0),Assumptions!$B$93,Assumptions!$C$93,Assumptions!$D$93) -> 65000 | I29: =CHOOSE(MATCH(Scenario,{"Bear","Base","Bull"},0),Assumptions!$E$93,Assumptions!$F$93,Assumptions!$G$93) -> 55000 | J29: =CHOOSE(MATCH(Scenario,{"Bear","Base","Bull"},0),Assumptions!$H$93,Assumptions!$I$93,Assumptions!$J$93) -> 45000 | K29: =CHOOSE(MATCH(Scenario,{"Bear","Base","Bull"},0),Assumptions!$K$93,Assumptions!$L$93,Assumptions!$M$93) -> 45000
B30: Other non-current liabilities | C30: 53325 | D30: 49142 | E30: 49848 | F30: 45888 | G30: 41549 | H30: =Assumptions!$B$94*IS!H14 -> 47441.624 | I30: =Assumptions!$B$94*IS!I14 -> 49853.572 | J30: =Assumptions!$B$94*IS!J14 -> 52443.461 | K30: =Assumptions!$B$94*IS!K14 -> 55227.626
B31: Total Non-Current Liabilities | C31: =SUM(C29:C30) -> 162431 | D31: =SUM(D29:D30) -> 148101 | E31: =SUM(E29:E30) -> 145129 | F31: =SUM(F29:F30) -> 131638 | G31: =SUM(G29:G30) -> 119877 | H31: =SUM(H29:H30) -> 112441.62 | I31: =SUM(I29:I30) -> 104853.57 | J31: =SUM(J29:J30) -> 97443.461 | K31: =SUM(K29:K30) -> 100227.63
B32: Total Liabilities | C32: =C26+C31 -> 287912 | D32: =D26+D31 -> 302083 | E32: =E26+E31 -> 290437 | F32: =F26+F31 -> 308030 | G32: =G26+G31 -> 285508 | H32: =H26+H31 -> 277991.12 | I32: =I26+I31 -> 276019.16 | J32: =J26+J31 -> 276769.27 | K32: =K26+K31 -> 288306.94
B34: SHAREHOLDERS' EQUITY
B35: Common stock & paid-in capital | C35: 57365 | D35: 64849 | E35: 73812 | F35: 83276 | G35: 93568 | H35: =G35+CFS!G12 -> 107110.96 | I35: =H35+CFS!H12 -> 121342.45 | J35: =I35+CFS!I12 -> 136313.27 | K35: =J35+CFS!J12 -> 152078.87
B36: Retained earnings | C36: 5562 | D36: -3068 | E36: -214 | F36: -19154 | G36: -14264 | H36: =G36+IS!H39+CFS!G24+CFS!G25 -> -38923.684 | I36: =H36+IS!I39+CFS!H24+CFS!H25 -> -47492.155 | J36: =I36+IS!J39+CFS!I24+CFS!I25 -> -56458.419 | K36: =J36+IS!K39+CFS!J24+CFS!J25 -> -65845.908
B37: Accumulated other comp. inc/(loss) | C37: 163 | D37: -11109 | E37: -11452 | F37: -7172 | G37: -5571 | H37: =G37+Assumptions!$B$95 -> -5571 | I37: =H37+Assumptions!$B$95 -> -5571 | J37: =I37+Assumptions!$B$95 -> -5571 | K37: =J37+Assumptions!$B$95 -> -5571
B38: Total Shareholders' Equity | C38: =SUM(C35:C37) -> 63090 | D38: =SUM(D35:D37) -> 50672 | E38: =SUM(E35:E37) -> 62146 | F38: =SUM(F35:F37) -> 56950 | G38: =SUM(G35:G37) -> 73733 | H38: =SUM(H35:H37) -> 62616.279 | I38: =SUM(I35:I37) -> 68279.298 | J38: =SUM(J35:J37) -> 74283.85 | K38: =SUM(K35:K37) -> 80661.961
B39: TOTAL LIABILITIES & EQUITY | C39: =C32+C38 -> 351002 | D39: =D32+D38 -> 352755 | E39: =E32+E38 -> 352583 | F39: =F32+F38 -> 364980 | G39: =G32+G38 -> 359241 | H39: =H32+H38 -> 340607.4 | I39: =I32+I38 -> 344298.46 | J39: =J32+J38 -> 351053.12 | K39: =K32+K38 -> 368968.9
B41: KEY METRICS
B42: Total Debt | C42: =C24+C25+C29 -> 124719 | D42: =D24+D25+D29 -> 120069 | E42: =E24+E25+E29 -> 111088 | F42: =F24+F25+F29 -> 106629 | G42: =G24+G25+G29 -> 98657 | H42: =H24+H25+H29 -> 74979 | I42: =I24+I25+I29 -> 62979 | J42: =J24+J25+J29 -> 52979 | K42: =K24+K25+K29 -> 52979
B43: Net Debt | C43: =C42-C5-C6-C15 -> -65797 | D43: =D42-D5-D6-D15 -> -49040 | E43: =E42-E5-E6-E15 -> -51011 | F43: =F42-F5-F6-F15 -> -50021 | G43: =G42-G5-G6-G15 -> -33763 | H43: =H42-H5-H6-H15 -> -41444.788 | I43: =I42-I5-I6-I15 -> -48685.601 | J43: =J42-J5-J6-J15 -> -56391.647 | K43: =K42-K5-K6-K15 -> -64606.634
B44: Working Capital | C44: =C11-C26 -> 9355 | D44: =D11-D26 -> -18577 | E44: =E11-E26 -> -1742 | F44: =F11-F26 -> -23405 | G44: =G11-G26 -> -17674 | H44: =H11-H26 -> -34540.364 | I44: =I11-I26 -> -36065.741 | J44: =J11-J26 -> -39858.504 | K44: =K11-K26 -> -35728.532
B45: Current Ratio | C45: =C11/C26 -> 1.0745531 | D45: =D11/D26 -> 0.87935603 | E45: =E11/E26 -> 0.98801167 | F45: =F11/F26 -> 0.86731258 | G45: =G11/G26 -> 0.89329292 | H45: =H11/H26 -> 0.7913593 | I45: =I11/I26 -> 0.78929327 | J45: =J11/J26 -> 0.77773136 | K45: =K11/K26 -> 0.81003476
B46: Quick Ratio | C46: =(C11-C8)/C26 -> 1.0221149 | D46: =(D11-D8)/D26 -> 0.84723539 | E46: =(E11-E8)/E26 -> 0.94444215 | F46: =(F11-F8)/F26 -> 0.82600685 | G46: =(G11-G8)/G26 -> 0.8587704 | H46: =(H11-H8)/H26 -> 0.75359609 | I46: =(I11-I8)/I26 -> 0.75132001 | J46: =(J11-J8)/J26 -> 0.74002443 | K46: =(K11-K8)/K26 -> 0.77260847
B47: Debt / Equity | C47: =C42/C38 -> 1.9768426 | D47: =D42/D38 -> 2.3695335 | E47: =E42/E38 -> 1.7875326 | F47: =F42/F38 -> 1.8723266 | G47: =G42/G38 -> 1.3380305 | H47: =H42/H38 -> 1.1974362 | I47: =I42/I38 -> 0.92237328 | J47: =J42/J38 -> 0.71319675 | K47: =K42/K38 -> 0.65680278

Sheet CFS
A1: CASH FLOW STATEMENT | FY2021A – FY2029E
A2: Indirect method | Reconciles net income to change in cash | Audit check: net change ties to BS
A4: USD Millions | B4: FY2021A | C4: FY2022A | D4: FY2023A | E4: FY2024A | F4: FY2025A | G4: FY2026E | H4: FY2027E | I4: FY2028E | J4: FY2029E
B5: Sep 25, 2021 | C5: Sep 24, 2022 | D5: Sep 30, 2023 | E5: Sep 28, 2024 | F5: Sep 27, 2025 | G5: Sep 26, 2026 | H5: Sep 25, 2027 | I5: Sep 30, 2028 | J5: Sep 30, 2029
A7: Cash & equivalents, beginning | B7: 39789 | C7: =B30 -> 35929 | D7: =C30 -> 24977 | E7: =D30 -> 30737 | F7: =E30 -> 29943 | G7: =F30 -> 35934 | H7: =G30 -> 23646 | I7: =H30 -> 23646 | J7: =I30 -> 23646
A9: OPERATING ACTIVITIES
A10: Depreciation & amortization | B10: =IS!B31 -> 11284 | C10: =IS!C31 -> 11104 | D10: =IS!D31 -> 11519 | E10: =IS!E31 -> 11445 | F10: =IS!F31 -> 11698 | G10: =Assumptions!G38 -> 12232.353 | H10: =Assumptions!H38 -> 12854.25 | I10: =Assumptions!I38 -> 13522.027 | J10: =Assumptions!J38 -> 14239.896
A11: Net income (from IS) | B11: =IS!B39 -> 94680 | C11: =IS!C39 -> 99803 | D11: =IS!D39 -> 96995 | E11: =IS!E39 -> 93736 | F11: =IS!F39 -> 112010 | G11: =IS!H39 -> 121294.28 | H11: =IS!I39 -> 129006.98 | I11: =IS!J39 -> 137448.63 | J11: =IS!K39 -> 146697.26
A12: Share-based compensation | B12: 7906 | C12: 9038 | D12: 10833 | E12: 11688 | F12: 12863 | G12: =Assumptions!G32*IS!H14 -> 13542.962 | H12: =Assumptions!H32*IS!I14 -> 14231.491 | I12: =Assumptions!I32*IS!J14 -> 14970.816 | J12: =Assumptions!J32*IS!K14 -> 15765.6
A13: Changes in working capital & other | B13: -9832 | C13: 2206 | D13: -8804 | E13: 1385 | F13: -25089 | G13: =-(BS!H7-BS!G7)-(BS!H8-BS!G8)-(BS!H9-BS!G9)-(BS!H10-BS!G10)+(BS!H21-BS!G21)+(BS!H22-BS!G22)+(BS!H23-BS!G23)-(BS!H16-BS!G16)+(BS!H30-BS!G30) -> 18798.509 | H13: =-(BS!I7-BS!H7)-(BS!I8-BS!H8)-(BS!I9-BS!H9)-(BS!I10-BS!H10)+(BS!I21-BS!H21)+(BS!I22-BS!H22)+(BS!I23-BS!H23)-(BS!I16-BS!H16)+(BS!I30-BS!H30) -> 1577.7935 | I13: =-(BS!J7-BS!I7)-(BS!J8-BS!I8)-(BS!J9-BS!I9)-(BS!J10-BS!I10)+(BS!J21-BS!I21)+(BS!J22-BS!I22)+(BS!J23-BS!I23)-(BS!J16-BS!I16)+(BS!J30-BS!I30) -> 1701.4952 | J13: =-(BS!K7-BS!J7)-(BS!K8-BS!J8)-(BS!K9-BS!J9)-(BS!K10-BS!J10)+(BS!K21-BS!J21)+(BS!K22-BS!J22)+(BS!K23-BS!J23)-(BS!K16-BS!J16)+(BS!K30-BS!J30) -> 1836.8757
A14: Cash from operating activities | B14: =B10+B11+B12+B13 -> 104038 | C14: =C10+C11+C12+C13 -> 122151 | D14: =D10+D11+D12+D13 -> 110543 | E14: =E10+E11+E12+E13 -> 118254 | F14: =F10+F11+F12+F13 -> 111482 | G14: =G10+G11+G12+G13 -> 165868.1 | H14: =H10+H11+H12+H13 -> 157670.51 | I14: =I10+I11+I12+I13 -> 167642.96 | J14: =J10+J11+J12+J13 -> 178539.63
A16: INVESTING ACTIVITIES
A17: Cash from investing activities | B17: =B19+B20 -> -14545 | C17: =C19+C20 -> -22354 | D17: =D19+D20 -> 3705 | E17: =E19+E20 -> 2935 | F17: =F19+F20 -> 15195 | G17: =G19+G20 -> -8524.1405 | H17: =H19+H20 -> -8095.0629 | I17: =I19+I20 -> -11228.074 | J17: =J19+J20 -> -14239.896
A19: Capital expenditures | B19: -11085 | C19: -10708 | D19: -10959 | E19: -9447 | F19: -12715 | G19: =-Assumptions!G37*IS!H14 -> -12232.353 | H19: =-Assumptions!H37*IS!I14 -> -12854.25 | I19: =-Assumptions!I37*IS!J14 -> -13522.027 | J19: =-Assumptions!J37*IS!K14 -> -14239.896
A20: Other investing (forecast: marketable securities, sold to hold cash at the Assumptions!B96 minimum) | B20: -3460 | C20: -11646 | D20: 14664 | E20: 12382 | F20: 27910 | G20: =-((BS!H6-BS!G6)+(BS!H15-BS!G15)) -> 3708.2125 | H20: =-((BS!I6-BS!H6)+(BS!I15-BS!H15)) -> 4759.1869 | I20: =-((BS!J6-BS!I6)+(BS!J15-BS!I15)) -> 2293.9532 | J20: =-((BS!K6-BS!J6)+(BS!K15-BS!J15)) -> 0
A21: Free cash flow (CFO − CapEx) | B21: =B14+B19 -> 92953 | C21: =C14+C19 -> 111443 | D21: =D14+D19 -> 99584 | E21: =E14+E19 -> 108807 | F21: =F14+F19 -> 98767 | G21: =G14+G19 -> 153635.75 | H21: =H14+H19 -> 144816.26 | I21: =I14+I19 -> 154120.94 | J21: =J14+J19 -> 164299.73
A23: FINANCING ACTIVITIES
A24: Dividends paid | B24: -14467 | C24: -14841 | D24: -15025 | E24: -15234 | F24: -15421 | G24: =-Assumptions!G42*Assumptions!G41*G21 -> -21893.095 | H24: =-Assumptions!H42*Assumptions!H41*H21 -> -20636.317 | I24: =-Assumptions!I42*Assumptions!I41*I21 -> -21962.233 | J24: =-Assumptions!J42*Assumptions!J41*J21 -> -23412.712
A25: Share repurchases | B25: -85971 | C25: -89402 | D25: -77550 | E25: -94949 | F25: -90711 | G25: =-(1-Assumptions!G42)*Assumptions!G41*G21 -> -124060.87 | H25: =-(1-Assumptions!H42)*Assumptions!H41*H21 -> -116939.13 | I25: =-(1-Assumptions!I42)*Assumptions!I41*I21 -> -124452.66 | J25: =-(1-Assumptions!J42)*Assumptions!J41*J21 -> -132672.04
A26: Net debt repayment & other financing | B26: 7085 | C26: -6506 | D26: -15913 | E26: -11800 | F26: -14554 | G26: =(BS!H24-BS!G24)+(BS!H25-BS!G25)+(BS!H29-BS!G29) -> -23678 | H26: =(BS!I24-BS!H24)+(BS!I25-BS!H25)+(BS!I29-BS!H29) -> -12000 | I26: =(BS!J24-BS!I24)+(BS!J25-BS!I25)+(BS!J29-BS!I29) -> -10000 | J26: =(BS!K24-BS!J24)+(BS!K25-BS!J25)+(BS!K29-BS!J29) -> 0
A27: Cash from financing activities | B27: =SUM(B24:B26) -> -93353 | C27: =SUM(C24:C26) -> -110749 | D27: =SUM(D24:D26) -> -108488 | E27: =SUM(E24:E26) -> -121983 | F27: =SUM(F24:F26) -> -120686 | G27: =SUM(G24:G26) -> -169631.96 | H27: =SUM(H24:H26) -> -149575.45 | I27: =SUM(I24:I26) -> -156414.89 | J27: =SUM(J24:J26) -> -156084.75
A29: Net change in cash | B29: =B14+B17+B27 -> -3860 | C29: =C14+C17+C27 -> -10952 | D29: =D14+D17+D27 -> 5760 | E29: =E14+E17+E27 -> -794 | F29: =F14+F17+F27 -> 5991 | G29: =G14+G17+G27 -> -12288 | H29: =H14+H17+H27 -> 0 | I29: =I14+I17+I27 -> 0 | J29: =J14+J17+J27 -> 8214.9867
A30: Cash & equivalents, ending | B30: =B7+B29 -> 35929 | C30: =C7+C29 -> 24977 | D30: =D7+D29 -> 30737 | E30: =E7+E29 -> 29943 | F30: =F7+F29 -> 35934 | G30: =G7+G29 -> 23646 | H30: =H7+H29 -> 23646 | I30: =I7+I29 -> 23646 | J30: =J7+J29 -> 31860.987
A33: FREE CASH FLOW
A34: Free Cash Flow | B34: =B14+B19 -> 92953 | C34: =C14+C19 -> 111443 | D34: =D14+D19 -> 99584 | E34: =E14+E19 -> 108807 | F34: =F14+F19 -> 98767 | G34: =G14+G19 -> 153635.75 | H34: =H14+H19 -> 144816.26 | I34: =I14+I19 -> 154120.94 | J34: =J14+J19 -> 164299.73
A35: FCF Margin % | B35: =B34/IS!B14 -> 0.25409699 | C35: =C34/IS!C14 -> 0.28261498 | D35: =D34/IS!D14 -> 0.25981711 | E35: =E34/IS!E14 -> 0.27825386 | F35: =F34/IS!F14 -> 0.23732882 | G35: =G34/IS!H14 -> 0.35167404 | H35: =H34/IS!I14 -> 0.31544862 | I35: =I34/IS!J14 -> 0.31913752 | J35: =J34/IS!K14 -> 0.32306363
A36: CapEx / Revenue % | B36: =-B19/IS!B14 -> 0.030302036 | C36: =-C19/IS!C14 -> 0.027155059 | D36: =-D19/IS!D14 -> 0.028592301 | E36: =-E19/IS!E14 -> 0.024158963 | F36: =-F19/IS!F14 -> 0.030553079 | G36: =-G19/IS!H14 -> 0.028 | H36: =-H19/IS!I14 -> 0.028 | I36: =-I19/IS!J14 -> 0.028 | J36: =-J19/IS!K14 -> 0.028
A38: Note: cash on the balance sheet (row 5) is this statement's ending cash. Marketable securities, other assets and liabilities are driven on the Assumptions sheet (rows 88 to 95); their movements appear in working capital or investing activities, so the balance sheet balances without a plug.

Sheet Ratios
A1: RATIOS | Profitability, Returns, Liquidity, Leverage
A2: All metrics calculated from IS, BS, and CFS sheets: fully formula-driven
A4: USD Millions | B4: FY2021A | C4: FY2022A | D4: FY2023A | E4: FY2024A | F4: FY2025A | G4: FY2026E | H4: FY2027E | I4: FY2028E | J4: FY2029E
A6: PROFITABILITY MARGINS
A7: Gross margin % | B7: =IS!B22/IS!B14 -> 0.4177936 | C7: =IS!C22/IS!C14 -> 0.43309631 | D7: =IS!D22/IS!D14 -> 0.4413113 | E7: =IS!E22/IS!E14 -> 0.4620635 | F7: =IS!F22/IS!F14 -> 0.46905164 | G7: =IS!H22/IS!H14 -> 0.47767887 | H7: =IS!I22/IS!I14 -> 0.48322857 | I7: =IS!J22/IS!J14 -> 0.48893871 | J7: =IS!K22/IS!K14 -> 0.4948017
A8: Operating margin % | B8: =IS!B29/IS!B14 -> 0.29782378 | C8: =IS!C29/IS!C14 -> 0.30288744 | D8: =IS!D29/IS!D14 -> 0.29821412 | E8: =IS!E29/IS!E14 -> 0.31510223 | F8: =IS!F29/IS!F14 -> 0.319708 | G8: =IS!H29/IS!H14 -> 0.32664004 | H8: =IS!I29/IS!I14 -> 0.33060207 | I8: =IS!J29/IS!J14 -> 0.33484029 | J8: =IS!K29/IS!K14 -> 0.33935502
A9: Net margin % | B9: =IS!B39/IS!B14 -> 0.25881793 | C9: =IS!C39/IS!C14 -> 0.25309641 | D9: =IS!D39/IS!D14 -> 0.25306234 | E9: =IS!E39/IS!E14 -> 0.23971256 | F9: =IS!F39/IS!F14 -> 0.26915064 | G9: =IS!H39/IS!H14 -> 0.27764403 | H9: =IS!I39/IS!I14 -> 0.28101176 | I9: =IS!J39/IS!J14 -> 0.28461424 | J9: =IS!K39/IS!K14 -> 0.28845176
A10: EBITDA margin % | B10: =(IS!B29+CFS!B10)/IS!B14 -> 0.3286698 | C10: =(IS!C29+CFS!C10)/IS!C14 -> 0.33104674 | D10: =(IS!D29+CFS!D10)/IS!D14 -> 0.32826748 | E10: =(IS!E29+CFS!E10)/IS!E14 -> 0.34437071 | F10: =(IS!F29+CFS!F10)/IS!F14 -> 0.34781731 | G10: =(IS!H29+CFS!G10)/IS!H14 -> 0.35464004 | H10: =(IS!I29+CFS!H10)/IS!I14 -> 0.35860207 | I10: =(IS!J29+CFS!I10)/IS!J14 -> 0.36284029 | J10: =(IS!K29+CFS!J10)/IS!K14 -> 0.36735502
A12: GROWTH (YoY)
A13: Revenue growth % | B13: , | C13: =IS!C14/IS!B14-1 -> 0.077937876 | D13: =IS!D14/IS!C14-1 -> -0.028004605 | E13: =IS!E14/IS!D14-1 -> 0.020219941 | F13: =IS!F14/IS!E14-1 -> 0.064255118 | G13: =IS!H14/IS!F14-1 -> 0.04976139 | H13: =IS!I14/IS!H14-1 -> 0.05084032 | I13: =IS!J14/IS!I14-1 -> 0.05194993 | J13: =IS!K14/IS!J14-1 -> 0.053088885
A14: Operating income growth % | B14: , | C14: =IS!C29/IS!B29-1 -> 0.096265225 | D14: =IS!D29/IS!C29-1 -> -0.04300175 | E14: =IS!E29/IS!D29-1 -> 0.077995818 | F14: =IS!F29/IS!E29-1 -> 0.079811063 | G14: =IS!H29/IS!F29-1 -> 0.072522755 | H14: =IS!I29/IS!H29-1 -> 0.063586661 | I14: =IS!J29/IS!I29-1 -> 0.065435587 | J14: =IS!K29/IS!J29-1 -> 0.067287935
A15: Net income growth % | B15: , | C15: =IS!C39/IS!B39-1 -> 0.054108576 | D15: =IS!D39/IS!C39-1 -> -0.028135427 | E15: =IS!E39/IS!D39-1 -> -0.03359967 | F15: =IS!F39/IS!E39-1 -> 0.19495178 | G15: =IS!H39/IS!F39-1 -> 0.082887954 | H15: =IS!I39/IS!H39-1 -> 0.063586661 | I15: =IS!J39/IS!I39-1 -> 0.065435587 | J15: =IS!K39/IS!J39-1 -> 0.067287935
A17: RETURNS
A18: Return on assets (ROA) | B18: =IS!B39/BS!C18 -> 0.26974205 | C18: =IS!C39/BS!D18 -> 0.28292441 | D18: =IS!D39/BS!E18 -> 0.27509835 | E18: =IS!E39/BS!F18 -> 0.25682503 | F18: =IS!F39/BS!G18 -> 0.31179626 | G18: =IS!H39/BS!H18 -> 0.3561117 | H18: =IS!I39/BS!I18 -> 0.3746952 | I18: =IS!J39/BS!J18 -> 0.39153227 | J18: =IS!K39/BS!K18 -> 0.39758706
A19: Return on equity (ROE) | B19: =IS!B39/BS!C38 -> 1.5007133 | C19: =IS!C39/BS!D38 -> 1.9695887 | D19: =IS!D39/BS!E38 -> 1.5607601 | E19: =IS!E39/BS!F38 -> 1.645935 | F19: =IS!F39/BS!G38 -> 1.5191298 | G19: =IS!H39/BS!H38 -> 1.9371046 | H19: =IS!I39/BS!I38 -> 1.8894011 | I19: =IS!J39/BS!J38 -> 1.8503164 | J19: =IS!K39/BS!K38 -> 1.8186672
A20: Return on invested capital | B20: =(IS!B29*(1-Assumptions!$B$50))/(BS!C42+BS!C38) -> 0.49308952 | C20: =(IS!C29*(1-Assumptions!$B$50))/(BS!D42+BS!D38) -> 0.59459327 | D20: =(IS!D29*(1-Assumptions!$B$50))/(BS!E42+BS!E38) -> 0.56083592 | E20: =(IS!E29*(1-Assumptions!$B$50))/(BS!F42+BS!F38) -> 0.64026311 | F20: =(IS!F29*(1-Assumptions!$B$50))/(BS!G42+BS!G38) -> 0.65602703 | G20: =(IS!H29*(1-Assumptions!$B$50))/(BS!H42+BS!H38) -> 0.88152937 | H20: =(IS!I29*(1-Assumptions!$B$50))/(BS!I42+BS!I38) -> 0.98284817 | I20: =(IS!J29*(1-Assumptions!$B$50))/(BS!J42+BS!J38) -> 1.0800373 | J20: =(IS!K29*(1-Assumptions!$B$50))/(BS!K42+BS!K38) -> 1.0976968
A22: LEVERAGE & LIQUIDITY
A23: Debt / Equity | B23: =BS!C42/BS!C38 -> 1.9768426 | C23: =BS!D42/BS!D38 -> 2.3695335 | D23: =BS!E42/BS!E38 -> 1.7875326 | E23: =BS!F42/BS!F38 -> 1.8723266 | F23: =BS!G42/BS!G38 -> 1.3380305 | G23: =BS!H42/BS!H38 -> 1.1974362 | H23: =BS!I42/BS!I38 -> 0.92237328 | I23: =BS!J42/BS!J38 -> 0.71319675 | J23: =BS!K42/BS!K38 -> 0.65680278
A24: Debt / Total capital | B24: =BS!C42/(BS!C42+BS!C38) -> 0.66407361 | C24: =BS!D42/(BS!D42+BS!D38) -> 0.70322301 | D24: =BS!E42/(BS!E42+BS!E38) -> 0.6412598 | E24: =BS!F42/(BS!F42+BS!F38) -> 0.65185018 | F24: =BS!G42/(BS!G42+BS!G38) -> 0.57228958 | G24: =BS!H42/(BS!H42+BS!H38) -> 0.54492422 | H24: =BS!I42/(BS!I42+BS!I38) -> 0.47980966 | I24: =BS!J42/(BS!J42+BS!J38) -> 0.41629588 | J24: =BS!K42/(BS!K42+BS!K38) -> 0.39642786
A25: Current ratio | B25: =BS!C11/BS!C26 -> 1.0745531 | C25: =BS!D11/BS!D26 -> 0.87935603 | D25: =BS!E11/BS!E26 -> 0.98801167 | E25: =BS!F11/BS!F26 -> 0.86731258 | F25: =BS!G11/BS!G26 -> 0.89329292 | G25: =BS!H11/BS!H26 -> 0.7913593 | H25: =BS!I11/BS!I26 -> 0.78929327 | I25: =BS!J11/BS!J26 -> 0.77773136 | J25: =BS!K11/BS!K26 -> 0.81003476
A26: Net debt ($M) | B26: =BS!C43 -> -65797 | C26: =BS!D43 -> -49040 | D26: =BS!E43 -> -51011 | E26: =BS!F43 -> -50021 | F26: =BS!G43 -> -33763 | G26: =BS!H43 -> -41444.788 | H26: =BS!I43 -> -48685.601 | I26: =BS!J43 -> -56391.647 | J26: =BS!K43 -> -64606.634
A28: CASH FLOW METRICS
A29: Operating cash flow ($M) | B29: =CFS!B14 -> 104038 | C29: =CFS!C14 -> 122151 | D29: =CFS!D14 -> 110543 | E29: =CFS!E14 -> 118254 | F29: =CFS!F14 -> 111482 | G29: =CFS!G14 -> 165868.1 | H29: =CFS!H14 -> 157670.51 | I29: =CFS!I14 -> 167642.96 | J29: =CFS!J14 -> 178539.63
A30: Free cash flow ($M) | B30: =CFS!B21 -> 92953 | C30: =CFS!C21 -> 111443 | D30: =CFS!D21 -> 99584 | E30: =CFS!E21 -> 108807 | F30: =CFS!F21 -> 98767 | G30: =CFS!G21 -> 153635.75 | H30: =CFS!H21 -> 144816.26 | I30: =CFS!I21 -> 154120.94 | J30: =CFS!J21 -> 164299.73
A31: FCF margin % | B31: =CFS!B21/IS!B14 -> 0.25409699 | C31: =CFS!C21/IS!C14 -> 0.28261498 | D31: =CFS!D21/IS!D14 -> 0.25981711 | E31: =CFS!E21/IS!E14 -> 0.27825386 | F31: =CFS!F21/IS!F14 -> 0.23732882 | G31: =CFS!G21/IS!H14 -> 0.35167404 | H31: =CFS!H21/IS!I14 -> 0.31544862 | I31: =CFS!I21/IS!J14 -> 0.31913752 | J31: =CFS!J21/IS!K14 -> 0.32306363
A32: FCF / Net income | B32: =CFS!B21/IS!B39 -> 0.98175961 | C32: =CFS!C21/IS!C39 -> 1.1166298 | D32: =CFS!D21/IS!D39 -> 1.0266921 | E32: =CFS!E21/IS!E39 -> 1.1607813 | F32: =CFS!F21/IS!F39 -> 0.88176948 | G32: =CFS!G21/IS!H39 -> 1.2666364 | H32: =CFS!H21/IS!I39 -> 1.122546 | I32: =CFS!I21/IS!J39 -> 1.1212985 | J32: =CFS!J21/IS!K39 -> 1.1199918
A33: CapEx / Revenue | B33: =-CFS!B19/IS!B14 -> 0.030302036 | C33: =-CFS!C19/IS!C14 -> 0.027155059 | D33: =-CFS!D19/IS!D14 -> 0.028592301 | E33: =-CFS!E19/IS!E14 -> 0.024158963 | F33: =-CFS!F19/IS!F14 -> 0.030553079 | G33: =-CFS!G19/IS!H14 -> 0.028 | H33: =-CFS!H19/IS!I14 -> 0.028 | I33: =-CFS!I19/IS!J14 -> 0.028 | J33: =-CFS!J19/IS!K14 -> 0.028

Sheet DCF
A1: DCF VALUATION | Discounted Cash Flow
A2: Enterprise value via FCF discounting + Gordon Growth terminal | WACC × g sensitivity table
A4: USD Millions | B4: FY2026E | C4: FY2027E | D4: FY2028E | E4: FY2029E | F4: Terminal
A6: UNLEVERED FREE CASH FLOW BUILD
A7: EBIT (operating income) | B7: =IS!H29 -> 142699.15 | C7: =IS!I29 -> 151772.92 | D7: =IS!J29 -> 161704.27 | E7: =IS!K29 -> 172585.01
A8: × (1 − scenario tax rate) | B8: =1-Assumptions!G25 -> 0.85 | C8: =1-Assumptions!H25 -> 0.85 | D8: =1-Assumptions!I25 -> 0.85 | E8: =1-Assumptions!J25 -> 0.85
A9: NOPAT | B9: =B7*B8 -> 121294.28 | C9: =C7*C8 -> 129006.98 | D9: =D7*D8 -> 137448.63 | E9: =E7*E8 -> 146697.26
A10: + Depreciation & amortization | B10: =CFS!G10 -> 12232.353 | C10: =CFS!H10 -> 12854.25 | D10: =CFS!I10 -> 13522.027 | E10: =CFS!J10 -> 14239.896
A11: − CapEx | B11: =CFS!G19 -> -12232.353 | C11: =CFS!H19 -> -12854.25 | D11: =CFS!I19 -> -13522.027 | E11: =CFS!J19 -> -14239.896
A12: − Change in working capital | B12: =CFS!G13 -> 18798.509 | C12: =CFS!H13 -> 1577.7935 | D12: =CFS!I13 -> 1701.4952 | E12: =CFS!J13 -> 1836.8757
A13: Unlevered free cash flow | B13: =B9+B10+B11+B12 -> 140092.79 | C13: =C9+C10+C11+C12 -> 130584.77 | D13: =D9+D10+D11+D12 -> 139150.12 | E13: =E9+E10+E11+E12 -> 148534.14 | F13: =E13*(1+Assumptions!$B$55)/(Assumptions!$B$54-Assumptions!$B$55) -> 2225840.5
A14: Fiscal year end | B14: =DATE(2026,9,26) -> 46291 | C14: =DATE(2027,9,25) -> 46655 | D14: =DATE(2028,9,30) -> 47026 | E14: =DATE(2029,9,29) -> 47390 | F14: =E14 -> 47390
A15: Years from valuation date | B15: =(B14-Assumptions!$B$60)/365.25 -> -0.0054757016 | C15: =(C14-Assumptions!$B$60)/365.25 -> 0.99110198 | D15: =(D14-Assumptions!$B$60)/365.25 -> 2.0068446 | E15: =(E14-Assumptions!$B$60)/365.25 -> 3.0034223 | F15: =E15 -> 3.0034223
A16: Discount factor (at WACC) | B16: =IF(B15<=0,0,1/(1+Assumptions!$B$54)^B15) -> 0 | C16: =IF(C15<=0,0,1/(1+Assumptions!$B$54)^C15) -> 0.91530532 | D16: =IF(D15<=0,0,1/(1+Assumptions!$B$54)^D15) -> 0.83594255 | E16: =IF(E15<=0,0,1/(1+Assumptions!$B$54)^E15) -> 0.76476865 | F16: =IF(F15<=0,0,1/(1+Assumptions!$B$54)^F15) -> 0.76476865
A17: Present value | B17: =B13*B16 -> 0 | C17: =C13*C16 -> 119524.94 | D17: =D13*D16 -> 116321.51 | E17: =E13*E16 -> 113594.25 | F17: =F13*F16 -> 1702253
A18: FY2026 ended before the valuation date, so its cash is counted in FY26E net cash, not discounted.
A19: VALUATION SUMMARY
A20: Sum PV of forecast FCFs | B20: =SUM(B17:E17) -> 349440.69
A21: PV of terminal value | B21: =F17 -> 1702253
A22: Enterprise value | B22: =B20+B21 -> 2051693.7
A23: + Net cash (FY26E) | B23: =BS!H5+BS!H6+BS!H15-BS!H42 -> 41444.788
A24: Equity value | B24: =B22+B23 -> 2093138.5
A25: ÷ Diluted shares (M) | B25: =Assumptions!$B$58 -> 15004.7
A26: Implied share price | B26: =B24/B25 -> 139.49886
A27: Current share price | B27: =Assumptions!$B$59 -> 338.4
A28: Upside / (downside) | B28: =B26/B27-1 -> -0.58776934
A31: SENSITIVITY | Implied Share Price by WACC × Terminal Growth
A33: WACC ↓ / g → | B33: =Assumptions!$B$55+(-0.01) -> 0.015 | C33: =Assumptions!$B$55+(-0.005) -> 0.02 | D33: =Assumptions!$B$55+(0) -> 0.025 | E33: =Assumptions!$B$55+(0.005) -> 0.03 | F33: =Assumptions!$B$55+(0.01) -> 0.035
A34: =Assumptions!$B$54+(-0.01) -> 0.0834 | B34: =($C$13/(1+$A34)^$C$15+$D$13/(1+$A34)^$D$15+$E$13/(1+$A34)^$E$15+($E$13*(1+B$33)/($A34-B$33))/(1+$A34)^$F$15+$B$23)/Assumptions!$B$58 -> 141.96423 | C34: =($C$13/(1+$A34)^$C$15+$D$13/(1+$A34)^$D$15+$E$13/(1+$A34)^$E$15+($E$13*(1+C$33)/($A34-C$33))/(1+$A34)^$F$15+$B$23)/Assumptions!$B$58 -> 151.68559 | D34: =($C$13/(1+$A34)^$C$15+$D$13/(1+$A34)^$D$15+$E$13/(1+$A34)^$E$15+($E$13*(1+D$33)/($A34-D$33))/(1+$A34)^$F$15+$B$23)/Assumptions!$B$58 -> 163.07156 | E34: =($C$13/(1+$A34)^$C$15+$D$13/(1+$A34)^$D$15+$E$13/(1+$A34)^$E$15+($E$13*(1+E$33)/($A34-E$33))/(1+$A34)^$F$15+$B$23)/Assumptions!$B$58 -> 176.58974 | F34: =($C$13/(1+$A34)^$C$15+$D$13/(1+$A34)^$D$15+$E$13/(1+$A34)^$E$15+($E$13*(1+F$33)/($A34-F$33))/(1+$A34)^$F$15+$B$23)/Assumptions!$B$58 -> 192.90093
A35: =Assumptions!$B$54+(-0.005) -> 0.0884 | B35: =($C$13/(1+$A35)^$C$15+$D$13/(1+$A35)^$D$15+$E$13/(1+$A35)^$E$15+($E$13*(1+B$33)/($A35-B$33))/(1+$A35)^$F$15+$B$23)/Assumptions!$B$58 -> 132.40331 | C35: =($C$13/(1+$A35)^$C$15+$D$13/(1+$A35)^$D$15+$E$13/(1+$A35)^$E$15+($E$13*(1+C$33)/($A35-C$33))/(1+$A35)^$F$15+$B$23)/Assumptions!$B$58 -> 140.72312 | D35: =($C$13/(1+$A35)^$C$15+$D$13/(1+$A35)^$D$15+$E$13/(1+$A35)^$E$15+($E$13*(1+D$33)/($A35-D$33))/(1+$A35)^$F$15+$B$23)/Assumptions!$B$58 -> 150.35522 | E35: =($C$13/(1+$A35)^$C$15+$D$13/(1+$A35)^$D$15+$E$13/(1+$A35)^$E$15+($E$13*(1+E$33)/($A35-E$33))/(1+$A35)^$F$15+$B$23)/Assumptions!$B$58 -> 161.63664 | F35: =($C$13/(1+$A35)^$C$15+$D$13/(1+$A35)^$D$15+$E$13/(1+$A35)^$E$15+($E$13*(1+F$33)/($A35-F$33))/(1+$A35)^$F$15+$B$23)/Assumptions!$B$58 -> 175.03069
A36: =Assumptions!$B$54+(0) -> 0.0934 | B36: =($C$13/(1+$A36)^$C$15+$D$13/(1+$A36)^$D$15+$E$13/(1+$A36)^$E$15+($E$13*(1+B$33)/($A36-B$33))/(1+$A36)^$F$15+$B$23)/Assumptions!$B$58 -> 124.06282 | C36: =($C$13/(1+$A36)^$C$15+$D$13/(1+$A36)^$D$15+$E$13/(1+$A36)^$E$15+($E$13*(1+C$33)/($A36-C$33))/(1+$A36)^$F$15+$B$23)/Assumptions!$B$58 -> 131.25509 | D36: =($C$13/(1+$A36)^$C$15+$D$13/(1+$A36)^$D$15+$E$13/(1+$A36)^$E$15+($E$13*(1+D$33)/($A36-D$33))/(1+$A36)^$F$15+$B$23)/Assumptions!$B$58 -> 139.49886 | E36: =($C$13/(1+$A36)^$C$15+$D$13/(1+$A36)^$D$15+$E$13/(1+$A36)^$E$15+($E$13*(1+E$33)/($A36-E$33))/(1+$A36)^$F$15+$B$23)/Assumptions!$B$58 -> 149.04291 | F36: =($C$13/(1+$A36)^$C$15+$D$13/(1+$A36)^$D$15+$E$13/(1+$A36)^$E$15+($E$13*(1+F$33)/($A36-F$33))/(1+$A36)^$F$15+$B$23)/Assumptions!$B$58 -> 160.22121
A37: =Assumptions!$B$54+(0.005) -> 0.0984 | B37: =($C$13/(1+$A37)^$C$15+$D$13/(1+$A37)^$D$15+$E$13/(1+$A37)^$E$15+($E$13*(1+B$33)/($A37-B$33))/(1+$A37)^$F$15+$B$23)/Assumptions!$B$58 -> 116.72324 | C37: =($C$13/(1+$A37)^$C$15+$D$13/(1+$A37)^$D$15+$E$13/(1+$A37)^$E$15+($E$13*(1+C$33)/($A37-C$33))/(1+$A37)^$F$15+$B$23)/Assumptions!$B$58 -> 122.99553 | D37: =($C$13/(1+$A37)^$C$15+$D$13/(1+$A37)^$D$15+$E$13/(1+$A37)^$E$15+($E$13*(1+D$33)/($A37-D$33))/(1+$A37)^$F$15+$B$23)/Assumptions!$B$58 -> 130.12236 | E37: =($C$13/(1+$A37)^$C$15+$D$13/(1+$A37)^$D$15+$E$13/(1+$A37)^$E$15+($E$13*(1+E$33)/($A37-E$33))/(1+$A37)^$F$15+$B$23)/Assumptions!$B$58 -> 138.29112 | F37: =($C$13/(1+$A37)^$C$15+$D$13/(1+$A37)^$D$15+$E$13/(1+$A37)^$E$15+($E$13*(1+F$33)/($A37-F$33))/(1+$A37)^$F$15+$B$23)/Assumptions!$B$58 -> 147.74833
A38: =Assumptions!$B$54+(0.01) -> 0.1034 | B38: =($C$13/(1+$A38)^$C$15+$D$13/(1+$A38)^$D$15+$E$13/(1+$A38)^$E$15+($E$13*(1+B$33)/($A38-B$33))/(1+$A38)^$F$15+$B$23)/Assumptions!$B$58 -> 110.21473 | C38: =($C$13/(1+$A38)^$C$15+$D$13/(1+$A38)^$D$15+$E$13/(1+$A38)^$E$15+($E$13*(1+C$33)/($A38-C$33))/(1+$A38)^$F$15+$B$23)/Assumptions!$B$58 -> 115.7271 | D38: =($C$13/(1+$A38)^$C$15+$D$13/(1+$A38)^$D$15+$E$13/(1+$A38)^$E$15+($E$13*(1+D$33)/($A38-D$33))/(1+$A38)^$F$15+$B$23)/Assumptions!$B$58 -> 121.94258 | E38: =($C$13/(1+$A38)^$C$15+$D$13/(1+$A38)^$D$15+$E$13/(1+$A38)^$E$15+($E$13*(1+E$33)/($A38-E$33))/(1+$A38)^$F$15+$B$23)/Assumptions!$B$58 -> 129.00486 | F38: =($C$13/(1+$A38)^$C$15+$D$13/(1+$A38)^$D$15+$E$13/(1+$A38)^$E$15+($E$13*(1+F$33)/($A38-F$33))/(1+$A38)^$F$15+$B$23)/Assumptions!$B$58 -> 137.09963
A40: Rows are WACC and columns terminal growth, centred on the active scenario; the centre cell equals the headline price.
A41: SENSITIVITY | Implied Share Price by Revenue Growth × Operating Margin
A42: Simplified one-stage build (WACC Assumptions!B54, tax B50, CapEx G37, D&A row 84). Axis values in blue are inputs. Separate from the main DCF, so its centre is not the headline price.
A43: Rev Growth ↓ / Op Margin → | B43: 0.28 | C43: 0.3 | D43: 0.32 | E43: 0.34 | F43: 0.36
A44: 0.02 | B44: =((IS!$F$14*(1+$A44))*(B$43*(1-Assumptions!$B$50)-Assumptions!$G$37+CHOOSE(MATCH(Scenario,{"Bear","Base","Bull"},0),Assumptions!$B$84,Assumptions!$C$84,Assumptions!$D$84))/(1+Assumptions!$B$54)^1+(IS!$F$14*(1+$A44)^2)*(B$43*(1-Assumptions!$B$50)-Assumptions!$G$37+CHOOSE(MATCH(Scenario,{"Bear","Base","Bull"},0),Assumptions!$B$84,Assumptions!$C$84,Assumptions!$D$84))/(1+Assumptions!$B$54)^2+(IS!$F$14*(1+$A44)^3)*(B$43*(1-Assumptions!$B$50)-Assumptions!$G$37+CHOOSE(MATCH(Scenario,{"Bear","Base","Bull"},0),Assumptions!$B$84,Assumptions!$C$84,Assumptions!$D$84))/(1+Assumptions!$B$54)^3+(IS!$F$14*(1+$A44)^4)*(B$43*(1-Assumptions!$B$50)-Assumptions!$G$37+CHOOSE(MATCH(Scenario,{"Bear","Base","Bull"},0),Assumptions!$B$84,Assumptions!$C$84,Assumptions!$D$84))/(1+Assumptions!$B$54)^4+(IS!$F$14*(1+$A44)^4)*(B$43*(1-Assumptions!$B$50)-Assumptions!$G$37+CHOOSE(MATCH(Scenario,{"Bear","Base","Bull"},0),Assumptions!$B$84,Assumptions!$C$84,Assumptions!$D$84))*(1+Assumptions!$B$55)/(Assumptions!$B$54-Assumptions!$B$55)/(1+Assumptions!$B$54)^4+$B$23)/Assumptions!$B$58 -> 99.936587 | C44: =((IS!$F$14*(1+$A44))*(C$43*(1-Assumptions!$B$50)-Assumptions!$G$37+CHOOSE(MATCH(Scenario,{"Bear","Base","Bull"},0),Assumptions!$B$84,Assumptions!$C$84,Assumptions!$D$84))/(1+Assumptions!$B$54)^1+(IS!$F$14*(1+$A44)^2)*(C$43*(1-Assumptions!$B$50)-Assumptions!$G$37+CHOOSE(MATCH(Scenario,{"Bear","Base","Bull"},0),Assumptions!$B$84,Assumptions!$C$84,Assumptions!$D$84))/(1+Assumptions!$B$54)^2+(IS!$F$14*(1+$A44)^3)*(C$43*(1-Assumptions!$B$50)-Assumptions!$G$37+CHOOSE(MATCH(Scenario,{"Bear","Base","Bull"},0),Assumptions!$B$84,Assumptions!$C$84,Assumptions!$D$84))/(1+Assumptions!$B$54)^3+(IS!$F$14*(1+$A44)^4)*(C$43*(1-Assumptions!$B$50)-Assumptions!$G$37+CHOOSE(MATCH(Scenario,{"Bear","Base","Bull"},0),Assumptions!$B$84,Assumptions!$C$84,Assumptions!$D$84))/(1+Assumptions!$B$54)^4+(IS!$F$14*(1+$A44)^4)*(C$43*(1-Assumptions!$B$50)-Assumptions!$G$37+CHOOSE(MATCH(Scenario,{"Bear","Base","Bull"},0),Assumptions!$B$84,Assumptions!$C$84,Assumptions!$D$84))*(1+Assumptions!$B$55)/(Assumptions!$B$54-Assumptions!$B$55)/(1+Assumptions!$B$54)^4+$B$23)/Assumptions!$B$58 -> 106.87762 | D44: =((IS!$F$14*(1+$A44))*(D$43*(1-Assumptions!$B$50)-Assumptions!$G$37+CHOOSE(MATCH(Scenario,{"Bear","Base","Bull"},0),Assumptions!$B$84,Assumptions!$C$84,Assumptions!$D$84))/(1+Assumptions!$B$54)^1+(IS!$F$14*(1+$A44)^2)*(D$43*(1-Assumptions!$B$50)-Assumptions!$G$37+CHOOSE(MATCH(Scenario,{"Bear","Base","Bull"},0),Assumptions!$B$84,Assumptions!$C$84,Assumptions!$D$84))/(1+Assumptions!$B$54)^2+(IS!$F$14*(1+$A44)^3)*(D$43*(1-Assumptions!$B$50)-Assumptions!$G$37+CHOOSE(MATCH(Scenario,{"Bear","Base","Bull"},0),Assumptions!$B$84,Assumptions!$C$84,Assumptions!$D$84))/(1+Assumptions!$B$54)^3+(IS!$F$14*(1+$A44)^4)*(D$43*(1-Assumptions!$B$50)-Assumptions!$G$37+CHOOSE(MATCH(Scenario,{"Bear","Base","Bull"},0),Assumptions!$B$84,Assumptions!$C$84,Assumptions!$D$84))/(1+Assumptions!$B$54)^4+(IS!$F$14*(1+$A44)^4)*(D$43*(1-Assumptions!$B$50)-Assumptions!$G$37+CHOOSE(MATCH(Scenario,{"Bear","Base","Bull"},0),Assumptions!$B$84,Assumptions!$C$84,Assumptions!$D$84))*(1+Assumptions!$B$55)/(Assumptions!$B$54-Assumptions!$B$55)/(1+Assumptions!$B$54)^4+$B$23)/Assumptions!$B$58 -> 113.81865 | E44: =((IS!$F$14*(1+$A44))*(E$43*(1-Assumptions!$B$50)-Assumptions!$G$37+CHOOSE(MATCH(Scenario,{"Bear","Base","Bull"},0),Assumptions!$B$84,Assumptions!$C$84,Assumptions!$D$84))/(1+Assumptions!$B$54)^1+(IS!$F$14*(1+$A44)^2)*(E$43*(1-Assumptions!$B$50)-Assumptions!$G$37+CHOOSE(MATCH(Scenario,{"Bear","Base","Bull"},0),Assumptions!$B$84,Assumptions!$C$84,Assumptions!$D$84))/(1+Assumptions!$B$54)^2+(IS!$F$14*(1+$A44)^3)*(E$43*(1-Assumptions!$B$50)-Assumptions!$G$37+CHOOSE(MATCH(Scenario,{"Bear","Base","Bull"},0),Assumptions!$B$84,Assumptions!$C$84,Assumptions!$D$84))/(1+Assumptions!$B$54)^3+(IS!$F$14*(1+$A44)^4)*(E$43*(1-Assumptions!$B$50)-Assumptions!$G$37+CHOOSE(MATCH(Scenario,{"Bear","Base","Bull"},0),Assumptions!$B$84,Assumptions!$C$84,Assumptions!$D$84))/(1+Assumptions!$B$54)^4+(IS!$F$14*(1+$A44)^4)*(E$43*(1-Assumptions!$B$50)-Assumptions!$G$37+CHOOSE(MATCH(Scenario,{"Bear","Base","Bull"},0),Assumptions!$B$84,Assumptions!$C$84,Assumptions!$D$84))*(1+Assumptions!$B$55)/(Assumptions!$B$54-Assumptions!$B$55)/(1+Assumptions!$B$54)^4+$B$23)/Assumptions!$B$58 -> 120.75969 | F44: =((IS!$F$14*(1+$A44))*(F$43*(1-Assumptions!$B$50)-Assumptions!$G$37+CHOOSE(MATCH(Scenario,{"Bear","Base","Bull"},0),Assumptions!$B$84,Assumptions!$C$84,Assumptions!$D$84))/(1+Assumptions!$B$54)^1+(IS!$F$14*(1+$A44)^2)*(F$43*(1-Assumptions!$B$50)-Assumptions!$G$37+CHOOSE(MATCH(Scenario,{"Bear","Base","Bull"},0),Assumptions!$B$84,Assumptions!$C$84,Assumptions!$D$84))/(1+Assumptions!$B$54)^2+(IS!$F$14*(1+$A44)^3)*(F$43*(1-Assumptions!$B$50)-Assumptions!$G$37+CHOOSE(MATCH(Scenario,{"Bear","Base","Bull"},0),Assumptions!$B$84,Assumptions!$C$84,Assumptions!$D$84))/(1+Assumptions!$B$54)^3+(IS!$F$14*(1+$A44)^4)*(F$43*(1-Assumptions!$B$50)-Assumptions!$G$37+CHOOSE(MATCH(Scenario,{"Bear","Base","Bull"},0),Assumptions!$B$84,Assumptions!$C$84,Assumptions!$D$84))/(1+Assumptions!$B$54)^4+(IS!$F$14*(1+$A44)^4)*(F$43*(1-Assumptions!$B$50)-Assumptions!$G$37+CHOOSE(MATCH(Scenario,{"Bear","Base","Bull"},0),Assumptions!$B$84,Assumptions!$C$84,Assumptions!$D$84))*(1+Assumptions!$B$55)/(Assumptions!$B$54-Assumptions!$B$55)/(1+Assumptions!$B$54)^4+$B$23)/Assumptions!$B$58 -> 127.70072
A45: 0.035 | B45: =((IS!$F$14*(1+$A45))*(B$43*(1-Assumptions!$B$50)-Assumptions!$G$37+CHOOSE(MATCH(Scenario,{"Bear","Base","Bull"},0),Assumptions!$B$84,Assumptions!$C$84,Assumptions!$D$84))/(1+Assumptions!$B$54)^1+(IS!$F$14*(1+$A45)^2)*(B$43*(1-Assumptions!$B$50)-Assumptions!$G$37+CHOOSE(MATCH(Scenario,{"Bear","Base","Bull"},0),Assumptions!$B$84,Assumptions!$C$84,Assumptions!$D$84))/(1+Assumptions!$B$54)^2+(IS!$F$14*(1+$A45)^3)*(B$43*(1-Assumptions!$B$50)-Assumptions!$G$37+CHOOSE(MATCH(Scenario,{"Bear","Base","Bull"},0),Assumptions!$B$84,Assumptions!$C$84,Assumptions!$D$84))/(1+Assumptions!$B$54)^3+(IS!$F$14*(1+$A45)^4)*(B$43*(1-Assumptions!$B$50)-Assumptions!$G$37+CHOOSE(MATCH(Scenario,{"Bear","Base","Bull"},0),Assumptions!$B$84,Assumptions!$C$84,Assumptions!$D$84))/(1+Assumptions!$B$54)^4+(IS!$F$14*(1+$A45)^4)*(B$43*(1-Assumptions!$B$50)-Assumptions!$G$37+CHOOSE(MATCH(Scenario,{"Bear","Base","Bull"},0),Assumptions!$B$84,Assumptions!$C$84,Assumptions!$D$84))*(1+Assumptions!$B$55)/(Assumptions!$B$54-Assumptions!$B$55)/(1+Assumptions!$B$54)^4+$B$23)/Assumptions!$B$58 -> 105.24275 | C45: =((IS!$F$14*(1+$A45))*(C$43*(1-Assumptions!$B$50)-Assumptions!$G$37+CHOOSE(MATCH(Scenario,{"Bear","Base","Bull"},0),Assumptions!$B$84,Assumptions!$C$84,Assumptions!$D$84))/(1+Assumptions!$B$54)^1+(IS!$F$14*(1+$A45)^2)*(C$43*(1-Assumptions!$B$50)-Assumptions!$G$37+CHOOSE(MATCH(Scenario,{"Bear","Base","Bull"},0),Assumptions!$B$84,Assumptions!$C$84,Assumptions!$D$84))/(1+Assumptions!$B$54)^2+(IS!$F$14*(1+$A45)^3)*(C$43*(1-Assumptions!$B$50)-Assumptions!$G$37+CHOOSE(MATCH(Scenario,{"Bear","Base","Bull"},0),Assumptions!$B$84,Assumptions!$C$84,Assumptions!$D$84))/(1+Assumptions!$B$54)^3+(IS!$F$14*(1+$A45)^4)*(C$43*(1-Assumptions!$B$50)-Assumptions!$G$37+CHOOSE(MATCH(Scenario,{"Bear","Base","Bull"},0),Assumptions!$B$84,Assumptions!$C$84,Assumptions!$D$84))/(1+Assumptions!$B$54)^4+(IS!$F$14*(1+$A45)^4)*(C$43*(1-Assumptions!$B$50)-Assumptions!$G$37+CHOOSE(MATCH(Scenario,{"Bear","Base","Bull"},0),Assumptions!$B$84,Assumptions!$C$84,Assumptions!$D$84))*(1+Assumptions!$B$55)/(Assumptions!$B$54-Assumptions!$B$55)/(1+Assumptions!$B$54)^4+$B$23)/Assumptions!$B$58 -> 112.56279 | D45: =((IS!$F$14*(1+$A45))*(D$43*(1-Assumptions!$B$50)-Assumptions!$G$37+CHOOSE(MATCH(Scenario,{"Bear","Base","Bull"},0),Assumptions!$B$84,Assumptions!$C$84,Assumptions!$D$84))/(1+Assumptions!$B$54)^1+(IS!$F$14*(1+$A45)^2)*(D$43*(1-Assumptions!$B$50)-Assumptions!$G$37+CHOOSE(MATCH(Scenario,{"Bear","Base","Bull"},0),Assumptions!$B$84,Assumptions!$C$84,Assumptions!$D$84))/(1+Assumptions!$B$54)^2+(IS!$F$14*(1+$A45)^3)*(D$43*(1-Assumptions!$B$50)-Assumptions!$G$37+CHOOSE(MATCH(Scenario,{"Bear","Base","Bull"},0),Assumptions!$B$84,Assumptions!$C$84,Assumptions!$D$84))/(1+Assumptions!$B$54)^3+(IS!$F$14*(1+$A45)^4)*(D$43*(1-Assumptions!$B$50)-Assumptions!$G$37+CHOOSE(MATCH(Scenario,{"Bear","Base","Bull"},0),Assumptions!$B$84,Assumptions!$C$84,Assumptions!$D$84))/(1+Assumptions!$B$54)^4+(IS!$F$14*(1+$A45)^4)*(D$43*(1-Assumptions!$B$50)-Assumptions!$G$37+CHOOSE(MATCH(Scenario,{"Bear","Base","Bull"},0),Assumptions!$B$84,Assumptions!$C$84,Assumptions!$D$84))*(1+Assumptions!$B$55)/(Assumptions!$B$54-Assumptions!$B$55)/(1+Assumptions!$B$54)^4+$B$23)/Assumptions!$B$58 -> 119.88284 | E45: =((IS!$F$14*(1+$A45))*(E$43*(1-Assumptions!$B$50)-Assumptions!$G$37+CHOOSE(MATCH(Scenario,{"Bear","Base","Bull"},0),Assumptions!$B$84,Assumptions!$C$84,Assumptions!$D$84))/(1+Assumptions!$B$54)^1+(IS!$F$14*(1+$A45)^2)*(E$43*(1-Assumptions!$B$50)-Assumptions!$G$37+CHOOSE(MATCH(Scenario,{"Bear","Base","Bull"},0),Assumptions!$B$84,Assumptions!$C$84,Assumptions!$D$84))/(1+Assumptions!$B$54)^2+(IS!$F$14*(1+$A45)^3)*(E$43*(1-Assumptions!$B$50)-Assumptions!$G$37+CHOOSE(MATCH(Scenario,{"Bear","Base","Bull"},0),Assumptions!$B$84,Assumptions!$C$84,Assumptions!$D$84))/(1+Assumptions!$B$54)^3+(IS!$F$14*(1+$A45)^4)*(E$43*(1-Assumptions!$B$50)-Assumptions!$G$37+CHOOSE(MATCH(Scenario,{"Bear","Base","Bull"},0),Assumptions!$B$84,Assumptions!$C$84,Assumptions!$D$84))/(1+Assumptions!$B$54)^4+(IS!$F$14*(1+$A45)^4)*(E$43*(1-Assumptions!$B$50)-Assumptions!$G$37+CHOOSE(MATCH(Scenario,{"Bear","Base","Bull"},0),Assumptions!$B$84,Assumptions!$C$84,Assumptions!$D$84))*(1+Assumptions!$B$55)/(Assumptions!$B$54-Assumptions!$B$55)/(1+Assumptions!$B$54)^4+$B$23)/Assumptions!$B$58 -> 127.20288 | F45: =((IS!$F$14*(1+$A45))*(F$43*(1-Assumptions!$B$50)-Assumptions!$G$37+CHOOSE(MATCH(Scenario,{"Bear","Base","Bull"},0),Assumptions!$B$84,Assumptions!$C$84,Assumptions!$D$84))/(1+Assumptions!$B$54)^1+(IS!$F$14*(1+$A45)^2)*(F$43*(1-Assumptions!$B$50)-Assumptions!$G$37+CHOOSE(MATCH(Scenario,{"Bear","Base","Bull"},0),Assumptions!$B$84,Assumptions!$C$84,Assumptions!$D$84))/(1+Assumptions!$B$54)^2+(IS!$F$14*(1+$A45)^3)*(F$43*(1-Assumptions!$B$50)-Assumptions!$G$37+CHOOSE(MATCH(Scenario,{"Bear","Base","Bull"},0),Assumptions!$B$84,Assumptions!$C$84,Assumptions!$D$84))/(1+Assumptions!$B$54)^3+(IS!$F$14*(1+$A45)^4)*(F$43*(1-Assumptions!$B$50)-Assumptions!$G$37+CHOOSE(MATCH(Scenario,{"Bear","Base","Bull"},0),Assumptions!$B$84,Assumptions!$C$84,Assumptions!$D$84))/(1+Assumptions!$B$54)^4+(IS!$F$14*(1+$A45)^4)*(F$43*(1-Assumptions!$B$50)-Assumptions!$G$37+CHOOSE(MATCH(Scenario,{"Bear","Base","Bull"},0),Assumptions!$B$84,Assumptions!$C$84,Assumptions!$D$84))*(1+Assumptions!$B$55)/(Assumptions!$B$54-Assumptions!$B$55)/(1+Assumptions!$B$54)^4+$B$23)/Assumptions!$B$58 -> 134.52293
A46: 0.05 | B46: =((IS!$F$14*(1+$A46))*(B$43*(1-Assumptions!$B$50)-Assumptions!$G$37+CHOOSE(MATCH(Scenario,{"Bear","Base","Bull"},0),Assumptions!$B$84,Assumptions!$C$84,Assumptions!$D$84))/(1+Assumptions!$B$54)^1+(IS!$F$14*(1+$A46)^2)*(B$43*(1-Assumptions!$B$50)-Assumptions!$G$37+CHOOSE(MATCH(Scenario,{"Bear","Base","Bull"},0),Assumptions!$B$84,Assumptions!$C$84,Assumptions!$D$84))/(1+Assumptions!$B$54)^2+(IS!$F$14*(1+$A46)^3)*(B$43*(1-Assumptions!$B$50)-Assumptions!$G$37+CHOOSE(MATCH(Scenario,{"Bear","Base","Bull"},0),Assumptions!$B$84,Assumptions!$C$84,Assumptions!$D$84))/(1+Assumptions!$B$54)^3+(IS!$F$14*(1+$A46)^4)*(B$43*(1-Assumptions!$B$50)-Assumptions!$G$37+CHOOSE(MATCH(Scenario,{"Bear","Base","Bull"},0),Assumptions!$B$84,Assumptions!$C$84,Assumptions!$D$84))/(1+Assumptions!$B$54)^4+(IS!$F$14*(1+$A46)^4)*(B$43*(1-Assumptions!$B$50)-Assumptions!$G$37+CHOOSE(MATCH(Scenario,{"Bear","Base","Bull"},0),Assumptions!$B$84,Assumptions!$C$84,Assumptions!$D$84))*(1+Assumptions!$B$55)/(Assumptions!$B$54-Assumptions!$B$55)/(1+Assumptions!$B$54)^4+$B$23)/Assumptions!$B$58 -> 110.77199 | C46: =((IS!$F$14*(1+$A46))*(C$43*(1-Assumptions!$B$50)-Assumptions!$G$37+CHOOSE(MATCH(Scenario,{"Bear","Base","Bull"},0),Assumptions!$B$84,Assumptions!$C$84,Assumptions!$D$84))/(1+Assumptions!$B$54)^1+(IS!$F$14*(1+$A46)^2)*(C$43*(1-Assumptions!$B$50)-Assumptions!$G$37+CHOOSE(MATCH(Scenario,{"Bear","Base","Bull"},0),Assumptions!$B$84,Assumptions!$C$84,Assumptions!$D$84))/(1+Assumptions!$B$54)^2+(IS!$F$14*(1+$A46)^3)*(C$43*(1-Assumptions!$B$50)-Assumptions!$G$37+CHOOSE(MATCH(Scenario,{"Bear","Base","Bull"},0),Assumptions!$B$84,Assumptions!$C$84,Assumptions!$D$84))/(1+Assumptions!$B$54)^3+(IS!$F$14*(1+$A46)^4)*(C$43*(1-Assumptions!$B$50)-Assumptions!$G$37+CHOOSE(MATCH(Scenario,{"Bear","Base","Bull"},0),Assumptions!$B$84,Assumptions!$C$84,Assumptions!$D$84))/(1+Assumptions!$B$54)^4+(IS!$F$14*(1+$A46)^4)*(C$43*(1-Assumptions!$B$50)-Assumptions!$G$37+CHOOSE(MATCH(Scenario,{"Bear","Base","Bull"},0),Assumptions!$B$84,Assumptions!$C$84,Assumptions!$D$84))*(1+Assumptions!$B$55)/(Assumptions!$B$54-Assumptions!$B$55)/(1+Assumptions!$B$54)^4+$B$23)/Assumptions!$B$58 -> 118.48698 | D46: =((IS!$F$14*(1+$A46))*(D$43*(1-Assumptions!$B$50)-Assumptions!$G$37+CHOOSE(MATCH(Scenario,{"Bear","Base","Bull"},0),Assumptions!$B$84,Assumptions!$C$84,Assumptions!$D$84))/(1+Assumptions!$B$54)^1+(IS!$F$14*(1+$A46)^2)*(D$43*(1-Assumptions!$B$50)-Assumptions!$G$37+CHOOSE(MATCH(Scenario,{"Bear","Base","Bull"},0),Assumptions!$B$84,Assumptions!$C$84,Assumptions!$D$84))/(1+Assumptions!$B$54)^2+(IS!$F$14*(1+$A46)^3)*(D$43*(1-Assumptions!$B$50)-Assumptions!$G$37+CHOOSE(MATCH(Scenario,{"Bear","Base","Bull"},0),Assumptions!$B$84,Assumptions!$C$84,Assumptions!$D$84))/(1+Assumptions!$B$54)^3+(IS!$F$14*(1+$A46)^4)*(D$43*(1-Assumptions!$B$50)-Assumptions!$G$37+CHOOSE(MATCH(Scenario,{"Bear","Base","Bull"},0),Assumptions!$B$84,Assumptions!$C$84,Assumptions!$D$84))/(1+Assumptions!$B$54)^4+(IS!$F$14*(1+$A46)^4)*(D$43*(1-Assumptions!$B$50)-Assumptions!$G$37+CHOOSE(MATCH(Scenario,{"Bear","Base","Bull"},0),Assumptions!$B$84,Assumptions!$C$84,Assumptions!$D$84))*(1+Assumptions!$B$55)/(Assumptions!$B$54-Assumptions!$B$55)/(1+Assumptions!$B$54)^4+$B$23)/Assumptions!$B$58 -> 126.20197 | E46: =((IS!$F$14*(1+$A46))*(E$43*(1-Assumptions!$B$50)-Assumptions!$G$37+CHOOSE(MATCH(Scenario,{"Bear","Base","Bull"},0),Assumptions!$B$84,Assumptions!$C$84,Assumptions!$D$84))/(1+Assumptions!$B$54)^1+(IS!$F$14*(1+$A46)^2)*(E$43*(1-Assumptions!$B$50)-Assumptions!$G$37+CHOOSE(MATCH(Scenario,{"Bear","Base","Bull"},0),Assumptions!$B$84,Assumptions!$C$84,Assumptions!$D$84))/(1+Assumptions!$B$54)^2+(IS!$F$14*(1+$A46)^3)*(E$43*(1-Assumptions!$B$50)-Assumptions!$G$37+CHOOSE(MATCH(Scenario,{"Bear","Base","Bull"},0),Assumptions!$B$84,Assumptions!$C$84,Assumptions!$D$84))/(1+Assumptions!$B$54)^3+(IS!$F$14*(1+$A46)^4)*(E$43*(1-Assumptions!$B$50)-Assumptions!$G$37+CHOOSE(MATCH(Scenario,{"Bear","Base","Bull"},0),Assumptions!$B$84,Assumptions!$C$84,Assumptions!$D$84))/(1+Assumptions!$B$54)^4+(IS!$F$14*(1+$A46)^4)*(E$43*(1-Assumptions!$B$50)-Assumptions!$G$37+CHOOSE(MATCH(Scenario,{"Bear","Base","Bull"},0),Assumptions!$B$84,Assumptions!$C$84,Assumptions!$D$84))*(1+Assumptions!$B$55)/(Assumptions!$B$54-Assumptions!$B$55)/(1+Assumptions!$B$54)^4+$B$23)/Assumptions!$B$58 -> 133.91696 | F46: =((IS!$F$14*(1+$A46))*(F$43*(1-Assumptions!$B$50)-Assumptions!$G$37+CHOOSE(MATCH(Scenario,{"Bear","Base","Bull"},0),Assumptions!$B$84,Assumptions!$C$84,Assumptions!$D$84))/(1+Assumptions!$B$54)^1+(IS!$F$14*(1+$A46)^2)*(F$43*(1-Assumptions!$B$50)-Assumptions!$G$37+CHOOSE(MATCH(Scenario,{"Bear","Base","Bull"},0),Assumptions!$B$84,Assumptions!$C$84,Assumptions!$D$84))/(1+Assumptions!$B$54)^2+(IS!$F$14*(1+$A46)^3)*(F$43*(1-Assumptions!$B$50)-Assumptions!$G$37+CHOOSE(MATCH(Scenario,{"Bear","Base","Bull"},0),Assumptions!$B$84,Assumptions!$C$84,Assumptions!$D$84))/(1+Assumptions!$B$54)^3+(IS!$F$14*(1+$A46)^4)*(F$43*(1-Assumptions!$B$50)-Assumptions!$G$37+CHOOSE(MATCH(Scenario,{"Bear","Base","Bull"},0),Assumptions!$B$84,Assumptions!$C$84,Assumptions!$D$84))/(1+Assumptions!$B$54)^4+(IS!$F$14*(1+$A46)^4)*(F$43*(1-Assumptions!$B$50)-Assumptions!$G$37+CHOOSE(MATCH(Scenario,{"Bear","Base","Bull"},0),Assumptions!$B$84,Assumptions!$C$84,Assumptions!$D$84))*(1+Assumptions!$B$55)/(Assumptions!$B$54-Assumptions!$B$55)/(1+Assumptions!$B$54)^4+$B$23)/Assumptions!$B$58 -> 141.63195
A47: 0.065 | B47: =((IS!$F$14*(1+$A47))*(B$43*(1-Assumptions!$B$50)-Assumptions!$G$37+CHOOSE(MATCH(Scenario,{"Bear","Base","Bull"},0),Assumptions!$B$84,Assumptions!$C$84,Assumptions!$D$84))/(1+Assumptions!$B$54)^1+(IS!$F$14*(1+$A47)^2)*(B$43*(1-Assumptions!$B$50)-Assumptions!$G$37+CHOOSE(MATCH(Scenario,{"Bear","Base","Bull"},0),Assumptions!$B$84,Assumptions!$C$84,Assumptions!$D$84))/(1+Assumptions!$B$54)^2+(IS!$F$14*(1+$A47)^3)*(B$43*(1-Assumptions!$B$50)-Assumptions!$G$37+CHOOSE(MATCH(Scenario,{"Bear","Base","Bull"},0),Assumptions!$B$84,Assumptions!$C$84,Assumptions!$D$84))/(1+Assumptions!$B$54)^3+(IS!$F$14*(1+$A47)^4)*(B$43*(1-Assumptions!$B$50)-Assumptions!$G$37+CHOOSE(MATCH(Scenario,{"Bear","Base","Bull"},0),Assumptions!$B$84,Assumptions!$C$84,Assumptions!$D$84))/(1+Assumptions!$B$54)^4+(IS!$F$14*(1+$A47)^4)*(B$43*(1-Assumptions!$B$50)-Assumptions!$G$37+CHOOSE(MATCH(Scenario,{"Bear","Base","Bull"},0),Assumptions!$B$84,Assumptions!$C$84,Assumptions!$D$84))*(1+Assumptions!$B$55)/(Assumptions!$B$54-Assumptions!$B$55)/(1+Assumptions!$B$54)^4+$B$23)/Assumptions!$B$58 -> 116.53064 | C47: =((IS!$F$14*(1+$A47))*(C$43*(1-Assumptions!$B$50)-Assumptions!$G$37+CHOOSE(MATCH(Scenario,{"Bear","Base","Bull"},0),Assumptions!$B$84,Assumptions!$C$84,Assumptions!$D$84))/(1+Assumptions!$B$54)^1+(IS!$F$14*(1+$A47)^2)*(C$43*(1-Assumptions!$B$50)-Assumptions!$G$37+CHOOSE(MATCH(Scenario,{"Bear","Base","Bull"},0),Assumptions!$B$84,Assumptions!$C$84,Assumptions!$D$84))/(1+Assumptions!$B$54)^2+(IS!$F$14*(1+$A47)^3)*(C$43*(1-Assumptions!$B$50)-Assumptions!$G$37+CHOOSE(MATCH(Scenario,{"Bear","Base","Bull"},0),Assumptions!$B$84,Assumptions!$C$84,Assumptions!$D$84))/(1+Assumptions!$B$54)^3+(IS!$F$14*(1+$A47)^4)*(C$43*(1-Assumptions!$B$50)-Assumptions!$G$37+CHOOSE(MATCH(Scenario,{"Bear","Base","Bull"},0),Assumptions!$B$84,Assumptions!$C$84,Assumptions!$D$84))/(1+Assumptions!$B$54)^4+(IS!$F$14*(1+$A47)^4)*(C$43*(1-Assumptions!$B$50)-Assumptions!$G$37+CHOOSE(MATCH(Scenario,{"Bear","Base","Bull"},0),Assumptions!$B$84,Assumptions!$C$84,Assumptions!$D$84))*(1+Assumptions!$B$55)/(Assumptions!$B$54-Assumptions!$B$55)/(1+Assumptions!$B$54)^4+$B$23)/Assumptions!$B$58 -> 124.65696 | D47: =((IS!$F$14*(1+$A47))*(D$43*(1-Assumptions!$B$50)-Assumptions!$G$37+CHOOSE(MATCH(Scenario,{"Bear","Base","Bull"},0),Assumptions!$B$84,Assumptions!$C$84,Assumptions!$D$84))/(1+Assumptions!$B$54)^1+(IS!$F$14*(1+$A47)^2)*(D$43*(1-Assumptions!$B$50)-Assumptions!$G$37+CHOOSE(MATCH(Scenario,{"Bear","Base","Bull"},0),Assumptions!$B$84,Assumptions!$C$84,Assumptions!$D$84))/(1+Assumptions!$B$54)^2+(IS!$F$14*(1+$A47)^3)*(D$43*(1-Assumptions!$B$50)-Assumptions!$G$37+CHOOSE(MATCH(Scenario,{"Bear","Base","Bull"},0),Assumptions!$B$84,Assumptions!$C$84,Assumptions!$D$84))/(1+Assumptions!$B$54)^3+(IS!$F$14*(1+$A47)^4)*(D$43*(1-Assumptions!$B$50)-Assumptions!$G$37+CHOOSE(MATCH(Scenario,{"Bear","Base","Bull"},0),Assumptions!$B$84,Assumptions!$C$84,Assumptions!$D$84))/(1+Assumptions!$B$54)^4+(IS!$F$14*(1+$A47)^4)*(D$43*(1-Assumptions!$B$50)-Assumptions!$G$37+CHOOSE(MATCH(Scenario,{"Bear","Base","Bull"},0),Assumptions!$B$84,Assumptions!$C$84,Assumptions!$D$84))*(1+Assumptions!$B$55)/(Assumptions!$B$54-Assumptions!$B$55)/(1+Assumptions!$B$54)^4+$B$23)/Assumptions!$B$58 -> 132.78329 | E47: =((IS!$F$14*(1+$A47))*(E$43*(1-Assumptions!$B$50)-Assumptions!$G$37+CHOOSE(MATCH(Scenario,{"Bear","Base","Bull"},0),Assumptions!$B$84,Assumptions!$C$84,Assumptions!$D$84))/(1+Assumptions!$B$54)^1+(IS!$F$14*(1+$A47)^2)*(E$43*(1-Assumptions!$B$50)-Assumptions!$G$37+CHOOSE(MATCH(Scenario,{"Bear","Base","Bull"},0),Assumptions!$B$84,Assumptions!$C$84,Assumptions!$D$84))/(1+Assumptions!$B$54)^2+(IS!$F$14*(1+$A47)^3)*(E$43*(1-Assumptions!$B$50)-Assumptions!$G$37+CHOOSE(MATCH(Scenario,{"Bear","Base","Bull"},0),Assumptions!$B$84,Assumptions!$C$84,Assumptions!$D$84))/(1+Assumptions!$B$54)^3+(IS!$F$14*(1+$A47)^4)*(E$43*(1-Assumptions!$B$50)-Assumptions!$G$37+CHOOSE(MATCH(Scenario,{"Bear","Base","Bull"},0),Assumptions!$B$84,Assumptions!$C$84,Assumptions!$D$84))/(1+Assumptions!$B$54)^4+(IS!$F$14*(1+$A47)^4)*(E$43*(1-Assumptions!$B$50)-Assumptions!$G$37+CHOOSE(MATCH(Scenario,{"Bear","Base","Bull"},0),Assumptions!$B$84,Assumptions!$C$84,Assumptions!$D$84))*(1+Assumptions!$B$55)/(Assumptions!$B$54-Assumptions!$B$55)/(1+Assumptions!$B$54)^4+$B$23)/Assumptions!$B$58 -> 140.90961 | F47: =((IS!$F$14*(1+$A47))*(F$43*(1-Assumptions!$B$50)-Assumptions!$G$37+CHOOSE(MATCH(Scenario,{"Bear","Base","Bull"},0),Assumptions!$B$84,Assumptions!$C$84,Assumptions!$D$84))/(1+Assumptions!$B$54)^1+(IS!$F$14*(1+$A47)^2)*(F$43*(1-Assumptions!$B$50)-Assumptions!$G$37+CHOOSE(MATCH(Scenario,{"Bear","Base","Bull"},0),Assumptions!$B$84,Assumptions!$C$84,Assumptions!$D$84))/(1+Assumptions!$B$54)^2+(IS!$F$14*(1+$A47)^3)*(F$43*(1-Assumptions!$B$50)-Assumptions!$G$37+CHOOSE(MATCH(Scenario,{"Bear","Base","Bull"},0),Assumptions!$B$84,Assumptions!$C$84,Assumptions!$D$84))/(1+Assumptions!$B$54)^3+(IS!$F$14*(1+$A47)^4)*(F$43*(1-Assumptions!$B$50)-Assumptions!$G$37+CHOOSE(MATCH(Scenario,{"Bear","Base","Bull"},0),Assumptions!$B$84,Assumptions!$C$84,Assumptions!$D$84))/(1+Assumptions!$B$54)^4+(IS!$F$14*(1+$A47)^4)*(F$43*(1-Assumptions!$B$50)-Assumptions!$G$37+CHOOSE(MATCH(Scenario,{"Bear","Base","Bull"},0),Assumptions!$B$84,Assumptions!$C$84,Assumptions!$D$84))*(1+Assumptions!$B$55)/(Assumptions!$B$54-Assumptions!$B$55)/(1+Assumptions!$B$54)^4+$B$23)/Assumptions!$B$58 -> 149.03593
A48: 0.08 | B48: =((IS!$F$14*(1+$A48))*(B$43*(1-Assumptions!$B$50)-Assumptions!$G$37+CHOOSE(MATCH(Scenario,{"Bear","Base","Bull"},0),Assumptions!$B$84,Assumptions!$C$84,Assumptions!$D$84))/(1+Assumptions!$B$54)^1+(IS!$F$14*(1+$A48)^2)*(B$43*(1-Assumptions!$B$50)-Assumptions!$G$37+CHOOSE(MATCH(Scenario,{"Bear","Base","Bull"},0),Assumptions!$B$84,Assumptions!$C$84,Assumptions!$D$84))/(1+Assumptions!$B$54)^2+(IS!$F$14*(1+$A48)^3)*(B$43*(1-Assumptions!$B$50)-Assumptions!$G$37+CHOOSE(MATCH(Scenario,{"Bear","Base","Bull"},0),Assumptions!$B$84,Assumptions!$C$84,Assumptions!$D$84))/(1+Assumptions!$B$54)^3+(IS!$F$14*(1+$A48)^4)*(B$43*(1-Assumptions!$B$50)-Assumptions!$G$37+CHOOSE(MATCH(Scenario,{"Bear","Base","Bull"},0),Assumptions!$B$84,Assumptions!$C$84,Assumptions!$D$84))/(1+Assumptions!$B$54)^4+(IS!$F$14*(1+$A48)^4)*(B$43*(1-Assumptions!$B$50)-Assumptions!$G$37+CHOOSE(MATCH(Scenario,{"Bear","Base","Bull"},0),Assumptions!$B$84,Assumptions!$C$84,Assumptions!$D$84))*(1+Assumptions!$B$55)/(Assumptions!$B$54-Assumptions!$B$55)/(1+Assumptions!$B$54)^4+$B$23)/Assumptions!$B$58 -> 122.52514 | C48: =((IS!$F$14*(1+$A48))*(C$43*(1-Assumptions!$B$50)-Assumptions!$G$37+CHOOSE(MATCH(Scenario,{"Bear","Base","Bull"},0),Assumptions!$B$84,Assumptions!$C$84,Assumptions!$D$84))/(1+Assumptions!$B$54)^1+(IS!$F$14*(1+$A48)^2)*(C$43*(1-Assumptions!$B$50)-Assumptions!$G$37+CHOOSE(MATCH(Scenario,{"Bear","Base","Bull"},0),Assumptions!$B$84,Assumptions!$C$84,Assumptions!$D$84))/(1+Assumptions!$B$54)^2+(IS!$F$14*(1+$A48)^3)*(C$43*(1-Assumptions!$B$50)-Assumptions!$G$37+CHOOSE(MATCH(Scenario,{"Bear","Base","Bull"},0),Assumptions!$B$84,Assumptions!$C$84,Assumptions!$D$84))/(1+Assumptions!$B$54)^3+(IS!$F$14*(1+$A48)^4)*(C$43*(1-Assumptions!$B$50)-Assumptions!$G$37+CHOOSE(MATCH(Scenario,{"Bear","Base","Bull"},0),Assumptions!$B$84,Assumptions!$C$84,Assumptions!$D$84))/(1+Assumptions!$B$54)^4+(IS!$F$14*(1+$A48)^4)*(C$43*(1-Assumptions!$B$50)-Assumptions!$G$37+CHOOSE(MATCH(Scenario,{"Bear","Base","Bull"},0),Assumptions!$B$84,Assumptions!$C$84,Assumptions!$D$84))*(1+Assumptions!$B$55)/(Assumptions!$B$54-Assumptions!$B$55)/(1+Assumptions!$B$54)^4+$B$23)/Assumptions!$B$58 -> 131.07964 | D48: =((IS!$F$14*(1+$A48))*(D$43*(1-Assumptions!$B$50)-Assumptions!$G$37+CHOOSE(MATCH(Scenario,{"Bear","Base","Bull"},0),Assumptions!$B$84,Assumptions!$C$84,Assumptions!$D$84))/(1+Assumptions!$B$54)^1+(IS!$F$14*(1+$A48)^2)*(D$43*(1-Assumptions!$B$50)-Assumptions!$G$37+CHOOSE(MATCH(Scenario,{"Bear","Base","Bull"},0),Assumptions!$B$84,Assumptions!$C$84,Assumptions!$D$84))/(1+Assumptions!$B$54)^2+(IS!$F$14*(1+$A48)^3)*(D$43*(1-Assumptions!$B$50)-Assumptions!$G$37+CHOOSE(MATCH(Scenario,{"Bear","Base","Bull"},0),Assumptions!$B$84,Assumptions!$C$84,Assumptions!$D$84))/(1+Assumptions!$B$54)^3+(IS!$F$14*(1+$A48)^4)*(D$43*(1-Assumptions!$B$50)-Assumptions!$G$37+CHOOSE(MATCH(Scenario,{"Bear","Base","Bull"},0),Assumptions!$B$84,Assumptions!$C$84,Assumptions!$D$84))/(1+Assumptions!$B$54)^4+(IS!$F$14*(1+$A48)^4)*(D$43*(1-Assumptions!$B$50)-Assumptions!$G$37+CHOOSE(MATCH(Scenario,{"Bear","Base","Bull"},0),Assumptions!$B$84,Assumptions!$C$84,Assumptions!$D$84))*(1+Assumptions!$B$55)/(Assumptions!$B$54-Assumptions!$B$55)/(1+Assumptions!$B$54)^4+$B$23)/Assumptions!$B$58 -> 139.63414 | E48: =((IS!$F$14*(1+$A48))*(E$43*(1-Assumptions!$B$50)-Assumptions!$G$37+CHOOSE(MATCH(Scenario,{"Bear","Base","Bull"},0),Assumptions!$B$84,Assumptions!$C$84,Assumptions!$D$84))/(1+Assumptions!$B$54)^1+(IS!$F$14*(1+$A48)^2)*(E$43*(1-Assumptions!$B$50)-Assumptions!$G$37+CHOOSE(MATCH(Scenario,{"Bear","Base","Bull"},0),Assumptions!$B$84,Assumptions!$C$84,Assumptions!$D$84))/(1+Assumptions!$B$54)^2+(IS!$F$14*(1+$A48)^3)*(E$43*(1-Assumptions!$B$50)-Assumptions!$G$37+CHOOSE(MATCH(Scenario,{"Bear","Base","Bull"},0),Assumptions!$B$84,Assumptions!$C$84,Assumptions!$D$84))/(1+Assumptions!$B$54)^3+(IS!$F$14*(1+$A48)^4)*(E$43*(1-Assumptions!$B$50)-Assumptions!$G$37+CHOOSE(MATCH(Scenario,{"Bear","Base","Bull"},0),Assumptions!$B$84,Assumptions!$C$84,Assumptions!$D$84))/(1+Assumptions!$B$54)^4+(IS!$F$14*(1+$A48)^4)*(E$43*(1-Assumptions!$B$50)-Assumptions!$G$37+CHOOSE(MATCH(Scenario,{"Bear","Base","Bull"},0),Assumptions!$B$84,Assumptions!$C$84,Assumptions!$D$84))*(1+Assumptions!$B$55)/(Assumptions!$B$54-Assumptions!$B$55)/(1+Assumptions!$B$54)^4+$B$23)/Assumptions!$B$58 -> 148.18864 | F48: =((IS!$F$14*(1+$A48))*(F$43*(1-Assumptions!$B$50)-Assumptions!$G$37+CHOOSE(MATCH(Scenario,{"Bear","Base","Bull"},0),Assumptions!$B$84,Assumptions!$C$84,Assumptions!$D$84))/(1+Assumptions!$B$54)^1+(IS!$F$14*(1+$A48)^2)*(F$43*(1-Assumptions!$B$50)-Assumptions!$G$37+CHOOSE(MATCH(Scenario,{"Bear","Base","Bull"},0),Assumptions!$B$84,Assumptions!$C$84,Assumptions!$D$84))/(1+Assumptions!$B$54)^2+(IS!$F$14*(1+$A48)^3)*(F$43*(1-Assumptions!$B$50)-Assumptions!$G$37+CHOOSE(MATCH(Scenario,{"Bear","Base","Bull"},0),Assumptions!$B$84,Assumptions!$C$84,Assumptions!$D$84))/(1+Assumptions!$B$54)^3+(IS!$F$14*(1+$A48)^4)*(F$43*(1-Assumptions!$B$50)-Assumptions!$G$37+CHOOSE(MATCH(Scenario,{"Bear","Base","Bull"},0),Assumptions!$B$84,Assumptions!$C$84,Assumptions!$D$84))/(1+Assumptions!$B$54)^4+(IS!$F$14*(1+$A48)^4)*(F$43*(1-Assumptions!$B$50)-Assumptions!$G$37+CHOOSE(MATCH(Scenario,{"Bear","Base","Bull"},0),Assumptions!$B$84,Assumptions!$C$84,Assumptions!$D$84))*(1+Assumptions!$B$55)/(Assumptions!$B$54-Assumptions!$B$55)/(1+Assumptions!$B$54)^4+$B$23)/Assumptions!$B$58 -> 156.74314
A51: TORNADO | Sensitivity of Implied Share Price to Key Drivers (±1 standard move)
A52: Driver | B52: Low Case | C52: High Case | D52: Low Price | E52: High Price | F52: Swing ($) | G52: Notes
A53: Revenue growth (avg) | B53: -1.0% | C53: +1.0% | D53: =((IS!$F$14*(1+(AVERAGE(IS!$H$15:$K$15))-0.01))*((AVERAGE(IS!$H$30:$K$30))*(1-(Assumptions!$B$50))-(Assumptions!$G$37)+CHOOSE(MATCH(Scenario,{"Bear","Base","Bull"},0),Assumptions!$B$84,Assumptions!$C$84,Assumptions!$D$84))/(1+(Assumptions!$B$54))^1+(IS!$F$14*(1+(AVERAGE(IS!$H$15:$K$15))-0.01)^2)*((AVERAGE(IS!$H$30:$K$30))*(1-(Assumptions!$B$50))-(Assumptions!$G$37)+CHOOSE(MATCH(Scenario,{"Bear","Base","Bull"},0),Assumptions!$B$84,Assumptions!$C$84,Assumptions!$D$84))/(1+(Assumptions!$B$54))^2+(IS!$F$14*(1+(AVERAGE(IS!$H$15:$K$15))-0.01)^3)*((AVERAGE(IS!$H$30:$K$30))*(1-(Assumptions!$B$50))-(Assumptions!$G$37)+CHOOSE(MATCH(Scenario,{"Bear","Base","Bull"},0),Assumptions!$B$84,Assumptions!$C$84,Assumptions!$D$84))/(1+(Assumptions!$B$54))^3+(IS!$F$14*(1+(AVERAGE(IS!$H$15:$K$15))-0.01)^4)*((AVERAGE(IS!$H$30:$K$30))*(1-(Assumptions!$B$50))-(Assumptions!$G$37)+CHOOSE(MATCH(Scenario,{"Bear","Base","Bull"},0),Assumptions!$B$84,Assumptions!$C$84,Assumptions!$D$84))/(1+(Assumptions!$B$54))^4+(IS!$F$14*(1+(AVERAGE(IS!$H$15:$K$15))-0.01)^4)*((AVERAGE(IS!$H$30:$K$30))*(1-(Assumptions!$B$50))-(Assumptions!$G$37)+CHOOSE(MATCH(Scenario,{"Bear","Base","Bull"},0),Assumptions!$B$84,Assumptions!$C$84,Assumptions!$D$84))*(1+(Assumptions!$B$55))/((Assumptions!$B$54)-(Assumptions!$B$55))/(1+(Assumptions!$B$54))^4+$B$23)/Assumptions!$B$58 -> 127.36545 | E53: =((IS!$F$14*(1+(AVERAGE(IS!$H$15:$K$15))+0.01))*((AVERAGE(IS!$H$30:$K$30))*(1-(Assumptions!$B$50))-(Assumptions!$G$37)+CHOOSE(MATCH(Scenario,{"Bear","Base","Bull"},0),Assumptions!$B$84,Assumptions!$C$84,Assumptions!$D$84))/(1+(Assumptions!$B$54))^1+(IS!$F$14*(1+(AVERAGE(IS!$H$15:$K$15))+0.01)^2)*((AVERAGE(IS!$H$30:$K$30))*(1-(Assumptions!$B$50))-(Assumptions!$G$37)+CHOOSE(MATCH(Scenario,{"Bear","Base","Bull"},0),Assumptions!$B$84,Assumptions!$C$84,Assumptions!$D$84))/(1+(Assumptions!$B$54))^2+(IS!$F$14*(1+(AVERAGE(IS!$H$15:$K$15))+0.01)^3)*((AVERAGE(IS!$H$30:$K$30))*(1-(Assumptions!$B$50))-(Assumptions!$G$37)+CHOOSE(MATCH(Scenario,{"Bear","Base","Bull"},0),Assumptions!$B$84,Assumptions!$C$84,Assumptions!$D$84))/(1+(Assumptions!$B$54))^3+(IS!$F$14*(1+(AVERAGE(IS!$H$15:$K$15))+0.01)^4)*((AVERAGE(IS!$H$30:$K$30))*(1-(Assumptions!$B$50))-(Assumptions!$G$37)+CHOOSE(MATCH(Scenario,{"Bear","Base","Bull"},0),Assumptions!$B$84,Assumptions!$C$84,Assumptions!$D$84))/(1+(Assumptions!$B$54))^4+(IS!$F$14*(1+(AVERAGE(IS!$H$15:$K$15))+0.01)^4)*((AVERAGE(IS!$H$30:$K$30))*(1-(Assumptions!$B$50))-(Assumptions!$G$37)+CHOOSE(MATCH(Scenario,{"Bear","Base","Bull"},0),Assumptions!$B$84,Assumptions!$C$84,Assumptions!$D$84))*(1+(Assumptions!$B$55))/((Assumptions!$B$54)-(Assumptions!$B$55))/(1+(Assumptions!$B$54))^4+$B$23)/Assumptions!$B$58 -> 136.34465 | F53: =ABS(E53-D53) -> 8.9792012 | G53: ="±1.0 pt off "&TEXT(AVERAGE(IS!H15:K15),"0.0%")&" average revenue growth" -> ±1.0 pt off 5.1% average revenue growth
A54: Operating margin | B54: -200 bps | C54: +200 bps | D54: =((IS!$F$14*(1+AVERAGE(IS!$H$15:$K$15)))*(((AVERAGE(IS!$H$30:$K$30))-0.02)*(1-(Assumptions!$B$50))-(Assumptions!$G$37)+CHOOSE(MATCH(Scenario,{"Bear","Base","Bull"},0),Assumptions!$B$84,Assumptions!$C$84,Assumptions!$D$84))/(1+(Assumptions!$B$54))^1+(IS!$F$14*(1+AVERAGE(IS!$H$15:$K$15))^2)*(((AVERAGE(IS!$H$30:$K$30))-0.02)*(1-(Assumptions!$B$50))-(Assumptions!$G$37)+CHOOSE(MATCH(Scenario,{"Bear","Base","Bull"},0),Assumptions!$B$84,Assumptions!$C$84,Assumptions!$D$84))/(1+(Assumptions!$B$54))^2+(IS!$F$14*(1+AVERAGE(IS!$H$15:$K$15))^3)*(((AVERAGE(IS!$H$30:$K$30))-0.02)*(1-(Assumptions!$B$50))-(Assumptions!$G$37)+CHOOSE(MATCH(Scenario,{"Bear","Base","Bull"},0),Assumptions!$B$84,Assumptions!$C$84,Assumptions!$D$84))/(1+(Assumptions!$B$54))^3+(IS!$F$14*(1+AVERAGE(IS!$H$15:$K$15))^4)*(((AVERAGE(IS!$H$30:$K$30))-0.02)*(1-(Assumptions!$B$50))-(Assumptions!$G$37)+CHOOSE(MATCH(Scenario,{"Bear","Base","Bull"},0),Assumptions!$B$84,Assumptions!$C$84,Assumptions!$D$84))/(1+(Assumptions!$B$54))^4+(IS!$F$14*(1+AVERAGE(IS!$H$15:$K$15))^4)*(((AVERAGE(IS!$H$30:$K$30))-0.02)*(1-(Assumptions!$B$50))-(Assumptions!$G$37)+CHOOSE(MATCH(Scenario,{"Bear","Base","Bull"},0),Assumptions!$B$84,Assumptions!$C$84,Assumptions!$D$84))*(1+(Assumptions!$B$55))/((Assumptions!$B$54)-(Assumptions!$B$55))/(1+(Assumptions!$B$54))^4+$B$23)/Assumptions!$B$58 -> 124.04134 | E54: =((IS!$F$14*(1+AVERAGE(IS!$H$15:$K$15)))*(((AVERAGE(IS!$H$30:$K$30))+0.02)*(1-(Assumptions!$B$50))-(Assumptions!$G$37)+CHOOSE(MATCH(Scenario,{"Bear","Base","Bull"},0),Assumptions!$B$84,Assumptions!$C$84,Assumptions!$D$84))/(1+(Assumptions!$B$54))^1+(IS!$F$14*(1+AVERAGE(IS!$H$15:$K$15))^2)*(((AVERAGE(IS!$H$30:$K$30))+0.02)*(1-(Assumptions!$B$50))-(Assumptions!$G$37)+CHOOSE(MATCH(Scenario,{"Bear","Base","Bull"},0),Assumptions!$B$84,Assumptions!$C$84,Assumptions!$D$84))/(1+(Assumptions!$B$54))^2+(IS!$F$14*(1+AVERAGE(IS!$H$15:$K$15))^3)*(((AVERAGE(IS!$H$30:$K$30))+0.02)*(1-(Assumptions!$B$50))-(Assumptions!$G$37)+CHOOSE(MATCH(Scenario,{"Bear","Base","Bull"},0),Assumptions!$B$84,Assumptions!$C$84,Assumptions!$D$84))/(1+(Assumptions!$B$54))^3+(IS!$F$14*(1+AVERAGE(IS!$H$15:$K$15))^4)*(((AVERAGE(IS!$H$30:$K$30))+0.02)*(1-(Assumptions!$B$50))-(Assumptions!$G$37)+CHOOSE(MATCH(Scenario,{"Bear","Base","Bull"},0),Assumptions!$B$84,Assumptions!$C$84,Assumptions!$D$84))/(1+(Assumptions!$B$54))^4+(IS!$F$14*(1+AVERAGE(IS!$H$15:$K$15))^4)*(((AVERAGE(IS!$H$30:$K$30))+0.02)*(1-(Assumptions!$B$50))-(Assumptions!$G$37)+CHOOSE(MATCH(Scenario,{"Bear","Base","Bull"},0),Assumptions!$B$84,Assumptions!$C$84,Assumptions!$D$84))*(1+(Assumptions!$B$55))/((Assumptions!$B$54)-(Assumptions!$B$55))/(1+(Assumptions!$B$54))^4+$B$23)/Assumptions!$B$58 -> 139.54724 | F54: =ABS(E54-D54) -> 15.505909 | G54: ="±2.0 pts off "&TEXT(AVERAGE(IS!H30:K30),"0.0%")&" average operating margin" -> ±2.0 pts off 33.3% average operating margin
A55: WACC | B55: +100 bps | C55: -100 bps | D55: =((IS!$F$14*(1+AVERAGE(IS!$H$15:$K$15)))*((AVERAGE(IS!$H$30:$K$30))*(1-(Assumptions!$B$50))-(Assumptions!$G$37)+CHOOSE(MATCH(Scenario,{"Bear","Base","Bull"},0),Assumptions!$B$84,Assumptions!$C$84,Assumptions!$D$84))/(1+((Assumptions!$B$54)+0.01))^1+(IS!$F$14*(1+AVERAGE(IS!$H$15:$K$15))^2)*((AVERAGE(IS!$H$30:$K$30))*(1-(Assumptions!$B$50))-(Assumptions!$G$37)+CHOOSE(MATCH(Scenario,{"Bear","Base","Bull"},0),Assumptions!$B$84,Assumptions!$C$84,Assumptions!$D$84))/(1+((Assumptions!$B$54)+0.01))^2+(IS!$F$14*(1+AVERAGE(IS!$H$15:$K$15))^3)*((AVERAGE(IS!$H$30:$K$30))*(1-(Assumptions!$B$50))-(Assumptions!$G$37)+CHOOSE(MATCH(Scenario,{"Bear","Base","Bull"},0),Assumptions!$B$84,Assumptions!$C$84,Assumptions!$D$84))/(1+((Assumptions!$B$54)+0.01))^3+(IS!$F$14*(1+AVERAGE(IS!$H$15:$K$15))^4)*((AVERAGE(IS!$H$30:$K$30))*(1-(Assumptions!$B$50))-(Assumptions!$G$37)+CHOOSE(MATCH(Scenario,{"Bear","Base","Bull"},0),Assumptions!$B$84,Assumptions!$C$84,Assumptions!$D$84))/(1+((Assumptions!$B$54)+0.01))^4+(IS!$F$14*(1+AVERAGE(IS!$H$15:$K$15))^4)*((AVERAGE(IS!$H$30:$K$30))*(1-(Assumptions!$B$50))-(Assumptions!$G$37)+CHOOSE(MATCH(Scenario,{"Bear","Base","Bull"},0),Assumptions!$B$84,Assumptions!$C$84,Assumptions!$D$84))*(1+(Assumptions!$B$55))/(((Assumptions!$B$54)+0.01)-(Assumptions!$B$55))/(1+((Assumptions!$B$54)+0.01))^4+$B$23)/Assumptions!$B$58 -> 115.20564 | E55: =((IS!$F$14*(1+AVERAGE(IS!$H$15:$K$15)))*((AVERAGE(IS!$H$30:$K$30))*(1-(Assumptions!$B$50))-(Assumptions!$G$37)+CHOOSE(MATCH(Scenario,{"Bear","Base","Bull"},0),Assumptions!$B$84,Assumptions!$C$84,Assumptions!$D$84))/(1+((Assumptions!$B$54)-0.01))^1+(IS!$F$14*(1+AVERAGE(IS!$H$15:$K$15))^2)*((AVERAGE(IS!$H$30:$K$30))*(1-(Assumptions!$B$50))-(Assumptions!$G$37)+CHOOSE(MATCH(Scenario,{"Bear","Base","Bull"},0),Assumptions!$B$84,Assumptions!$C$84,Assumptions!$D$84))/(1+((Assumptions!$B$54)-0.01))^2+(IS!$F$14*(1+AVERAGE(IS!$H$15:$K$15))^3)*((AVERAGE(IS!$H$30:$K$30))*(1-(Assumptions!$B$50))-(Assumptions!$G$37)+CHOOSE(MATCH(Scenario,{"Bear","Base","Bull"},0),Assumptions!$B$84,Assumptions!$C$84,Assumptions!$D$84))/(1+((Assumptions!$B$54)-0.01))^3+(IS!$F$14*(1+AVERAGE(IS!$H$15:$K$15))^4)*((AVERAGE(IS!$H$30:$K$30))*(1-(Assumptions!$B$50))-(Assumptions!$G$37)+CHOOSE(MATCH(Scenario,{"Bear","Base","Bull"},0),Assumptions!$B$84,Assumptions!$C$84,Assumptions!$D$84))/(1+((Assumptions!$B$54)-0.01))^4+(IS!$F$14*(1+AVERAGE(IS!$H$15:$K$15))^4)*((AVERAGE(IS!$H$30:$K$30))*(1-(Assumptions!$B$50))-(Assumptions!$G$37)+CHOOSE(MATCH(Scenario,{"Bear","Base","Bull"},0),Assumptions!$B$84,Assumptions!$C$84,Assumptions!$D$84))*(1+(Assumptions!$B$55))/(((Assumptions!$B$54)-0.01)-(Assumptions!$B$55))/(1+((Assumptions!$B$54)-0.01))^4+$B$23)/Assumptions!$B$58 -> 154.06937 | F55: =ABS(E55-D55) -> 38.863739 | G55: Lower WACC = higher PV
A56: Terminal growth | B56: -50 bps | C56: +50 bps | D56: =((IS!$F$14*(1+AVERAGE(IS!$H$15:$K$15)))*((AVERAGE(IS!$H$30:$K$30))*(1-(Assumptions!$B$50))-(Assumptions!$G$37)+CHOOSE(MATCH(Scenario,{"Bear","Base","Bull"},0),Assumptions!$B$84,Assumptions!$C$84,Assumptions!$D$84))/(1+(Assumptions!$B$54))^1+(IS!$F$14*(1+AVERAGE(IS!$H$15:$K$15))^2)*((AVERAGE(IS!$H$30:$K$30))*(1-(Assumptions!$B$50))-(Assumptions!$G$37)+CHOOSE(MATCH(Scenario,{"Bear","Base","Bull"},0),Assumptions!$B$84,Assumptions!$C$84,Assumptions!$D$84))/(1+(Assumptions!$B$54))^2+(IS!$F$14*(1+AVERAGE(IS!$H$15:$K$15))^3)*((AVERAGE(IS!$H$30:$K$30))*(1-(Assumptions!$B$50))-(Assumptions!$G$37)+CHOOSE(MATCH(Scenario,{"Bear","Base","Bull"},0),Assumptions!$B$84,Assumptions!$C$84,Assumptions!$D$84))/(1+(Assumptions!$B$54))^3+(IS!$F$14*(1+AVERAGE(IS!$H$15:$K$15))^4)*((AVERAGE(IS!$H$30:$K$30))*(1-(Assumptions!$B$50))-(Assumptions!$G$37)+CHOOSE(MATCH(Scenario,{"Bear","Base","Bull"},0),Assumptions!$B$84,Assumptions!$C$84,Assumptions!$D$84))/(1+(Assumptions!$B$54))^4+(IS!$F$14*(1+AVERAGE(IS!$H$15:$K$15))^4)*((AVERAGE(IS!$H$30:$K$30))*(1-(Assumptions!$B$50))-(Assumptions!$G$37)+CHOOSE(MATCH(Scenario,{"Bear","Base","Bull"},0),Assumptions!$B$84,Assumptions!$C$84,Assumptions!$D$84))*(1+((Assumptions!$B$55)-0.005))/((Assumptions!$B$54)-((Assumptions!$B$55)-0.005))/(1+(Assumptions!$B$54))^4+$B$23)/Assumptions!$B$58 -> 124.48823 | E56: =((IS!$F$14*(1+AVERAGE(IS!$H$15:$K$15)))*((AVERAGE(IS!$H$30:$K$30))*(1-(Assumptions!$B$50))-(Assumptions!$G$37)+CHOOSE(MATCH(Scenario,{"Bear","Base","Bull"},0),Assumptions!$B$84,Assumptions!$C$84,Assumptions!$D$84))/(1+(Assumptions!$B$54))^1+(IS!$F$14*(1+AVERAGE(IS!$H$15:$K$15))^2)*((AVERAGE(IS!$H$30:$K$30))*(1-(Assumptions!$B$50))-(Assumptions!$G$37)+CHOOSE(MATCH(Scenario,{"Bear","Base","Bull"},0),Assumptions!$B$84,Assumptions!$C$84,Assumptions!$D$84))/(1+(Assumptions!$B$54))^2+(IS!$F$14*(1+AVERAGE(IS!$H$15:$K$15))^3)*((AVERAGE(IS!$H$30:$K$30))*(1-(Assumptions!$B$50))-(Assumptions!$G$37)+CHOOSE(MATCH(Scenario,{"Bear","Base","Bull"},0),Assumptions!$B$84,Assumptions!$C$84,Assumptions!$D$84))/(1+(Assumptions!$B$54))^3+(IS!$F$14*(1+AVERAGE(IS!$H$15:$K$15))^4)*((AVERAGE(IS!$H$30:$K$30))*(1-(Assumptions!$B$50))-(Assumptions!$G$37)+CHOOSE(MATCH(Scenario,{"Bear","Base","Bull"},0),Assumptions!$B$84,Assumptions!$C$84,Assumptions!$D$84))/(1+(Assumptions!$B$54))^4+(IS!$F$14*(1+AVERAGE(IS!$H$15:$K$15))^4)*((AVERAGE(IS!$H$30:$K$30))*(1-(Assumptions!$B$50))-(Assumptions!$G$37)+CHOOSE(MATCH(Scenario,{"Bear","Base","Bull"},0),Assumptions!$B$84,Assumptions!$C$84,Assumptions!$D$84))*(1+((Assumptions!$B$55)+0.005))/((Assumptions!$B$54)-((Assumptions!$B$55)+0.005))/(1+(Assumptions!$B$54))^4+$B$23)/Assumptions!$B$58 -> 140.25272 | F56: =ABS(E56-D56) -> 15.764488 | G56: Gordon growth tail
A57: Effective tax rate | B57: +200 bps | C57: -200 bps | D57: =((IS!$F$14*(1+AVERAGE(IS!$H$15:$K$15)))*((AVERAGE(IS!$H$30:$K$30))*(1-((Assumptions!$B$50)+0.02))-(Assumptions!$G$37)+CHOOSE(MATCH(Scenario,{"Bear","Base","Bull"},0),Assumptions!$B$84,Assumptions!$C$84,Assumptions!$D$84))/(1+(Assumptions!$B$54))^1+(IS!$F$14*(1+AVERAGE(IS!$H$15:$K$15))^2)*((AVERAGE(IS!$H$30:$K$30))*(1-((Assumptions!$B$50)+0.02))-(Assumptions!$G$37)+CHOOSE(MATCH(Scenario,{"Bear","Base","Bull"},0),Assumptions!$B$84,Assumptions!$C$84,Assumptions!$D$84))/(1+(Assumptions!$B$54))^2+(IS!$F$14*(1+AVERAGE(IS!$H$15:$K$15))^3)*((AVERAGE(IS!$H$30:$K$30))*(1-((Assumptions!$B$50)+0.02))-(Assumptions!$G$37)+CHOOSE(MATCH(Scenario,{"Bear","Base","Bull"},0),Assumptions!$B$84,Assumptions!$C$84,Assumptions!$D$84))/(1+(Assumptions!$B$54))^3+(IS!$F$14*(1+AVERAGE(IS!$H$15:$K$15))^4)*((AVERAGE(IS!$H$30:$K$30))*(1-((Assumptions!$B$50)+0.02))-(Assumptions!$G$37)+CHOOSE(MATCH(Scenario,{"Bear","Base","Bull"},0),Assumptions!$B$84,Assumptions!$C$84,Assumptions!$D$84))/(1+(Assumptions!$B$54))^4+(IS!$F$14*(1+AVERAGE(IS!$H$15:$K$15))^4)*((AVERAGE(IS!$H$30:$K$30))*(1-((Assumptions!$B$50)+0.02))-(Assumptions!$G$37)+CHOOSE(MATCH(Scenario,{"Bear","Base","Bull"},0),Assumptions!$B$84,Assumptions!$C$84,Assumptions!$D$84))*(1+(Assumptions!$B$55))/((Assumptions!$B$54)-(Assumptions!$B$55))/(1+(Assumptions!$B$54))^4+$B$23)/Assumptions!$B$58 -> 128.75824 | E57: =((IS!$F$14*(1+AVERAGE(IS!$H$15:$K$15)))*((AVERAGE(IS!$H$30:$K$30))*(1-((Assumptions!$B$50)-0.02))-(Assumptions!$G$37)+CHOOSE(MATCH(Scenario,{"Bear","Base","Bull"},0),Assumptions!$B$84,Assumptions!$C$84,Assumptions!$D$84))/(1+(Assumptions!$B$54))^1+(IS!$F$14*(1+AVERAGE(IS!$H$15:$K$15))^2)*((AVERAGE(IS!$H$30:$K$30))*(1-((Assumptions!$B$50)-0.02))-(Assumptions!$G$37)+CHOOSE(MATCH(Scenario,{"Bear","Base","Bull"},0),Assumptions!$B$84,Assumptions!$C$84,Assumptions!$D$84))/(1+(Assumptions!$B$54))^2+(IS!$F$14*(1+AVERAGE(IS!$H$15:$K$15))^3)*((AVERAGE(IS!$H$30:$K$30))*(1-((Assumptions!$B$50)-0.02))-(Assumptions!$G$37)+CHOOSE(MATCH(Scenario,{"Bear","Base","Bull"},0),Assumptions!$B$84,Assumptions!$C$84,Assumptions!$D$84))/(1+(Assumptions!$B$54))^3+(IS!$F$14*(1+AVERAGE(IS!$H$15:$K$15))^4)*((AVERAGE(IS!$H$30:$K$30))*(1-((Assumptions!$B$50)-0.02))-(Assumptions!$G$37)+CHOOSE(MATCH(Scenario,{"Bear","Base","Bull"},0),Assumptions!$B$84,Assumptions!$C$84,Assumptions!$D$84))/(1+(Assumptions!$B$54))^4+(IS!$F$14*(1+AVERAGE(IS!$H$15:$K$15))^4)*((AVERAGE(IS!$H$30:$K$30))*(1-((Assumptions!$B$50)-0.02))-(Assumptions!$G$37)+CHOOSE(MATCH(Scenario,{"Bear","Base","Bull"},0),Assumptions!$B$84,Assumptions!$C$84,Assumptions!$D$84))*(1+(Assumptions!$B$55))/((Assumptions!$B$54)-(Assumptions!$B$55))/(1+(Assumptions!$B$54))^4+$B$23)/Assumptions!$B$58 -> 134.83034 | F57: =ABS(E57-D57) -> 6.0721021 | G57: Higher tax cuts NOPAT
A58: CapEx % revenue | B58: +50 bps | C58: -50 bps | D58: =((IS!$F$14*(1+AVERAGE(IS!$H$15:$K$15)))*((AVERAGE(IS!$H$30:$K$30))*(1-(Assumptions!$B$50))-((Assumptions!$G$37)+0.005))/(1+(Assumptions!$B$54))^1+(IS!$F$14*(1+AVERAGE(IS!$H$15:$K$15))^2)*((AVERAGE(IS!$H$30:$K$30))*(1-(Assumptions!$B$50))-((Assumptions!$G$37)+0.005))/(1+(Assumptions!$B$54))^2+(IS!$F$14*(1+AVERAGE(IS!$H$15:$K$15))^3)*((AVERAGE(IS!$H$30:$K$30))*(1-(Assumptions!$B$50))-((Assumptions!$G$37)+0.005))/(1+(Assumptions!$B$54))^3+(IS!$F$14*(1+AVERAGE(IS!$H$15:$K$15))^4)*((AVERAGE(IS!$H$30:$K$30))*(1-(Assumptions!$B$50))-((Assumptions!$G$37)+0.005))/(1+(Assumptions!$B$54))^4+(IS!$F$14*(1+AVERAGE(IS!$H$15:$K$15))^4)*((AVERAGE(IS!$H$30:$K$30))*(1-(Assumptions!$B$50))-((Assumptions!$G$37)+0.005))*(1+(Assumptions!$B$55))/((Assumptions!$B$54)-(Assumptions!$B$55))/(1+(Assumptions!$B$54))^4+$B$23)/Assumptions!$B$58 -> 116.74444 | E58: =((IS!$F$14*(1+AVERAGE(IS!$H$15:$K$15)))*((AVERAGE(IS!$H$30:$K$30))*(1-(Assumptions!$B$50))-((Assumptions!$G$37)-0.005))/(1+(Assumptions!$B$54))^1+(IS!$F$14*(1+AVERAGE(IS!$H$15:$K$15))^2)*((AVERAGE(IS!$H$30:$K$30))*(1-(Assumptions!$B$50))-((Assumptions!$G$37)-0.005))/(1+(Assumptions!$B$54))^2+(IS!$F$14*(1+AVERAGE(IS!$H$15:$K$15))^3)*((AVERAGE(IS!$H$30:$K$30))*(1-(Assumptions!$B$50))-((Assumptions!$G$37)-0.005))/(1+(Assumptions!$B$54))^3+(IS!$F$14*(1+AVERAGE(IS!$H$15:$K$15))^4)*((AVERAGE(IS!$H$30:$K$30))*(1-(Assumptions!$B$50))-((Assumptions!$G$37)-0.005))/(1+(Assumptions!$B$54))^4+(IS!$F$14*(1+AVERAGE(IS!$H$15:$K$15))^4)*((AVERAGE(IS!$H$30:$K$30))*(1-(Assumptions!$B$50))-((Assumptions!$G$37)-0.005))*(1+(Assumptions!$B$55))/((Assumptions!$B$54)-(Assumptions!$B$55))/(1+(Assumptions!$B$54))^4+$B$23)/Assumptions!$B$58 -> 121.305 | F58: =ABS(E58-D58) -> 4.5605614 | G58: Higher capex = lower FCF
A64: FOOTBALL FIELD | Valuation Range by Methodology (Implied $/share)
A65: Methodology | B65: Low | C65: Mid | D65: High | E65: Range Width | F65: Notes
A66: DCF, WACC ±50 bps × g ±50 bps | B66: =C37 -> 122.99553 | C66: =D36 -> 139.49886 | D66: =E35 -> 161.63664 | E66: =D66-B66 -> 38.641107 | F66: Main DCF, active scenario
A67: Simplified DCF, growth × margin grid | B67: =MIN(B44:F48) -> 99.936587 | C67: =MEDIAN(B44:F48) -> 126.20197 | D67: =MAX(B44:F48) -> 156.74314 | E67: =D67-B67 -> 56.806558 | F67: One-stage build, separate from the main DCF
A68: DCF, Bear / Base / Bull scenarios | B68: 75.86 | C68: =B26 -> 139.49886 | D68: 265.54 | E68: =D68-B68 -> 189.68 | F68: Bear and Bull recorded with each scenario active on 2 Oct 2026; Base links to B26
A69: P/E multiple (22-30x) | B69: =IS!$K$44*Assumptions!$B$97*$E$16 -> 182.39493 | C69: =IS!$K$44*Assumptions!$C$97*$E$16 -> 215.55764 | D69: =IS!$K$44*Assumptions!$D$97*$E$16 -> 248.72036 | E69: =D69-B69 -> 66.325429 | F69: FY29E diluted EPS × multiples on Assumptions row 97, discounted
A70: EV/EBITDA (16-22x) | B70: =((IS!$K$29+CFS!$J$10)*Assumptions!$B$98*$E$16+$B$23)/Assumptions!$B$58 -> 155.1174 | C70: =((IS!$K$29+CFS!$J$10)*Assumptions!$C$98*$E$16+$B$23)/Assumptions!$B$58 -> 183.68402 | D70: =((IS!$K$29+CFS!$J$10)*Assumptions!$D$98*$E$16+$B$23)/Assumptions!$B$58 -> 212.25064 | E70: =D70-B70 -> 57.133231 | F70: FY29E EBITDA × multiples on Assumptions row 98, discounted, plus FY26E net cash
A71: 52-week range | B71: 245.27 | C71: =(B71+D71)/2 -> 293.17 | D71: 341.07 | E71: =D71-B71 -> 95.8 | F71: 52-week closing range to 28 Sep 2026 (STOCKHISTORY)
A72: Analyst target (consensus) | B72: 215 | C72: 340 | D72: 405 | E72: =D72-B72 -> 190 | F72: 44 analysts, low / median / high, stockanalysis.com, 29 Sep 2026
A73: Current share price | B73: =Assumptions!$B$59 -> 338.4 | C73: =Assumptions!$B$59 -> 338.4 | D73: =Assumptions!$B$59 -> 338.4 | E73: 0 | F73: Close on 28 Sep 2026, Assumptions!B59

Sheet Validation
A1: DATA VALIDATION | 10-K Source Audit Trail
A2: Live error-detection dashboard: historical values vs. 10-K + structural integrity + forecast sanity checks
A3: MODEL HEALTH | B3: =IF(AND(E87=0,COUNTIF(B122:J122,"✓")=9,COUNTIF(B123:J123,"✓")+COUNTIF(B123:J123,"n/a*")=9),"✅ ALL CHECKS PASS","⚠ "&(E87+(9-COUNTIF(B122:J122,"✓"))+(9-COUNTIF(B123:J123,"✓")-COUNTIF(B123:J123,"n/a*")))&" ISSUES — see details below") -> ✅ ALL CHECKS PASS
A5: SOURCE DOCUMENTS
A6: [1] | B6: Apple Inc. Form 10-K FY2025 | E6: Filed Oct 31, 2025 | F6: Primary source for FY23, FY24, FY25 line items | H6: Open 10-K on SEC.gov →
A7: [2] | B7: Apple Inc. Form 10-K FY2022 | E7: Filed Oct 28, 2022 | F7: Primary source for FY21 and FY22 line items | H7: Open 10-K on SEC.gov →
A8: [3] | B8: Apple Inc. Form 10-K FY2023 | E8: Filed Nov 3, 2023 | F8: Cross-verification for FY21, FY22, FY23 | H8: Open 10-K on SEC.gov →
A9: [4] | B9: Apple FY25 Q4 Press Release | E9: Released Oct 30, 2025 | F9: Full FY25 + FY24 consolidated statements PDF | H9: Open Apple PDF →
A10: [5] | B10: Apple FY22 Q4 Press Release | E10: Released Oct 27, 2022 | F10: Full FY22 + FY21 consolidated statements PDF | H10: Open Apple PDF →
A11: [6] | B11: SEC EDGAR: All Apple 10-K filings | E11: Live SEC database | F11: Browse all Apple Inc. 10-K filings (CIK: 0000320193) | H11: Browse SEC EDGAR →
A12: [7] | B12: Apple Investor Relations | E12: Live company page | F12: All SEC filings, press releases, financial data | H12: Open Apple IR page →
A14: INCOME STATEMENT | Historical Validation (USD Millions)
A15: Line item | B15: FY21A | C15: FY22A | D15: FY23A | E15: FY24A | F15: FY25A | G15: Check | H15: Source
A16: Products revenue | B16: 297392 | C16: 316199 | D16: 298085 | E16: 294866 | F16: 307003 | G16: {=IF(SUMPRODUCT(ABS(B16:F16-IS!B8:F8))<1,"✓","✗ "&TEXT(SUMPRODUCT(ABS(B16:F16-IS!B8:F8)),"#,##0.0"))} -> ✓ | H16: 10-K FY22/FY25 p.29
A17: Services revenue | B17: 68425 | C17: 78129 | D17: 85200 | E17: 96169 | F17: 109158 | G17: {=IF(SUMPRODUCT(ABS(B17:F17-IS!B13:F13))<1,"✓","✗ "&TEXT(SUMPRODUCT(ABS(B17:F17-IS!B13:F13)),"#,##0.0"))} -> ✓ | H17: 10-K FY22/FY25 p.29
A18: Total revenue (calc) | B18: 365817 | C18: 394328 | D18: 383285 | E18: 391035 | F18: 416161 | G18: {=IF(SUMPRODUCT(ABS(B18:F18-IS!B14:F14))<1,"✓","✗ "&TEXT(SUMPRODUCT(ABS(B18:F18-IS!B14:F14)),"#,##0.0"))} -> ✓ | H18: Calculated
A19: Cost of products | B19: 192266 | C19: 201471 | D19: 189282 | E19: 185233 | F19: 194116 | G19: {=IF(SUMPRODUCT(ABS(B19:F19-IS!B19:F19))<1,"✓","✗ "&TEXT(SUMPRODUCT(ABS(B19:F19-IS!B19:F19)),"#,##0.0"))} -> ✓ | H19: 10-K FY22/FY25 p.29
A20: Cost of services | B20: 20715 | C20: 22075 | D20: 24855 | E20: 25119 | F20: 26844 | G20: {=IF(SUMPRODUCT(ABS(B20:F20-IS!B20:F20))<1,"✓","✗ "&TEXT(SUMPRODUCT(ABS(B20:F20-IS!B20:F20)),"#,##0.0"))} -> ✓ | H20: 10-K FY22/FY25 p.29
A21: Total cost of sales | B21: 212981 | C21: 223546 | D21: 214137 | E21: 210352 | F21: 220960 | G21: {=IF(SUMPRODUCT(ABS(B21:F21-IS!B21:F21))<1,"✓","✗ "&TEXT(SUMPRODUCT(ABS(B21:F21-IS!B21:F21)),"#,##0.0"))} -> ✓ | H21: Calculated
A22: Gross profit (calc) | B22: 152836 | C22: 170782 | D22: 169148 | E22: 180683 | F22: 195201 | G22: {=IF(SUMPRODUCT(ABS(B22:F22-IS!B22:F22))<1,"✓","✗ "&TEXT(SUMPRODUCT(ABS(B22:F22-IS!B22:F22)),"#,##0.0"))} -> ✓ | H22: Calculated
A23: R&D expense | B23: 21914 | C23: 26251 | D23: 29915 | E23: 31370 | F23: 34550 | G23: {=IF(SUMPRODUCT(ABS(B23:F23-IS!B26:F26))<1,"✓","✗ "&TEXT(SUMPRODUCT(ABS(B23:F23-IS!B26:F26)),"#,##0.0"))} -> ✓ | H23: 10-K FY22/FY25 p.29
A24: SG&A expense | B24: 21973 | C24: 25094 | D24: 24932 | E24: 26097 | F24: 27601 | G24: {=IF(SUMPRODUCT(ABS(B24:F24-IS!B27:F27))<1,"✓","✗ "&TEXT(SUMPRODUCT(ABS(B24:F24-IS!B27:F27)),"#,##0.0"))} -> ✓ | H24: 10-K FY22/FY25 p.29
A25: Total operating expenses | B25: 43887 | C25: 51345 | D25: 54847 | E25: 57467 | F25: 62151 | G25: {=IF(SUMPRODUCT(ABS(B25:F25-IS!B28:F28))<1,"✓","✗ "&TEXT(SUMPRODUCT(ABS(B25:F25-IS!B28:F28)),"#,##0.0"))} -> ✓ | H25: Calculated
A26: Operating income (calc) | B26: 108949 | C26: 119437 | D26: 114301 | E26: 123216 | F26: 133050 | G26: {=IF(SUMPRODUCT(ABS(B26:F26-IS!B29:F29))<1,"✓","✗ "&TEXT(SUMPRODUCT(ABS(B26:F26-IS!B29:F29)),"#,##0.0"))} -> ✓ | H26: 10-K FY22/FY25 p.29
A27: Other income/(expense) | B27: 258 | C27: -334 | D27: -565 | E27: 269 | F27: -321 | G27: {=IF(SUMPRODUCT(ABS(B27:F27-IS!B35:F35))<1,"✓","✗ "&TEXT(SUMPRODUCT(ABS(B27:F27-IS!B35:F35)),"#,##0.0"))} -> ✓ | H27: 10-K FY22/FY25 p.29
A28: Pre-tax income (calc) | B28: 109207 | C28: 119103 | D28: 113736 | E28: 123485 | F28: 132729 | G28: {=IF(SUMPRODUCT(ABS(B28:F28-IS!B36:F36))<1,"✓","✗ "&TEXT(SUMPRODUCT(ABS(B28:F28-IS!B36:F36)),"#,##0.0"))} -> ✓ | H28: Calculated
A29: Income tax expense | B29: 14527 | C29: 19300 | D29: 16741 | E29: 29749 | F29: 20719 | G29: {=IF(SUMPRODUCT(ABS(B29:F29-IS!B37:F37))<1,"✓","✗ "&TEXT(SUMPRODUCT(ABS(B29:F29-IS!B37:F37)),"#,##0.0"))} -> ✓ | H29: 10-K FY22/FY25 p.29
A30: Net income (calc) | B30: 94680 | C30: 99803 | D30: 96995 | E30: 93736 | F30: 112010 | G30: {=IF(SUMPRODUCT(ABS(B30:F30-IS!B39:F39))<1,"✓","✗ "&TEXT(SUMPRODUCT(ABS(B30:F30-IS!B39:F39)),"#,##0.0"))} -> ✓ | H30: 10-K FY22/FY25 p.29
A31: Diluted EPS ($) | B31: 5.61 | C31: 6.11 | D31: 6.13 | E31: 6.08 | F31: 7.46 | G31: {=IF(SUMPRODUCT(ABS(B31:F31-IS!B44:F44))<0.05,"✓","✗ "&TEXT(SUMPRODUCT(ABS(B31:F31-IS!B44:F44)),"#,##0.0"))} -> ✓ | H31: 10-K FY22/FY25 p.29
A34: BALANCE SHEET | Historical Validation (USD Millions)
A35: Line item | B35: FY21A | C35: FY22A | D35: FY23A | E35: FY24A | F35: FY25A | G35: Check | H35: Source
A36: Cash & equivalents | B36: 34940 | C36: 23646 | D36: 29965 | E36: 29943 | F36: 35934 | G36: =IF((ABS(B36-(BS!C5))+ABS(C36-(BS!D5))+ABS(D36-(BS!E5))+ABS(E36-(BS!F5))+ABS(F36-(BS!G5)))<5,"✓","✗ "&TEXT(ABS(B36-(BS!C5))+ABS(C36-(BS!D5))+ABS(D36-(BS!E5))+ABS(E36-(BS!F5))+ABS(F36-(BS!G5)),"#,##0")) -> ✓ | H36: 10-K FY22/FY23/FY25 p.31
A37: Marketable securities (current) | B37: 27699 | C37: 24658 | D37: 31590 | E37: 35228 | F37: 18763 | G37: =IF((ABS(B37-(BS!C6))+ABS(C37-(BS!D6))+ABS(D37-(BS!E6))+ABS(E37-(BS!F6))+ABS(F37-(BS!G6)))<5,"✓","✗ "&TEXT(ABS(B37-(BS!C6))+ABS(C37-(BS!D6))+ABS(D37-(BS!E6))+ABS(E37-(BS!F6))+ABS(F37-(BS!G6)),"#,##0")) -> ✓ | H37: 10-K FY22/FY23/FY25 p.31
A38: Marketable securities (non-curr) | B38: 127877 | C38: 120805 | D38: 100544 | E38: 91479 | F38: 77723 | G38: =IF((ABS(B38-(BS!C15))+ABS(C38-(BS!D15))+ABS(D38-(BS!E15))+ABS(E38-(BS!F15))+ABS(F38-(BS!G15)))<5,"✓","✗ "&TEXT(ABS(B38-(BS!C15))+ABS(C38-(BS!D15))+ABS(D38-(BS!E15))+ABS(E38-(BS!F15))+ABS(F38-(BS!G15)),"#,##0")) -> ✓ | H38: 10-K FY22/FY23/FY25 p.31
A39: Accounts receivable, net | B39: 26278 | C39: 28184 | D39: 29508 | E39: 33410 | F39: 39777 | G39: =IF((ABS(B39-(BS!C7))+ABS(C39-(BS!D7))+ABS(D39-(BS!E7))+ABS(E39-(BS!F7))+ABS(F39-(BS!G7)))<5,"✓","✗ "&TEXT(ABS(B39-(BS!C7))+ABS(C39-(BS!D7))+ABS(D39-(BS!E7))+ABS(E39-(BS!F7))+ABS(F39-(BS!G7)),"#,##0")) -> ✓ | H39: 10-K FY22/FY23/FY25 p.31
A40: Inventory | B40: 6580 | C40: 4946 | D40: 6331 | E40: 7286 | F40: 5718 | G40: =IF((ABS(B40-(BS!C8))+ABS(C40-(BS!D8))+ABS(D40-(BS!E8))+ABS(E40-(BS!F8))+ABS(F40-(BS!G8)))<5,"✓","✗ "&TEXT(ABS(B40-(BS!C8))+ABS(C40-(BS!D8))+ABS(D40-(BS!E8))+ABS(E40-(BS!F8))+ABS(F40-(BS!G8)),"#,##0")) -> ✓ | H40: 10-K FY22/FY23/FY25 p.31
A41: Vendor non-trade receivables | B41: 25228 | C41: 32748 | D41: 31477 | E41: 32833 | F41: 33180 | G41: =IF((ABS(B41-(BS!C9))+ABS(C41-(BS!D9))+ABS(D41-(BS!E9))+ABS(E41-(BS!F9))+ABS(F41-(BS!G9)))<5,"✓","✗ "&TEXT(ABS(B41-(BS!C9))+ABS(C41-(BS!D9))+ABS(D41-(BS!E9))+ABS(E41-(BS!F9))+ABS(F41-(BS!G9)),"#,##0")) -> ✓ | H41: 10-K FY22/FY23/FY25 p.31
A42: Other current assets | B42: 14111 | C42: 21223 | D42: 14695 | E42: 14287 | F42: 14585 | G42: =IF((ABS(B42-(BS!C10))+ABS(C42-(BS!D10))+ABS(D42-(BS!E10))+ABS(E42-(BS!F10))+ABS(F42-(BS!G10)))<5,"✓","✗ "&TEXT(ABS(B42-(BS!C10))+ABS(C42-(BS!D10))+ABS(D42-(BS!E10))+ABS(E42-(BS!F10))+ABS(F42-(BS!G10)),"#,##0")) -> ✓ | H42: 10-K FY22/FY23/FY25 p.31
A43: Total current assets | B43: 134836 | C43: 135405 | D43: 143566 | E43: 152987 | F43: 147957 | G43: =IF((ABS(B43-(BS!C11))+ABS(C43-(BS!D11))+ABS(D43-(BS!E11))+ABS(E43-(BS!F11))+ABS(F43-(BS!G11)))<5,"✓","✗ "&TEXT(ABS(B43-(BS!C11))+ABS(C43-(BS!D11))+ABS(D43-(BS!E11))+ABS(E43-(BS!F11))+ABS(F43-(BS!G11)),"#,##0")) -> ✓ | H43: Calculated
A44: Property, plant & equipment, net | B44: 39440 | C44: 42117 | D44: 43715 | E44: 45680 | F44: 49834 | G44: =IF((ABS(B44-(BS!C14))+ABS(C44-(BS!D14))+ABS(D44-(BS!E14))+ABS(E44-(BS!F14))+ABS(F44-(BS!G14)))<5,"✓","✗ "&TEXT(ABS(B44-(BS!C14))+ABS(C44-(BS!D14))+ABS(D44-(BS!E14))+ABS(E44-(BS!F14))+ABS(F44-(BS!G14)),"#,##0")) -> ✓ | H44: 10-K FY22/FY23/FY25 p.31
A45: Other non-current assets | B45: 48849 | C45: 54428 | D45: 64758 | E45: 74834 | F45: 83727 | G45: =IF((ABS(B45-(BS!C16))+ABS(C45-(BS!D16))+ABS(D45-(BS!E16))+ABS(E45-(BS!F16))+ABS(F45-(BS!G16)))<5,"✓","✗ "&TEXT(ABS(B45-(BS!C16))+ABS(C45-(BS!D16))+ABS(D45-(BS!E16))+ABS(E45-(BS!F16))+ABS(F45-(BS!G16)),"#,##0")) -> ✓ | H45: 10-K FY22/FY23/FY25 p.31
A46: Total assets | B46: 351002 | C46: 352755 | D46: 352583 | E46: 364980 | F46: 359241 | G46: =IF((ABS(B46-(BS!C18))+ABS(C46-(BS!D18))+ABS(D46-(BS!E18))+ABS(E46-(BS!F18))+ABS(F46-(BS!G18)))<5,"✓","✗ "&TEXT(ABS(B46-(BS!C18))+ABS(C46-(BS!D18))+ABS(D46-(BS!E18))+ABS(E46-(BS!F18))+ABS(F46-(BS!G18)),"#,##0")) -> ✓ | H46: 10-K FY22/FY23/FY25 p.31
A47: Accounts payable | B47: 54763 | C47: 64115 | D47: 62611 | E47: 68960 | F47: 69860 | G47: =IF((ABS(B47-(BS!C21))+ABS(C47-(BS!D21))+ABS(D47-(BS!E21))+ABS(E47-(BS!F21))+ABS(F47-(BS!G21)))<5,"✓","✗ "&TEXT(ABS(B47-(BS!C21))+ABS(C47-(BS!D21))+ABS(D47-(BS!E21))+ABS(E47-(BS!F21))+ABS(F47-(BS!G21)),"#,##0")) -> ✓ | H47: 10-K FY22/FY23/FY25 p.31
A48: Other current liabilities | B48: 47493 | C48: 60845 | D48: 58829 | E48: 78304 | F48: 66387 | G48: =IF((ABS(B48-(BS!C22))+ABS(C48-(BS!D22))+ABS(D48-(BS!E22))+ABS(E48-(BS!F22))+ABS(F48-(BS!G22)))<5,"✓","✗ "&TEXT(ABS(B48-(BS!C22))+ABS(C48-(BS!D22))+ABS(D48-(BS!E22))+ABS(E48-(BS!F22))+ABS(F48-(BS!G22)),"#,##0")) -> ✓ | H48: 10-K FY22/FY23/FY25 p.31
A49: Deferred revenue | B49: 7612 | C49: 7912 | D49: 8061 | E49: 8249 | F49: 9055 | G49: =IF((ABS(B49-(BS!C23))+ABS(C49-(BS!D23))+ABS(D49-(BS!E23))+ABS(E49-(BS!F23))+ABS(F49-(BS!G23)))<5,"✓","✗ "&TEXT(ABS(B49-(BS!C23))+ABS(C49-(BS!D23))+ABS(D49-(BS!E23))+ABS(E49-(BS!F23))+ABS(F49-(BS!G23)),"#,##0")) -> ✓ | H49: 10-K FY22/FY23/FY25 p.31
A50: Commercial paper | B50: 6000 | C50: 9982 | D50: 5985 | E50: 9967 | F50: 7979 | G50: =IF((ABS(B50-(BS!C24))+ABS(C50-(BS!D24))+ABS(D50-(BS!E24))+ABS(E50-(BS!F24))+ABS(F50-(BS!G24)))<5,"✓","✗ "&TEXT(ABS(B50-(BS!C24))+ABS(C50-(BS!D24))+ABS(D50-(BS!E24))+ABS(E50-(BS!F24))+ABS(F50-(BS!G24)),"#,##0")) -> ✓ | H50: 10-K FY22/FY23/FY25 p.31
A51: Term debt (current) | B51: 9613 | C51: 11128 | D51: 9822 | E51: 10912 | F51: 12350 | G51: =IF((ABS(B51-(BS!C25))+ABS(C51-(BS!D25))+ABS(D51-(BS!E25))+ABS(E51-(BS!F25))+ABS(F51-(BS!G25)))<5,"✓","✗ "&TEXT(ABS(B51-(BS!C25))+ABS(C51-(BS!D25))+ABS(D51-(BS!E25))+ABS(E51-(BS!F25))+ABS(F51-(BS!G25)),"#,##0")) -> ✓ | H51: 10-K FY22/FY23/FY25 p.31; Q4 statements
A52: Total current liabilities | B52: 125481 | C52: 153982 | D52: 145308 | E52: 176392 | F52: 165631 | G52: =IF((ABS(B52-(BS!C26))+ABS(C52-(BS!D26))+ABS(D52-(BS!E26))+ABS(E52-(BS!F26))+ABS(F52-(BS!G26)))<5,"✓","✗ "&TEXT(ABS(B52-(BS!C26))+ABS(C52-(BS!D26))+ABS(D52-(BS!E26))+ABS(E52-(BS!F26))+ABS(F52-(BS!G26)),"#,##0")) -> ✓ | H52: Calculated
A53: Long-term debt (non-current) | B53: 109106 | C53: 98959 | D53: 95281 | E53: 85750 | F53: 78328 | G53: =IF((ABS(B53-(BS!C29))+ABS(C53-(BS!D29))+ABS(D53-(BS!E29))+ABS(E53-(BS!F29))+ABS(F53-(BS!G29)))<5,"✓","✗ "&TEXT(ABS(B53-(BS!C29))+ABS(C53-(BS!D29))+ABS(D53-(BS!E29))+ABS(E53-(BS!F29))+ABS(F53-(BS!G29)),"#,##0")) -> ✓ | H53: 10-K FY22/FY23/FY25 p.31
A54: Other non-current liabilities | B54: 53325 | C54: 49142 | D54: 49848 | E54: 45888 | F54: 41549 | G54: =IF((ABS(B54-(BS!C30))+ABS(C54-(BS!D30))+ABS(D54-(BS!E30))+ABS(E54-(BS!F30))+ABS(F54-(BS!G30)))<5,"✓","✗ "&TEXT(ABS(B54-(BS!C30))+ABS(C54-(BS!D30))+ABS(D54-(BS!E30))+ABS(E54-(BS!F30))+ABS(F54-(BS!G30)),"#,##0")) -> ✓ | H54: 10-K FY22/FY23/FY25 p.31
A55: Total liabilities | B55: 287912 | C55: 302083 | D55: 290437 | E55: 308030 | F55: 285508 | G55: =IF((ABS(B55-(BS!C32))+ABS(C55-(BS!D32))+ABS(D55-(BS!E32))+ABS(E55-(BS!F32))+ABS(F55-(BS!G32)))<5,"✓","✗ "&TEXT(ABS(B55-(BS!C32))+ABS(C55-(BS!D32))+ABS(D55-(BS!E32))+ABS(E55-(BS!F32))+ABS(F55-(BS!G32)),"#,##0")) -> ✓ | H55: 10-K FY22/FY23/FY25 p.31
A56: Common stock and APIC | B56: 57365 | C56: 64849 | D56: 73812 | E56: 83276 | F56: 93568 | G56: =IF((ABS(B56-(BS!C35))+ABS(C56-(BS!D35))+ABS(D56-(BS!E35))+ABS(E56-(BS!F35))+ABS(F56-(BS!G35)))<5,"✓","✗ "&TEXT(ABS(B56-(BS!C35))+ABS(C56-(BS!D35))+ABS(D56-(BS!E35))+ABS(E56-(BS!F35))+ABS(F56-(BS!G35)),"#,##0")) -> ✓ | H56: 10-K FY22/FY23/FY25 p.31
A57: Retained earnings (deficit) | B57: 5562 | C57: -3068 | D57: -214 | E57: -19154 | F57: -14264 | G57: =IF((ABS(B57-(BS!C36))+ABS(C57-(BS!D36))+ABS(D57-(BS!E36))+ABS(E57-(BS!F36))+ABS(F57-(BS!G36)))<5,"✓","✗ "&TEXT(ABS(B57-(BS!C36))+ABS(C57-(BS!D36))+ABS(D57-(BS!E36))+ABS(E57-(BS!F36))+ABS(F57-(BS!G36)),"#,##0")) -> ✓ | H57: 10-K FY22/FY23/FY25 p.31
A58: Accumulated OCI (loss) | B58: 163 | C58: -11109 | D58: -11452 | E58: -7172 | F58: -5571 | G58: =IF((ABS(B58-(BS!C37))+ABS(C58-(BS!D37))+ABS(D58-(BS!E37))+ABS(E58-(BS!F37))+ABS(F58-(BS!G37)))<5,"✓","✗ "&TEXT(ABS(B58-(BS!C37))+ABS(C58-(BS!D37))+ABS(D58-(BS!E37))+ABS(E58-(BS!F37))+ABS(F58-(BS!G37)),"#,##0")) -> ✓ | H58: 10-K FY22/FY23/FY25 p.31
A59: Shareholders' equity | B59: 63090 | C59: 50672 | D59: 62146 | E59: 56950 | F59: 73733 | G59: =IF((ABS(B59-(BS!C38))+ABS(C59-(BS!D38))+ABS(D59-(BS!E38))+ABS(E59-(BS!F38))+ABS(F59-(BS!G38)))<5,"✓","✗ "&TEXT(ABS(B59-(BS!C38))+ABS(C59-(BS!D38))+ABS(D59-(BS!E38))+ABS(E59-(BS!F38))+ABS(F59-(BS!G38)),"#,##0")) -> ✓ | H59: 10-K FY22/FY23/FY25 p.31
A60: Total liabilities + equity | B60: 351002 | C60: 352755 | D60: 352583 | E60: 364980 | F60: 359241 | G60: =IF((ABS(B60-(BS!C39))+ABS(C60-(BS!D39))+ABS(D60-(BS!E39))+ABS(E60-(BS!F39))+ABS(F60-(BS!G39)))<5,"✓","✗ "&TEXT(ABS(B60-(BS!C39))+ABS(C60-(BS!D39))+ABS(D60-(BS!E39))+ABS(E60-(BS!F39))+ABS(F60-(BS!G39)),"#,##0")) -> ✓ | H60: Calculated (= Total assets)
A61: BALANCE CHECK (must = 0) | B61: =BS!C18-BS!C39 -> 0 | C61: =BS!D18-BS!D39 -> 0 | D61: =BS!E18-BS!E39 -> 0 | E61: =BS!F18-BS!F39 -> 0 | F61: =BS!G18-BS!G39 -> 0 | G61: =IF(ABS(BS!C18-BS!C39)+ABS(BS!D18-BS!D39)+ABS(BS!E18-BS!E39)+ABS(BS!F18-BS!F39)+ABS(BS!G18-BS!G39)<5,"✓","✗ BS imbalances detected") -> ✓ | H61: Audit row
A64: CASH FLOW STATEMENT | Historical Validation (USD Millions)
A65: Line item | B65: FY21A | C65: FY22A | D65: FY23A | E65: FY24A | F65: FY25A | G65: Check | H65: Source
A66: Beginning cash | B66: 39789 | C66: 35929 | D66: 24977 | E66: 30737 | F66: 29943 | G66: =IF((ABS(B66-CFS!B7)+ABS(C66-CFS!C7)+ABS(D66-CFS!D7)+ABS(E66-CFS!E7)+ABS(F66-CFS!F7))<5,"✓","✗ "&TEXT(ABS(B66-CFS!B7)+ABS(C66-CFS!C7)+ABS(D66-CFS!D7)+ABS(E66-CFS!E7)+ABS(F66-CFS!F7),"#,##0")) -> ✓ | H66: 10-K FY22/FY25 p.33
A67: Depreciation & amortization | B67: 11284 | C67: 11104 | D67: 11519 | E67: 11445 | F67: 11698 | G67: =IF((ABS(B67-CFS!B10)+ABS(C67-CFS!C10)+ABS(D67-CFS!D10)+ABS(E67-CFS!E10)+ABS(F67-CFS!F10))<5,"✓","✗ "&TEXT(ABS(B67-CFS!B10)+ABS(C67-CFS!C10)+ABS(D67-CFS!D10)+ABS(E67-CFS!E10)+ABS(F67-CFS!F10),"#,##0")) -> ✓ | H67: 10-K FY22/FY25 p.33
A68: Share-based compensation | B68: 7906 | C68: 9038 | D68: 10833 | E68: 11688 | F68: 12863 | G68: =IF((ABS(B68-CFS!B12)+ABS(C68-CFS!C12)+ABS(D68-CFS!D12)+ABS(E68-CFS!E12)+ABS(F68-CFS!F12))<5,"✓","✗ "&TEXT(ABS(B68-CFS!B12)+ABS(C68-CFS!C12)+ABS(D68-CFS!D12)+ABS(E68-CFS!E12)+ABS(F68-CFS!F12),"#,##0")) -> ✓ | H68: 10-K FY22/FY25 p.33
A69: Changes in WC & other (plug) | B69: -9832 | C69: 2206 | D69: -8804 | E69: 1385 | F69: -25089 | G69: =IF((ABS(B69-CFS!B13)+ABS(C69-CFS!C13)+ABS(D69-CFS!D13)+ABS(E69-CFS!E13)+ABS(F69-CFS!F13))<5,"✓","✗ "&TEXT(ABS(B69-CFS!B13)+ABS(C69-CFS!C13)+ABS(D69-CFS!D13)+ABS(E69-CFS!E13)+ABS(F69-CFS!F13),"#,##0")) -> ✓ | H69: 10-K (CFO - NI - D&A - SBC)
A70: Cash from operations | B70: 104038 | C70: 122151 | D70: 110543 | E70: 118254 | F70: 111482 | G70: =IF((ABS(B70-CFS!B14)+ABS(C70-CFS!C14)+ABS(D70-CFS!D14)+ABS(E70-CFS!E14)+ABS(F70-CFS!F14))<5,"✓","✗ "&TEXT(ABS(B70-CFS!B14)+ABS(C70-CFS!C14)+ABS(D70-CFS!D14)+ABS(E70-CFS!E14)+ABS(F70-CFS!F14),"#,##0")) -> ✓ | H70: 10-K FY22/FY25 p.33
A71: Capital expenditures | B71: -11085 | C71: -10708 | D71: -10959 | E71: -9447 | F71: -12715 | G71: =IF((ABS(B71-CFS!B19)+ABS(C71-CFS!C19)+ABS(D71-CFS!D19)+ABS(E71-CFS!E19)+ABS(F71-CFS!F19))<5,"✓","✗ "&TEXT(ABS(B71-CFS!B19)+ABS(C71-CFS!C19)+ABS(D71-CFS!D19)+ABS(E71-CFS!E19)+ABS(F71-CFS!F19),"#,##0")) -> ✓ | H71: 10-K FY22/FY25 p.33
A72: Other investing | B72: -3460 | C72: -11646 | D72: 14664 | E72: 12382 | F72: 27910 | G72: =IF((ABS(B72-CFS!B20)+ABS(C72-CFS!C20)+ABS(D72-CFS!D20)+ABS(E72-CFS!E20)+ABS(F72-CFS!F20))<5,"✓","✗ "&TEXT(ABS(B72-CFS!B20)+ABS(C72-CFS!C20)+ABS(D72-CFS!D20)+ABS(E72-CFS!E20)+ABS(F72-CFS!F20),"#,##0")) -> ✓ | H72: 10-K (Total CFI - CapEx)
A73: Cash from investing | B73: -14545 | C73: -22354 | D73: 3705 | E73: 2935 | F73: 15195 | G73: =IF((ABS(B73-CFS!B17)+ABS(C73-CFS!C17)+ABS(D73-CFS!D17)+ABS(E73-CFS!E17)+ABS(F73-CFS!F17))<5,"✓","✗ "&TEXT(ABS(B73-CFS!B17)+ABS(C73-CFS!C17)+ABS(D73-CFS!D17)+ABS(E73-CFS!E17)+ABS(F73-CFS!F17),"#,##0")) -> ✓ | H73: 10-K FY22/FY25 p.33
A74: Free cash flow (CFO - CapEx) | B74: 92953 | C74: 111443 | D74: 99584 | E74: 108807 | F74: 98767 | G74: =IF((ABS(B74-CFS!B21)+ABS(C74-CFS!C21)+ABS(D74-CFS!D21)+ABS(E74-CFS!E21)+ABS(F74-CFS!F21))<5,"✓","✗ "&TEXT(ABS(B74-CFS!B21)+ABS(C74-CFS!C21)+ABS(D74-CFS!D21)+ABS(E74-CFS!E21)+ABS(F74-CFS!F21),"#,##0")) -> ✓ | H74: Calculated
A75: Dividends paid | B75: -14467 | C75: -14841 | D75: -15025 | E75: -15234 | F75: -15421 | G75: =IF((ABS(B75-CFS!B24)+ABS(C75-CFS!C24)+ABS(D75-CFS!D24)+ABS(E75-CFS!E24)+ABS(F75-CFS!F24))<5,"✓","✗ "&TEXT(ABS(B75-CFS!B24)+ABS(C75-CFS!C24)+ABS(D75-CFS!D24)+ABS(E75-CFS!E24)+ABS(F75-CFS!F24),"#,##0")) -> ✓ | H75: 10-K FY22/FY25 p.33
A76: Share repurchases | B76: -85971 | C76: -89402 | D76: -77550 | E76: -94949 | F76: -90711 | G76: =IF((ABS(B76-CFS!B25)+ABS(C76-CFS!C25)+ABS(D76-CFS!D25)+ABS(E76-CFS!E25)+ABS(F76-CFS!F25))<5,"✓","✗ "&TEXT(ABS(B76-CFS!B25)+ABS(C76-CFS!C25)+ABS(D76-CFS!D25)+ABS(E76-CFS!E25)+ABS(F76-CFS!F25),"#,##0")) -> ✓ | H76: 10-K FY22/FY25 p.33
A77: Other financing | B77: 7085 | C77: -6506 | D77: -15913 | E77: -11800 | F77: -14554 | G77: =IF((ABS(B77-CFS!B26)+ABS(C77-CFS!C26)+ABS(D77-CFS!D26)+ABS(E77-CFS!E26)+ABS(F77-CFS!F26))<5,"✓","✗ "&TEXT(ABS(B77-CFS!B26)+ABS(C77-CFS!C26)+ABS(D77-CFS!D26)+ABS(E77-CFS!E26)+ABS(F77-CFS!F26),"#,##0")) -> ✓ | H77: 10-K (Total CFF - Div - Buybacks)
A78: Cash from financing | B78: -93353 | C78: -110749 | D78: -108488 | E78: -121983 | F78: -120686 | G78: =IF((ABS(B78-CFS!B27)+ABS(C78-CFS!C27)+ABS(D78-CFS!D27)+ABS(E78-CFS!E27)+ABS(F78-CFS!F27))<5,"✓","✗ "&TEXT(ABS(B78-CFS!B27)+ABS(C78-CFS!C27)+ABS(D78-CFS!D27)+ABS(E78-CFS!E27)+ABS(F78-CFS!F27),"#,##0")) -> ✓ | H78: 10-K FY22/FY25 p.33
A79: Net change in cash | B79: -3860 | C79: -10952 | D79: 5760 | E79: -794 | F79: 5991 | G79: =IF((ABS(B79-CFS!B29)+ABS(C79-CFS!C29)+ABS(D79-CFS!D29)+ABS(E79-CFS!E29)+ABS(F79-CFS!F29))<5,"✓","✗ "&TEXT(ABS(B79-CFS!B29)+ABS(C79-CFS!C29)+ABS(D79-CFS!D29)+ABS(E79-CFS!E29)+ABS(F79-CFS!F29),"#,##0")) -> ✓ | H79: Calculated
A80: Ending cash | B80: 35929 | C80: 24977 | D80: 30737 | E80: 29943 | F80: 35934 | G80: =IF((ABS(B80-CFS!B30)+ABS(C80-CFS!C30)+ABS(D80-CFS!D30)+ABS(E80-CFS!E30)+ABS(F80-CFS!F30))<5,"✓","✗ "&TEXT(ABS(B80-CFS!B30)+ABS(C80-CFS!C30)+ABS(D80-CFS!D30)+ABS(E80-CFS!E30)+ABS(F80-CFS!F30),"#,##0")) -> ✓ | H80: 10-K FY22/FY25 p.33
A83: VALIDATION SUMMARY
A85: Total historical data points verified | E85: =COUNTA(G16:G31)+COUNTA(G36:G61)+COUNTA(G66:G80) -> 57
A86: Data points matching 10-K filings | E86: =COUNTIF(G16:G31,"✓*")+COUNTIF(G36:G61,"✓*")+COUNTIF(G66:G80,"✓*")&" of "&(COUNTA(G16:G31)+COUNTA(G36:G61)+COUNTA(G66:G80))&" ("&TEXT((COUNTIF(G16:G31,"✓*")+COUNTIF(G36:G61,"✓*")+COUNTIF(G66:G80,"✓*"))/(COUNTA(G16:G31)+COUNTA(G36:G61)+COUNTA(G66:G80)),"0%")&")" -> 57 of 57 (100%)
A87: Mismatches | E87: =COUNTIF(G16:G31,"✗*")+COUNTIF(G36:G61,"✗*")+COUNTIF(G66:G80,"✗*") -> 0
A88: Balance sheet check (Assets - L - E) | E88: =IF(COUNTIF(B122:J122,"✓")=9,"$0 in all 9 years (5 historical + 4 projected)","⚠ IMBALANCE: "&(9-COUNTIF(B122:J122,"✓"))&" year(s) fail BS check — see row 114") -> $0 in all 9 years (5 historical + 4 projected)
A89: Cash flow ties to BS change in cash | E89: =IF(COUNTIF(B123:J123,"✓")+COUNTIF(B123:J123,"n/a*")=9,"✓ All years: ending cash flows to next period’s beginning","✗ CASH TIE BROKEN") -> ✓ All years: ending cash flows to next period’s beginning
A90: Projection methodology | E90: Driver-based: segment growth, GM%, OpEx growth, WC days, capital return %
A91: Balancing item | E91: None: cash flows from the cash flow statement and every other line has its own driver, so the balance check in the structural tests can fail.
A94: VALIDATION METHODOLOGY
A95: 1. Every hardcoded historical value (BLUE cells in IS, BS, CFS) was cross-referenced against Apple Inc.'s SEC 10-K filings.
A96: 2. Bundled lines (e.g., "Other current liabilities") are footnoted with the components that sum to the model figure.
A97: 3. All calculated totals (subtotals, sums) tie to the 10-K reported totals via formula.
A98: 4. The balance sheet balances in all 9 years (5 historical, 4 forecast) without a plug; see the structural checks.
A99: 5. Cash flow statement ending cash ties to balance sheet cash & equivalents in the next period.
A100: 6. Validation performed: May 2026 against 10-K filings dated Oct 2022, Nov 2023, Oct 2025.
A101: 7. Web verification cross-checked SEC EDGAR (sec.gov) and Apple Investor Relations (apple.com/newsroom) PDFs.
A103: FORECAST SANITY CHECKS | FY2026E – FY2029E
A104: Plausibility band tests: flags forecasts that drift outside reasonable financial ranges.
A106: Check | B106: FY26E | C106: FY27E | D106: FY28E | E106: FY29E | G106: Expected range
A107: Revenue growth in [-5%, +15%] band | B107: =IF(AND(IS!H15>=-0.05,IS!H15<=0.15),"✓ "&TEXT(IS!H15,"0.0%"),"✗ "&TEXT(IS!H15,"0.0%")) -> ✓ 5.0% | C107: =IF(AND(IS!I15>=-0.05,IS!I15<=0.15),"✓ "&TEXT(IS!I15,"0.0%"),"✗ "&TEXT(IS!I15,"0.0%")) -> ✓ 5.1% | D107: =IF(AND(IS!J15>=-0.05,IS!J15<=0.15),"✓ "&TEXT(IS!J15,"0.0%"),"✗ "&TEXT(IS!J15,"0.0%")) -> ✓ 5.2% | E107: =IF(AND(IS!K15>=-0.05,IS!K15<=0.15),"✓ "&TEXT(IS!K15,"0.0%"),"✗ "&TEXT(IS!K15,"0.0%")) -> ✓ 5.3% | G107: -5% to +15%
A108: Gross margin in [40%, 55%] band | B108: =IF(AND(IS!H23>=0.4,IS!H23<=0.55),"✓ "&TEXT(IS!H23,"0.0%"),"✗ "&TEXT(IS!H23,"0.0%")) -> ✓ 47.8% | C108: =IF(AND(IS!I23>=0.4,IS!I23<=0.55),"✓ "&TEXT(IS!I23,"0.0%"),"✗ "&TEXT(IS!I23,"0.0%")) -> ✓ 48.3% | D108: =IF(AND(IS!J23>=0.4,IS!J23<=0.55),"✓ "&TEXT(IS!J23,"0.0%"),"✗ "&TEXT(IS!J23,"0.0%")) -> ✓ 48.9% | E108: =IF(AND(IS!K23>=0.4,IS!K23<=0.55),"✓ "&TEXT(IS!K23,"0.0%"),"✗ "&TEXT(IS!K23,"0.0%")) -> ✓ 49.5% | G108: 40% to 55%
A109: Operating margin in [25%, 40%] band | B109: =IF(AND(IS!H30>=0.25,IS!H30<=0.4),"✓ "&TEXT(IS!H30,"0.0%"),"✗ "&TEXT(IS!H30,"0.0%")) -> ✓ 32.7% | C109: =IF(AND(IS!I30>=0.25,IS!I30<=0.4),"✓ "&TEXT(IS!I30,"0.0%"),"✗ "&TEXT(IS!I30,"0.0%")) -> ✓ 33.1% | D109: =IF(AND(IS!J30>=0.25,IS!J30<=0.4),"✓ "&TEXT(IS!J30,"0.0%"),"✗ "&TEXT(IS!J30,"0.0%")) -> ✓ 33.5% | E109: =IF(AND(IS!K30>=0.25,IS!K30<=0.4),"✓ "&TEXT(IS!K30,"0.0%"),"✗ "&TEXT(IS!K30,"0.0%")) -> ✓ 33.9% | G109: 25% to 40%
A110: Effective tax rate in [10%, 25%] | B110: =IF(AND(IS!H38>=0.1,IS!H38<=0.25),"✓ "&TEXT(IS!H38,"0.0%"),"✗ "&TEXT(IS!H38,"0.0%")) -> ✓ 15.0% | C110: =IF(AND(IS!I38>=0.1,IS!I38<=0.25),"✓ "&TEXT(IS!I38,"0.0%"),"✗ "&TEXT(IS!I38,"0.0%")) -> ✓ 15.0% | D110: =IF(AND(IS!J38>=0.1,IS!J38<=0.25),"✓ "&TEXT(IS!J38,"0.0%"),"✗ "&TEXT(IS!J38,"0.0%")) -> ✓ 15.0% | E110: =IF(AND(IS!K38>=0.1,IS!K38<=0.25),"✓ "&TEXT(IS!K38,"0.0%"),"✗ "&TEXT(IS!K38,"0.0%")) -> ✓ 15.0% | G110: 10% to 25%
A111: Net margin in [20%, 35%] band | B111: =IF(AND(IS!H40>=0.2,IS!H40<=0.35),"✓ "&TEXT(IS!H40,"0.0%"),"✗ "&TEXT(IS!H40,"0.0%")) -> ✓ 27.8% | C111: =IF(AND(IS!I40>=0.2,IS!I40<=0.35),"✓ "&TEXT(IS!I40,"0.0%"),"✗ "&TEXT(IS!I40,"0.0%")) -> ✓ 28.1% | D111: =IF(AND(IS!J40>=0.2,IS!J40<=0.35),"✓ "&TEXT(IS!J40,"0.0%"),"✗ "&TEXT(IS!J40,"0.0%")) -> ✓ 28.5% | E111: =IF(AND(IS!K40>=0.2,IS!K40<=0.35),"✓ "&TEXT(IS!K40,"0.0%"),"✗ "&TEXT(IS!K40,"0.0%")) -> ✓ 28.8% | G111: 20% to 35%
A112: CapEx % revenue in [1.5%, 5%] | B112: =IF(AND(-CFS!G19/IS!H14>=0.015,-CFS!G19/IS!H14<=0.05),"✓ "&TEXT(-CFS!G19/IS!H14,"0.0%"),"✗ "&TEXT(-CFS!G19/IS!H14,"0.0%")) -> ✓ 2.8% | C112: =IF(AND(-CFS!H19/IS!I14>=0.015,-CFS!H19/IS!I14<=0.05),"✓ "&TEXT(-CFS!H19/IS!I14,"0.0%"),"✗ "&TEXT(-CFS!H19/IS!I14,"0.0%")) -> ✓ 2.8% | D112: =IF(AND(-CFS!I19/IS!J14>=0.015,-CFS!I19/IS!J14<=0.05),"✓ "&TEXT(-CFS!I19/IS!J14,"0.0%"),"✗ "&TEXT(-CFS!I19/IS!J14,"0.0%")) -> ✓ 2.8% | E112: =IF(AND(-CFS!J19/IS!K14>=0.015,-CFS!J19/IS!K14<=0.05),"✓ "&TEXT(-CFS!J19/IS!K14,"0.0%"),"✗ "&TEXT(-CFS!J19/IS!K14,"0.0%")) -> ✓ 2.8% | G112: 1.5% to 5%
A113: FCF margin in [20%, 40%] | B113: =IF(AND(CFS!G21/IS!H14>=0.2,CFS!G21/IS!H14<=0.4),"✓ "&TEXT(CFS!G21/IS!H14,"0.0%"),"✗ "&TEXT(CFS!G21/IS!H14,"0.0%")) -> ✓ 35.2% | C113: =IF(AND(CFS!H21/IS!I14>=0.2,CFS!H21/IS!I14<=0.4),"✓ "&TEXT(CFS!H21/IS!I14,"0.0%"),"✗ "&TEXT(CFS!H21/IS!I14,"0.0%")) -> ✓ 31.5% | D113: =IF(AND(CFS!I21/IS!J14>=0.2,CFS!I21/IS!J14<=0.4),"✓ "&TEXT(CFS!I21/IS!J14,"0.0%"),"✗ "&TEXT(CFS!I21/IS!J14,"0.0%")) -> ✓ 31.9% | E113: =IF(AND(CFS!J21/IS!K14>=0.2,CFS!J21/IS!K14<=0.4),"✓ "&TEXT(CFS!J21/IS!K14,"0.0%"),"✗ "&TEXT(CFS!J21/IS!K14,"0.0%")) -> ✓ 32.3% | G113: 20% to 40%
...

Sheet Pivots
B2: PIVOT ANALYSIS | APPLE INC. (NASDAQ: AAPL)
B3: Slice-and-dice analytical layer | Source: IS, CFS, Ratios sheets (direct cell refs) | Filter via cell B7
B6: PERIOD TYPE FILTER | G6: ACTIVE PERIODS
B7: All | G7: =IF($B$7="All","9 of 9 (FY21–FY29)",IF($B$7="Actual","5 of 9 (FY21A–FY25A)","4 of 9 (FY26E–FY29E)")) -> 9 of 9 (FY21–FY29)
B8: Click B7 to toggle (All / Actual / Estimate). All four pivot tables and charts update instantly.
B11: 1. REVENUE MIX | Products vs Services Revenue ($M)
B12: Line Item | F12: FY2021A | G12: FY2022A | H12: FY2023A | I12: FY2024A | J12: FY2025A | K12: FY2026E | L12: FY2027E | M12: FY2028E | N12: FY2029E
B13: Products revenue | F13: =IF(OR($B$7="All",$B$7="Actual"),IS!B8,NA()) -> 297392 | G13: =IF(OR($B$7="All",$B$7="Actual"),IS!C8,NA()) -> 316199 | H13: =IF(OR($B$7="All",$B$7="Actual"),IS!D8,NA()) -> 298085 | I13: =IF(OR($B$7="All",$B$7="Actual"),IS!E8,NA()) -> 294866 | J13: =IF(OR($B$7="All",$B$7="Actual"),IS!F8,NA()) -> 307003 | K13: =IF(OR($B$7="All",$B$7="Estimate"),IS!H8,NA()) -> 316250.16 | L13: =IF(OR($B$7="All",$B$7="Estimate"),IS!I8,NA()) -> 325795.7 | M13: =IF(OR($B$7="All",$B$7="Estimate"),IS!J8,NA()) -> 335650 | N13: =IF(OR($B$7="All",$B$7="Estimate"),IS!K8,NA()) -> 345823.84
B14: Services revenue | F14: =IF(OR($B$7="All",$B$7="Actual"),IS!B13,NA()) -> 68425 | G14: =IF(OR($B$7="All",$B$7="Actual"),IS!C13,NA()) -> 78129 | H14: =IF(OR($B$7="All",$B$7="Actual"),IS!D13,NA()) -> 85200 | I14: =IF(OR($B$7="All",$B$7="Actual"),IS!E13,NA()) -> 96169 | J14: =IF(OR($B$7="All",$B$7="Actual"),IS!F13,NA()) -> 109158 | K14: =IF(OR($B$7="All",$B$7="Estimate"),IS!H13,NA()) -> 120619.59 | L14: =IF(OR($B$7="All",$B$7="Estimate"),IS!I13,NA()) -> 133284.65 | M14: =IF(OR($B$7="All",$B$7="Estimate"),IS!J13,NA()) -> 147279.53 | N14: =IF(OR($B$7="All",$B$7="Estimate"),IS!K13,NA()) -> 162743.89
B15: Total revenue | F15: =IF(OR($B$7="All",$B$7="Actual"),IS!B14,NA()) -> 365817 | G15: =IF(OR($B$7="All",$B$7="Actual"),IS!C14,NA()) -> 394328 | H15: =IF(OR($B$7="All",$B$7="Actual"),IS!D14,NA()) -> 383285 | I15: =IF(OR($B$7="All",$B$7="Actual"),IS!E14,NA()) -> 391035 | J15: =IF(OR($B$7="All",$B$7="Actual"),IS!F14,NA()) -> 416161 | K15: =IF(OR($B$7="All",$B$7="Estimate"),IS!H14,NA()) -> 436869.75 | L15: =IF(OR($B$7="All",$B$7="Estimate"),IS!I14,NA()) -> 459080.35 | M15: =IF(OR($B$7="All",$B$7="Estimate"),IS!J14,NA()) -> 482929.54 | N15: =IF(OR($B$7="All",$B$7="Estimate"),IS!K14,NA()) -> 508567.73
B17: 2. MARGINS | Profitability Trajectory (% of Revenue)
B18: Line Item | F18: FY2021A | G18: FY2022A | H18: FY2023A | I18: FY2024A | J18: FY2025A | K18: FY2026E | L18: FY2027E | M18: FY2028E | N18: FY2029E
B19: Gross margin % | F19: =IF(OR($B$7="All",$B$7="Actual"),Ratios!B7,NA()) -> 0.4177936 | G19: =IF(OR($B$7="All",$B$7="Actual"),Ratios!C7,NA()) -> 0.43309631 | H19: =IF(OR($B$7="All",$B$7="Actual"),Ratios!D7,NA()) -> 0.4413113 | I19: =IF(OR($B$7="All",$B$7="Actual"),Ratios!E7,NA()) -> 0.4620635 | J19: =IF(OR($B$7="All",$B$7="Actual"),Ratios!F7,NA()) -> 0.46905164 | K19: =IF(OR($B$7="All",$B$7="Estimate"),Ratios!G7,NA()) -> 0.47767887 | L19: =IF(OR($B$7="All",$B$7="Estimate"),Ratios!H7,NA()) -> 0.48322857 | M19: =IF(OR($B$7="All",$B$7="Estimate"),Ratios!I7,NA()) -> 0.48893871 | N19: =IF(OR($B$7="All",$B$7="Estimate"),Ratios!J7,NA()) -> 0.4948017
B20: Operating margin % | F20: =IF(OR($B$7="All",$B$7="Actual"),Ratios!B8,NA()) -> 0.29782378 | G20: =IF(OR($B$7="All",$B$7="Actual"),Ratios!C8,NA()) -> 0.30288744 | H20: =IF(OR($B$7="All",$B$7="Actual"),Ratios!D8,NA()) -> 0.29821412 | I20: =IF(OR($B$7="All",$B$7="Actual"),Ratios!E8,NA()) -> 0.31510223 | J20: =IF(OR($B$7="All",$B$7="Actual"),Ratios!F8,NA()) -> 0.319708 | K20: =IF(OR($B$7="All",$B$7="Estimate"),Ratios!G8,NA()) -> 0.32664004 | L20: =IF(OR($B$7="All",$B$7="Estimate"),Ratios!H8,NA()) -> 0.33060207 | M20: =IF(OR($B$7="All",$B$7="Estimate"),Ratios!I8,NA()) -> 0.33484029 | N20: =IF(OR($B$7="All",$B$7="Estimate"),Ratios!J8,NA()) -> 0.33935502
B21: Net margin % | F21: =IF(OR($B$7="All",$B$7="Actual"),Ratios!B9,NA()) -> 0.25881793 | G21: =IF(OR($B$7="All",$B$7="Actual"),Ratios!C9,NA()) -> 0.25309641 | H21: =IF(OR($B$7="All",$B$7="Actual"),Ratios!D9,NA()) -> 0.25306234 | I21: =IF(OR($B$7="All",$B$7="Actual"),Ratios!E9,NA()) -> 0.23971256 | J21: =IF(OR($B$7="All",$B$7="Actual"),Ratios!F9,NA()) -> 0.26915064 | K21: =IF(OR($B$7="All",$B$7="Estimate"),Ratios!G9,NA()) -> 0.27764403 | L21: =IF(OR($B$7="All",$B$7="Estimate"),Ratios!H9,NA()) -> 0.28101176 | M21: =IF(OR($B$7="All",$B$7="Estimate"),Ratios!I9,NA()) -> 0.28461424 | N21: =IF(OR($B$7="All",$B$7="Estimate"),Ratios!J9,NA()) -> 0.28845176
B23: 3. FREE CASH FLOW | Operating Cash + CapEx → FCF ($M)
B24: Line Item | F24: FY2021A | G24: FY2022A | H24: FY2023A | I24: FY2024A | J24: FY2025A | K24: FY2026E | L24: FY2027E | M24: FY2028E | N24: FY2029E
B25: Cash from operations | F25: =IF(OR($B$7="All",$B$7="Actual"),CFS!B14,NA()) -> 104038 | G25: =IF(OR($B$7="All",$B$7="Actual"),CFS!C14,NA()) -> 122151 | H25: =IF(OR($B$7="All",$B$7="Actual"),CFS!D14,NA()) -> 110543 | I25: =IF(OR($B$7="All",$B$7="Actual"),CFS!E14,NA()) -> 118254 | J25: =IF(OR($B$7="All",$B$7="Actual"),CFS!F14,NA()) -> 111482 | K25: =IF(OR($B$7="All",$B$7="Estimate"),CFS!G14,NA()) -> 165868.1 | L25: =IF(OR($B$7="All",$B$7="Estimate"),CFS!H14,NA()) -> 157670.51 | M25: =IF(OR($B$7="All",$B$7="Estimate"),CFS!I14,NA()) -> 167642.96 | N25: =IF(OR($B$7="All",$B$7="Estimate"),CFS!J14,NA()) -> 178539.63
B26: Capital expenditures | F26: =IF(OR($B$7="All",$B$7="Actual"),CFS!B19,NA()) -> -11085 | G26: =IF(OR($B$7="All",$B$7="Actual"),CFS!C19,NA()) -> -10708 | H26: =IF(OR($B$7="All",$B$7="Actual"),CFS!D19,NA()) -> -10959 | I26: =IF(OR($B$7="All",$B$7="Actual"),CFS!E19,NA()) -> -9447 | J26: =IF(OR($B$7="All",$B$7="Actual"),CFS!F19,NA()) -> -12715 | K26: =IF(OR($B$7="All",$B$7="Estimate"),CFS!G19,NA()) -> -12232.353 | L26: =IF(OR($B$7="All",$B$7="Estimate"),CFS!H19,NA()) -> -12854.25 | M26: =IF(OR($B$7="All",$B$7="Estimate"),CFS!I19,NA()) -> -13522.027 | N26: =IF(OR($B$7="All",$B$7="Estimate"),CFS!J19,NA()) -> -14239.896
B27: Free cash flow | F27: =IF(OR($B$7="All",$B$7="Actual"),CFS!B21,NA()) -> 92953 | G27: =IF(OR($B$7="All",$B$7="Actual"),CFS!C21,NA()) -> 111443 | H27: =IF(OR($B$7="All",$B$7="Actual"),CFS!D21,NA()) -> 99584 | I27: =IF(OR($B$7="All",$B$7="Actual"),CFS!E21,NA()) -> 108807 | J27: =IF(OR($B$7="All",$B$7="Actual"),CFS!F21,NA()) -> 98767 | K27: =IF(OR($B$7="All",$B$7="Estimate"),CFS!G21,NA()) -> 153635.75 | L27: =IF(OR($B$7="All",$B$7="Estimate"),CFS!H21,NA()) -> 144816.26 | M27: =IF(OR($B$7="All",$B$7="Estimate"),CFS!I21,NA()) -> 154120.94 | N27: =IF(OR($B$7="All",$B$7="Estimate"),CFS!J21,NA()) -> 164299.73
B29: 4. CAPITAL RETURN | Dividends + Share Repurchases ($M)
B30: Line Item | F30: FY2021A | G30: FY2022A | H30: FY2023A | I30: FY2024A | J30: FY2025A | K30: FY2026E | L30: FY2027E | M30: FY2028E | N30: FY2029E
B31: Dividends paid | F31: =IF(OR($B$7="All",$B$7="Actual"),CFS!B24,NA()) -> -14467 | G31: =IF(OR($B$7="All",$B$7="Actual"),CFS!C24,NA()) -> -14841 | H31: =IF(OR($B$7="All",$B$7="Actual"),CFS!D24,NA()) -> -15025 | I31: =IF(OR($B$7="All",$B$7="Actual"),CFS!E24,NA()) -> -15234 | J31: =IF(OR($B$7="All",$B$7="Actual"),CFS!F24,NA()) -> -15421 | K31: =IF(OR($B$7="All",$B$7="Estimate"),CFS!G24,NA()) -> -21893.095 | L31: =IF(OR($B$7="All",$B$7="Estimate"),CFS!H24,NA()) -> -20636.317 | M31: =IF(OR($B$7="All",$B$7="Estimate"),CFS!I24,NA()) -> -21962.233 | N31: =IF(OR($B$7="All",$B$7="Estimate"),CFS!J24,NA()) -> -23412.712
B32: Share repurchases | F32: =IF(OR($B$7="All",$B$7="Actual"),CFS!B25,NA()) -> -85971 | G32: =IF(OR($B$7="All",$B$7="Actual"),CFS!C25,NA()) -> -89402 | H32: =IF(OR($B$7="All",$B$7="Actual"),CFS!D25,NA()) -> -77550 | I32: =IF(OR($B$7="All",$B$7="Actual"),CFS!E25,NA()) -> -94949 | J32: =IF(OR($B$7="All",$B$7="Actual"),CFS!F25,NA()) -> -90711 | K32: =IF(OR($B$7="All",$B$7="Estimate"),CFS!G25,NA()) -> -124060.87 | L32: =IF(OR($B$7="All",$B$7="Estimate"),CFS!H25,NA()) -> -116939.13 | M32: =IF(OR($B$7="All",$B$7="Estimate"),CFS!I25,NA()) -> -124452.66 | N32: =IF(OR($B$7="All",$B$7="Estimate"),CFS!J25,NA()) -> -132672.04
B36: Pivots auto-update via direct cell references to IS, CFS, and Ratios sheets | Filter via cell B7 | All values traceable to source statements
