Workbook

Sheet Inputs
A1: MILLERKNOLL, INC.: model inputs
A2: $ in millions unless noted; rates as decimals
A4: Last reported quarter of FY2027 | C4: 0
A5: Shares outstanding, latest 10-Q/10-K cover (millions) | C5: 68.123238
A7: Gross margin | C7: 0.3874
A8: SG&A, % of revenue | C8: 0.3078
A9: Other operating expenses, % of revenue | C9: 0.0254
A10: Depreciation and amortization, % of revenue | C10: 0.0386
A11: Capital expenditures, % of revenue | C11: 0.0318
A12: Tax rate | C12: 0.253
A13: Days sales outstanding (on revenue) | C13: 34
A14: Days inventory outstanding (on cost of revenue) | C14: 75.8
A15: Days payables outstanding (on cost of revenue) | C15: 43.3
A16: Shareholder payouts and other financing, % of net income | C16: 1
... A24: Terminal growth rate | C24: 0.025
A26: Revenue growth drivers by segment: see the Revenue sheet

Sheet Revenue
A1: MILLERKNOLL, INC.: revenue by segment
A2: $ in millions
C3: Q1 FY2026 | D3: Q2 FY2026 | E3: Q3 FY2026 | F3: Q4 FY2026 | G3: FY2026 | H3: Q1 FY2027 | I3: Q2 FY2027 | J3: Q3 FY2027 | K3: Q4 FY2027 | L3: FY2027 | M3: FY2028E | N3: FY2029E | O3: FY2030E | P3: FY2031E
C4: A | D4: A | E4: A | F4: A | G4: A | H4: =IF(1<=Inputs!$C$4,"A","E") | I4: =IF(2<=Inputs!$C$4,"A","E") | J4: =IF(3<=Inputs!$C$4,"A","E") | K4: =IF(4<=Inputs!$C$4,"A","E") | M4: E | N4: E | O4: E | P4: E
A6: Global Retail | C6: 254.3 | D6: 275.8 | E6: 281.1 | F6: =G6-C6-D6-E6 | G6: 1106.5 | H6: =C6*(1+L12) | I6: =D6*(1+L12) | J6: =E6*(1+L12) | K6: =F6*(1+L12) | L6: =SUM(H6:K6) | M6: =L6*(1+M12) | N6: =M6*(1+N12) | O6: =N6*(1+O12) | P6: =O6*(1+P12)
A7: International Contract | C7: 167.5 | D7: 170.9 | E7: 156.9 | F7: =G7-C7-D7-E7 | G7: 674 | H7: =C7*(1+L13) | I7: =D7*(1+L13) | J7: =E7*(1+L13) | K7: =F7*(1+L13) | L7: =SUM(H7:K7) | M7: =L7*(1+M13) | N7: =M7*(1+N13) | O7: =N7*(1+O13) | P7: =O7*(1+P13)
A8: North America Contract | C8: 533.9 | D8: 508.5 | E8: 488.6 | F8: =G8-C8-D8-E8 | G8: 2061.2 | H8: =C8*(1+L14) | I8: =D8*(1+L14) | J8: =E8*(1+L14) | K8: =F8*(1+L14) | L8: =SUM(H8:K8) | M8: =L8*(1+M14) | N8: =M8*(1+N14) | O8: =N8*(1+O14) | P8: =O8*(1+P14)
A9: Total revenue | C9: =C6+C7+C8 | D9: =D6+D7+D8 | E9: =E6+E7+E8 | F9: =F6+F7+F8 | G9: =G6+G7+G8 | H9: =H6+H7+H8 | I9: =I6+I7+I8 | J9: =J6+J7+J8 | ... P9: =P6+P7+P8
A11: Growth drivers: FY2027 quarters vs. the same quarter of FY2026 (column L), and each forecast year
A12: Growth: Global Retail | L12: 0.059 | M12: 0.059 | N12: 0.05 | O12: 0.041 | P12: 0.032
A13: Growth: International Contract | L13: 0.021 | M13: 0.021 | N13: 0.02 | O13: 0.02 | P13: 0.02
A14: Growth: North America Contract | L14: 0.049 | M14: 0.049 | N14: 0.042 | O14: 0.034 | P14: 0.027

Sheet IS
A1: MILLERKNOLL, INC.: income statement
A2: $ in millions
C3: Q1 FY2026 | D3: Q2 FY2026 | E3: Q3 FY2026 | F3: Q4 FY2026 | G3: FY2026 | H3: Q1 FY2027 | I3: Q2 FY2027 | J3: Q3 FY2027 | K3: Q4 FY2027 | L3: FY2027 | M3: FY2028E | N3: FY2029E | O3: FY2030E | P3: FY2031E
C4: A | D4: A | E4: A | F4: A | G4: A | H4: =IF(1<=Inputs!$C$4,"A","E") | I4: =IF(2<=Inputs!$C$4,"A","E") | J4: =IF(3<=Inputs!$C$4,"A","E") | K4: =IF(4<=Inputs!$C$4,"A","E") | M4: E | N4: E | O4: E | P4: E
A6: Revenue | C6: =Revenue!C9 | D6: =Revenue!D9 | E6: =Revenue!E9 | F6: =Revenue!F9 | G6: =Revenue!G9 | H6: =Revenue!H9 | I6: =Revenue!I9 | J6: =Revenue!J9 | ... P6: =Revenue!P9
A7: Cost of revenue | C7: 587.6 | D7: 583 | E7: 573.7 | F7: =G7-C7-D7-E7 | G7: 2352.9 | H7: =H6*(1-Inputs!$C$7) | I7: =I6*(1-Inputs!$C$7) | J7: =J6*(1-Inputs!$C$7) | K7: =K6*(1-Inputs!$C$7) | L7: =SUM(H7:K7) | M7: =M6*(1-Inputs!$C$7) | N7: =N6*(1-Inputs!$C$7) | O7: =O6*(1-Inputs!$C$7) | P7: =P6*(1-Inputs!$C$7)
A8: Gross profit | C8: =C6-C7 | D8: =D6-D7 | E8: =E6-E7 | F8: =F6-F7 | G8: =G6-G7 | H8: =H6-H7 | I8: =I6-I7 | J8: =J6-J7 | ... P8: =P6-P7
A9: Selling, general and administrative | C9: 293.8 | D9: 298.3 | E9: 285.5 | F9: =G9-C9-D9-E9 | G9: 1178.3 | H9: =H6*Inputs!$C$8 | I9: =I6*Inputs!$C$8 | J9: =J6*Inputs!$C$8 | K9: =K6*Inputs!$C$8 | L9: =SUM(H9:K9) | M9: =M6*Inputs!$C$8 | N9: =N6*Inputs!$C$8 | O9: =O6*Inputs!$C$8 | P9: =P6*Inputs!$C$8
A10: Other operating expenses, net | C10: =C8-C9-C11 | D10: =D8-D9-D11 | E10: =E8-E9-E11 | F10: =F8-F9-F11 | G10: =G8-G9-G11 | H10: =H6*Inputs!$C$9 | I10: =I6*Inputs!$C$9 | J10: =J6*Inputs!$C$9 | K10: =K6*Inputs!$C$9 | L10: =L8-L9-L11 | M10: =M6*Inputs!$C$9 | N10: =N6*Inputs!$C$9 | O10: =O6*Inputs!$C$9 | P10: =P6*Inputs!$C$9
A11: Operating income | C11: 53.5 | D11: 48.5 | E11: 44.9 | F11: =G11-C11-D11-E11 | G11: 198.3 | H11: =H8-H9-H10 | I11: =I8-I9-I10 | J11: =J8-J9-J10 | K11: =K8-K9-K10 | L11: =SUM(H11:K11) | M11: =M8-M9-M10 | N11: =N8-N9-N10 | O11: =O8-O9-O10 | P11: =P8-P9-P10
A12: Interest expense | C12: 18.4 | D12: 17.9 | E12: 17.2 | F12: =G12-C12-D12-E12 | G12: 69.9 | H12: =Inputs!$C$17/4 | I12: =Inputs!$C$17/4 | J12: =Inputs!$C$17/4 | K12: =Inputs!$C$17/4 | L12: =SUM(H12:K12) | M12: =Inputs!$C$17 | N12: =Inputs!$C$17 | O12: =Inputs!$C$17 | P12: =Inputs!$C$17
A13: Other non-operating income (expense), net | C13: =C14-C11+C12 | D13: =D14-D11+D12 | E13: =E14-E11+E12 | F13: =F14-F11+F12 | G13: =G14-G11+G12 | H13: =Inputs!$C$18 | I13: =Inputs!$C$18 | J13: =Inputs!$C$18 | K13: =Inputs!$C$18 | L13: =L14-L11+L12 | M13: =Inputs!$C$18*4 | N13: =Inputs!$C$18*4 | O13: =Inputs!$C$18*4 | P13: =Inputs!$C$18*4
A14: Income before income taxes | C14: 28.7 | D14: 32.5 | E14: 29.2 | F14: =G14-C14-D14-E14 | G14: 128.2 | H14: =H11-H12+H13 | I14: =I11-I12+I13 | J14: =J11-J12+J13 | K14: =K11-K12+K13 | L14: =SUM(H14:K14) | M14: =M11-M12+M13 | N14: =N11-N12+N13 | O14: =O11-O12+O13 | P14: =P11-P12+P13
A15: Income tax expense | C15: 7.6 | D15: 7.3 | E15: 5.6 | F15: =G15-C15-D15-E15 | G15: 32.4 | H15: =H14*Inputs!$C$12 | I15: =I14*Inputs!$C$12 | J15: =J14*Inputs!$C$12 | K15: =K14*Inputs!$C$12 | L15: =SUM(H15:K15) | M15: =M14*Inputs!$C$12 | N15: =N14*Inputs!$C$12 | O15: =O14*Inputs!$C$12 | P15: =P14*Inputs!$C$12
A16: Other items after tax, incl. non-controlling interests | C16: =C17-(C14-C15) | D16: =D17-(D14-D15) | E16: =E17-(E14-E15) | F16: =F17-(F14-F15) | G16: =G17-(G14-G15) | H16: =Inputs!$C$19 | I16: =Inputs!$C$19 | J16: =Inputs!$C$19 | K16: =Inputs!$C$19 | L16: =L17-(L14-L15) | M16: =Inputs!$C$19*4 | N16: =Inputs!$C$19*4 | O16: =Inputs!$C$19*4 | P16: =Inputs!$C$19*4
A17: Net income attributable to the company | C17: 20.2 | D17: 24.2 | E17: 23.5 | F17: =G17-C17-D17-E17 | G17: 91.5 | H17: =H14-H15+H16 | I17: =I14-I15+I16 | J17: =J14-J15+J16 | K17: =K14-K15+K16 | L17: =SUM(H17:K17) | M17: =M14-M15+M16 | N17: =N14-N15+N16 | O17: =O14-O15+O16 | P17: =P14-P15+P16
A18: Memo: depreciation and amortization (cash flow statement) | C18: =CF!C25 | D18: =CF!D25-CF!C25 | E18: =CF!E25-CF!D25 | F18: =CF!G25-CF!E25 | G18: =CF!G25 | H18: =H6*Inputs!$C$10 | I18: =I6*Inputs!$C$10 | J18: =J6*Inputs!$C$10 | K18: =K6*Inputs!$C$10 | L18: =SUM(H18:K18) | M18: =M6*Inputs!$C$10 | N18: =N6*Inputs!$C$10 | O18: =O6*Inputs!$C$10 | P18: =P6*Inputs!$C$10
A19: EBITDA (operating income + D&A) | C19: =C11+C18 | D19: =D11+D18 | E19: =E11+E18 | F19: =F11+F18 | G19: =G11+G18 | H19: =H11+H18 | I19: =I11+I18 | J19: =J11+J18 | ... P19: =P11+P18

Sheet BS
A1: MILLERKNOLL, INC.: balance sheet
A2: $ in millions
G3: FY2026 | H3: Q1 FY2027 | I3: Q2 FY2027 | J3: Q3 FY2027 | K3: Q4 FY2027 | M3: FY2028E | N3: FY2029E | O3: FY2030E | P3: FY2031E
G4: A | H4: =IF(1<=Inputs!$C$4,"A","E") | I4: =IF(2<=Inputs!$C$4,"A","E") | J4: =IF(3<=Inputs!$C$4,"A","E") | K4: =IF(4<=Inputs!$C$4,"A","E") | M4: E | N4: E | O4: E | P4: E
A6: Cash and cash equivalents | G6: 167.7 | H6: =CF!H17 | I6: =CF!I17 | J6: =CF!J17 | K6: =CF!K17 | M6: =CF!M17 | N6: =CF!N17 | O6: =CF!O17 | P6: =CF!P17
A7: Accounts receivable, net | G7: 357.4 | H7: =IS!H6*Inputs!$C$13/91.25 | I7: =IS!I6*Inputs!$C$13/91.25 | J7: =IS!J6*Inputs!$C$13/91.25 | K7: =IS!K6*Inputs!$C$13/91.25 | M7: =IS!M6*Inputs!$C$13/365 | N7: =IS!N6*Inputs!$C$13/365 | O7: =IS!O6*Inputs!$C$13/365 | P7: =IS!P6*Inputs!$C$13/365
A8: Inventories | G8: 488.4 | H8: =IS!H7*Inputs!$C$14/91.25 | I8: =IS!I7*Inputs!$C$14/91.25 | J8: =IS!J7*Inputs!$C$14/91.25 | K8: =IS!K7*Inputs!$C$14/91.25 | M8: =IS!M7*Inputs!$C$14/365 | N8: =IS!N7*Inputs!$C$14/365 | O8: =IS!O7*Inputs!$C$14/365 | P8: =IS!P7*Inputs!$C$14/365
A9: Other current assets | G9: =G10-G6-G7-G8 | H9: =G9 | I9: =H9 | J9: =I9 | K9: =J9 | M9: =K9 | N9: =M9 | O9: =N9 | P9: =O9
A10: Total current assets | G10: 1137.2 | H10: =H6+H7+H8+H9 | I10: =I6+I7+I8+I9 | J10: =J6+J7+J8+J9 | K10: =K6+K7+K8+K9 | M10: =M6+M7+M8+M9 | N10: =N6+N7+N8+N9 | O10: =O6+O7+O8+O9 | P10: =P6+P7+P8+P9
A11: Property and equipment, net | G11: 511.3 | H11: =G11-CF!H10-IS!H18 | I11: =H11-CF!I10-IS!I18 | J11: =I11-CF!J10-IS!J18 | K11: =J11-CF!K10-IS!K18 | M11: =K11-CF!M10-IS!M18 | N11: =M11-CF!N10-IS!N18 | O11: =N11-CF!O10-IS!O18 | P11: =O11-CF!P10-IS!P18
A12: Goodwill | G12: 1161.3 | H12: =G12 | I12: =H12 | J12: =I12 | K12: =J12 | M12: =K12 | N12: =M12 | O12: =N12 | P12: =O12
A13: Amortizable intangible assets, net | G13: 214 | H13: =G13 | I13: =H13 | J13: =I13 | K13: =J13 | M13: =K13 | N13: =M13 | O13: =N13 | P13: =O13
A14: Other non-current assets | G14: =G15-G10-G11-G12-G13 | H14: =G14 | I14: =H14 | J14: =I14 | K14: =J14 | M14: =K14 | N14: =M14 | O14: =N14 | P14: =O14
A15: Total assets | G15: 4000.5 | H15: =H10+H11+H12+H13+H14 | I15: =I10+I11+I12+I13+I14 | J15: =J10+J11+J12+J13+J14 | K15: =K10+K11+K12+K13+K14 | M15: =M10+M11+M12+M13+M14 | N15: =N10+N11+N12+N13+N14 | O15: =O10+O11+O12+O13+O14 | P15: =P10+P11+P12+P13+P14
A16: Accounts payable | G16: 279.1 | H16: =IS!H7*Inputs!$C$15/91.25 | I16: =IS!I7*Inputs!$C$15/91.25 | J16: =IS!J7*Inputs!$C$15/91.25 | K16: =IS!K7*Inputs!$C$15/91.25 | M16: =IS!M7*Inputs!$C$15/365 | N16: =IS!N7*Inputs!$C$15/365 | O16: =IS!O7*Inputs!$C$15/365 | P16: =IS!P7*Inputs!$C$15/365
A17: Short-term borrowings | G17: 0 | H17: =G17 | I17: =H17 | J17: =I17 | K17: =J17 | M17: =K17 | N17: =M17 | O17: =N17 | P17: =O17
A18: Short-term borrowings and current portion of long-term debt | G18: 25.1 | H18: =G18 | I18: =H18 | J18: =I18 | K18: =J18 | M18: =K18 | N18: =M18 | O18: =N18 | P18: =O18
A19: Other current liabilities | G19: =G20-G16-G17-G18 | H19: =G19 | I19: =H19 | J19: =I19 | K19: =J19 | M19: =K19 | N19: =M19 | O19: =N19 | P19: =O19
A20: Total current liabilities | G20: 721.1 | H20: =H16+H17+H18+H19 | I20: =I16+I17+I18+I19 | J20: =J16+J17+J18+J19 | K20: =K16+K17+K18+K19 | M20: =M16+M17+M18+M19 | N20: =N16+N17+N18+N19 | O20: =O16+O17+O18+O19 | P20: =P16+P17+P18+P19
A21: Long-term debt | G21: 1260.6 | H21: =G21 | I21: =H21 | J21: =I21 | K21: =J21 | M21: =K21 | N21: =M21 | O21: =N21 | P21: =O21
A22: Other non-current liabilities | G22: =G28-G20-G21-G24-G25-G26 | H22: =G22 | I22: =H22 | J22: =I22 | K22: =J22 | M22: =K22 | N22: =M22 | O22: =N22 | P22: =O22
A23: Total liabilities | G23: =G28-G24-G25-G26 | H23: =H28-H24-H25-H26 | I23: =I28-I24-I25-I26 | J23: =J28-J24-J25-J26 | K23: =K28-K24-K25-K26 | M23: =M28-M24-M25-M26 | N23: =N28-N24-N25-N26 | O23: =O28-O24-O25-O26 | P23: =P28-P24-P25-P26
A24: Redeemable non-controlling interests | G24: 63.3 | H24: =G24 | I24: =H24 | J24: =I24 | K24: =J24 | M24: =K24 | N24: =M24 | O24: =N24 | P24: =O24
A25: Shareholders' equity (company) | G25: 1342.6 | H25: =G25+IS!H17+CF!H13 | I25: =H25+IS!I17+CF!I13 | J25: =I25+IS!J17+CF!J13 | K25: =J25+IS!K17+CF!K13 | M25: =K25+IS!M17+CF!M13 | N25: =M25+IS!N17+CF!N13 | O25: =N25+IS!O17+CF!O13 | P25: =O25+IS!P17+CF!P13
A26: Non-controlling interests | G26: 0 | H26: =G26 | I26: =H26 | J26: =I26 | K26: =J26 | M26: =K26 | N26: =M26 | O26: =N26 | P26: =O26
A27: Total equity | G27: =G25+G26 | H27: =H25+H26 | I27: =I25+I26 | J27: =J25+J26 | K27: =K25+K26 | M27: =M25+M26 | N27: =N25+N26 | O27: =O25+O26 | P27: =P25+P26
A28: Total liabilities and equity | G28: 4000.5 | H28: =H20+H21+H22+H24+H25+H26 | I28: =I20+I21+I22+I24+I25+I26 | J28: =J20+J21+J22+J24+J25+J26 | K28: =K20+K21+K22+K24+K25+K26 | M28: =M20+M21+M22+M24+M25+M26 | N28: =N20+N21+N22+N24+N25+N26 | O28: =O20+O21+O22+O24+O25+O26 | P28: =P20+P21+P22+P24+P25+P26
A29: Check: total assets - total liabilities and equity (should be 0) | G29: =G15-G28 | H29: =H15-H28 | I29: =I15-I28 | J29: =J15-J28 | K29: =K15-K28 | M29: =M15-M28 | N29: =N15-N28 | O29: =O15-O28 | P29: =P15-P28

Sheet CF
A1: MILLERKNOLL, INC.: cash flow statement
A2: $ in millions
G3: FY2026 | H3: Q1 FY2027 | I3: Q2 FY2027 | J3: Q3 FY2027 | K3: Q4 FY2027 | L3: FY2027 | M3: FY2028E | N3: FY2029E | O3: FY2030E | P3: FY2031E
G4: A | H4: =IF(1<=Inputs!$C$4,"A","E") | I4: =IF(2<=Inputs!$C$4,"A","E") | J4: =IF(3<=Inputs!$C$4,"A","E") | K4: =IF(4<=Inputs!$C$4,"A","E") | M4: E | N4: E | O4: E | P4: E
A6: Net income | G6: =IS!G17 | H6: =IS!H17 | I6: =IS!I17 | J6: =IS!J17 | K6: =IS!K17 | L6: =IS!L17 | M6: =IS!M17 | N6: =IS!N17 | ... P6: =IS!P17
A7: Depreciation and amortization | G7: =IS!G18 | H7: =IS!H18 | I7: =IS!I18 | J7: =IS!J18 | K7: =IS!K18 | L7: =IS!L18 | M7: =IS!M18 | N7: =IS!N18 | ... P7: =IS!P18
A8: Working capital and other operating items | G8: =G9-G6-G7 | H8: =BS!G7-BS!H7+BS!G8-BS!H8+BS!H16-BS!G16 | I8: =BS!H7-BS!I7+BS!H8-BS!I8+BS!I16-BS!H16 | J8: =BS!I7-BS!J7+BS!I8-BS!J8+BS!J16-BS!I16 | K8: =BS!J7-BS!K7+BS!J8-BS!K8+BS!K16-BS!J16 | L8: =SUM(H8:K8) | M8: =BS!K7-BS!M7+BS!K8-BS!M8+BS!M16-BS!K16 | N8: =BS!M7-BS!N7+BS!M8-BS!N8+BS!N16-BS!M16 | O8: =BS!N7-BS!O7+BS!N8-BS!O8+BS!O16-BS!N16 | P8: =BS!O7-BS!P7+BS!O8-BS!P8+BS!P16-BS!O16
A9: Cash from operating activities | G9: =G21 | H9: =H6+H7+H8 | I9: =I6+I7+I8 | J9: =J6+J7+J8 | K9: =K6+K7+K8 | L9: =SUM(H9:K9) | M9: =M6+M7+M8 | N9: =N6+N7+N8 | O9: =O6+O7+O8 | P9: =P6+P7+P8
A10: Capital expenditures | G10: =G22 | H10: =-IS!H6*Inputs!$C$11 | I10: =-IS!I6*Inputs!$C$11 | J10: =-IS!J6*Inputs!$C$11 | K10: =-IS!K6*Inputs!$C$11 | L10: =SUM(H10:K10) | M10: =-IS!M6*Inputs!$C$11 | N10: =-IS!N6*Inputs!$C$11 | O10: =-IS!O6*Inputs!$C$11 | P10: =-IS!P6*Inputs!$C$11
A11: Other investing activities | G11: =G12-G10 | H11: =Inputs!$C$20 | I11: =Inputs!$C$20 | J11: =Inputs!$C$20 | K11: =Inputs!$C$20 | L11: =SUM(H11:K11) | M11: =Inputs!$C$20*4 | N11: =Inputs!$C$20*4 | O11: =Inputs!$C$20*4 | P11: =Inputs!$C$20*4
A12: Cash from investing activities | G12: =G23 | H12: =H10+H11 | I12: =I10+I11 | J12: =J10+J11 | K12: =K10+K11 | L12: =SUM(H12:K12) | M12: =M10+M11 | N12: =N10+N11 | O12: =O10+O11 | P12: =P10+P11
A13: Cash from financing activities | G13: =G24 | H13: =-IS!H17*Inputs!$C$16 | I13: =-IS!I17*Inputs!$C$16 | J13: =-IS!J17*Inputs!$C$16 | K13: =-IS!K17*Inputs!$C$16 | L13: =SUM(H13:K13) | M13: =-IS!M17*Inputs!$C$16 | N13: =-IS!N17*Inputs!$C$16 | O13: =-IS!O17*Inputs!$C$16 | P13: =-IS!P17*Inputs!$C$16
A14: Exchange rate effect, restricted cash and other | H14: =Inputs!$C$21 | I14: =Inputs!$C$21 | J14: =Inputs!$C$21 | K14: =Inputs!$C$21 | L14: =SUM(H14:K14) | M14: =Inputs!$C$21*4 | N14: =Inputs!$C$21*4 | O14: =Inputs!$C$21*4 | P14: =Inputs!$C$21*4
A15: Net change in cash | H15: =H9+H12+H13+H14 | I15: =I9+I12+I13+I14 | J15: =J9+J12+J13+J14 | K15: =K9+K12+K13+K14 | L15: =SUM(H15:K15) | M15: =M9+M12+M13+M14 | N15: =N9+N12+N13+N14 | O15: =O9+O12+O13+O14 | P15: =P9+P12+P13+P14
A16: Cash at beginning of period | H16: =BS!G6 | I16: =BS!H6 | J16: =BS!I6 | K16: =BS!J6 | L16: =BS!G6 | M16: =BS!K6 | N16: =BS!M6 | O16: =BS!N6 | P16: =BS!O6
A17: Cash at end of period | H17: =H16+H15 | I17: =I16+I15 | J17: =J16+J15 | K17: =K16+K15 | L17: =L16+L15 | M17: =M16+M15 | N17: =N16+N15 | O17: =O16+O15 | P17: =P16+P15
A18: Free cash flow (operating cash flow + capital expenditures) | G18: =G9+G10 | H18: =H9+H10 | I18: =I9+I10 | J18: =J9+J10 | K18: =K9+K10 | L18: =L9+L10 | M18: =M9+M10 | N18: =N9+N10 | ... P18: =P9+P10
A20: As reported in each filing (year to date)
A21: Cash from operating activities, year to date (as reported) | G21: 199.9
A22: Capital expenditures, year to date (as reported) | G22: -122.3
A23: Cash from investing activities, year to date (as reported) | G23: -115.6
A24: Cash from financing activities, year to date (as reported) | G24: -117
A25: Depreciation and amortization, year to date (as reported) | C25: 35.4 | D25: 72 | E25: 110.1 | G25: 148.3

Sheet DCF
A1: MILLERKNOLL, INC.: unlevered DCF and valuation
A2: $ in millions
H3: Q1 FY2027 | I3: Q2 FY2027 | J3: Q3 FY2027 | K3: Q4 FY2027 | M3: FY2028E | N3: FY2029E | O3: FY2030E | P3: FY2031E
H4: =IF(1<=Inputs!$C$4,"A","E") | I4: =IF(2<=Inputs!$C$4,"A","E") | J4: =IF(3<=Inputs!$C$4,"A","E") | K4: =IF(4<=Inputs!$C$4,"A","E") | M4: E | N4: E | O4: E | P4: E
A6: Fiscal quarter | H6: 1 | I6: 2 | J6: 3 | K6: 4
A7: EBIT | H7: =IS!H11 | I7: =IS!I11 | J7: =IS!J11 | K7: =IS!K11 | M7: =IS!M11 | N7: =IS!N11 | O7: =IS!O11 | P7: =IS!P11
A8: Tax on EBIT | H8: =-H7*Inputs!$C$12 | I8: =-I7*Inputs!$C$12 | J8: =-J7*Inputs!$C$12 | K8: =-K7*Inputs!$C$12 | M8: =-M7*Inputs!$C$12 | N8: =-N7*Inputs!$C$12 | O8: =-O7*Inputs!$C$12 | P8: =-P7*Inputs!$C$12
A9: NOPAT | H9: =H7+H8 | I9: =I7+I8 | J9: =J7+J8 | K9: =K7+K8 | M9: =M7+M8 | N9: =N7+N8 | O9: =O7+O8 | P9: =P7+P8
A10: Depreciation and amortization | H10: =IS!H18 | I10: =IS!I18 | J10: =IS!J18 | K10: =IS!K18 | M10: =IS!M18 | N10: =IS!N18 | O10: =IS!O18 | P10: =IS!P18
A11: Capital expenditures | H11: =CF!H10 | I11: =CF!I10 | J11: =CF!J10 | K11: =CF!K10 | M11: =CF!M10 | N11: =CF!N10 | O11: =CF!O10 | P11: =CF!P10
A12: Working capital and other | H12: =CF!H8 | I12: =CF!I8 | J12: =CF!J8 | K12: =CF!K8 | M12: =CF!M8 | N12: =CF!N8 | O12: =CF!O8 | P12: =CF!P8
A13: Unlevered free cash flow | H13: =H9+H10+H11+H12 | I13: =I9+I10+I11+I12 | J13: =J9+J10+J11+J12 | K13: =K9+K10+K11+K12 | M13: =M9+M10+M11+M12 | N13: =N9+N10+N11+N12 | O13: =O9+O10+O11+O12 | P13: =P9+P10+P11+P12
A14: Discount period (years from the balance sheet date) | M14: =C20+1 | N14: =C20+2 | O14: =C20+3 | P14: =C20+4
A15: Discount factor | M15: =1/(1+Inputs!$C$23)^M14 | N15: =1/(1+Inputs!$C$23)^N14 | O15: =1/(1+Inputs!$C$23)^O14 | P15: =1/(1+Inputs!$C$23)^P14
A16: PV of unlevered free cash flow | M16: =M13*M15 | N16: =N13*N15 | O16: =O13*O15 | P16: =P13*P15
A18: Revenue, last four reported quarters | C18: =SUM(IS!C6:F6)
A19: EBITDA, last four reported quarters | C19: =SUM(IS!C19:F19)
A20: Rest of the current fiscal year (years) | C20: =(4-Inputs!$C$4)/4
A21: Unlevered free cash flow, rest of the current fiscal year | C21: =SUMPRODUCT((H6:K6>Inputs!$C$4)*H13:K13)
A22: Discount factor, rest of the current fiscal year | C22: =1/(1+Inputs!$C$23)^C20
A23: PV, rest of the current fiscal year | C23: =C21*C22
A24: Terminal value (Gordon growth, end of last forecast year) | C24: =P13*(1+Inputs!$C$24)/(Inputs!$C$23-Inputs!$C$24)
A25: PV of terminal value | C25: =C24*P15
A26: Enterprise value | C26: =C23+SUM(M16:P16)+C25
A27: Less: cash and cash equivalents (latest reported balance sheet) | C27: =BS!G6
A28: Short-term borrowings (latest reported balance sheet) | C28: =BS!G17
A29: Current portion of long-term debt (latest reported balance sheet) | C29: =BS!G18
A30: Long-term debt (latest reported balance sheet) | C30: =BS!G21
A31: Net debt | C31: =C28+C29+C30-C27
A32: Non-controlling interests, incl. redeemable (latest reported balance sheet) | C32: =BS!G26+BS!G24
A33: Equity value | C33: =C26-C31-C32
A34: Shares outstanding | C34: =Inputs!$C$5
A35: Equity value per share ($) | C35: =C33/C34
A36: Enterprise value / EBITDA, last four reported quarters (x) | C36: =C26/C19

Sheet Scratch
