Workbook

Sheet Valuations & Forecasting
A1: Consolidated Statements of Income - USD ($) shares in Millions, $ in Millions | B1: 12 Months Ended | Q1: 3 Months Ended
B2: May 31, 2015 | C2: May 31, 2016 | D2: May 31, 2017 | E2: May 31, 2018 | F2: May 31, 2019 | G2: May 31, 2020 | H2: May 31, 2021 | I2: May 31, 2022 | J2: May 31, 2023 | K2: May 31, 2024 E | L2: May 31, 2024 (Audited) | N2: May 31, 2025 E | O2: May 31, 2026 E | Q2: Aug. 31, 2020 | R2: Nov. 30, 2020 | S2: Feb. 28, 2021 | T2: May. 31, 2021 | V2: Aug. 31, 2021 | W2: Nov. 30, 2021 | X2: Feb. 28, 2022 | Y2: May. 31, 2022 | AA2: Aug. 31, 2022 | AB2: Nov. 30, 2022 | AC2: Feb. 28, 2023 | AD2: May. 31, 2023 | AF2: Aug. 31, 2023 | AG2: Nov. 30, 2023 | AH2: Feb. 29, 2024 | AI2: May. 31, 2024 E | AJ2: May. 31, 2024 | AM2: Aug. 31, 2024 E | AN2: Nov. 30, 2024 E | AO2: Feb. 29, 2025 E | AP2: May. 31, 2025 E
A3: Income Statement [Abstract]
A4: North America
A5: Footwear | E5: 9322 | F5: 10045 | G5: 9329 | H5: 11644 | I5: 12228 | J5: =AA5+AB5+AC5+AD5 -> 14897 | K5: =AF5+AG5+AH5+AI5 -> 14940 | L5: =SUM(AF5:AH5)+AJ5 -> 14537 | M5: =L5/K5-1 -> -0.026974565 | N5: =SUM(AM5:AP5) -> 15550 | O5: 16700 | Q5: 2957 | R5: 2512 | S5: 2382 | T5: 3793 | V5: 3264 | W5: 2852 | X5: 2532 | Y5: 3580 | AA5: 3805 | AB5: 3963 | AC5: 3322 | AD5: 3807 | AF5: 3733 | AG5: 3757 | AH5: 3460 | AI5: 3990 | AJ5: 3587 | AK5: =AJ5/AI5-1 -> -0.10100251 | AM5: 3900 | AN5: 3900 | AO5: 3600 | AP5: 4150
A6: Apparel | E6: 4938 | F6: 5260 | G6: 4639 | H6: 5028 | I6: 5492 | J6: =AA6+AB6+AC6+AD6 -> 5947 | K6: =AF6+AG6+AH6+AI6 -> 5925 | L6: =SUM(AF6:AH6)+AJ6 -> 5953 | M6: =L6/K6-1 -> 0.0047257384 | N6: =SUM(AM6:AP6) -> 6015 | O6: 6200 | Q6: 1125 | R6: 1368 | S6: 1087 | T6: 1448 | V6: 1430 | W6: 1480 | X6: 1207 | Y6: 1375 | AA6: 1494 | AB6: 1685 | AC6: 1419 | AD6: 1349 | AF6: 1479 | AG6: 1668 | AH6: 1408 | AI6: 1370 | AJ6: 1398 | AK6: =AJ6/AI6-1 -> 0.020437956 | AM6: 1500 | AN6: 1700 | AO6: 1420 | AP6: 1395
A7: Equipment | E7: 595 | F7: 597 | G7: 516 | H7: 507 | I7: 633 | J7: =AA7+AB7+AC7+AD7 -> 764 | K7: =AF7+AG7+AH7+AI7 -> 843 | L7: =SUM(AF7:AH7)+AJ7 -> 906 | M7: =L7/K7-1 -> 0.074733096 | N7: =SUM(AM7:AP7) -> 940 | O7: 1030 | Q7: 143 | R7: 126 | S7: 95 | T7: 143 | V7: 185 | W7: 145 | X7: 143 | Y7: 160 | AA7: 211 | AB7: 182 | AC7: 172 | AD7: 199 | AF7: 211 | AG7: 200 | AH7: 202 | AI7: 230 | AJ7: 293 | AK7: =AJ7/AI7-1 -> 0.27391304 | AM7: 220 | AN7: 220 | AO7: 240 | AP7: 260
A8: Total | B8: =B5+B6+B7 -> 0 | C8: =C5+C6+C7 -> 0 | D8: =D5+D6+D7 -> 0 | E8: =E5+E6+E7 -> 14855 | F8: =F5+F6+F7 -> 15902 | G8: =G5+G6+G7 -> 14484 | H8: =H5+H6+H7 -> 17179 | I8: =I5+I6+I7 -> 18353 | ... L8: =L5+L6+L7 -> 21396 | M8: =L8/K8-1 -> -0.014372582 | N8: =SUM(AM8:AP8) -> 22505 | O8: =O5+O6+O7 -> 23930 | Q8: =Q5+Q6+Q7 -> 4225 | R8: =R5+R6+R7 -> 4006 | S8: =S5+S6+S7 -> 3564 | T8: =T5+T6+T7 -> 5384 | V8: =V5+V6+V7 -> 4879 | W8: =W5+W6+W7 -> 4477 | X8: =X5+X6+X7 -> 3882 | Y8: =Y5+Y6+Y7 -> 5115 | AA8: =AA5+AA6+AA7 -> 5510 | AB8: =AB5+AB6+AB7 -> 5830 | AC8: =AC5+AC6+AC7 -> 4913 | AD8: =AD5+AD6+AD7 -> 5355 | AF8: =AF5+AF6+AF7 -> 5423 | AG8: =AG5+AG6+AG7 -> 5625 | AH8: =AH5+AH6+AH7 -> 5070 | AI8: =AI5+AI6+AI7 -> 5590 | AJ8: =AJ5+AJ6+AJ7 -> 5278 | AK8: =AJ8/AI8-1 -> -0.055813953 | AM8: =AM5+AM6+AM7 -> 5620 | AN8: =AN5+AN6+AN7 -> 5820 | AO8: =AO5+AO6+AO7 -> 5260 | AP8: =AP5+AP6+AP7 -> 5805
A9: Europe, Middle East & Africa
A10: Footwear | E10: 5875 | F10: 6293 | G10: 5892 | H10: 6970 | I10: 7388 | J10: =AA10+AB10+AC10+AD10 -> 8260 | K10: =AF10+AG10+AH10+AI10 -> 8606 | L10: =SUM(AF10:AH10)+AJ10 -> 8473 | M10: =L10/K10-1 -> -0.015454334 | N10: =SUM(AM10:AP10) -> 9100 | O10: 9500 | Q10: 1802 | R10: 1731 | S10: 1606 | T10: 1831 | V10: 1983 | W10: 1806 | X10: 1569 | Y10: 2030 | AA10: 2012 | AB10: 2063 | AC10: 2011 | AD10: 2174 | AF10: 2260 | AG10: 2186 | AH10: 1960 | AI10: 2200 | AJ10: 2067 | AK10: =AJ10/AI10-1 -> -0.060454545 | AM10: 2500 | AN10: 2300 | AO10: 2050 | AP10: 2250
A11: Apparel | E11: 2940 | F11: 3087 | G11: 3053 | H11: 3996 | I11: 4527 | J11: =AA11+AB11+AC11+AD11 -> 4566 | K11: =AF11+AG11+AH11+AI11 -> 4266 | L11: =SUM(AF11:AH11)+AJ11 -> 4380 | M11: =L11/K11-1 -> 0.026722925 | N11: =SUM(AM11:AP11) -> 4305 | O11: 4500 | Q11: 971 | R11: 1104 | S11: 898 | T11: 1023 | V11: 1159 | W11: 1202 | X11: 1083 | Y11: 1083 | AA11: 1153 | AB11: 1281 | AC11: 1094 | AD11: 1038 | AF11: 1137 | AG11: 1200 | AH11: 994 | AI11: 935 | AJ11: 1049 | AK11: =AJ11/AI11-1 -> 0.12192513 | AM11: 1140 | AN11: 1220 | AO11: 1000 | AP11: 945
A12: Equipment | E12: 427 | F12: 432 | G12: 402 | H12: 490 | I12: 564 | J12: =AA12+AB12+AC12+AD12 -> 592 | K12: =AF12+AG12+AH12+AI12 -> 753 | L12: =SUM(AF12:AH12)+AJ12 -> 754 | M12: =L12/K12-1 -> 0.0013280212 | N12: =SUM(AM12:AP12) -> 944 | O12: 1050 | Q12: 137 | R12: 123 | S12: 105 | T12: 125 | V12: 165 | W12: 134 | X12: 127 | Y12: 138 | AA12: 168 | AB12: 145 | AC12: 141 | AD12: 138 | AF12: 213 | AG12: 181 | AH12: 184 | AI12: 175 | AJ12: 176 | AK12: =AJ12/AI12-1 -> 0.0057142857 | AM12: 265 | AN12: 224 | AO12: 235 | AP12: 220
A13: Total | B13: =B10+B11+B12 -> 0 | C13: =C10+C11+C12 -> 0 | D13: =D10+D11+D12 -> 0 | E13: =E10+E11+E12 -> 9242 | F13: =F10+F11+F12 -> 9812 | G13: =G10+G11+G12 -> 9347 | H13: =H10+H11+H12 -> 11456 | I13: =I10+I11+I12 -> 12479 | ... L13: =L10+L11+L12 -> 13607 | M13: =L13/K13-1 -> -0.0013211009 | N13: =SUM(AM13:AP13) -> 14349 | O13: =O10+O11+O12 -> 15050 | Q13: =Q10+Q11+Q12 -> 2910 | R13: =R10+R11+R12 -> 2958 | S13: =S10+S11+S12 -> 2609 | T13: 2979 | V13: =V10+V11+V12 -> 3307 | W13: =W10+W11+W12 -> 3142 | X13: =X10+X11+X12 -> 2779 | Y13: =Y10+Y11+Y12 -> 3251 | AA13: =AA10+AA11+AA12 -> 3333 | AB13: =AB10+AB11+AB12 -> 3489 | AC13: =AC10+AC11+AC12 -> 3246 | AD13: =AD10+AD11+AD12 -> 3350 | AF13: =AF10+AF11+AF12 -> 3610 | AG13: =AG10+AG11+AG12 -> 3567 | AH13: =AH10+AH11+AH12 -> 3138 | AI13: =AI10+AI11+AI12 -> 3310 | AJ13: =AJ10+AJ11+AJ12 -> 3292 | AK13: =AJ13/AI13-1 -> -0.0054380665 | AM13: =AM10+AM11+AM12 -> 3905 | AN13: =AN10+AN11+AN12 -> 3744 | AO13: =AO10+AO11+AO12 -> 3285 | AP13: =AP10+AP11+AP12 -> 3415
A14: Greater China
A15: Footwear | E15: 3496 | F15: 4262 | G15: 4635 | H15: 5748 | I15: 5416 | J15: =AA15+AB15+AC15+AD15 -> 5435 | K15: =AF15+AG15+AH15+AI15 -> 5595 | L15: =SUM(AF15:AH15)+AJ15 -> 5552 | M15: =L15/K15-1 -> -0.0076854334 | N15: =SUM(AM15:AP15) -> 5800 | O15: 6000 | Q15: 1251 | R15: 1567 | S15: 1614 | T15: 1316 | V15: 1449 | W15: 1235 | X15: 1554 | Y15: 1178 | AA15: 1233 | AB15: 1370 | AC15: 1496 | AD15: 1336 | AF15: 1287 | AG15: 1361 | AH15: 1547 | AI15: 1400 | AJ15: 1357 | AK15: =AJ15/AI15-1 -> -0.030714286 | AM15: 1350 | AN15: 1370 | AO15: 1600 | AP15: 1480
A16: Apparel | E16: 1508 | F16: 1808 | G16: 1896 | H16: 2347 | I16: 1938 | J16: =AA16+AB16+AC16+AD16 -> 1666 | K16: =AF16+AG16+AH16+AI16 -> 1848 | L16: =SUM(AF16:AH16)+AJ16 -> 1828 | M16: =L16/K16-1 -> -0.010822511 | N16: =SUM(AM16:AP16) -> 2090 | O16: 2300 | Q16: 478 | R16: 681 | S16: 616 | T16: 572 | V16: 476 | W16: 564 | X16: 548 | Y16: 350 | AA16: 374 | AB16: 393 | AC16: 461 | AD16: 438 | AF16: 401 | AG16: 469 | AH16: 498 | AI16: 480 | AJ16: 460 | AK16: =AJ16/AI16-1 -> -0.041666667 | AM16: 430 | AN16: 560 | AO16: 550 | AP16: 550
A17: Equipment | E17: 130 | F17: 138 | G17: 148 | H17: 195 | I17: 193 | J17: =AA17+AB17+AC17+AD17 -> 147 | K17: =AF17+AG17+AH17+AI17 -> 156 | L17: =SUM(AF17:AH17)+AJ17 -> 165 | M17: =L17/K17-1 -> 0.057692308 | N17: =SUM(AM17:AP17) -> 170 | O17: 190 | Q17: 51 | R17: 50 | S17: 49 | T17: 45 | V17: 57 | W17: 45 | X17: 58 | Y17: 33 | AA17: 49 | AB17: 25 | AC17: 37 | AD17: 36 | AF17: 47 | AG17: 33 | AH17: 39 | AI17: 37 | AJ17: 46 | AK17: =AJ17/AI17-1 -> 0.24324324 | AM17: 48 | AN17: 42 | AO17: 41 | AP17: 39
A18: Total | B18: =B15+B16+B17 -> 0 | C18: =C15+C16+C17 -> 0 | D18: =D15+D16+D17 -> 0 | E18: =E15+E16+E17 -> 5134 | F18: =F15+F16+F17 -> 6208 | G18: =G15+G16+G17 -> 6679 | H18: =H15+H16+H17 -> 8290 | I18: =I15+I16+I17 -> 7547 | ... L18: =L15+L16+L17 -> 7545 | M18: =L18/K18-1 -> -0.0071061982 | N18: =SUM(AM18:AP18) -> 8060 | O18: =O15+O16+O17 -> 8490 | Q18: =Q15+Q16+Q17 -> 1780 | R18: =R15+R16+R17 -> 2298 | S18: =S15+S16+S17 -> 2279 | T18: =T15+T16+T17 -> 1933 | V18: =V15+V16+V17 -> 1982 | W18: =W15+W16+W17 -> 1844 | X18: =X15+X16+X17 -> 2160 | Y18: =Y15+Y16+Y17 -> 1561 | AA18: =AA15+AA16+AA17 -> 1656 | AB18: =AB15+AB16+AB17 -> 1788 | AC18: =AC15+AC16+AC17 -> 1994 | AD18: =AD15+AD16+AD17 -> 1810 | AF18: =AF15+AF16+AF17 -> 1735 | AG18: =AG15+AG16+AG17 -> 1863 | AH18: =AH15+AH16+AH17 -> 2084 | AI18: =AI15+AI16+AI17 -> 1917 | AJ18: =AJ15+AJ16+AJ17 -> 1863 | AK18: =AJ18/AI18-1 -> -0.028169014 | AM18: =AM15+AM16+AM17 -> 1828 | AN18: =AN15+AN16+AN17 -> 1972 | AO18: =AO15+AO16+AO17 -> 2191 | AP18: =AP15+AP16+AP17 -> 2069
A19: Asian Pacific & Latin America
A20: Footwear | E20: 3575 | F20: 3622 | G20: 3449 | H20: 3659 | I20: 4111 | J20: =AA20+AB20+AC20+AD20 -> 4543 | K20: =AF20+AG20+AH20+AI20 -> 4939 | L20: =SUM(AF20:AH20)+AJ20 -> 4865 | M20: =L20/K20-1 -> -0.01498279 | N20: =SUM(AM20:AP20) -> 5440 | O20: 5900 | Q20: 758 | R20: 991 | S20: 903 | T20: 1007 | V20: 1022 | W20: 887 | X20: 1005 | Y20: 1197 | AA20: 1064 | AB20: 1108 | AC20: 1141 | AD20: 1230 | AF20: 1141 | AG20: 1303 | AH20: 1195 | AI20: 1300 | AJ20: 1226 | AK20: =AJ20/AI20-1 -> -0.056923077 | AM20: 1230 | AN20: 1560 | AO20: 1260 | AP20: 1390
A21: Apparel | E21: 1347 | F21: 1395 | G21: 1365 | H21: 1494 | I21: 1610 | J21: =AA21+AB21+AC21+AD21 -> 1664 | K21: =AF21+AG21+AH21+AI21 -> 1593 | L21: =SUM(AF21:AH21)+AJ21 -> 1614 | M21: =L21/K21-1 -> 0.013182674 | N21: =SUM(AM21:AP21) -> 1610 | O21: 1730 | Q21: 301 | R21: 432 | S21: 365 | T21: 396 | V21: 385 | W21: 402 | X21: 394 | Y21: 429 | AA21: 413 | AB21: 435 | AC21: 407 | AD21: 409 | AF21: 371 | AG21: 437 | AH21: 390 | AI21: 395 | AJ21: 416 | AK21: =AJ21/AI21-1 -> 0.053164557 | AM21: 370 | AN21: 440 | AO21: 400 | AP21: 400
A22: Equipment | E22: 244 | F22: 237 | G22: 214 | H22: 190 | I22: 234 | J22: =AA22+AB22+AC22+AD22 -> 224 | K22: =AF22+AG22+AH22+AI22 -> 247 | L22: =SUM(AF22:AH22)+AJ22 -> 250 | M22: =L22/K22-1 -> 0.012145749 | N22: =SUM(AM22:AP22) -> 276 | O22: 290 | Q22: 40 | R22: 48 | S22: 47 | T22: 55 | V22: 58 | W22: 58 | X22: 62 | Y22: 56 | AA22: 58 | AB22: 56 | AC22: 53 | AD22: 57 | AF22: 60 | AG22: 65 | AH22: 62 | AI22: 60 | AJ22: 63 | AK22: =AJ22/AI22-1 -> 0.05 | AM22: 62 | AN22: 77 | AO22: 73 | AP22: 64
A23: Total | B23: =B20+B21+B22 -> 0 | C23: =C20+C21+C22 -> 0 | D23: =D20+D21+D22 -> 0 | E23: =E20+E21+E22 -> 5166 | F23: =F20+F21+F22 -> 5254 | G23: =G20+G21+G22 -> 5028 | H23: =H20+H21+H22 -> 5343 | I23: =I20+I21+I22 -> 5955 | ... L23: =L20+L21+L22 -> 6729 | M23: =L23/K23-1 -> -0.0073757191 | N23: =SUM(AM23:AP23) -> 7326 | O23: =O20+O21+O22 -> 7920 | Q23: =Q20+Q21+Q22 -> 1099 | R23: =R20+R21+R22 -> 1471 | S23: =S20+S21+S22 -> 1315 | T23: =T20+T21+T22 -> 1458 | V23: =V20+V21+V22 -> 1465 | W23: =W20+W21+W22 -> 1347 | X23: =X20+X21+X22 -> 1461 | Y23: =Y20+Y21+Y22 -> 1682 | AA23: =AA20+AA21+AA22 -> 1535 | AB23: =AB20+AB21+AB22 -> 1599 | AC23: =AC20+AC21+AC22 -> 1601 | AD23: =AD20+AD21+AD22 -> 1696 | AF23: =AF20+AF21+AF22 -> 1572 | AG23: =AG20+AG21+AG22 -> 1805 | AH23: =AH20+AH21+AH22 -> 1647 | AI23: =AI20+AI21+AI22 -> 1755 | AJ23: =AJ20+AJ21+AJ22 -> 1705 | AK23: =AJ23/AI23-1 -> -0.028490028 | AM23: =AM20+AM21+AM22 -> 1662 | AN23: =AN20+AN21+AN22 -> 2077 | AO23: =AO20+AO21+AO22 -> 1733 | AP23: =AP20+AP21+AP22 -> 1854
A24: Global Brand Division2 | E24: 88 | F24: 42 | G24: 30 | H24: 25 | I24: 102 | J24: =AA24+AB24+AC24+AD24 -> 58 | K24: =AF24+AG24+AH24+AI24 -> 45 | L24: =SUM(AF24:AH24)+AJ24 -> 45 | M24: =L24/K24-1 -> 0 | N24: =SUM(AM24:AP24) -> 56 | O24: 60 | Q24: 4 | R24: 8 | S24: 6 | T24: 7 | V24: 7 | W24: 6 | X24: 41 | Y24: 48 | AA24: 14 | AB24: 18 | AC24: 12 | AD24: 14 | AF24: 13 | AG24: 12 | AH24: 9 | AI24: 11 | AJ24: 11 | AK24: =AJ24/AI24-1 -> 0 | AM24: 14 | AN24: 15 | AO24: 11 | AP24: 16
A25: Total Nike Brand | B25: =B24+B23+B18+B13+B8 -> 0 | C25: =C24+C23+C18+C13+C8 -> 0 | D25: =D24+D23+D18+D13+D8 -> 0 | E25: =E24+E23+E18+E13+E8 -> 34485 | F25: =F24+F23+F18+F13+F8 -> 37218 | G25: =G24+G23+G18+G13+G8 -> 35568 | H25: =H24+H23+H18+H13+H8 -> 42293 | I25: =I24+I23+I18+I13+I8 -> 44436 | ... L25: =L24+L23+L18+L13+L8 -> 49322 | M25: =L25/K25-1 -> -0.0087225661 | N25: =SUM(AM25:AP25) -> 52296 | O25: =O24+O23+O18+O13+O8 -> 55450 | Q25: =Q24+Q23+Q18+Q13+Q8 -> 10018 | R25: =R24+R23+R18+R13+R8 -> 10741 | S25: =S24+S23+S18+S13+S8 -> 9773 | T25: =T24+T23+T18+T13+T8 -> 11761 | V25: =V24+V23+V18+V13+V8 -> 11640 | W25: =W24+W23+W18+W13+W8 -> 10816 | X25: =X24+X23+X18+X13+X8 -> 10323 | Y25: =Y24+Y23+Y18+Y13+Y8 -> 11657 | AA25: =AA24+AA23+AA18+AA13+AA8 -> 12048 | AB25: =AB24+AB23+AB18+AB13+AB8 -> 12724 | AC25: =AC24+AC23+AC18+AC13+AC8 -> 11766 | AD25: =AD24+AD23+AD18+AD13+AD8 -> 12225 | AF25: =AF24+AF23+AF18+AF13+AF8 -> 12353 | AG25: =AG24+AG23+AG18+AG13+AG8 -> 12872 | AH25: =AH24+AH23+AH18+AH13+AH8 -> 11948 | AI25: =AI24+AI23+AI18+AI13+AI8 -> 12583 | AJ25: =AJ24+AJ23+AJ18+AJ13+AJ8 -> 12149 | AK25: =AJ25/AI25-1 -> -0.03449098 | AM25: =AM24+AM23+AM18+AM13+AM8 -> 13029 | AN25: =AN24+AN23+AN18+AN13+AN8 -> 13628 | AO25: =AO24+AO23+AO18+AO13+AO8 -> 12480 | AP25: =AP24+AP23+AP18+AP13+AP8 -> 13159
A26: Converse | E26: 1886 | F26: 1906 | G26: 1846 | H26: 2205 | I26: 2346 | J26: =AA26+AB26+AC26+AD26 -> 2427 | K26: =AF26+AG26+AH26+AI26 -> 2102 | L26: =SUM(AF26:AH26)+AJ26 -> 2082 | M26: =L26/K26-1 -> -0.0095147479 | N26: =SUM(AM26:AP26) -> 2135 | O26: 2300 | Q26: 563 | R26: 476 | S26: 570 | T26: 596 | V26: 629 | W26: 557 | X26: 567 | Y26: 593 | AA26: 643 | AB26: 586 | AC26: 612 | AD26: 586 | AF26: 588 | AG26: 519 | AH26: 495 | AI26: 500 | AJ26: 480 | AK26: =AJ26/AI26-1 -> -0.04 | AM26: 590 | AN26: 525 | AO26: 510 | AP26: 510
A27: Corporate3 | E27: 26 | F27: -7 | G27: -11 | H27: 40 | I27: -72 | J27: =AA27+AB27+AC27+AD27 -> 27 | K27: =AF27+AG27+AH27+AI27 -> -29 | L27: =SUM(AF27:AH27)+AJ27 -> -42 | M27: =L27/K27-1 -> 0.44827586 | N27: =SUM(AM27:AP27) -> -2 | O27: 20 | Q27: 13 | R27: 26 | S27: 14 | T27: -13 | V27: -21 | W27: -16 | X27: -19 | Y27: -16 | AA27: -4 | AB27: 5 | AC27: 12 | AD27: 14 | AF27: -2 | AG27: -3 | AH27: -14 | AI27: -10 | AJ27: -23 | AK27: =AJ27/AI27-1 -> 1.3 | AM27: 1 | AN27: 2 | AO27: -2 | AP27: -3
A28: Total Nike Brand:
A29: Footwear | E29: =E5+E10+E15+E20 -> 22268 | F29: =F5+F10+F15+F20 -> 24222 | G29: =G5+G10+G15+G20 -> 23305 | H29: =H5+H10+H15+H20 -> 28021 | I29: =I5+I10+I15+I20 -> 29143 | J29: =J5+J10+J15+J20 -> 33135 | K29: =K5+K10+K15+K20 -> 34080 | L29: =SUM(AF29:AH29)+AJ29 -> 33427 | M29: =L29/K29-1 -> -0.019160798 | N29: =N5+N10+N15+N20 -> 35890 | O29: =O5+O10+O15+O20 -> 38100 | Q29: =Q5+Q10+Q15+Q20 -> 6768 | R29: =R5+R10+R15+R20 -> 6801 | S29: =S5+S10+S15+S20 -> 6505 | T29: =T5+T10+T15+T20 -> 7947 | V29: =V5+V10+V15+V20 -> 7718 | W29: =W5+W10+W15+W20 -> 6780 | X29: =X5+X10+X15+X20 -> 6660 | Y29: =Y5+Y10+Y15+Y20 -> 7985 | AA29: =AA5+AA10+AA15+AA20 -> 8114 | AB29: =AB5+AB10+AB15+AB20 -> 8504 | AC29: =AC5+AC10+AC15+AC20 -> 7970 | AD29: =AD5+AD10+AD15+AD20 -> 8547 | AF29: =AF5+AF10+AF15+AF20 -> 8421 | AG29: =AG5+AG10+AG15+AG20 -> 8607 | AH29: =AH5+AH10+AH15+AH20 -> 8162 | AI29: =AI5+AI10+AI15+AI20 -> 8890 | AJ29: =AJ5+AJ10+AJ15+AJ20 -> 8237 | AK29: =AJ29/AI29-1 -> -0.073453318 | AM29: =AM5+AM10+AM15+AM20 -> 8980 | AN29: =AN5+AN10+AN15+AN20 -> 9130 | AO29: =AO5+AO10+AO15+AO20 -> 8510 | AP29: =AP5+AP10+AP15+AP20 -> 9270
A30: Apparel | E30: =E6+E11+E16+E21 -> 10733 | F30: =F6+F11+F16+F21 -> 11550 | G30: =G6+G11+G16+G21 -> 10953 | H30: =H6+H11+H16+H21 -> 12865 | I30: =I6+I11+I16+I21 -> 13567 | J30: =J6+J11+J16+J21 -> 13843 | K30: =K6+K11+K16+K21 -> 13632 | L30: =SUM(AF30:AH30)+AJ30 -> 13775 | M30: =L30/K30-1 -> 0.010490023 | N30: =N6+N11+N16+N21 -> 14020 | O30: =O6+O11+O16+O21 -> 14730 | Q30: =Q6+Q11+Q16+Q21 -> 2875 | R30: =R6+R11+R16+R21 -> 3585 | S30: =S6+S11+S16+S21 -> 2966 | T30: =T6+T11+T16+T21 -> 3439 | V30: =V6+V11+V16+V21 -> 3450 | W30: =W6+W11+W16+W21 -> 3648 | X30: =X6+X11+X16+X21 -> 3232 | Y30: =Y6+Y11+Y16+Y21 -> 3237 | AA30: =AA6+AA11+AA16+AA21 -> 3434 | AB30: =AB6+AB11+AB16+AB21 -> 3794 | AC30: =AC6+AC11+AC16+AC21 -> 3381 | AD30: =AD6+AD11+AD16+AD21 -> 3234 | AF30: =AF6+AF11+AF16+AF21 -> 3388 | AG30: =AG6+AG11+AG16+AG21 -> 3774 | AH30: =AH6+AH11+AH16+AH21 -> 3290 | AI30: =AI6+AI11+AI16+AI21 -> 3180 | AJ30: =AJ6+AJ11+AJ16+AJ21 -> 3323 | AK30: =AJ30/AI30-1 -> 0.044968553 | AM30: =AM6+AM11+AM16+AM21 -> 3440 | AN30: =AN6+AN11+AN16+AN21 -> 3920 | AO30: =AO6+AO11+AO16+AO21 -> 3370 | AP30: =AP6+AP11+AP16+AP21 -> 3290
A31: Equipment | E31: =E7+E12+E17+E22 -> 1396 | F31: =F7+F12+F17+F22 -> 1404 | G31: =G7+G12+G17+G22 -> 1280 | H31: =H7+H12+H17+H22 -> 1382 | I31: =I7+I12+I17+I22 -> 1624 | J31: =J7+J12+J17+J22 -> 1727 | K31: =K7+K12+K17+K22 -> 1999 | L31: =SUM(AF31:AH31)+AJ31 -> 2075 | M31: =L31/K31-1 -> 0.03801901 | N31: =N7+N12+N17+N22 -> 2330 | O31: =O7+O12+O17+O22 -> 2560 | Q31: =Q7+Q12+Q17+Q22 -> 371 | R31: =R7+R12+R17+R22 -> 347 | S31: =S7+S12+S17+S22 -> 296 | T31: =T7+T12+T17+T22 -> 368 | V31: =V7+V12+V17+V22 -> 465 | W31: =W7+W12+W17+W22 -> 382 | X31: =X7+X12+X17+X22 -> 390 | Y31: =Y7+Y12+Y17+Y22 -> 387 | AA31: =AA7+AA12+AA17+AA22 -> 486 | AB31: =AB7+AB12+AB17+AB22 -> 408 | AC31: =AC7+AC12+AC17+AC22 -> 403 | AD31: =AD7+AD12+AD17+AD22 -> 430 | AF31: =AF7+AF12+AF17+AF22 -> 531 | AG31: =AG7+AG12+AG17+AG22 -> 479 | AH31: =AH7+AH12+AH17+AH22 -> 487 | AI31: =AI7+AI12+AI17+AI22 -> 502 | AJ31: =AJ7+AJ12+AJ17+AJ22 -> 578 | AK31: =AJ31/AI31-1 -> 0.15139442 | AM31: =AM7+AM12+AM17+AM22 -> 595 | AN31: =AN7+AN12+AN17+AN22 -> 563 | AO31: =AO7+AO12+AO17+AO22 -> 589 | AP31: =AP7+AP12+AP17+AP22 -> 583
A32: Revenues | B32: 30601 | C32: 32376 | D32: 34350 | E32: 36397 | F32: 39117 | G32: 37403 | H32: =H27+H26+H25 -> 44538 | I32: =I27+I26+I25 -> 46710 | J32: =J27+J26+J25 -> 51217 | K32: =K27+K26+K25 -> 51829 | L32: =SUM(AF32:AH32)+AJ32 -> 51362 | M32: =L32/K32-1 -> -0.0090103996 | N32: =SUM(AM32:AP32) -> 54429 | O32: =O27+O26+O25 -> 57770 | Q32: 10594 | R32: 11243 | S32: 10357 | T32: 12344 | V32: 12248 | W32: 11357 | X32: 10871 | Y32: =Y27+Y26+Y25 -> 12234 | AA32: =AA27+AA26+AA25 -> 12687 | AB32: =AB27+AB26+AB25 -> 13315 | AC32: =AC27+AC26+AC25 -> 12390 | AD32: =AD27+AD26+AD25 -> 12825 | AF32: =AF27+AF26+AF25 -> 12939 | AG32: =AG27+AG26+AG25 -> 13388 | AH32: =AH27+AH26+AH25 -> 12429 | AI32: =AI27+AI26+AI25 -> 13073 | AJ32: 12606 | AK32: =AJ32/AI32-1 -> -0.035722481 | AM32: =AM27+AM26+AM25 -> 13620 | AN32: =AN27+AN26+AN25 -> 14155 | AO32: =AO27+AO26+AO25 -> 12988 | AP32: =AP27+AP26+AP25 -> 13666
A33: Cost of sales | B33: 16534 | C33: 17405 | D33: 19038 | E33: 20441 | F33: 21643 | G33: 21162 | H33: 24576 | I33: 25231 | J33: 28925 | K33: =AF33+AG33+AH33+AI33 -> 28803 | L33: =SUM(AF33:AH33)+AJ33 -> 28475 | M33: =L33/K33-1 -> -0.011387703 | N33: =SUM(AM33:AP33) -> 29450 | O33: 31500 | Q33: 5853 | R33: 6396 | S33: 5638 | T33: 6689 | V33: 6552 | W33: 6144 | X33: 5804 | Y33: 6731 | AA33: 7072 | AB33: 7604 | AC33: 7019 | AD33: 7230 | AF33: 7219 | AG33: 7417 | AH33: 6867 | AI33: 7300 | AJ33: 6972 | AK33: =AJ33/AI33-1 -> -0.044931507 | AM33: 7350 | AN33: 7500 | AO33: 7100 | AP33: 7500
A34: Gross profit | B34: 14067 | C34: 14971 | D34: 15312 | E34: 15956 | F34: 17474 | G34: =G32-G33 -> 16241 | H34: =H32-H33 -> 19962 | I34: =I32-I33 -> 21479 | J34: =J32-J33 -> 22292 | K34: =K32-K33 -> 23026 | L34: =L32-L33 -> 22887 | M34: =L34/K34-1 -> -0.0060366542 | N34: =SUM(AM34:AP34) -> 24979 | O34: =O32-O33 -> 26270 | Q34: 4741 | R34: 4847 | S34: 4719 | T34: 5655 | V34: 5696 | W34: 5213 | X34: 5067 | Y34: =Y32-Y33 -> 5503 | AA34: =AA32-AA33 -> 5615 | AB34: =AB32-AB33 -> 5711 | AC34: =AC32-AC33 -> 5371 | AD34: =AD32-AD33 -> 5595 | AF34: =AF32-AF33 -> 5720 | AG34: =AG32-AG33 -> 5971 | AH34: =AH32-AH33 -> 5562 | AI34: =AI32-AI33 -> 5773 | AJ34: =AJ32-AJ33 -> 5634 | AK34: =AJ34/AI34-1 -> -0.024077603 | AM34: =AM32-AM33 -> 6270 | AN34: =AN32-AN33 -> 6655 | AO34: =AO32-AO33 -> 5888 | AP34: =AP32-AP33 -> 6166
A35: Demand creation expense | B35: 3213 | C35: 3278 | D35: 3341 | E35: 3577 | F35: 3753 | G35: 3592 | H35: 3114 | I35: 3850 | J35: =AA35+AB35+AC35+AD35 -> 4060 | K35: =AF35+AG35+AH35+AI35 -> 4344 | L35: =SUM(AF35:AH35)+AJ35 -> 4285 | M35: =L35/K35-1 -> -0.013581952 | N35: =SUM(AM35:AP35) -> 4720 | O35: 5100 | Q35: 677 | R35: 729 | S35: 711 | T35: 997 | V35: 918 | W35: 1017 | X35: 854 | Y35: 1061 | AA35: 943 | AB35: 1102 | AC35: 923 | AD35: 1092 | AF35: 1069 | AG35: 1114 | AH35: 1011 | AI35: 1150 | AJ35: 1091 | AK35: =AJ35/AI35-1 -> -0.051304348 | AM35: 1200 | AN35: 1200 | AO35: 1100 | AP35: 1220
A36: Operating overhead expense | B36: 6679 | C36: 7191 | D36: 7222 | E36: 7934 | F36: 8949 | G36: 9534 | H36: 9911 | I36: 10954 | J36: =AA36+AB36+AC36+AD36 -> 12317 | K36: =AF36+AG36+AH36+AI36 -> 12724 | L36: =SUM(AF36:AH36)+AJ36 -> 12291 | M36: =L36/K36-1 -> -0.034030179 | N36: =SUM(AM36:AP36) -> 13200 | O36: 13700 | Q36: 2298 | R36: 2538 | S36: 2330 | T36: 2745 | V36: 2654 | W36: 2742 | X36: 2584 | Y36: 2974 | AA36: 2977 | AB36: 3022 | AC36: 3036 | AD36: 3282 | AF36: 3047 | AG36: 3032 | AH36: 3215 | AI36: 3430 | AJ36: 2997 | AK36: =AJ36/AI36-1 -> -0.12623907 | AM36: 3100 | AN36: 3100 | AO36: 3400 | AP36: 3600
A37: Total selling and administrative expense | B37: 9892 | C37: 10469 | D37: 10563 | E37: 11511 | F37: 12702 | G37: 13126 | H37: 13025 | I37: 14804 | J37: =AA37+AB37+AC37+AD37 -> 16377 | K37: =AF37+AG37+AH37+AI37 -> 16788 | L37: =SUM(AF37:AH37)+AJ37 -> 16576 | M37: =L37/K37-1 -> -0.012628068 | N37: =SUM(AM37:AP37) -> 17250 | O37: 17700 | Q37: 2975 | R37: 3267 | S37: 3041 | T37: 3742 | V37: 3572 | W37: 3759 | X37: 3438 | Y37: 4035 | AA37: 3920 | AB37: 4124 | AC37: 3959 | AD37: 4374 | AF37: 4116 | AG37: 4146 | AH37: 4226 | AI37: 4300 | AJ37: 4088 | AK37: =AJ37/AI37-1 -> -0.049302326 | AM37: 4300 | AN37: 4200 | AO37: 4350 | AP37: 4400
A38: Total Operating Expenses | B38: =B35+B36+B37 -> 19784 | C38: =C35+C36+C37 -> 20938 | D38: =D35+D36+D37 -> 21126 | E38: =E35+E36+E37 -> 23022 | F38: =F35+F36+F37 -> 25404 | G38: =G35+G36+G37 -> 26252 | H38: =H35+H36+H37 -> 26050 | I38: =I35+I36+I37 -> 29608 | ... L38: =L35+L36+L37 -> 33152 | M38: =L38/K38-1 -> -0.020793951 | N38: =N35+N36+N37 -> 35170 | O38: =O35+O36+O37 -> 36500 | Q38: =Q35+Q36+Q37 -> 5950 | R38: =R35+R36+R37 -> 6534 | S38: =S35+S36+S37 -> 6082 | T38: =T35+T36+T37 -> 7484 | V38: =V35+V36+V37 -> 7144 | W38: =W35+W36+W37 -> 7518 | X38: =X35+X36+X37 -> 6876 | Y38: =Y35+Y36+Y37 -> 8070 | AA38: =AA35+AA36+AA37 -> 7840 | AB38: =AB35+AB36+AB37 -> 8248 | AC38: =AC35+AC36+AC37 -> 7918 | AD38: =AD35+AD36+AD37 -> 8748 | AF38: =AF35+AF36+AF37 -> 8232 | AG38: =AG35+AG36+AG37 -> 8292 | AH38: =AH35+AH36+AH37 -> 8452 | AI38: =AI35+AI36+AI37 -> 8880 | AJ38: =AJ35+AJ36+AJ37 -> 8176 | AK38: =AJ38/AI38-1 -> -0.079279279 | AM38: =AM35+AM36+AM37 -> 8600 | AN38: =AN35+AN36+AN37 -> 8500 | AO38: =AO35+AO36+AO37 -> 8850 | AP38: =AP35+AP36+AP37 -> 9220
A39: Operating Income | B39: =B34-B37 -> 4175 | C39: =C34-C37 -> 4502 | D39: =D34-D37 -> 4749 | E39: =E34-E37 -> 4445 | F39: =F34-F37 -> 4772 | G39: =G34-G37 -> 3115 | H39: =H34-H37 -> 6937 | I39: =I34-I37 -> 6675 | ... L39: =L34-L37 -> 6311 | M39: =L39/K39-1 -> 0.011702469 | N39: =N34-N37 -> 7729 | O39: =O34-O37 -> 8570 | Q39: 1766 | R39: 1580 | S39: 1678 | T39: 1913 | V39: 2124 | W39: 1454 | X39: 1629 | Y39: =Y34-Y37 -> 1468 | AA39: =AA34-AA37 -> 1695 | AB39: =AB34-AB37 -> 1587 | AC39: =AC34-AC37 -> 1412 | AD39: =AD34-AD37 -> 1221 | AF39: =AF34-AF37 -> 1604 | AG39: =AG34-AG37 -> 1825 | AH39: =AH34-AH37 -> 1336 | AI39: =AI34-AI37 -> 1473 | AJ39: =AJ34-AJ37 -> 1546 | AK39: =AJ39/AI39-1 -> 0.049558724 | AM39: =AM34-AM37 -> 1970 | AN39: =AN34-AN37 -> 2455 | AO39: =AO34-AO37 -> 1538 | AP39: =AP34-AP37 -> 1766
A40: Interest expense (income), net | B40: 28 | C40: 19 | D40: 59 | E40: 54 | F40: 49 | G40: 89 | H40: 262 | I40: 205 | J40: =AA40+AB40+AC40+AD40 -> -6 | K40: =AF40+AG40+AH40+AI40 -> -158 | L40: =SUM(AF40:AH40)+AJ40 -> -161 | M40: =L40/K40-1 -> 0.018987342 | N40: =SUM(AM40:AP40) -> -143 | O40: -120 | Q40: 65 | R40: 70 | S40: 64 | T40: 63 | V40: 57 | W40: 55 | X40: 53 | Y40: 40 | AA40: 13 | AB40: 16 | AC40: -7 | AD40: -28 | AF40: -34 | AG40: -22 | AH40: -52 | AI40: -50 | AJ40: -53 | AK40: =AJ40/AI40-1 -> 0.06 | AM40: -30 | AN40: -20 | AO40: -48 | AP40: -45
A41: Other (income) expense, net | B41: -58 | C41: -140 | D41: -196 | E41: 66 | F41: -78 | G41: 139 | H41: 14 | I41: -181 | J41: =AA41+AB41+AC41+AD41 -> -280 | K41: =AF41+AG41+AH41+AI41 -> -100.9 | L41: =SUM(AF41:AH41)+AJ41 -> -228 | M41: =L41/K41-1 -> 1.259663 | N41: =SUM(AM41:AP41) -> -175 | O41: -200 | Q41: -14 | R41: 54 | S41: -22 | T41: -4 | V41: -39 | W41: -102 | X41: -94 | Y41: 54 | AA41: -146 | AB41: -79 | AC41: -58 | AD41: 3 | AF41: -10 | AG41: -75 | AH41: -16 | AI41: 0.1 | AJ41: -127 | AK41: =AJ41/AI41-1 -> -1271 | AM41: -20 | AN41: -90 | AO41: -80 | AP41: 15
A42: EBIT | B42: 4205 | C42: 4623 | D42: 4886 | E42: 4325 | F42: 4801 | G42: 2887 | H42: 6661 | I42: =I39-I40-I41 -> 6651 | J42: =J39-J40-J41 -> 6201 | K42: =K39-K40-K41 -> 6496.9 | L42: =SUM(AF42:AH42)+AJ42 -> 6700 | M42: =L42/K42-1 -> 0.031261063 | N42: =N39-N40-N41 -> 8047 | O42: =O39-O40-O41 -> 8890 | Q42: 1715 | R42: 1456 | S42: 1636 | T42: 1854 | V42: 2106 | W42: 1501 | X42: 1670 | Y42: 1374 | AA42: 1828 | AB42: 1650 | AC42: 1477 | AD42: 1246 | AF42: =AF39-AF40-AF41 -> 1648 | AG42: =AG39-AG40-AG41 -> 1922 | AH42: =AH39-AH40-AH41 -> 1404 | AI42: =AI39-AI40-AI41 -> 1522.9 | AJ42: 1726 | AK42: =AJ42/AI42-1 -> 0.13336398 | AM42: =AM39-AM40-AM41 -> 2020 | AN42: =AN39-AN40-AN41 -> 2565 | AO42: =AO39-AO40-AO41 -> 1666 | AP42: =AP39-AP40-AP41 -> 1796
A43: Income tax expense | B43: 932 | C43: 863 | D43: 646 | E43: 2392 | F43: 772 | G43: 348 | H43: 934 | I43: 605 | J43: =AA43+AB43+AC43+AD43 -> 1131 | K43: =AF43+AG43+AH43+AI43 -> 1021 | L43: =SUM(AF43:AH43)+AJ43 -> 1000 | M43: =L43/K43-1 -> -0.020568071 | N43: =SUM(AM43:AP43) -> 1155.7783 | O43: =O42*O44 -> 1511.3 | Q43: 197 | R43: 205 | S43: 187 | T43: 345 | V43: 232 | W43: 164 | X43: 274 | Y43: -65 | AA43: 360 | AB43: 319 | AC43: 237 | AD43: 215 | AF43: 198 | AG43: 344 | AH43: 232 | AI43: 247 | AJ43: 226 | AK43: =AJ43/AI43-1 -> -0.085020243 | AM43: =AM42*AM44 -> 342.72199 | AN43: =AN42*AN44 -> 422.45714 | AO43: =AO42*AO44 -> 186.97164 | AP43: =AP42*AP44 -> 203.62755
A44: Effective Tax Rate | E44: =E43/E42 -> 0.55306358 | F44: =F43/F42 -> 0.16079983 | G44: =G43/G42 -> 0.12054035 | H44: =H43/H42 -> 0.14021919 | I44: =I43/I42 -> 0.090963765 | J44: =J43/J42 -> 0.18238994 | K44: =K43/K42 -> 0.15715187 | L44: =L43/L42 -> 0.14925373 | M44: =L44/K44-1 -> -0.050258015 | N44: =N43/N42 -> 0.14362847 | O44: 0.17 | Q44: =Q43/Q42 -> 0.1148688 | R44: =R43/R42 -> 0.1407967 | S44: =S43/S42 -> 0.11430318 | T44: =T43/T42 -> 0.18608414 | V44: =V43/V42 -> 0.11016144 | W44: =W43/W42 -> 0.10926049 | X44: =X43/X42 -> 0.16407186 | Y44: =Y43/Y42 -> -0.047307132 | AA44: =AA43/AA42 -> 0.19693654 | AB44: =AB43/AB42 -> 0.19333333 | AC44: =AC43/AC42 -> 0.16046039 | AD44: =AD43/AD42 -> 0.17255217 | AF44: =AF43/AF42 -> 0.12014563 | AG44: =AG43/AG42 -> 0.17898023 | AH44: =AH43/AH42 -> 0.16524217 | AI44: =AI43/AI42 -> 0.16219056 | AJ44: =AJ43/AJ42 -> 0.13093859 | AK44: =AJ44/AI44-1 -> -0.19268675 | AM44: =AVERAGE(AA44:AH44) -> 0.16966435 | AN44: =AVERAGE(AB44:AI44) -> 0.16470064 | AO44: =AVERAGE(AC44:AL44) -> 0.11222787 | AP44: =AVERAGE(AD44:AM44) -> 0.11337837
A45: NET INCOME | B45: 3273 | C45: 3760 | D45: 4240 | E45: 1933 | F45: 4029 | G45: 2539 | H45: 5727 | I45: 6046 | J45: =J42-J43 -> 5070 | K45: =K42-K43 -> 5475.9 | L45: =L42-L43 -> 5700 | M45: =L45/K45-1 -> 0.040924779 | N45: =N42-N43 -> 6891.2217 | O45: =O42-O43 -> 7378.7 | Q45: 1518 | R45: 1251 | S45: 1449 | T45: 1509 | V45: 1874 | W45: 1337 | X45: 1396 | Y45: 1439 | AA45: =AA42-AA43 -> 1468 | AB45: =AB42-AB43 -> 1331 | AC45: =AC42-AC43 -> 1240 | AD45: =AD42-AD43 -> 1031 | AF45: =AF42-AF43 -> 1450 | AG45: =AG42-AG43 -> 1578 | AH45: =AH42-AH43 -> 1172 | AI45: =AI42-AI43 -> 1275.9 | AJ45: =AJ42-AJ43 -> 1500 | AK45: =AJ45/AI45-1 -> 0.17564072 | AM45: =AM42-AM43 -> 1677.278 | AN45: =AN42-AN43 -> 2142.5429 | AO45: =AO42-AO43 -> 1479.0284 | AP45: =AP42-AP43 -> 1592.3725
A46: Earnings per common share:
A47: Basic (in dollars per share) | B47: 1.9 | C47: 2.21 | D47: 2.56 | E47: 1.19 | F47: 2.55 | G47: 1.63 | H47: =H45/H50 -> 3.6408137 | I47: =I45/I50 -> 3.8294908 | J47: =J45/J50 -> 3.2675947 | K47: =K45/K50 -> 3.6011443 | L47: =L45/L50 -> 3.7559304 | M47: =L47/K47-1 -> 0.042982485 | N47: =N45/N50 -> 4.4893952 | O47: =O45/O50 -> 4.7913636 | Q47: 0.97 | R47: 0.8 | S47: 0.92 | T47: 0.96 | V47: 1.18 | W47: 0.84 | X47: 0.88 | Y47: =Y45/Y50 -> 0.9153944 | AA47: 0.94 | AB47: 0.85 | AC47: 0.8 | AD47: =AD45/AD50 -> 0.67100553 | AF47: 0.95 | AG47: 1.04 | AH47: =AH45/AH50 -> 0.77451758 | AI47: =AI45/AI50 -> 0.83940789 | AJ47: =AJ45/AJ50 -> 0.99469496 | AK47: =AJ47/AI47-1 -> 0.18499596 | AM47: =AM45/AM50 -> 1.0891416 | AN47: =AN45/AN50 -> 1.4003548 | AO47: =AO45/AO50 -> 0.97304498 | AP47: =AP45/AP50 -> 1.0273371
A48: Diluted (in dollars per share) | B48: 1.85 | C48: 2.16 | D48: 2.51 | E48: 1.17 | F48: 2.49 | G48: 1.6 | H48: =H45/H51 -> 3.558469 | I48: =I45/I51 -> 3.7534145 | J48: =J45/J51 -> 3.2296594 | K48: =K45/K51 -> 3.566258 | L48: =L45/L51 -> 3.7262208 | M48: =L48/K48-1 -> 0.044854531 | N48: =N45/N51 -> 4.4531319 | O48: =O45/O51 -> 4.7604516 | Q48: 0.95 | R48: 0.78 | S48: 0.9 | T48: 0.93 | V48: 1.16 | W48: 0.83 | X48: 0.87 | Y48: =Y45/Y51 -> 0.90219436 | AA48: 0.93 | AB48: 0.85 | AC48: 0.79 | AD48: =AD45/AD51 -> 0.66246868 | AF48: 0.94 | AG48: 1.03 | AH48: =AH45/AH51 -> 0.76776941 | AI48: =AI45/AI51 -> 0.82850649 | AJ48: =AJ45/AJ51 -> 0.98898925 | AK48: =AJ48/AI48-1 -> 0.19370127 | AM48: =AM45/AM51 -> 1.0821148 | AN48: =AN45/AN51 -> 1.3822857 | AO48: =AO45/AO51 -> 0.96040803 | AP48: =AP45/AP51 -> 1.0273371
A49: Weighted average common shares outstanding:
A50: Basic (in shares) | B50: =B45/B47 -> 1722.6316 | C50: =C45/C47 -> 1701.3575 | D50: =D45/D47 -> 1656.25 | E50: 1623.8 | F50: 1579.7 | G50: 1558.8 | H50: 1573 | I50: 1578.8 | J50: =AVERAGE(AA50:AD50) -> 1551.6 | K50: =AVERAGE(AF50:AI50) -> 1520.6 | L50: 1517.6 | M50: =L50/K50-1 -> -0.0019729054 | N50: =AVERAGE(AM50:AP50) -> 1535 | O50: 1540 | Q50: 1561.8 | R50: 1573 | S50: 1578 | T50: 1579 | V50: 1581.9 | W50: 1582.4 | X50: 1579 | Y50: 1572 | AA50: 1567.1 | AB50: 1559 | AC50: 1543.8 | AD50: 1536.5 | AF50: 1528.4 | AG50: 1520.8 | AH50: 1513.2 | AI50: 1520 | AJ50: 1508 | AK50: =AJ50/AI50-1 -> -0.0078947368 | AM50: 1540 | AN50: 1530 | AO50: 1520 | AP50: 1550
A51: Diluted (in shares) | B51: =B45/B48 -> 1769.1892 | C51: =C45/C48 -> 1740.7407 | D51: =D45/D48 -> 1689.243 | E51: 1659.1 | F51: 1618.4 | G51: 1591.6 | H51: 1609.4 | I51: 1610.8 | J51: =AVERAGE(AA51:AD51) -> 1569.825 | K51: =AVERAGE(AF51:AI51) -> 1535.475 | L51: 1529.7 | M51: =L51/K51-1 -> -0.0037610511 | N51: =AVERAGE(AM51:AP51) -> 1547.5 | O51: 1550 | Q51: 1593.3 | R51: 1609.5 | S51: 1616.9 | T51: 1614.9 | V51: 1619.6 | W51: 1617.4 | X51: 1610.7 | Y51: 1595 | AA51: 1585.8 | AB51: 1572.4 | AC51: 1564.8 | AD51: 1556.3 | AF51: 1543.3 | AG51: 1532.1 | AH51: 1526.5 | AI51: 1540 | AJ51: 1516.7 | AK51: =AJ51/AI51-1 -> -0.01512987 | AM51: 1550 | AN51: 1550 | AO51: 1540 | AP51: 1550
A53: Growth Rates
A54: North America | B54: North America | C54: North America | D54: North America
A55: Footwear | B55: Footwear | C55: Footwear | D55: Footwear | E55: =(E5-D5)/ABS(D5) -> #DIV/0! | F55: =(F5-E5)/ABS(E5) -> 0.077558464 | G55: =(G5-F5)/ABS(F5) -> -0.071279243 | H55: =(H5-G5)/ABS(G5) -> 0.24815093 | I55: =(I5-H5)/ABS(H5) -> 0.050154586 | J55: =(J5-I5)/ABS(I5) -> 0.21826955 | K55: =(K5-J5)/ABS(J5) -> 0.0028864872 | L55: =(L5-J5)/ABS(J5) -> -0.024165939 | M55: =L55/K55-1 -> -9.372093 | N55: =(N5-K5)/ABS(K5) -> 0.040829987 | O55: =(O5-N5)/ABS(N5) -> 0.073954984 | V55: =(V5-Q5)/ABS(Q5) -> 0.10382144 | W55: =(W5-R5)/ABS(R5) -> 0.13535032 | X55: =(X5-S5)/ABS(S5) -> 0.062972292 | Y55: =(Y5-T5)/ABS(T5) -> -0.056156077 | AA55: =(AA5-V5)/ABS(V5) -> 0.16574755 | AB55: =(AB5-W5)/ABS(W5) -> 0.38955119 | AC55: =(AC5-X5)/ABS(X5) -> 0.31200632 | AD55: =(AD5-Y5)/ABS(Y5) -> 0.063407821 | AF55: =(AF5-AA5)/ABS(AA5) -> -0.01892247 | AG55: =(AG5-AB5)/ABS(AB5) -> -0.051980823 | AH55: =(AH5-AC5)/ABS(AC5) -> 0.04154124 | AI55: =(AI5-AD5)/ABS(AD5) -> 0.048069346 | AJ55: =(AJ5-AD5)/ABS(AD5) -> -0.057788285 | AK55: =AJ55/AI55-1 -> -2.2021858 | AM55: =(AM5-AF5)/ABS(AF5) -> 0.044736137 | AN55: =(AN5-AG5)/ABS(AG5) -> 0.038062284 | AO55: =(AO5-AH5)/ABS(AH5) -> 0.040462428 | AP55: =(AP5-AI5)/ABS(AI5) -> 0.040100251
A56: Apparel | B56: Apparel | C56: Apparel | D56: Apparel | E56: =(E6-D6)/ABS(D6) -> #DIV/0! | F56: =(F6-E6)/ABS(E6) -> 0.065208586 | G56: =(G6-F6)/ABS(F6) -> -0.11806084 | H56: =(H6-G6)/ABS(G6) -> 0.083854279 | I56: =(I6-H6)/ABS(H6) -> 0.092283214 | J56: =(J6-I6)/ABS(I6) -> 0.082847779 | K56: =(K6-J6)/ABS(J6) -> -0.0036993442 | L56: =(L6-J6)/ABS(J6) -> 0.0010089121 | M56: =L56/K56-1 -> -1.2727273 | N56: =(N6-K6)/ABS(K6) -> 0.015189873 | O56: =(O6-N6)/ABS(N6) -> 0.030756442 | V56: =(V6-Q6)/ABS(Q6) -> 0.27111111 | W56: =(W6-R6)/ABS(R6) -> 0.081871345 | X56: =(X6-S6)/ABS(S6) -> 0.11039558 | Y56: =(Y6-T6)/ABS(T6) -> -0.050414365 | AA56: =(AA6-V6)/ABS(V6) -> 0.044755245 | AB56: =(AB6-W6)/ABS(W6) -> 0.13851351 | AC56: =(AC6-X6)/ABS(X6) -> 0.17564209 | AD56: =(AD6-Y6)/ABS(Y6) -> -0.018909091 | AF56: =(AF6-AA6)/ABS(AA6) -> -0.010040161 | AG56: =(AG6-AB6)/ABS(AB6) -> -0.010089021 | AH56: =(AH6-AC6)/ABS(AC6) -> -0.007751938 | AI56: =(AI6-AD6)/ABS(AD6) -> 0.015567087 | AJ56: =(AJ6-AD6)/ABS(AD6) -> 0.036323202 | AK56: =AJ56/AI56-1 -> 1.3333333 | AM56: =(AM6-AF6)/ABS(AF6) -> 0.014198783 | AN56: =(AN6-AG6)/ABS(AG6) -> 0.019184652 | AO56: =(AO6-AH6)/ABS(AH6) -> 0.0085227273 | AP56: =(AP6-AI6)/ABS(AI6) -> 0.018248175
A57: Equipment | B57: Equipment | C57: Equipment | D57: Equipment | E57: =(E7-D7)/ABS(D7) -> #DIV/0! | F57: =(F7-E7)/ABS(E7) -> 0.0033613445 | G57: =(G7-F7)/ABS(F7) -> -0.13567839 | H57: =(H7-G7)/ABS(G7) -> -0.01744186 | I57: =(I7-H7)/ABS(H7) -> 0.24852071 | J57: =(J7-I7)/ABS(I7) -> 0.20695103 | K57: =(K7-J7)/ABS(J7) -> 0.10340314 | L57: =(L7-J7)/ABS(J7) -> 0.18586387 | M57: =L57/K57-1 -> 0.79746835 | N57: =(N7-K7)/ABS(K7) -> 0.11506524 | O57: =(O7-N7)/ABS(N7) -> 0.095744681 | V57: =(V7-Q7)/ABS(Q7) -> 0.29370629 | W57: =(W7-R7)/ABS(R7) -> 0.15079365 | X57: =(X7-S7)/ABS(S7) -> 0.50526316 | Y57: =(Y7-T7)/ABS(T7) -> 0.11888112 | AA57: =(AA7-V7)/ABS(V7) -> 0.14054054 | AB57: =(AB7-W7)/ABS(W7) -> 0.25517241 | AC57: =(AC7-X7)/ABS(X7) -> 0.2027972 | AD57: =(AD7-Y7)/ABS(Y7) -> 0.24375 | AF57: =(AF7-AA7)/ABS(AA7) -> 0 | AG57: =(AG7-AB7)/ABS(AB7) -> 0.098901099 | AH57: =(AH7-AC7)/ABS(AC7) -> 0.1744186 | AI57: =(AI7-AD7)/ABS(AD7) -> 0.15577889 | AJ57: =(AJ7-AD7)/ABS(AD7) -> 0.47236181 | AK57: =AJ57/AI57-1 -> 2.0322581 | AM57: =(AM7-AF7)/ABS(AF7) -> 0.042654028 | AN57: =(AN7-AG7)/ABS(AG7) -> 0.1 | AO57: =(AO7-AH7)/ABS(AH7) -> 0.18811881 | AP57: =(AP7-AI7)/ABS(AI7) -> 0.13043478
A58: Total | B58: Total | C58: Total | D58: Total | E58: =(E8-D8)/ABS(D8) -> #DIV/0! | F58: =(F8-E8)/ABS(E8) -> 0.070481319 | G58: =(G8-F8)/ABS(F8) -> -0.089171173 | H58: =(H8-G8)/ABS(G8) -> 0.18606738 | I58: =(I8-H8)/ABS(H8) -> 0.068339251 | J58: =(J8-I8)/ABS(I8) -> 0.1773552 | K58: =(K8-J8)/ABS(J8) -> 0.0046279156 | L58: =(L8-J8)/ABS(J8) -> -0.009811181 | M58: =L58/K58-1 -> -3.12 | N58: =(N8-K8)/ABS(K8) -> 0.036714575 | O58: =(O8-N8)/ABS(N8) -> 0.063319262 | V58: =(V8-Q8)/ABS(Q8) -> 0.1547929 | W58: =(W8-R8)/ABS(R8) -> 0.11757364 | X58: =(X8-S8)/ABS(S8) -> 0.089225589 | Y58: =(Y8-T8)/ABS(T8) -> -0.049962853 | AA58: =(AA8-V8)/ABS(V8) -> 0.12932978 | AB58: =(AB8-W8)/ABS(W8) -> 0.3022113 | AC58: =(AC8-X8)/ABS(X8) -> 0.26558475 | AD58: =(AD8-Y8)/ABS(Y8) -> 0.046920821 | AF58: =(AF8-AA8)/ABS(AA8) -> -0.015789474 | AG58: =(AG8-AB8)/ABS(AB8) -> -0.03516295 | AH58: =(AH8-AC8)/ABS(AC8) -> 0.031956035 | AI58: =(AI8-AD8)/ABS(AD8) -> 0.04388422 | AJ58: =(AJ8-AD8)/ABS(AD8) -> -0.014379085 | AK58: =AJ58/AI58-1 -> -1.3276596 | AM58: =(AM8-AF8)/ABS(AF8) -> 0.036326756 | AN58: =(AN8-AG8)/ABS(AG8) -> 0.034666667 | AO58: =(AO8-AH8)/ABS(AH8) -> 0.037475345 | AP58: =(AP8-AI8)/ABS(AI8) -> 0.038461538
A59: Europe, Middle East & Africa | B59: Europe, Middle East & Africa | C59: Europe, Middle East & Africa | D59: Europe, Middle East & Africa
A60: Footwear | B60: Footwear | C60: Footwear | D60: Footwear | E60: =(E10-D10)/ABS(D10) -> #DIV/0! | F60: =(F10-E10)/ABS(E10) -> 0.071148936 | G60: =(G10-F10)/ABS(F10) -> -0.063721595 | H60: =(H10-G10)/ABS(G10) -> 0.18295995 | I60: =(I10-H10)/ABS(H10) -> 0.059971306 | J60: =(J10-I10)/ABS(I10) -> 0.11802924 | K60: =(K10-J10)/ABS(J10) -> 0.04188862 | L60: =(L10-J10)/ABS(J10) -> 0.025786925 | M60: =L60/K60-1 -> -0.38439306 | N60: =(N10-K10)/ABS(K10) -> 0.057401813 | O60: =(O10-N10)/ABS(N10) -> 0.043956044 | V60: =(V10-Q10)/ABS(Q10) -> 0.10044395 | W60: =(W10-R10)/ABS(R10) -> 0.043327556 | X60: =(X10-S10)/ABS(S10) -> -0.023038605 | Y60: =(Y10-T10)/ABS(T10) -> 0.10868378 | AA60: =(AA10-V10)/ABS(V10) -> 0.014624307 | AB60: =(AB10-W10)/ABS(W10) -> 0.14230343 | AC60: =(AC10-X10)/ABS(X10) -> 0.28170809 | AD60: =(AD10-Y10)/ABS(Y10) -> 0.070935961 | AF60: =(AF10-AA10)/ABS(AA10) -> 0.12326044 | AG60: =(AG10-AB10)/ABS(AB10) -> 0.05962191 | AH60: =(AH10-AC10)/ABS(AC10) -> -0.025360517 | AI60: =(AI10-AD10)/ABS(AD10) -> 0.011959522 | AJ60: =(AJ10-AD10)/ABS(AD10) -> -0.049218031 | AK60: =AJ60/AI60-1 -> -5.1153846 | AM60: =(AM10-AF10)/ABS(AF10) -> 0.10619469 | AN60: =(AN10-AG10)/ABS(AG10) -> 0.052150046 | AO60: =(AO10-AH10)/ABS(AH10) -> 0.045918367 | AP60: =(AP10-AI10)/ABS(AI10) -> 0.022727273
A61: Apparel | B61: Apparel | C61: Apparel | D61: Apparel | E61: =(E11-D11)/ABS(D11) -> #DIV/0! | F61: =(F11-E11)/ABS(E11) -> 0.05 | G61: =(G11-F11)/ABS(F11) -> -0.011013929 | H61: =(H11-G11)/ABS(G11) -> 0.30887651 | I61: =(I11-H11)/ABS(H11) -> 0.13288288 | J61: =(J11-I11)/ABS(I11) -> 0.0086149768 | K61: =(K11-J11)/ABS(J11) -> -0.065703022 | L61: =(L11-J11)/ABS(J11) -> -0.040735874 | M61: =L61/K61-1 -> -0.38 | N61: =(N11-K11)/ABS(K11) -> 0.0091420534 | O61: =(O11-N11)/ABS(N11) -> 0.045296167 | V61: =(V11-Q11)/ABS(Q11) -> 0.19361483 | W61: =(W11-R11)/ABS(R11) -> 0.088768116 | X61: =(X11-S11)/ABS(S11) -> 0.20601336 | Y61: =(Y11-T11)/ABS(T11) -> 0.058651026 | AA61: =(AA11-V11)/ABS(V11) -> -0.0051768766 | AB61: =(AB11-W11)/ABS(W11) -> 0.065723794 | AC61: =(AC11-X11)/ABS(X11) -> 0.010156971 | AD61: =(AD11-Y11)/ABS(Y11) -> -0.041551247 | AF61: =(AF11-AA11)/ABS(AA11) -> -0.013876843 | AG61: =(AG11-AB11)/ABS(AB11) -> -0.06323185 | AH61: =(AH11-AC11)/ABS(AC11) -> -0.091407678 | AI61: =(AI11-AD11)/ABS(AD11) -> -0.099229287 | AJ61: =(AJ11-AD11)/ABS(AD11) -> 0.010597303 | AK61: =AJ61/AI61-1 -> -1.1067961 | AM61: =(AM11-AF11)/ABS(AF11) -> 0.0026385224 | AN61: =(AN11-AG11)/ABS(AG11) -> 0.016666667 | AO61: =(AO11-AH11)/ABS(AH11) -> 0.0060362173 | AP61: =(AP11-AI11)/ABS(AI11) -> 0.010695187
A62: Equipment | B62: Equipment | C62: Equipment | D62: Equipment | E62: =(E12-D12)/ABS(D12) -> #DIV/0! | F62: =(F12-E12)/ABS(E12) -> 0.011709602 | G62: =(G12-F12)/ABS(F12) -> -0.069444444 | H62: =(H12-G12)/ABS(G12) -> 0.21890547 | I62: =(I12-H12)/ABS(H12) -> 0.15102041 | J62: =(J12-I12)/ABS(I12) -> 0.04964539 | K62: =(K12-J12)/ABS(J12) -> 0.27195946 | L62: =(L12-J12)/ABS(J12) -> 0.27364865 | M62: =L62/K62-1 -> 0.0062111801 | N62: =(N12-K12)/ABS(K12) -> 0.25365206 | O62: =(O12-N12)/ABS(N12) -> 0.11228814 | V62: =(V12-Q12)/ABS(Q12) -> 0.20437956 | W62: =(W12-R12)/ABS(R12) -> 0.089430894 | X62: =(X12-S12)/ABS(S12) -> 0.20952381 | Y62: =(Y12-T12)/ABS(T12) -> 0.104 | AA62: =(AA12-V12)/ABS(V12) -> 0.018181818 | AB62: =(AB12-W12)/ABS(W12) -> 0.082089552 | AC62: =(AC12-X12)/ABS(X12) -> 0.11023622 | AD62: =(AD12-Y12)/ABS(Y12) -> 0 | AF62: =(AF12-AA12)/ABS(AA12) -> 0.26785714 | AG62: =(AG12-AB12)/ABS(AB12) -> 0.24827586 | AH62: =(AH12-AC12)/ABS(AC12) -> 0.30496454 | AI62: =(AI12-AD12)/ABS(AD12) -> 0.26811594 | AJ62: =(AJ12-AD12)/ABS(AD12) -> 0.27536232 | AK62: =AJ62/AI62-1 -> 0.027027027 | AM62: =(AM12-AF12)/ABS(AF12) -> 0.24413146 | AN62: =(AN12-AG12)/ABS(AG12) -> 0.23756906 | AO62: =(AO12-AH12)/ABS(AH12) -> 0.27717391 | AP62: =(AP12-AI12)/ABS(AI12) -> 0.25714286
A63: Total | B63: Total | C63: Total | D63: Total | E63: =(E13-D13)/ABS(D13) -> #DIV/0! | F63: =(F13-E13)/ABS(E13) -> 0.061674962 | G63: =(G13-F13)/ABS(F13) -> -0.04739095 | H63: =(H13-G13)/ABS(G13) -> 0.22563389 | I63: =(I13-H13)/ABS(H13) -> 0.089298184 | J63: =(J13-I13)/ABS(I13) -> 0.075246414 | K63: =(K13-J13)/ABS(J13) -> 0.015427038 | L63: =(L13-J13)/ABS(J13) -> 0.014085557 | M63: =L63/K63-1 -> -0.086956522 | N63: =(N13-K13)/ABS(K13) -> 0.053137615 | O63: =(O13-N13)/ABS(N13) -> 0.048853579 | V63: =(V13-Q13)/ABS(Q13) -> 0.13642612 | W63: =(W13-R13)/ABS(R13) -> 0.062204192 | X63: =(X13-S13)/ABS(S13) -> 0.065159065 | Y63: =(Y13-T13)/ABS(T13) -> 0.091305807 | AA63: =(AA13-V13)/ABS(V13) -> 0.0078621107 | AB63: =(AB13-W13)/ABS(W13) -> 0.11043921 | AC63: =(AC13-X13)/ABS(X13) -> 0.16804606 | AD63: =(AD13-Y13)/ABS(Y13) -> 0.030452169 | AF63: =(AF13-AA13)/ABS(AA13) -> 0.083108311 | AG63: =(AG13-AB13)/ABS(AB13) -> 0.022355976 | AH63: =(AH13-AC13)/ABS(AC13) -> -0.033271719 | AI63: =(AI13-AD13)/ABS(AD13) -> -0.011940299 | AJ63: =(AJ13-AD13)/ABS(AD13) -> -0.017313433 | AK63: =AJ63/AI63-1 -> 0.45 | AM63: =(AM13-AF13)/ABS(AF13) -> 0.081717452 | AN63: =(AN13-AG13)/ABS(AG13) -> 0.049621531 | AO63: =(AO13-AH13)/ABS(AH13) -> 0.046845124 | AP63: =(AP13-AI13)/ABS(AI13) -> 0.031722054
A64: Greater China | B64: Greater China | C64: Greater China | D64: Greater China | AM64: =(AM14-AF14)/ABS(AF14) -> #DIV/0! | AN64: =(AN14-AG14)/ABS(AG14) -> #DIV/0! | AO64: =(AO14-AH14)/ABS(AH14) -> #DIV/0! | AP64: =(AP14-AI14)/ABS(AI14) -> #DIV/0!
A65: Footwear | B65: Footwear | C65: Footwear | D65: Footwear | E65: =(E15-D15)/ABS(D15) -> #DIV/0! | F65: =(F15-E15)/ABS(E15) -> 0.21910755 | G65: =(G15-F15)/ABS(F15) -> 0.087517597 | H65: =(H15-G15)/ABS(G15) -> 0.24012945 | I65: =(I15-H15)/ABS(H15) -> -0.057759221 | J65: =(J15-I15)/ABS(I15) -> 0.0035081241 | K65: =(K15-J15)/ABS(J15) -> 0.029438822 | L65: =(L15-J15)/ABS(J15) -> 0.021527139 | M65: =L65/K65-1 -> -0.26875 | N65: =(N15-K15)/ABS(K15) -> 0.036639857 | O65: =(O15-N15)/ABS(N15) -> 0.034482759 | V65: =(V15-Q15)/ABS(Q15) -> 0.15827338 | W65: =(W15-R15)/ABS(R15) -> -0.21186981 | X65: =(X15-S15)/ABS(S15) -> -0.037174721 | Y65: =(Y15-T15)/ABS(T15) -> -0.10486322 | AA65: =(AA15-V15)/ABS(V15) -> -0.14906832 | AB65: =(AB15-W15)/ABS(W15) -> 0.10931174 | AC65: =(AC15-X15)/ABS(X15) -> -0.037323037 | AD65: =(AD15-Y15)/ABS(Y15) -> 0.13412564 | AF65: =(AF15-AA15)/ABS(AA15) -> 0.04379562 | AG65: =(AG15-AB15)/ABS(AB15) -> -0.0065693431 | AH65: =(AH15-AC15)/ABS(AC15) -> 0.034090909 | AI65: =(AI15-AD15)/ABS(AD15) -> 0.047904192 | AJ65: =(AJ15-AD15)/ABS(AD15) -> 0.015718563 | AK65: =AJ65/AI65-1 -> -0.671875 | AM65: =(AM15-AF15)/ABS(AF15) -> 0.048951049 | AN65: =(AN15-AG15)/ABS(AG15) -> 0.0066127847 | AO65: =(AO15-AH15)/ABS(AH15) -> 0.034259858 | AP65: =(AP15-AI15)/ABS(AI15) -> 0.057142857
A66: Apparel | B66: Apparel | C66: Apparel | D66: Apparel | E66: =(E16-D16)/ABS(D16) -> #DIV/0! | F66: =(F16-E16)/ABS(E16) -> 0.19893899 | G66: =(G16-F16)/ABS(F16) -> 0.048672566 | H66: =(H16-G16)/ABS(G16) -> 0.2378692 | I66: =(I16-H16)/ABS(H16) -> -0.17426502 | J66: =(J16-I16)/ABS(I16) -> -0.14035088 | K66: =(K16-J16)/ABS(J16) -> 0.1092437 | L66: =(L16-J16)/ABS(J16) -> 0.097238896 | M66: =L66/K66-1 -> -0.10989011 | N66: =(N16-K16)/ABS(K16) -> 0.13095238 | O66: =(O16-N16)/ABS(N16) -> 0.10047847 | V66: =(V16-Q16)/ABS(Q16) -> -0.0041841004 | W66: =(W16-R16)/ABS(R16) -> -0.17180617 | X66: =(X16-S16)/ABS(S16) -> -0.11038961 | Y66: =(Y16-T16)/ABS(T16) -> -0.38811189 | AA66: =(AA16-V16)/ABS(V16) -> -0.21428571 | AB66: =(AB16-W16)/ABS(W16) -> -0.30319149 | AC66: =(AC16-X16)/ABS(X16) -> -0.15875912 | AD66: =(AD16-Y16)/ABS(Y16) -> 0.25142857 | AF66: =(AF16-AA16)/ABS(AA16) -> 0.072192513 | AG66: =(AG16-AB16)/ABS(AB16) -> 0.19338422 | AH66: =(AH16-AC16)/ABS(AC16) -> 0.080260304 | AI66: =(AI16-AD16)/ABS(AD16) -> 0.095890411 | AJ66: =(AJ16-AD16)/ABS(AD16) -> 0.050228311 | AK66: =AJ66/AI66-1 -> -0.47619048 | AM66: =(AM16-AF16)/ABS(AF16) -> 0.072319202 | AN66: =(AN16-AG16)/ABS(AG16) -> 0.19402985 | AO66: =(AO16-AH16)/ABS(AH16) -> 0.10441767 | AP66: =(AP16-AI16)/ABS(AI16) -> 0.14583333
A67: Equipment | B67: Equipment | C67: Equipment | D67: Equipment | E67: =(E17-D17)/ABS(D17) -> #DIV/0! | F67: =(F17-E17)/ABS(E17) -> 0.061538462 | G67: =(G17-F17)/ABS(F17) -> 0.072463768 | H67: =(H17-G17)/ABS(G17) -> 0.31756757 | I67: =(I17-H17)/ABS(H17) -> -0.01025641 | J67: =(J17-I17)/ABS(I17) -> -0.23834197 | K67: =(K17-J17)/ABS(J17) -> 0.06122449 | L67: =(L17-J17)/ABS(J17) -> 0.12244898 | M67: =L67/K67-1 -> 1 | N67: =(N17-K17)/ABS(K17) -> 0.08974359 | O67: =(O17-N17)/ABS(N17) -> 0.11764706 | V67: =(V17-Q17)/ABS(Q17) -> 0.11764706 | W67: =(W17-R17)/ABS(R17) -> -0.1 | X67: =(X17-S17)/ABS(S17) -> 0.18367347 | Y67: =(Y17-T17)/ABS(T17) -> -0.26666667 | AA67: =(AA17-V17)/ABS(V17) -> -0.14035088 | AB67: =(AB17-W17)/ABS(W17) -> -0.44444444 | AC67: =(AC17-X17)/ABS(X17) -> -0.36206897 | AD67: =(AD17-Y17)/ABS(Y17) -> 0.090909091 | AF67: =(AF17-AA17)/ABS(AA17) -> -0.040816327 | AG67: =(AG17-AB17)/ABS(AB17) -> 0.32 | AH67: =(AH17-AC17)/ABS(AC17) -> 0.054054054 | AI67: =(AI17-AD17)/ABS(AD17) -> 0.027777778 | AJ67: =(AJ17-AD17)/ABS(AD17) -> 0.27777778 | AK67: =AJ67/AI67-1 -> 9 | AM67: =(AM17-AF17)/ABS(AF17) -> 0.021276596 | AN67: =(AN17-AG17)/ABS(AG17) -> 0.27272727 | AO67: =(AO17-AH17)/ABS(AH17) -> 0.051282051 | AP67: =(AP17-AI17)/ABS(AI17) -> 0.054054054
A68: Total | B68: Total | C68: Total | D68: Total | E68: =(E18-D18)/ABS(D18) -> #DIV/0! | F68: =(F18-E18)/ABS(E18) -> 0.20919361 | G68: =(G18-F18)/ABS(F18) -> 0.075869845 | H68: =(H18-G18)/ABS(G18) -> 0.24120377 | I68: =(I18-H18)/ABS(H18) -> -0.089626055 | J68: =(J18-I18)/ABS(I18) -> -0.039618391 | K68: =(K18-J18)/ABS(J18) -> 0.048427152 | L68: =(L18-J18)/ABS(J18) -> 0.040976821 | M68: =L68/K68-1 -> -0.15384615 | N68: =(N18-K18)/ABS(K18) -> 0.060665877 | O68: =(O18-N18)/ABS(N18) -> 0.053349876 | V68: =(V18-Q18)/ABS(Q18) -> 0.11348315 | W68: =(W18-R18)/ABS(R18) -> -0.1975631 | X68: =(X18-S18)/ABS(S18) -> -0.052215884 | Y68: =(Y18-T18)/ABS(T18) -> -0.19244697 | AA68: =(AA18-V18)/ABS(V18) -> -0.16448032 | AB68: =(AB18-W18)/ABS(W18) -> -0.030368764 | AC68: =(AC18-X18)/ABS(X18) -> -0.076851852 | AD68: =(AD18-Y18)/ABS(Y18) -> 0.15951313 | AF68: =(AF18-AA18)/ABS(AA18) -> 0.047705314 | AG68: =(AG18-AB18)/ABS(AB18) -> 0.041946309 | AH68: =(AH18-AC18)/ABS(AC18) -> 0.045135406 | AI68: =(AI18-AD18)/ABS(AD18) -> 0.059116022 | AJ68: =(AJ18-AD18)/ABS(AD18) -> 0.029281768 | AK68: =AJ68/AI68-1 -> -0.5046729 | AM68: =(AM18-AF18)/ABS(AF18) -> 0.053602305 | AN68: =(AN18-AG18)/ABS(AG18) -> 0.058507783 | AO68: =(AO18-AH18)/ABS(AH18) -> 0.05134357 | AP68: =(AP18-AI18)/ABS(AI18) -> 0.079290558
A69: Asian Pacific & Latin America | B69: Asian Pacific & Latin America | C69: Asian Pacific & Latin America | D69: Asian Pacific & Latin America | AM69: =(AM19-AF19)/ABS(AF19) -> #DIV/0! | AN69: =(AN19-AG19)/ABS(AG19) -> #DIV/0! | AO69: =(AO19-AH19)/ABS(AH19) -> #DIV/0! | AP69: =(AP19-AI19)/ABS(AI19) -> #DIV/0!
A70: Footwear | B70: Footwear | C70: Footwear | D70: Footwear | E70: =(E20-D20)/ABS(D20) -> #DIV/0! | F70: =(F20-E20)/ABS(E20) -> 0.013146853 | G70: =(G20-F20)/ABS(F20) -> -0.047763666 | H70: =(H20-G20)/ABS(G20) -> 0.060887214 | I70: =(I20-H20)/ABS(H20) -> 0.12353102 | J70: =(J20-I20)/ABS(I20) -> 0.10508392 | K70: =(K20-J20)/ABS(J20) -> 0.08716707 | L70: =(L20-J20)/ABS(J20) -> 0.070878274 | M70: =L70/K70-1 -> -0.18686869 | N70: =(N20-K20)/ABS(K20) -> 0.10143754 | O70: =(O20-N20)/ABS(N20) -> 0.084558824 | V70: =(V20-Q20)/ABS(Q20) -> 0.34828496 | W70: =(W20-R20)/ABS(R20) -> -0.1049445 | X70: =(X20-S20)/ABS(S20) -> 0.11295681 | Y70: =(Y20-T20)/ABS(T20) -> 0.18867925 | AA70: =(AA20-V20)/ABS(V20) -> 0.04109589 | AB70: =(AB20-W20)/ABS(W20) -> 0.24915445 | AC70: =(AC20-X20)/ABS(X20) -> 0.13532338 | AD70: =(AD20-Y20)/ABS(Y20) -> 0.027568922 | AF70: =(AF20-AA20)/ABS(AA20) -> 0.072368421 | AG70: =(AG20-AB20)/ABS(AB20) -> 0.17599278 | AH70: =(AH20-AC20)/ABS(AC20) -> 0.047326906 | AI70: =(AI20-AD20)/ABS(AD20) -> 0.056910569 | AJ70: =(AJ20-AD20)/ABS(AD20) -> -0.0032520325 | AK70: =AJ70/AI70-1 -> -1.0571429 | AM70: =(AM20-AF20)/ABS(AF20) -> 0.078001753 | AN70: =(AN20-AG20)/ABS(AG20) -> 0.19723715 | AO70: =(AO20-AH20)/ABS(AH20) -> 0.054393305 | AP70: =(AP20-AI20)/ABS(AI20) -> 0.069230769
A71: Apparel | B71: Apparel | C71: Apparel | D71: Apparel | E71: =(E21-D21)/ABS(D21) -> #DIV/0! | F71: =(F21-E21)/ABS(E21) -> 0.035634744 | G71: =(G21-F21)/ABS(F21) -> -0.021505376 | H71: =(H21-G21)/ABS(G21) -> 0.094505495 | I71: =(I21-H21)/ABS(H21) -> 0.077643909 | J71: =(J21-I21)/ABS(I21) -> 0.033540373 | K71: =(K21-J21)/ABS(J21) -> -0.042668269 | L71: =(L21-J21)/ABS(J21) -> -0.030048077 | M71: =L71/K71-1 -> -0.29577465 | N71: =(N21-K21)/ABS(K21) -> 0.010671689 | O71: =(O21-N21)/ABS(N21) -> 0.074534161 | V71: =(V21-Q21)/ABS(Q21) -> 0.27906977 | W71: =(W21-R21)/ABS(R21) -> -0.069444444 | X71: =(X21-S21)/ABS(S21) -> 0.079452055 | Y71: =(Y21-T21)/ABS(T21) -> 0.083333333 | AA71: =(AA21-V21)/ABS(V21) -> 0.072727273 | AB71: =(AB21-W21)/ABS(W21) -> 0.082089552 | AC71: =(AC21-X21)/ABS(X21) -> 0.032994924 | AD71: =(AD21-Y21)/ABS(Y21) -> -0.046620047 | AF71: =(AF21-AA21)/ABS(AA21) -> -0.10169492 | AG71: =(AG21-AB21)/ABS(AB21) -> 0.0045977011 | AH71: =(AH21-AC21)/ABS(AC21) -> -0.041769042 | AI71: =(AI21-AD21)/ABS(AD21) -> -0.034229829 | AJ71: =(AJ21-AD21)/ABS(AD21) -> 0.017114914 | AK71: =AJ71/AI71-1 -> -1.5 | AM71: =(AM21-AF21)/ABS(AF21) -> -0.0026954178 | AN71: =(AN21-AG21)/ABS(AG21) -> 0.0068649886 | AO71: =(AO21-AH21)/ABS(AH21) -> 0.025641026 | AP71: =(AP21-AI21)/ABS(AI21) -> 0.012658228
A72: Equipment | B72: Equipment | C72: Equipment | D72: Equipment | E72: =(E22-D22)/ABS(D22) -> #DIV/0! | F72: =(F22-E22)/ABS(E22) -> -0.028688525 | G72: =(G22-F22)/ABS(F22) -> -0.097046414 | H72: =(H22-G22)/ABS(G22) -> -0.11214953 | I72: =(I22-H22)/ABS(H22) -> 0.23157895 | J72: =(J22-I22)/ABS(I22) -> -0.042735043 | K72: =(K22-J22)/ABS(J22) -> 0.10267857 | L72: =(L22-J22)/ABS(J22) -> 0.11607143 | M72: =L72/K72-1 -> 0.13043478 | N72: =(N22-K22)/ABS(K22) -> 0.11740891 | O72: =(O22-N22)/ABS(N22) -> 0.050724638 | V72: =(V22-Q22)/ABS(Q22) -> 0.45 | W72: =(W22-R22)/ABS(R22) -> 0.20833333 | X72: =(X22-S22)/ABS(S22) -> 0.31914894 | Y72: =(Y22-T22)/ABS(T22) -> 0.018181818 | AA72: =(AA22-V22)/ABS(V22) -> 0 | AB72: =(AB22-W22)/ABS(W22) -> -0.034482759 | AC72: =(AC22-X22)/ABS(X22) -> -0.14516129 | AD72: =(AD22-Y22)/ABS(Y22) -> 0.017857143 | AF72: =(AF22-AA22)/ABS(AA22) -> 0.034482759 | AG72: =(AG22-AB22)/ABS(AB22) -> 0.16071429 | AH72: =(AH22-AC22)/ABS(AC22) -> 0.16981132 | AI72: =(AI22-AD22)/ABS(AD22) -> 0.052631579 | AJ72: =(AJ22-AD22)/ABS(AD22) -> 0.10526316 | AK72: =AJ72/AI72-1 -> 1 | AM72: =(AM22-AF22)/ABS(AF22) -> 0.033333333 | AN72: =(AN22-AG22)/ABS(AG22) -> 0.18461538 | AO72: =(AO22-AH22)/ABS(AH22) -> 0.17741935 | AP72: =(AP22-AI22)/ABS(AI22) -> 0.066666667
A73: Total | B73: Total | C73: Total | D73: Total | E73: =(E23-D23)/ABS(D23) -> #DIV/0! | F73: =(F23-E23)/ABS(E23) -> 0.017034456 | G73: =(G23-F23)/ABS(F23) -> -0.043014846 | H73: =(H23-G23)/ABS(G23) -> 0.062649165 | I73: =(I23-H23)/ABS(H23) -> 0.11454239 | J73: =(J23-I23)/ABS(I23) -> 0.07993283 | K73: =(K23-J23)/ABS(J23) -> 0.054112891 | L73: =(L23-J23)/ABS(J23) -> 0.04633805 | M73: =L73/K73-1 -> -0.14367816 | N73: =(N23-K23)/ABS(K23) -> 0.080690367 | O73: =(O23-N23)/ABS(N23) -> 0.081081081 | V73: =(V23-Q23)/ABS(Q23) -> 0.33303003 | W73: =(W23-R23)/ABS(R23) -> -0.084296397 | X73: =(X23-S23)/ABS(S23) -> 0.11102662 | Y73: =(Y23-T23)/ABS(T23) -> 0.15363512 | AA73: =(AA23-V23)/ABS(V23) -> 0.04778157 | AB73: =(AB23-W23)/ABS(W23) -> 0.18708241 | AC73: =(AC23-X23)/ABS(X23) -> 0.095824778 | AD73: =(AD23-Y23)/ABS(Y23) -> 0.0083234245 | AF73: =(AF23-AA23)/ABS(AA23) -> 0.024104235 | AG73: =(AG23-AB23)/ABS(AB23) -> 0.12883052 | AH73: =(AH23-AC23)/ABS(AC23) -> 0.028732042 | AI73: =(AI23-AD23)/ABS(AD23) -> 0.034787736 | AJ73: =(AJ23-AD23)/ABS(AD23) -> 0.0053066038 | AK73: =AJ73/AI73-1 -> -0.84745763 | AM73: =(AM23-AF23)/ABS(AF23) -> 0.057251908 | AN73: =(AN23-AG23)/ABS(AG23) -> 0.15069252 | AO73: =(AO23-AH23)/ABS(AH23) -> 0.052216151 | AP73: =(AP23-AI23)/ABS(AI23) -> 0.056410256
A74: Global Brand Division2 | B74: Global Brand Division2 | C74: Global Brand Division2 | D74: Global Brand Division2 | E74: =(E24-D24)/ABS(D24) -> #DIV/0! | F74: =(F24-E24)/ABS(E24) -> -0.52272727 | G74: =(G24-F24)/ABS(F24) -> -0.28571429 | H74: =(H24-G24)/ABS(G24) -> -0.16666667 | I74: =(I24-H24)/ABS(H24) -> 3.08 | J74: =(J24-I24)/ABS(I24) -> -0.43137255 | K74: =(K24-J24)/ABS(J24) -> -0.22413793 | L74: =(L24-J24)/ABS(J24) -> -0.22413793 | M74: =L74/K74-1 -> 0 | N74: =(N24-K24)/ABS(K24) -> 0.24444444 | O74: =(O24-N24)/ABS(N24) -> 0.071428571 | V74: =(V24-Q24)/ABS(Q24) -> 0.75 | W74: =(W24-R24)/ABS(R24) -> -0.25 | X74: =(X24-S24)/ABS(S24) -> 5.8333333 | Y74: =(Y24-T24)/ABS(T24) -> 5.8571429 | AA74: =(AA24-V24)/ABS(V24) -> 1 | AB74: =(AB24-W24)/ABS(W24) -> 2 | AC74: =(AC24-X24)/ABS(X24) -> -0.70731707 | AD74: =(AD24-Y24)/ABS(Y24) -> -0.70833333 | AF74: =(AF24-AA24)/ABS(AA24) -> -0.071428571 | AG74: =(AG24-AB24)/ABS(AB24) -> -0.33333333 | AH74: =(AH24-AC24)/ABS(AC24) -> -0.25 | AI74: =(AI24-AD24)/ABS(AD24) -> -0.21428571 | AJ74: =(AJ24-AD24)/ABS(AD24) -> -0.21428571 | AK74: =AJ74/AI74-1 -> 0 | AM74: =(AM24-AF24)/ABS(AF24) -> 0.076923077 | AN74: =(AN24-AG24)/ABS(AG24) -> 0.25 | AO74: =(AO24-AH24)/ABS(AH24) -> 0.22222222 | AP74: =(AP24-AI24)/ABS(AI24) -> 0.45454545
A75: Total Nike Brand | B75: Total Nike Brand | C75: Total Nike Brand | D75: Total Nike Brand | E75: =(E25-D25)/ABS(D25) -> #DIV/0! | F75: =(F25-E25)/ABS(E25) -> 0.079251849 | G75: =(G25-F25)/ABS(F25) -> -0.044333387 | H75: =(H25-G25)/ABS(G25) -> 0.18907445 | I75: =(I25-H25)/ABS(H25) -> 0.050670324 | J75: =(J25-I25)/ABS(I25) -> 0.097376001 | K75: =(K25-J25)/ABS(J25) -> 0.0203638 | L75: =(L25-J25)/ABS(J25) -> 0.01146361 | M75: =L75/K75-1 -> -0.43705942 | N75: =(N25-K25)/ABS(K25) -> 0.05104912 | O75: =(O25-N25)/ABS(N25) -> 0.06031054 | V75: =(V25-Q25)/ABS(Q25) -> 0.16190856 | W75: =(W25-R25)/ABS(R25) -> 0.0069825901 | X75: =(X25-S25)/ABS(S25) -> 0.056277499 | Y75: =(Y25-T25)/ABS(T25) -> -0.0088427855 | AA75: =(AA25-V25)/ABS(V25) -> 0.035051546 | AB75: =(AB25-W25)/ABS(W25) -> 0.17640533 | AC75: =(AC25-X25)/ABS(X25) -> 0.13978495 | AD75: =(AD25-Y25)/ABS(Y25) -> 0.048726087 | AF75: =(AF25-AA25)/ABS(AA25) -> 0.025315405 | AG75: =(AG25-AB25)/ABS(AB25) -> 0.011631562 | AH75: =(AH25-AC25)/ABS(AC25) -> 0.015468298 | AI75: =(AI25-AD25)/ABS(AD25) -> 0.029284254 | AJ75: =(AJ25-AD25)/ABS(AD25) -> -0.0062167689 | AK75: =AJ75/AI75-1 -> -1.2122905 | AM75: =(AM25-AF25)/ABS(AF25) -> 0.054723549 | AN75: =(AN25-AG25)/ABS(AG25) -> 0.058732132 | AO75: =(AO25-AH25)/ABS(AH25) -> 0.044526281 | AP75: =(AP25-AI25)/ABS(AI25) -> 0.045776047
A76: Converse | B76: Converse | C76: Converse | D76: Converse | E76: =(E26-D26)/ABS(D26) -> #DIV/0! | F76: =(F26-E26)/ABS(E26) -> 0.010604454 | G76: =(G26-F26)/ABS(F26) -> -0.031479538 | H76: =(H26-G26)/ABS(G26) -> 0.19447454 | I76: =(I26-H26)/ABS(H26) -> 0.063945578 | J76: =(J26-I26)/ABS(I26) -> 0.034526854 | K76: =(K26-J26)/ABS(J26) -> -0.13391018 | L76: =(L26-J26)/ABS(J26) -> -0.1421508 | M76: =L76/K76-1 -> 0.061538462 | N76: =(N26-K26)/ABS(K26) -> 0.015699334 | O76: =(O26-N26)/ABS(N26) -> 0.077283372 | V76: =(V26-Q26)/ABS(Q26) -> 0.11722913 | W76: =(W26-R26)/ABS(R26) -> 0.17016807 | X76: =(X26-S26)/ABS(S26) -> -0.0052631579 | Y76: =(Y26-T26)/ABS(T26) -> -0.005033557 | AA76: =(AA26-V26)/ABS(V26) -> 0.022257552 | AB76: =(AB26-W26)/ABS(W26) -> 0.052064632 | AC76: =(AC26-X26)/ABS(X26) -> 0.079365079 | AD76: =(AD26-Y26)/ABS(Y26) -> -0.011804384 | AF76: =(AF26-AA26)/ABS(AA26) -> -0.085536547 | AG76: =(AG26-AB26)/ABS(AB26) -> -0.11433447 | AH76: =(AH26-AC26)/ABS(AC26) -> -0.19117647 | AI76: =(AI26-AD26)/ABS(AD26) -> -0.14675768 | AJ76: =(AJ26-AD26)/ABS(AD26) -> -0.18088737 | AK76: =AJ76/AI76-1 -> 0.23255814 | AM76: =(AM26-AF26)/ABS(AF26) -> 0.0034013605 | AN76: =(AN26-AG26)/ABS(AG26) -> 0.011560694 | AO76: =(AO26-AH26)/ABS(AH26) -> 0.03030303 | AP76: =(AP26-AI26)/ABS(AI26) -> 0.02
A77: Corporate3 | B77: Corporate3 | C77: Corporate3 | D77: Corporate3 | E77: =(E27-D27)/ABS(D27) -> #DIV/0! | F77: =(F27-E27)/ABS(E27) -> -1.2692308 | G77: =(G27-F27)/ABS(F27) -> -0.57142857 | H77: =(H27-G27)/ABS(G27) -> 4.6363636 | I77: =(I27-H27)/ABS(H27) -> -2.8 | J77: =(J27-I27)/ABS(I27) -> 1.375 | K77: =(K27-J27)/ABS(J27) -> -2.0740741 | L77: =(L27-J27)/ABS(J27) -> -2.5555556 | M77: =L77/K77-1 -> 0.23214286 | N77: =(N27-K27)/ABS(K27) -> 0.93103448 | O77: =(O27-N27)/ABS(N27) -> 11 | V77: =(V27-Q27)/ABS(Q27) -> -2.6153846 | W77: =(W27-R27)/ABS(R27) -> -1.6153846 | X77: =(X27-S27)/ABS(S27) -> -2.3571429 | Y77: =(Y27-T27)/ABS(T27) -> -0.23076923 | AA77: =(AA27-V27)/ABS(V27) -> 0.80952381 | AB77: =(AB27-W27)/ABS(W27) -> 1.3125 | AC77: =(AC27-X27)/ABS(X27) -> 1.6315789 | AD77: =(AD27-Y27)/ABS(Y27) -> 1.875 | AF77: =(AF27-AA27)/ABS(AA27) -> 0.5 | AG77: =(AG27-AB27)/ABS(AB27) -> -1.6 | AH77: =(AH27-AC27)/ABS(AC27) -> -2.1666667 | AI77: =(AI27-AD27)/ABS(AD27) -> -1.7142857 | AJ77: =(AJ27-AD27)/ABS(AD27) -> -2.6428571 | AK77: =AJ77/AI77-1 -> 0.54166667 | AM77: =(AM27-AF27)/ABS(AF27) -> 1.5 | AN77: =(AN27-AG27)/ABS(AG27) -> 1.6666667 | AO77: =(AO27-AH27)/ABS(AH27) -> 0.85714286 | AP77: =(AP27-AI27)/ABS(AI27) -> 0.7
A78: Total Nike Brand
A79: Footwear | E79: =E29/D29-1 -> #DIV/0! | F79: =F29/E29-1 -> 0.087749237 | G79: =G29/F29-1 -> -0.037858145 | H79: =H29/G29-1 -> 0.20236001 | I79: =I29/H29-1 -> 0.040041398 | J79: =J29/I29-1 -> 0.13697972 | K79: =K29/J29-1 -> 0.028519692 | L79: =L29/J29-1 -> 0.008812434 | M79: =L79/K79-1 -> -0.69100529 | N79: =N29/K29-1 -> 0.053110329 | O79: =O29/N29-1 -> 0.061577041 | V79: =V29/Q29-1 -> 0.14036643 | W79: =W29/R29-1 -> -0.0030877812 | X79: =X29/S29-1 -> 0.023827825 | Y79: =Y29/T29-1 -> 0.0047816786 | AA79: =AA29/V29-1 -> 0.051308629 | AB79: =AB29/W29-1 -> 0.25427729 | AC79: =AC29/X29-1 -> 0.1966967 | AD79: =AD29/Y29-1 -> 0.070381966 | AF79: =AF29/AA29-1 -> 0.037835839 | AG79: =AG29/AB29-1 -> 0.012111947 | AH79: =AH29/AC29-1 -> 0.024090339 | AI79: =AI29/AD29-1 -> 0.04013104 | AJ79: =AJ29/AD29-1 -> -0.036270036 | AK79: =AJ79/AI79-1 -> -1.9037901 | AM79: =AM29/AF29-1 -> 0.066381665 | AN79: =AN29/AG29-1 -> 0.060764494 | AO79: =AO29/AH29-1 -> 0.042636609 | AP79: =AP29/AI29-1 -> 0.042744657
A80: Apparel | E80: =E30/D30-1 -> #DIV/0! | F80: =F30/E30-1 -> 0.076120376 | G80: =G30/F30-1 -> -0.051688312 | H80: =H30/G30-1 -> 0.17456405 | I80: =I30/H30-1 -> 0.054566654 | J80: =J30/I30-1 -> 0.020343481 | K80: =K30/J30-1 -> -0.015242361 | L80: =L30/J30-1 -> -0.00491223 | M80: =L80/K80-1 -> -0.67772512 | N80: =N30/K30-1 -> 0.028462441 | O80: =O30/N30-1 -> 0.05064194 | V80: =V30/Q30-1 -> 0.2 | W80: =W30/R30-1 -> 0.017573222 | X80: =X30/S30-1 -> 0.089683075 | Y80: =Y30/T30-1 -> -0.058738005 | AA80: =AA30/V30-1 -> -0.0046376812 | AB80: =AB30/W30-1 -> 0.04002193 | AC80: =AC30/X30-1 -> 0.046101485 | AD80: =AD30/Y30-1 -> -0.00092678406 | AF80: =AF30/AA30-1 -> -0.013395457 | AG80: =AG30/AB30-1 -> -0.0052714813 | AH80: =AH30/AC30-1 -> -0.026915114 | AI80: =AI30/AD30-1 -> -0.016697588 | AJ80: =AJ30/AD30-1 -> 0.027520099 | AK80: =AJ80/AI80-1 -> -2.6481481 | AM80: =AM30/AF30-1 -> 0.015348288 | AN80: =AN30/AG30-1 -> 0.038685745 | AO80: =AO30/AH30-1 -> 0.024316109 | AP80: =AP30/AI30-1 -> 0.034591195
A81: Equipment | E81: =E31/D31-1 -> #DIV/0! | F81: =F31/E31-1 -> 0.005730659 | G81: =G31/F31-1 -> -0.088319088 | H81: =H31/G31-1 -> 0.0796875 | I81: =I31/H31-1 -> 0.17510854 | J81: =J31/I31-1 -> 0.063423645 | K81: =K31/J31-1 -> 0.15749855 | L81: =L31/J31-1 -> 0.2015055 | M81: =L81/K81-1 -> 0.27941176 | N81: =N31/K31-1 -> 0.16558279 | O81: =O31/N31-1 -> 0.098712446 | V81: =V31/Q31-1 -> 0.25336927 | W81: =W31/R31-1 -> 0.10086455 | X81: =X31/S31-1 -> 0.31756757 | Y81: =Y31/T31-1 -> 0.051630435 | AA81: =AA31/V31-1 -> 0.04516129 | AB81: =AB31/W31-1 -> 0.068062827 | AC81: =AC31/X31-1 -> 0.033333333 | AD81: =AD31/Y31-1 -> 0.11111111 | AF81: =AF31/AA31-1 -> 0.092592593 | AG81: =AG31/AB31-1 -> 0.17401961 | AH81: =AH31/AC31-1 -> 0.20843672 | AI81: =AI31/AD31-1 -> 0.16744186 | AJ81: =AJ31/AD31-1 -> 0.34418605 | AK81: =AJ81/AI81-1 -> 1.0555556 | AM81: =AM31/AF31-1 -> 0.12052731 | AN81: =AN31/AG31-1 -> 0.17536534 | AO81: =AO31/AH31-1 -> 0.20944559 | AP81: =AP31/AI31-1 -> 0.16135458
A82: Revenues | C82: =(C32-B32)/ABS(B32) -> 0.05800464 | D82: =(D32-C32)/ABS(C32) -> 0.06097109 | E82: =(E32-D32)/ABS(D32) -> 0.059592431 | F82: =(F32-E32)/ABS(E32) -> 0.074731434 | G82: =(G32-F32)/ABS(F32) -> -0.043817266 | H82: =(H32-G32)/ABS(G32) -> 0.1907601 | I82: =(I32-H32)/ABS(H32) -> 0.048767345 | J82: =(J32-I32)/ABS(I32) -> 0.096488975 | K82: =(K32-J32)/ABS(J32) -> 0.011949158 | L82: =L32/J32-1 -> 0.0028310912 | M82: =L82/K82-1 -> -0.7630719 | N82: =(N32-K32)/ABS(K32) -> 0.050164966 | O82: =(O32-N32)/ABS(N32) -> 0.061382719 | V82: =(V32-Q32)/ABS(Q32) -> 0.15612611 | W82: =(W32-R32)/ABS(R32) -> 0.010139642 | X82: =(X32-S32)/ABS(S32) -> 0.049628271 | Y82: =(Y32-T32)/ABS(T32) -> -0.0089112119 | AA82: =(AA32-V32)/ABS(V32) -> 0.035842587 | AB82: =(AB32-W32)/ABS(W32) -> 0.17240468 | AC82: =(AC32-X32)/ABS(X32) -> 0.13972956 | AD82: =(AD32-Y32)/ABS(Y32) -> 0.048307994 | AF82: =(AF32-AA32)/ABS(AA32) -> 0.019862852 | AG82: =(AG32-AB32)/ABS(AB32) -> 0.0054825385 | AH82: =(AH32-AC32)/ABS(AC32) -> 0.0031476998 | AI82: =(AI32-AD32)/ABS(AD32) -> 0.019337232 | AJ82: =AJ32/AD32-1 -> -0.017076023 | AK82: =AJ82/AI82-1 -> -1.8830645 | AM82: =(AM32-AF32)/ABS(AF32) -> 0.052631579 | AN82: =(AN32-AG32)/ABS(AG32) -> 0.057290111 | AO82: =(AO32-AH32)/ABS(AH32) -> 0.044975461 | AP82: =(AP32-AI32)/ABS(AI32) -> 0.045360667
A83: Cost of sales | C83: =(C33-B33)/ABS(B33) -> 0.052679327 | D83: =(D33-C33)/ABS(C33) -> 0.093823614 | E83: =(E33-D33)/ABS(D33) -> 0.073694716 | F83: =(F33-E33)/ABS(E33) -> 0.058803385 | G83: =(G33-F33)/ABS(F33) -> -0.022224276 | H83: =(H33-G33)/ABS(G33) -> 0.16132691 | I83: =(I33-H33)/ABS(H33) -> 0.026652018 | J83: =(J33-I33)/ABS(I33) -> 0.1464072 | K83: =(K33-J33)/ABS(J33) -> -0.0042178047 | L83: =L33/J33-1 -> -0.015557476 | M83: =L83/K83-1 -> 2.6885246 | N83: =(N33-K33)/ABS(K33) -> 0.022462938 | O83: =(O33-N33)/ABS(N33) -> 0.069609508 | V83: =(V33-Q33)/ABS(Q33) -> 0.11942594 | W83: =(W33-R33)/ABS(R33) -> -0.039399625 | X83: =(X33-S33)/ABS(S33) -> 0.029443065 | Y83: =(Y33-T33)/ABS(T33) -> 0.0062789655 | AA83: =(AA33-V33)/ABS(V33) -> 0.079365079 | AB83: =(AB33-W33)/ABS(W33) -> 0.23763021 | AC83: =(AC33-X33)/ABS(X33) -> 0.20933839 | AD83: =(AD33-Y33)/ABS(Y33) -> 0.074134601 | AF83: =(AF33-AA33)/ABS(AA33) -> 0.020786199 | AG83: =(AG33-AB33)/ABS(AB33) -> -0.02459232 | AH83: =(AH33-AC33)/ABS(AC33) -> -0.021655506 | AI83: =(AI33-AD33)/ABS(AD33) -> 0.0096818811 | AJ83: =AJ33/AD33-1 -> -0.035684647 | AK83: =AJ83/AI83-1 -> -4.6857143 | AM83: =(AM33-AF33)/ABS(AF33) -> 0.018146558 | AN83: =(AN33-AG33)/ABS(AG33) -> 0.011190508 | AO83: =(AO33-AH33)/ABS(AH33) -> 0.033930392 | AP83: =(AP33-AI33)/ABS(AI33) -> 0.02739726
A84: Gross profit | C84: =(C34-B34)/ABS(B34) -> 0.06426388 | D84: =(D34-C34)/ABS(C34) -> 0.02277737 | E84: =(E34-D34)/ABS(D34) -> 0.042058516 | F84: =(F34-E34)/ABS(E34) -> 0.095136626 | G84: =(G34-F34)/ABS(F34) -> -0.070561978 | H84: =(H34-G34)/ABS(G34) -> 0.22911151 | I84: =(I34-H34)/ABS(H34) -> 0.075994389 | J84: =(J34-I34)/ABS(I34) -> 0.037850924 | K84: =(K34-J34)/ABS(J34) -> 0.03292661 | L84: =L34/J34-1 -> 0.02669119 | M84: =L84/K84-1 -> -0.1893733 | N84: =(N34-K34)/ABS(K34) -> 0.084817163 | O84: =(O34-N34)/ABS(N34) -> 0.051683414 | V84: =(V34-Q34)/ABS(Q34) -> 0.2014343 | W84: =(W34-R34)/ABS(R34) -> 0.075510625 | X84: =(X34-S34)/ABS(S34) -> 0.073744437 | Y84: =(Y34-T34)/ABS(T34) -> -0.026878868 | AA84: =(AA34-V34)/ABS(V34) -> -0.014220506 | AB84: =(AB34-W34)/ABS(W34) -> 0.095530405 | AC84: =(AC34-X34)/ABS(X34) -> 0.059996053 | AD84: =(AD34-Y34)/ABS(Y34) -> 0.016718154 | AF84: =(AF34-AA34)/ABS(AA34) -> 0.018699911 | AG84: =(AG34-AB34)/ABS(AB34) -> 0.045526178 | AH84: =(AH34-AC34)/ABS(AC34) -> 0.035561348 | AI84: =(AI34-AD34)/ABS(AD34) -> 0.03181412 | AJ84: =AJ34/AD34-1 -> 0.0069705094 | AK84: =AJ84/AI84-1 -> -0.78089888 | AM84: =(AM34-AF34)/ABS(AF34) -> 0.096153846 | AN84: =(AN34-AG34)/ABS(AG34) -> 0.11455368 | AO84: =(AO34-AH34)/ABS(AH34) -> 0.05861201 | AP84: =(AP34-AI34)/ABS(AI34) -> 0.068075524
A85: Demand creation expense | C85: =(C35-B35)/ABS(B35) -> 0.020230314 | D85: =(D35-C35)/ABS(C35) -> 0.019219036 | E85: =(E35-D35)/ABS(D35) -> 0.070637534 | F85: =(F35-E35)/ABS(E35) -> 0.049203243 | G85: =(G35-F35)/ABS(F35) -> -0.042899014 | H85: =(H35-G35)/ABS(G35) -> -0.1330735 | I85: =(I35-H35)/ABS(H35) -> 0.23635196 | J85: =(J35-I35)/ABS(I35) -> 0.054545455 | K85: =(K35-J35)/ABS(J35) -> 0.069950739 | L85: =L35/J35-1 -> 0.055418719 | M85: =L85/K85-1 -> -0.20774648 | N85: =(N35-K35)/ABS(K35) -> 0.086556169 | O85: =(O35-N35)/ABS(N35) -> 0.080508475 | V85: =(V35-Q35)/ABS(Q35) -> 0.35598227 | W85: =(W35-R35)/ABS(R35) -> 0.39506173 | X85: =(X35-S35)/ABS(S35) -> 0.20112518 | Y85: =(Y35-T35)/ABS(T35) -> 0.064192578 | AA85: =(AA35-V35)/ABS(V35) -> 0.027233115 | AB85: =(AB35-W35)/ABS(W35) -> 0.083579154 | AC85: =(AC35-X35)/ABS(X35) -> 0.080796253 | AD85: =(AD35-Y35)/ABS(Y35) -> 0.029217719 | AF85: =(AF35-AA35)/ABS(AA35) -> 0.13361612 | AG85: =(AG35-AB35)/ABS(AB35) -> 0.010889292 | AH85: =(AH35-AC35)/ABS(AC35) -> 0.095341278 | AI85: =(AI35-AD35)/ABS(AD35) -> 0.053113553 | AJ85: =AJ35/AD35-1 -> -0.00091575092 | AK85: =AJ85/AI85-1 -> -1.0172414 | AM85: =(AM35-AF35)/ABS(AF35) -> 0.12254443 | AN85: =(AN35-AG35)/ABS(AG35) -> 0.077199282 | AO85: =(AO35-AH35)/ABS(AH35) -> 0.088031652 | AP85: =(AP35-AI35)/ABS(AI35) -> 0.060869565
A86: Operating overhead expense | C86: =(C36-B36)/ABS(B36) -> 0.076658182 | D86: =(D36-C36)/ABS(C36) -> 0.0043109442 | E86: =(E36-D36)/ABS(D36) -> 0.098587649 | F86: =(F36-E36)/ABS(E36) -> 0.12793043 | G86: =(G36-F36)/ABS(F36) -> 0.065370432 | H86: =(H36-G36)/ABS(G36) -> 0.039542689 | I86: =(I36-H36)/ABS(H36) -> 0.10523661 | J86: =(J36-I36)/ABS(I36) -> 0.12442943 | K86: =(K36-J36)/ABS(J36) -> 0.033043761 | L86: =L36/J36-1 -> -0.0021109036 | M86: =L86/K86-1 -> -1.0638821 | N86: =(N36-K36)/ABS(K36) -> 0.03740962 | O86: =(O36-N36)/ABS(N36) -> 0.037878788 | V86: =(V36-Q36)/ABS(Q36) -> 0.15491732 | W86: =(W36-R36)/ABS(R36) -> 0.080378251 | X86: =(X36-S36)/ABS(S36) -> 0.10901288 | Y86: =(Y36-T36)/ABS(T36) -> 0.083424408 | AA86: =(AA36-V36)/ABS(V36) -> 0.12170309 | AB86: =(AB36-W36)/ABS(W36) -> 0.10211524 | AC86: =(AC36-X36)/ABS(X36) -> 0.1749226 | AD86: =(AD36-Y36)/ABS(Y36) -> 0.10356422 | AF86: =(AF36-AA36)/ABS(AA36) -> 0.023513604 | AG86: =(AG36-AB36)/ABS(AB36) -> 0.0033090668 | AH86: =(AH36-AC36)/ABS(AC36) -> 0.058959157 | AI86: =(AI36-AD36)/ABS(AD36) -> 0.045094455 | AJ86: =AJ36/AD36-1 -> -0.086837294 | AK86: =AJ86/AI86-1 -> -2.9256757 | AM86: =(AM36-AF36)/ABS(AF36) -> 0.017394158 | AN86: =(AN36-AG36)/ABS(AG36) -> 0.022427441 | AO86: =(AO36-AH36)/ABS(AH36) -> 0.057542768 | AP86: =(AP36-AI36)/ABS(AI36) -> 0.049562682
A87: Total selling and administrative expense | C87: =(C37-B37)/ABS(B37) -> 0.058329964 | D87: =(D37-C37)/ABS(C37) -> 0.0089788901 | E87: =(E37-D37)/ABS(D37) -> 0.089747231 | F87: =(F37-E37)/ABS(E37) -> 0.10346625 | G87: =(G37-F37)/ABS(F37) -> 0.03338057 | H87: =(H37-G37)/ABS(G37) -> -0.0076946518 | I87: =(I37-H37)/ABS(H37) -> 0.13658349 | J87: =(J37-I37)/ABS(I37) -> 0.10625507 | K87: =(K37-J37)/ABS(J37) -> 0.025096171 | L87: =L37/J37-1 -> 0.012151188 | M87: =L87/K87-1 -> -0.51581509 | N87: =(N37-K37)/ABS(K37) -> 0.027519657 | O87: =(O37-N37)/ABS(N37) -> 0.026086957 | V87: =(V37-Q37)/ABS(Q37) -> 0.20067227 | W87: =(W37-R37)/ABS(R37) -> 0.15059688 | X87: =(X37-S37)/ABS(S37) -> 0.13054916 | Y87: =(Y37-T37)/ABS(T37) -> 0.078300374 | AA87: =(AA37-V37)/ABS(V37) -> 0.097424412 | AB87: =(AB37-W37)/ABS(W37) -> 0.097100293 | AC87: =(AC37-X37)/ABS(X37) -> 0.15154159 | AD87: =(AD37-Y37)/ABS(Y37) -> 0.08401487 | AF87: =(AF37-AA37)/ABS(AA37) -> 0.05 | AG87: =(AG37-AB37)/ABS(AB37) -> 0.0053346266 | AH87: =(AH37-AC37)/ABS(AC37) -> 0.067441273 | AI87: =(AI37-AD37)/ABS(AD37) -> -0.016918153 | AJ87: =(AJ37-AD37)/ABS(AD37) -> -0.065386374 | AK87: =AJ87/AI87-1 -> 2.8648649 | AM87: =(AM37-AF37)/ABS(AF37) -> 0.044703596 | AN87: =(AN37-AG37)/ABS(AG37) -> 0.013024602 | AO87: =(AO37-AH37)/ABS(AH37) -> 0.029342168 | AP87: =(AP37-AI37)/ABS(AI37) -> 0.023255814
A88: Total Operating Expenses | E88: =(E38-D38)/ABS(D38) -> 0.089747231 | F88: =(F38-E38)/ABS(E38) -> 0.10346625 | G88: =(G38-F38)/ABS(F38) -> 0.03338057 | H88: =(H38-G38)/ABS(G38) -> -0.0076946518 | I88: =(I38-H38)/ABS(H38) -> 0.13658349 | J88: =(J38-I38)/ABS(I38) -> 0.10625507 | K88: =(K38-J38)/ABS(J38) -> 0.033644746 | L88: =L38/J38-1 -> 0.012151188 | M88: =L88/K88-1 -> -0.63883848 | N88: =(N38-K38)/ABS(K38) -> 0.038811437 | O88: =(O38-N38)/ABS(N38) -> 0.037816321 | V88: =(V38-Q38)/ABS(Q38) -> 0.20067227 | W88: =(W38-R38)/ABS(R38) -> 0.15059688 | X88: =(X38-S38)/ABS(S38) -> 0.13054916 | Y88: =(Y38-T38)/ABS(T38) -> 0.078300374 | AA88: =(AA38-V38)/ABS(V38) -> 0.097424412 | AB88: =(AB38-W38)/ABS(W38) -> 0.097100293 | AC88: =(AC38-X38)/ABS(X38) -> 0.15154159 | AD88: =(AD38-Y38)/ABS(Y38) -> 0.08401487 | AF88: =(AF38-AA38)/ABS(AA38) -> 0.05 | AG88: =(AG38-AB38)/ABS(AB38) -> 0.0053346266 | AH88: =(AH38-AC38)/ABS(AC38) -> 0.067441273 | AI88: =(AI38-AD38)/ABS(AD38) -> 0.015089163 | AJ88: =(AJ38-AD38)/ABS(AD38) -> -0.065386374 | AK88: =AJ88/AI88-1 -> -5.3333333 | AM88: =(AM38-AF38)/ABS(AF38) -> 0.044703596 | AN88: =(AN38-AG38)/ABS(AG38) -> 0.025084419 | AO88: =(AO38-AH38)/ABS(AH38) -> 0.047089446 | AP88: =(AP38-AI38)/ABS(AI38) -> 0.038288288
A89: Operating Income | E89: =(E39-D39)/ABS(D39) -> -0.064013477 | F89: =(F39-E39)/ABS(E39) -> 0.073565804 | G89: =(G39-F39)/ABS(F39) -> -0.34723386 | H89: =(H39-G39)/ABS(G39) -> 1.2269663 | I89: =(I39-H39)/ABS(H39) -> -0.037768488 | J89: =(J39-I39)/ABS(I39) -> -0.11385768 | K89: =(K39-J39)/ABS(J39) -> 0.054606932 | L89: =L39/J39-1 -> 0.066948436 | M89: =L89/K89-1 -> 0.22600619 | N89: =(N39-K39)/ABS(K39) -> 0.23901892 | O89: =(O39-N39)/ABS(N39) -> 0.10881097 | V89: =(V39-Q39)/ABS(Q39) -> 0.20271801 | W89: =(W39-R39)/ABS(R39) -> -0.079746835 | X89: =(X39-S39)/ABS(S39) -> -0.02920143 | Y89: =(Y39-T39)/ABS(T39) -> -0.23261892 | AA89: =(AA39-V39)/ABS(V39) -> -0.2019774 | AB89: =(AB39-W39)/ABS(W39) -> 0.091471802 | AC89: =(AC39-X39)/ABS(X39) -> -0.13321056 | AD89: =(AD39-Y39)/ABS(Y39) -> -0.16825613 | AF89: =(AF39-AA39)/ABS(AA39) -> -0.053687316 | AG89: =(AG39-AB39)/ABS(AB39) -> 0.14996849 | AH89: =(AH39-AC39)/ABS(AC39) -> -0.053824363 | AI89: =(AI39-AD39)/ABS(AD39) -> 0.20638821 | AJ89: =(AJ39-AD39)/ABS(AD39) -> 0.26617527 | AK89: =AJ89/AI89-1 -> 0.28968254 | AM89: =(AM39-AF39)/ABS(AF39) -> 0.22817955 | AN89: =(AN39-AG39)/ABS(AG39) -> 0.34520548 | AO89: =(AO39-AH39)/ABS(AH39) -> 0.1511976 | AP89: =(AP39-AI39)/ABS(AI39) -> 0.19891378
A90: Interest expense (income), net | C90: =(C40-B40)/ABS(B40) -> -0.32142857 | D90: =(D40-C40)/ABS(C40) -> 2.1052632 | E90: =(E40-D40)/ABS(D40) -> -0.084745763 | F90: =(F40-E40)/ABS(E40) -> -0.092592593 | G90: =(G40-F40)/ABS(F40) -> 0.81632653 | H90: =(H40-G40)/ABS(G40) -> 1.9438202 | I90: =(I40-H40)/ABS(H40) -> -0.21755725 | J90: =(J40-I40)/ABS(I40) -> -1.0292683 | K90: =(K40-J40)/ABS(J40) -> -25.333333 | L90: =L40/J40-1 -> 25.833333 | M90: =L90/K90-1 -> -2.0197368 | N90: =(N40-K40)/ABS(K40) -> 0.094936709 | O90: =(O40-N40)/ABS(N40) -> 0.16083916 | V90: =(V40-Q40)/ABS(Q40) -> -0.12307692 | W90: =(W40-R40)/ABS(R40) -> -0.21428571 | X90: =(X40-S40)/ABS(S40) -> -0.171875 | Y90: =(Y40-T40)/ABS(T40) -> -0.36507937 | AA90: =(AA40-V40)/ABS(V40) -> -0.77192982 | AB90: =(AB40-W40)/ABS(W40) -> -0.70909091 | AC90: =(AC40-X40)/ABS(X40) -> -1.1320755 | AD90: =(AD40-Y40)/ABS(Y40) -> -1.7 | AF90: =(AF40-AA40)/ABS(AA40) -> -3.6153846 | AG90: =(AG40-AB40)/ABS(AB40) -> -2.375 | AH90: =(AH40-AC40)/ABS(AC40) -> -6.4285714 | AI90: =(AI40-AD40)/ABS(AD40) -> -0.78571429 | AJ90: =(AJ40-AD40)/ABS(AD40) -> -0.89285714 | AK90: =AJ90/AI90-1 -> 0.13636364 | AM90: =(AM40-AF40)/ABS(AF40) -> 0.11764706 | AN90: =(AN40-AG40)/ABS(AG40) -> 0.090909091 | AO90: =(AO40-AH40)/ABS(AH40) -> 0.076923077 | AP90: =(AP40-AI40)/ABS(AI40) -> 0.1
A91: Other (income) expense, net | C91: =(C41-B41)/ABS(B41) -> -1.4137931 | D91: =(D41-C41)/ABS(C41) -> -0.4 | E91: =(E41-D41)/ABS(D41) -> 1.3367347 | F91: =(F41-E41)/ABS(E41) -> -2.1818182 | G91: =(G41-F41)/ABS(F41) -> 2.7820513 | H91: =(H41-G41)/ABS(G41) -> -0.89928058 | I91: =(I41-H41)/ABS(H41) -> -13.928571 | J91: =(J41-I41)/ABS(I41) -> -0.54696133 | K91: =(K41-J41)/ABS(J41) -> 0.63964286 | L91: =L41/J41-1 -> -0.18571429 | M91: =L91/K91-1 -> -1.2903406 | N91: =(N41-K41)/ABS(K41) -> -0.73439049 | O91: =(O41-N41)/ABS(N41) -> -0.14285714 | V91: =(V41-Q41)/ABS(Q41) -> -1.7857143 | W91: =(W41-R41)/ABS(R41) -> -2.8888889 | X91: =(X41-S41)/ABS(S41) -> -3.2727273 | Y91: =(Y41-T41)/ABS(T41) -> 14.5 | AA91: =(AA41-V41)/ABS(V41) -> -2.7435897 | AB91: =(AB41-W41)/ABS(W41) -> 0.2254902 | AC91: =(AC41-X41)/ABS(X41) -> 0.38297872 | AD91: =(AD41-Y41)/ABS(Y41) -> -0.94444444 | AF91: =(AF41-AA41)/ABS(AA41) -> 0.93150685 | AG91: =(AG41-AB41)/ABS(AB41) -> 0.050632911 | AH91: =(AH41-AC41)/ABS(AC41) -> 0.72413793 | AI91: =(AI41-AD41)/ABS(AD41) -> -0.96666667 | AJ91: =(AJ41-AD41)/ABS(AD41) -> -43.333333 | AK91: =AJ91/AI91-1 -> 43.827586 | AM91: =(AM41-AF41)/ABS(AF41) -> -1 | AN91: =(AN41-AG41)/ABS(AG41) -> -0.2 | AO91: =(AO41-AH41)/ABS(AH41) -> -4 | AP91: =(AP41-AI41)/ABS(AI41) -> 149
A92: Income before income taxes | C92: =(C42-B42)/ABS(B42) -> 0.09940547 | D92: =(D42-C42)/ABS(C42) -> 0.056889466 | E92: =(E42-D42)/ABS(D42) -> -0.11481785 | F92: =(F42-E42)/ABS(E42) -> 0.1100578 | G92: =(G42-F42)/ABS(F42) -> -0.39866694 | H92: =(H42-G42)/ABS(G42) -> 1.3072393 | I92: =(I42-H42)/ABS(H42) -> -0.0015012761 | J92: =(J42-I42)/ABS(I42) -> -0.067658999 | K92: =(K42-J42)/ABS(J42) -> 0.04771811 | L92: =L42/J42-1 -> 0.080470892 | M92: =L92/K92-1 -> 0.68638053 | N92: =(N42-K42)/ABS(K42) -> 0.23859071 | O92: =(O42-N42)/ABS(N42) -> 0.10475954 | V92: =(V42-Q42)/ABS(Q42) -> 0.22798834 | W92: =(W42-R42)/ABS(R42) -> 0.030906593 | X92: =(X42-S42)/ABS(S42) -> 0.020782396 | Y92: =(Y42-T42)/ABS(T42) -> -0.25889968 | AA92: =(AA42-V42)/ABS(V42) -> -0.1320038 | AB92: =(AB42-W42)/ABS(W42) -> 0.099267155 | AC92: =(AC42-X42)/ABS(X42) -> -0.11556886 | AD92: =(AD42-Y42)/ABS(Y42) -> -0.093158661 | AF92: =(AF42-AA42)/ABS(AA42) -> -0.098468271 | AG92: =(AG42-AB42)/ABS(AB42) -> 0.16484848 | AH92: =(AH42-AC42)/ABS(AC42) -> -0.049424509 | AI92: =(AI42-AD42)/ABS(AD42) -> 0.22223114 | AJ92: =(AJ42-AD42)/ABS(AD42) -> 0.38523274 | AK92: =AJ92/AI92-1 -> 0.73347779 | AM92: =(AM42-AF42)/ABS(AF42) -> 0.22572816 | AN92: =(AN42-AG42)/ABS(AG42) -> 0.33454735 | AO92: =(AO42-AH42)/ABS(AH42) -> 0.18660969 | AP92: =(AP42-AI42)/ABS(AI42) -> 0.17932891
A93: Income tax expense | C93: =(C43-B43)/ABS(B43) -> -0.074034335 | D93: =(D43-C43)/ABS(C43) -> -0.25144844 | E93: =(E43-D43)/ABS(D43) -> 2.7027864 | F93: =(F43-E43)/ABS(E43) -> -0.67725753 | G93: =(G43-F43)/ABS(F43) -> -0.5492228 | H93: =(H43-G43)/ABS(G43) -> 1.683908 | I93: =(I43-H43)/ABS(H43) -> -0.35224839 | J93: =(J43-I43)/ABS(I43) -> 0.86942149 | K93: =(K43-J43)/ABS(J43) -> -0.097259063 | L93: =L43/J43-1 -> -0.1158267 | M93: =L93/K93-1 -> 0.19090909 | N93: =(N43-K43)/ABS(K43) -> 0.13200618 | O93: =(O43-N43)/ABS(N43) -> 0.3076037 | V93: =(V43-Q43)/ABS(Q43) -> 0.17766497 | W93: =(W43-R43)/ABS(R43) -> -0.2 | X93: =(X43-S43)/ABS(S43) -> 0.46524064 | Y93: =(Y43-T43)/ABS(T43) -> -1.1884058 | AA93: =(AA43-V43)/ABS(V43) -> 0.55172414 | AB93: =(AB43-W43)/ABS(W43) -> 0.94512195 | AC93: =(AC43-X43)/ABS(X43) -> -0.1350365 | AD93: =(AD43-Y43)/ABS(Y43) -> 4.3076923 | AF93: =(AF43-AA43)/ABS(AA43) -> -0.45 | AG93: =(AG43-AB43)/ABS(AB43) -> 0.078369906 | AH93: =(AH43-AC43)/ABS(AC43) -> -0.021097046 | AI93: =(AI43-AD43)/ABS(AD43) -> 0.14883721 | AJ93: =(AJ43-AD43)/ABS(AD43) -> 0.051162791 | AK93: =AJ93/AI93-1 -> -0.65625 | AM93: =(AM43-AF43)/ABS(AF43) -> 0.73091914 | AN93: =(AN43-AG43)/ABS(AG43) -> 0.22807308 | AO93: =(AO43-AH43)/ABS(AH43) -> -0.19408778 | AP93: =(AP43-AI43)/ABS(AI43) -> -0.17559697
A94: NET INCOME | C94: =(C45-B45)/ABS(B45) -> 0.14879316 | D94: =(D45-C45)/ABS(C45) -> 0.12765957 | E94: =(E45-D45)/ABS(D45) -> -0.54410377 | F94: =(F45-E45)/ABS(E45) -> 1.0843249 | G94: =(G45-F45)/ABS(F45) -> -0.36981881 | H94: =(H45-G45)/ABS(G45) -> 1.2556124 | I94: =(I45-H45)/ABS(H45) -> 0.055701065 | J94: =(J45-I45)/ABS(I45) -> -0.16142904 | K94: =(K45-J45)/ABS(J45) -> 0.080059172 | L94: =(L45-J45)/ABS(J45) -> 0.12426036 | M94: =L94/K94-1 -> 0.55210643 | N94: =(N45-K45)/ABS(K45) -> 0.25846376 | O94: =(O45-N45)/ABS(N45) -> 0.070739027 | V94: =(V45-Q45)/ABS(Q45) -> 0.2345191 | W94: =(W45-R45)/ABS(R45) -> 0.068745004 | X94: =(X45-S45)/ABS(S45) -> -0.03657695 | Y94: =(Y45-T45)/ABS(T45) -> -0.046388337 | AA94: =(AA45-V45)/ABS(V45) -> -0.21664888 | AB94: =(AB45-W45)/ABS(W45) -> -0.0044876589 | AC94: =(AC45-X45)/ABS(X45) -> -0.11174785 | AD94: =(AD45-Y45)/ABS(Y45) -> -0.28353023 | AF94: =(AF45-AA45)/ABS(AA45) -> -0.01226158 | AG94: =(AG45-AB45)/ABS(AB45) -> 0.18557476 | AH94: =(AH45-AC45)/ABS(AC45) -> -0.05483871 | AI94: =(AI45-AD45)/ABS(AD45) -> 0.23753637 | AJ94: =(AJ44-AD44)/ABS(AD44) -> -0.24116522 | AK94: =AJ94/AI94-1 -> -2.015277 | AM94: =(AM45-AF45)/ABS(AF45) -> 0.15674346 | AN94: =(AN45-AG45)/ABS(AG45) -> 0.35775847 | AO94: =(AO45-AH45)/ABS(AH45) -> 0.26196959 | AP94: =(AP45-AI45)/ABS(AI45) -> 0.2480386
A95: Earnings per common share:
A96: Basic (in dollars per share) | C96: =(C47-B47)/ABS(B47) -> 0.16315789 | D96: =(D47-C47)/ABS(C47) -> 0.15837104 | E96: =(E47-D47)/ABS(D47) -> -0.53515625 | F96: =(F47-E47)/ABS(E47) -> 1.1428571 | G96: =(G47-F47)/ABS(F47) -> -0.36078431 | H96: =(H47-G47)/ABS(G47) -> 1.2336281 | I96: =(I47-H47)/ABS(H47) -> 0.051822761 | J96: =(J47-I47)/ABS(I47) -> -0.14672865 | K96: =(K47-J47)/ABS(J47) -> 0.102078 | L96: =(L47-J47)/ABS(J47) -> 0.14944805 | M96: =L96/K96-1 -> 0.46405739 | N96: =(N47-K47)/ABS(K47) -> 0.24665797 | O96: =(O47-N47)/ABS(N47) -> 0.067262601 | V96: =(V47-Q47)/ABS(Q47) -> 0.21649485 | W96: =(W47-R47)/ABS(R47) -> 0.05 | X96: =(X47-S47)/ABS(S47) -> -0.043478261 | Y96: =(Y47-T47)/ABS(T47) -> -0.046464165 | AA96: =(AA47-V47)/ABS(V47) -> -0.20338983 | AB96: =(AB47-W47)/ABS(W47) -> 0.011904762 | AC96: =(AC47-X47)/ABS(X47) -> -0.090909091 | AD96: =(AD47-Y47)/ABS(Y47) -> -0.26697658 | AF96: =(AF47-AA47)/ABS(AA47) -> 0.010638298 | AG96: =(AG47-AB47)/ABS(AB47) -> 0.22352941 | AH96: =(AH47-AC47)/ABS(AC47) -> -0.031853027 | AI96: =(AI47-AD47)/ABS(AD47) -> 0.25097016 | AJ96: =(AJ47-AD47)/ABS(AD47) -> 0.48239457 | AK96: =AJ96/AI96-1 -> 0.92211928 | AM96: =(AM47-AF47)/ABS(AF47) -> 0.14646481 | AN96: =(AN47-AG47)/ABS(AG47) -> 0.34649501 | AO96: =(AO47-AH47)/ABS(AH47) -> 0.25632394 | AP96: =(AP47-AI47)/ABS(AI47) -> 0.22388302
A97: Diluted (in dollars per share) | C97: =(C48-B48)/ABS(B48) -> 0.16756757 | D97: =(D48-C48)/ABS(C48) -> 0.16203704 | E97: =(E48-D48)/ABS(D48) -> -0.53386454 | F97: =(F48-E48)/ABS(E48) -> 1.1282051 | G97: =(G48-F48)/ABS(F48) -> -0.35742972 | H97: =(H48-G48)/ABS(G48) -> 1.2240431 | I97: =(I48-H48)/ABS(H48) -> 0.05478352 | J97: =(J48-I48)/ABS(I48) -> -0.13954097 | K97: =(K48-J48)/ABS(J48) -> 0.1042211 | L97: =(L48-J48)/ABS(J48) -> 0.15375042 | M97: =L97/K97-1 -> 0.47523314 | N97: =(N48-K48)/ABS(K48) -> 0.24868474 | O97: =(O48-N48)/ABS(N48) -> 0.069012028 | V97: =(V48-Q48)/ABS(Q48) -> 0.22105263 | W97: =(W48-R48)/ABS(R48) -> 0.064102564 | X97: =(X48-S48)/ABS(S48) -> -0.033333333 | Y97: =(Y48-T48)/ABS(T48) -> -0.02989854 | AA97: =(AA48-V48)/ABS(V48) -> -0.19827586 | AB97: =(AB48-W48)/ABS(W48) -> 0.024096386 | AC97: =(AC48-X48)/ABS(X48) -> -0.091954023 | AD97: =(AD48-Y48)/ABS(Y48) -> -0.26571401 | AF97: =(AF48-AA48)/ABS(AA48) -> 0.010752688 | AG97: =(AG48-AB48)/ABS(AB48) -> 0.21176471 | AH97: =(AH48-AC48)/ABS(AC48) -> -0.028139991 | AI97: =(AI48-AD48)/ABS(AD48) -> 0.25063497 | AJ97: =(AJ48-AD48)/ABS(AD48) -> 0.49288455 | AK97: =AJ97/AI97-1 -> 0.96654342 | AM97: =(AM48-AF48)/ABS(AF48) -> 0.15118601 | AN97: =(AN48-AG48)/ABS(AG48) -> 0.34202497 | AO97: =(AO48-AH48)/ABS(AH48) -> 0.25090687 | AP97: =(AP48-AI48)/ABS(AI48) -> 0.23998674
A98: Weighted average common shares outstanding:
A99: Basic (in shares) | C99: =(C50-B50)/ABS(B50) -> -0.012349775 | D99: =(D50-C50)/ABS(C50) -> -0.026512633 | E99: =(E50-D50)/ABS(D50) -> -0.019592453 | F99: =(F50-E50)/ABS(E50) -> -0.027158517 | G99: =(G50-F50)/ABS(F50) -> -0.01323036 | H99: =(H50-G50)/ABS(G50) -> 0.0091095715 | I99: =(I50-H50)/ABS(H50) -> 0.0036872219 | J99: =(J50-I50)/ABS(I50) -> -0.017228275 | K99: =(K50-J50)/ABS(J50) -> -0.019979376 | L99: =(L50-J50)/ABS(J50) -> -0.021912864 | M99: =L99/K99-1 -> 0.096774194 | N99: =(N50-K50)/ABS(K50) -> 0.0094699461 | O99: =(O50-N50)/ABS(N50) -> 0.003257329 | V99: =(V50-Q50)/ABS(Q50) -> 0.012869766 | W99: =(W50-R50)/ABS(R50) -> 0.0059758423 | X99: =(X50-S50)/ABS(S50) -> 0.00063371356 | Y99: =(Y50-T50)/ABS(T50) -> -0.0044331856 | AA99: =(AA50-V50)/ABS(V50) -> -0.0093558379 | AB99: =(AB50-W50)/ABS(W50) -> -0.014787664 | AC99: =(AC50-X50)/ABS(X50) -> -0.02229259 | AD99: =(AD50-Y50)/ABS(Y50) -> -0.022582697 | AF99: =(AF50-AA50)/ABS(AA50) -> -0.024695297 | AG99: =(AG50-AB50)/ABS(AB50) -> -0.024502886 | AH99: =(AH50-AC50)/ABS(AC50) -> -0.01982122 | AI99: =(AI50-AD50)/ABS(AD50) -> -0.010738692 | AJ99: =(AJ50-AD50)/ABS(AD50) -> -0.01854865 | AK99: =AJ99/AI99-1 -> 0.72727273 | AM99: =(AM50-AF50)/ABS(AF50) -> 0.0075896362 | AN99: =(AN50-AG50)/ABS(AG50) -> 0.0060494477 | AO99: =(AO50-AH50)/ABS(AH50) -> 0.004493788 | AP99: =(AP50-AI50)/ABS(AI50) -> 0.019736842
A100: Diluted (in shares) | C100: =(C51-B51)/ABS(B51) -> -0.016079936 | D100: =(D51-C51)/ABS(C51) -> -0.029583792 | E100: =(E51-D51)/ABS(D51) -> -0.017844104 | F100: =(F51-E51)/ABS(E51) -> -0.024531372 | G100: =(G51-F51)/ABS(F51) -> -0.016559565 | H100: =(H51-G51)/ABS(G51) -> 0.011183715 | I100: =(I51-H51)/ABS(H51) -> 0.0008698894 | J100: =(J51-I51)/ABS(I51) -> -0.025437671 | K100: =(K51-J51)/ABS(J51) -> -0.02188142 | L100: =(L51-J51)/ABS(J51) -> -0.025560174 | M100: =L100/K100-1 -> 0.16812227 | N100: =(N51-K51)/ABS(K51) -> 0.0078314528 | O100: =(O51-N51)/ABS(N51) -> 0.0016155089 | V100: =(V51-Q51)/ABS(Q51) -> 0.016506621 | W100: =(W51-R51)/ABS(R51) -> 0.0049083566 | X100: =(X51-S51)/ABS(S51) -> -0.0038344981 | Y100: =(Y51-T51)/ABS(T51) -> -0.012322744 | AA100: =(AA51-V51)/ABS(V51) -> -0.02086935 | AB100: =(AB51-W51)/ABS(W51) -> -0.027822431 | AC100: =(AC51-X51)/ABS(X51) -> -0.028496927 | AD100: =(AD51-Y51)/ABS(Y51) -> -0.024263323 | AF100: =(AF51-AA51)/ABS(AA51) -> -0.026800353 | AG100: =(AG51-AB51)/ABS(AB51) -> -0.025629611 | AH100: =(AH51-AC51)/ABS(AC51) -> -0.024475971 | AI100: =(AI51-AD51)/ABS(AD51) -> -0.010473559 | AJ100: =(AJ51-AD51)/ABS(AD51) -> -0.025444966 | AK100: =AJ100/AI100-1 -> 1.4294479 | AM100: =(AM51-AF51)/ABS(AF51) -> 0.0043413465 | AN100: =(AN51-AG51)/ABS(AG51) -> 0.01168331 | AO100: =(AO51-AH51)/ABS(AH51) -> 0.0088437602 | AP100: =(AP51-AI51)/ABS(AI51) -> 0.0064935065
A102: Ratios
...

Sheet Balance Sheet
A1: Consolidated Balance Sheets - USD ($) $ in Millions | B1: May 31, 2015 | C1: May 31, 2016 | D1: May 31, 2017 | E1: May 31, 2018 | F1: May 31, 2019 | G1: May 31, 2020 | H1: May 31, 2021 | I1: May 31, 2022 | J1: May 31, 2023 | K1: May 31, 2024
A2: Current assets:
A3: Cash and equivalents | B3: $ 3,852 | C3: 3138 | D3: 3808 | E3: $ 4,249 | F3: 4466 | G3: 8348 | H3: 9889 | I3: 8574 | J3: 7441 | K3: 9860
A4: Short-term investments | B4: 2072 | C4: 2319 | D4: 2371 | E4: 996 | F4: 197 | G4: 439 | H4: 3587 | I4: 4423 | J4: 3234 | K4: 1722
A5: Accounts receivable, net | B5: 3358 | C5: 3241 | D5: 3677 | E5: 3498 | F5: 4272 | G5: 2749 | H5: 4463 | I5: 4667 | J5: 4131 | K5: 4427
A6: Inventories | B6: 4337 | C6: 4838 | D6: 5055 | E6: 5261 | F6: 5622 | G6: 7367 | H6: 6854 | I6: 8420 | J6: 8454 | K6: 7519
A7: Prepaid expenses and other current assets | B7: 1968 | C7: 1489 | D7: 1150 | E7: 1130 | F7: 1968 | G7: 1653 | H7: 1498 | I7: 2129 | J7: 1942 | K7: 1854
A8: Total current assets | B8: 15587 | C8: 15025 | D8: 16061 | E8: 15134 | F8: 16525 | G8: 20556 | H8: 26291 | I8: 28213 | J8: 25202 | K8: 25382
A9: Property, plant and equipment, net | B9: 3011 | C9: 3520 | D9: 3989 | E9: 4454 | F9: 4744 | G9: 4866 | H9: 4904 | I9: 4791 | J9: 5081 | K9: 5000
A10: Operating lease right-of-use assets, net | B10: 0 | C10: 0 | D10: 0 | E10: 0 | F10: 0 | G10: 3097 | H10: 3113 | I10: 2926 | J10: 2923 | K10: 2718
A11: Identifiable intangible assets, net | B11: 281 | C11: 281 | D11: 283 | E11: 285 | F11: 283 | G11: 274 | H11: 269 | I11: 286 | J11: 274 | K11: 259
A12: Goodwill | B12: 131 | C12: 131 | D12: 139 | E12: 154 | F12: 154 | G12: 223 | H12: 242 | I12: 284 | J12: 281 | K12: 240
A13: Deferred income taxes and other assets | B13: 2587 | C13: 2422 | D13: 2787 | E13: 2509 | F13: 2011 | G13: 2326 | H13: 2921 | I13: 3821 | J13: 3770 | K13: 4511
A14: TOTAL ASSETS | B14: 21597 | C14: 21379 | D14: 23259 | E14: 22536 | F14: 23717 | G14: 31342 | H14: 37740 | I14: 40321 | J14: 37531 | K14: 38110
A15: Current liabilities:
A16: Current portion of long-term debt | B16: 107 | C16: 44 | D16: 6 | E16: 6 | F16: 6 | G16: 3 | H16: 0 | I16: 500 | J16: 0 | K16: 1000
A17: Notes payable | B17: 74 | C17: 1 | D17: 325 | E17: 336 | F17: 9 | G17: 248 | H17: 2 | I17: 10 | J17: 6 | K17: 6
A18: Accounts payable | B18: 2131 | C18: 2191 | D18: 2048 | E18: 2279 | F18: 2612 | G18: 2248 | H18: 2836 | I18: 3358 | J18: 2862 | K18: 2851
A19: Current portion of operating lease liabilities | B19: 0 | C19: 0 | D19: 0 | E19: 0 | F19: 0 | G19: 445 | H19: 467 | I19: 420 | J19: 425 | K19: 477
A20: Accrued liabilities | B20: 3949 | C20: 3037 | D20: 3011 | E20: 3269 | F20: 5010 | G20: 5184 | H20: 6063 | I20: 6220 | J20: 5723 | K20: 5725
A21: Income taxes payable | B21: 71 | C21: 85 | D21: 84 | E21: 150 | F21: 229 | G21: 156 | H21: 306 | I21: 222 | J21: 240 | K21: 534
A22: Total current liabilities | B22: 6332 | C22: 5358 | D22: 5474 | E22: 6040 | F22: 7866 | G22: 8284 | H22: 9674 | I22: 10730 | J22: 9256 | K22: 10593
A23: Long-term debt | B23: 1079 | C23: 1993 | D23: 3471 | E23: 3468 | F23: 3464 | G23: 9406 | H23: 9413 | I23: 8920 | J23: 8927 | K23: 7903
A24: Operating lease liabilities | B24: 0 | C24: 0 | D24: 0 | E24: 0 | F24: 0 | G24: 2913 | H24: 2931 | I24: 2777 | J24: 2786 | K24: 2566
A25: Deferred income taxes and other liabilities | B25: 1479 | C25: 1770 | D25: 1907 | E25: 3216 | F25: 3347 | G25: 2684 | H25: 2955 | I25: 2613 | J25: 2558 | K25: 2618
A26: Commitments and contingencies (Note 16)
A27: Redeemable preferred stock | B27: 0 | C27: 0 | D27: 0 | E27: 0 | F27: 0 | G27: 0 | H27: 0 | I27: 0 | J27: 0 | K27: 0
A28: Shareholders' equity:
A29: Capital in excess of stated value | B29: 6773 | C29: 7786 | D29: 8638 | E29: 6384 | F29: 7163 | G29: 8299 | H29: 9965 | I29: 11484 | J29: 12412 | K29: 13409
A30: Accumulated other comprehensive income (loss) | B30: 1246 | C30: 318 | D30: -213 | E30: -92 | F30: 231 | G30: -56 | H30: -380 | I30: 318 | J30: 231 | K30: 53
A31: Retained earnings (deficit) | B31: 4685 | C31: 4151 | D31: 3979 | E31: 3517 | F31: 1643 | G31: -191 | H31: 3179 | I31: 3476 | J31: 1358 | K31: 965
A32: Total shareholders' equity | B32: 12707 | C32: 12258 | D32: 12407 | E32: 9812 | F32: 9040 | G32: 8055 | H32: 12767 | I32: 15281 | J32: 14004 | K32: 14430
A33: TOTAL LIABILITIES AND SHAREHOLDERS' EQUITY | B33: 21597 | C33: 21379 | D33: 23259 | E33: 22536 | F33: 23717 | G33: 31342 | H33: 37740 | I33: 40321 | J33: 37531 | K33: 38110
A34: Class A Convertible Common Stock
A35: Shareholders' equity:
A36: Common stock at stated value | B36: 0 | C36: 0 | D36: 0 | E36: 0 | F36: 0 | G36: 0 | H36: 0 | I36: 0 | J36: 0 | K36: 0
A37: Class B Common Stock
A38: Shareholders' equity:
A39: Common stock at stated value | B39: $ 3 | C39: 3 | D39: 3 | E39: $ 3 | F39: 3 | G39: 3 | H39: 3 | I39: 3 | J39: 3 | K39: 3

Sheet Statement of Operations
A1: Consolidated Statements of Income - USD ($) shares in Millions, $ in Millions | B1: 12 Months Ended | M1: 2021 | R1: 2022 | W1: 2023 | AB1: 2024
B2: May 31, 2015 | C2: May 31, 2016 | D2: May 31, 2017 | E2: May 31, 2018 | F2: May 31, 2019 | G2: May 31, 2020 | H2: May 31, 2021 | I2: May 31, 2022 | J2: May 31, 2023 | K2: May 31, 2024 | M2: Aug. 31, 2020 | N2: Nov. 30, 2020 | O2: Feb. 28, 2021 | P2: May. 31, 2021 | R2: Aug. 31, 2021 | S2: Nov. 30, 2021 | T2: Feb. 28, 2022 | U2: May. 31, 2022 | W2: Aug. 31, 2022 | X2: Nov. 30, 2022 | Y2: Feb. 28, 2023 | Z2: May. 31, 2023 | AB2: Aug. 31, 2023 | AC2: Nov. 30, 2023 | AD2: Feb. 29, 2024 | AE2: May. 31, 2024
A3: Income Statement [Abstract]
A4: Revenues | B4: 30601 | C4: 32376 | D4: 34350 | E4: 36397 | F4: 39117 | G4: 37403 | H4: 44538 | I4: 46710 | J4: 51217 | K4: 51362 | M4: 10594 | N4: 11243 | O4: 10357 | P4: 12344 | R4: 12248 | S4: 11357 | T4: 10871 | U4: 12234 | W4: 12687 | X4: 13315 | Y4: 12390 | Z4: 12825 | AB4: 12939 | AC4: 13388 | AD4: 12429 | AE4: =K4-SUM(AB4:AD4) -> 12606
A5: Cost of sales | B5: 16534 | C5: 17405 | D5: 19038 | E5: 20441 | F5: 21643 | G5: 21162 | H5: 24576 | I5: 25231 | J5: 28925 | K5: 28475 | M5: 5853 | N5: 6396 | O5: 5638 | P5: 6689 | R5: 6552 | S5: 6144 | T5: 5804 | U5: 6731 | W5: 7072 | X5: 7604 | Y5: 7019 | Z5: 7230 | AB5: 7219 | AC5: 7417 | AD5: 6867 | AE5: =K5-SUM(AB5:AD5) -> 6972
A6: Gross profit | B6: =B4-B5 -> 14067 | C6: =C4-C5 -> 14971 | D6: =D4-D5 -> 15312 | E6: =E4-E5 -> 15956 | F6: =F4-F5 -> 17474 | G6: =G4-G5 -> 16241 | H6: =H4-H5 -> 19962 | I6: =I4-I5 -> 21479 | ... K6: =K4-K5 -> 22887 | M6: =M4-M5 -> 4741 | N6: =N4-N5 -> 4847 | O6: =O4-O5 -> 4719 | P6: =P4-P5 -> 5655 | R6: =R4-R5 -> 5696 | S6: =S4-S5 -> 5213 | T6: =T4-T5 -> 5067 | U6: =U4-U5 -> 5503 | W6: =W4-W5 -> 5615 | X6: =X4-X5 -> 5711 | Y6: =Y4-Y5 -> 5371 | Z6: =Z4-Z5 -> 5595 | AB6: =AB4-AB5 -> 5720 | AC6: =AC4-AC5 -> 5971 | AD6: =AD4-AD5 -> 5562 | AE6: =AE4-AE5 -> 5634
A7: Demand creation expense | B7: 3213 | C7: 3278 | D7: 3341 | E7: 3577 | F7: 3753 | G7: 3592 | H7: 3114 | I7: 3850 | J7: 4060 | K7: 4285 | M7: 677 | N7: 729 | O7: 711 | P7: 997 | R7: 918 | S7: 1017 | T7: 854 | U7: 1061 | W7: 943 | X7: 1102 | Y7: 923 | Z7: 1092 | AB7: 1069 | AC7: 1114 | AD7: 1011 | AE7: =K7-SUM(AB7:AD7) -> 1091
A8: Operating overhead expense | B8: 6679 | C8: 7191 | D8: 7222 | E8: 7934 | F8: 8949 | G8: 9534 | H8: 9911 | I8: 10954 | J8: 12317 | K8: 12291 | M8: 2298 | N8: 2538 | O8: 2330 | P8: 2745 | R8: 2654 | S8: 2742 | T8: 2584 | U8: 2974 | W8: 2977 | X8: 3022 | Y8: 3036 | Z8: 3282 | AB8: 3047 | AC8: 3032 | AD8: 3215 | AE8: =K8-SUM(AB8:AD8) -> 2997
A9: Total selling and administrative expense | B9: 9892 | C9: 10469 | D9: 10563 | E9: 11511 | F9: 12702 | G9: 13126 | H9: 13025 | I9: 14804 | J9: 16377 | K9: 16576 | M9: 2975 | N9: 3267 | O9: 3041 | P9: 3742 | R9: 3572 | S9: 3759 | T9: 3438 | U9: 4035 | W9: 3920 | X9: 4124 | Y9: 3959 | Z9: 4374 | AB9: 4116 | AC9: 4146 | AD9: 4226 | AE9: =K9-SUM(AB9:AD9) -> 4088
A10: Operating Income | B10: =B6-B9 -> 4175 | C10: =C6-C9 -> 4502 | D10: =D6-D9 -> 4749 | E10: =E6-E9 -> 4445 | F10: =F6-F9 -> 4772 | G10: =G6-G9 -> 3115 | H10: =H6-H9 -> 6937 | I10: =I6-I9 -> 6675 | ... K10: =K6-K9 -> 6311 | M10: =M6-M9 -> 1766 | N10: =N6-N9 -> 1580 | O10: =O6-O9 -> 1678 | P10: =P6-P9 -> 1913 | R10: =R6-R9 -> 2124 | S10: =S6-S9 -> 1454 | T10: =T6-T9 -> 1629 | U10: =U6-U9 -> 1468 | W10: =W6-W9 -> 1695 | X10: =X6-X9 -> 1587 | Y10: =Y6-Y9 -> 1412 | Z10: =Z6-Z9 -> 1221 | AB10: =AB6-AB9 -> 1604 | AC10: =AC6-AC9 -> 1825 | AD10: =AD6-AD9 -> 1336 | AE10: =AE6-AE9 -> 1546
A11: Interest expense (income), net | B11: 28 | C11: 19 | D11: 59 | E11: 54 | F11: 49 | G11: 89 | H11: 262 | I11: 205 | J11: -6 | K11: -161 | M11: 65 | N11: 70 | O11: 64 | P11: 63 | R11: 57 | S11: 55 | T11: 53 | U11: 40 | W11: 13 | X11: 16 | Y11: -7 | Z11: -28 | AB11: -34 | AC11: -22 | AD11: -52 | AE11: =K11-SUM(AB11:AD11) -> -53
A12: Other (income) expense, net | B12: -58 | C12: -140 | D12: -196 | E12: 66 | F12: -78 | G12: 139 | H12: 14 | I12: -181 | J12: -280 | K12: -228 | M12: -14 | N12: 54 | O12: -22 | P12: -4 | R12: -39 | S12: -102 | T12: -94 | U12: 54 | W12: -146 | X12: -79 | Y12: -58 | Z12: 3 | AB12: -10 | AC12: -75 | AD12: -16 | AE12: =K12-SUM(AB12:AD12) -> -127
A13: Income before income taxes | B13: 4205 | C13: 4623 | D13: 4886 | E13: 4325 | F13: 4801 | G13: 2887 | H13: 6661 | I13: 6651 | J13: 6201 | K13: 6700 | M13: 1715 | N13: 1456 | O13: 1636 | P13: =P10-P11-P12 -> 1854 | R13: =R10-R11-R12 -> 2106 | S13: =S10-S11-S12 -> 1501 | T13: =T10-T11-T12 -> 1670 | U13: =U10-U11-U12 -> 1374 | W13: 1828 | X13: 1650 | Y13: 1477 | Z13: 1246 | AB13: 1648 | AC13: 1922 | AD13: 1404 | AE13: =K13-SUM(AB13:AD13) -> 1726
A14: Income tax expense | B14: 932 | C14: 863 | D14: 646 | E14: 2392 | F14: 772 | G14: 348 | H14: 934 | I14: 605 | J14: 1131 | K14: 1000 | M14: 197 | N14: 205 | O14: 187 | P14: 345 | R14: 232 | S14: 164 | T14: 274 | U14: -65 | W14: 360 | X14: 319 | Y14: 237 | Z14: 215 | AB14: 198 | AC14: 344 | AD14: 232 | AE14: =K14-SUM(AB14:AD14) -> 226
A15: NET INCOME | B15: 3273 | C15: 3760 | D15: 4240 | E15: 1933 | F15: 4029 | G15: 2539 | H15: 5727 | I15: 6046 | J15: 5070 | K15: 5700 | M15: 1518 | N15: 1251 | O15: 1449 | P15: =P13-P14 -> 1509 | R15: =R13-R14 -> 1874 | S15: =S13-S14 -> 1337 | T15: =T13-T14 -> 1396 | U15: =U13-U14 -> 1439 | W15: 1468 | X15: 1331 | Y15: 1240 | Z15: 1031 | AB15: 1450 | AC15: 1578 | AD15: 1172 | AE15: =K15-SUM(AB15:AD15) -> 1500
A16: Earnings per common share:
A17: Basic (in dollars per share) | B17: 1.9 | C17: 2.21 | D17: 2.56 | E17: 1.19 | F17: 2.55 | G17: 1.63 | H17: =H15/H20 -> 3.6408137 | I17: =I15/I20 -> 3.8294908 | J17: =J15/J20 -> 3.2675947 | K17: 3.76 | M17: 0.97 | N17: 0.8 | O17: 0.92 | P17: =P$15/P20 -> 0.95566814 | R17: 1.18 | S17: 0.84 | T17: 0.88 | U17: =U15/U20 -> 0.9153944 | W17: 0.94 | X17: 0.85 | Y17: 0.8 | Z17: =Z15/Z20 -> 0.67100553 | AB17: 0.95 | AC17: 1.04 | AD17: 0.77
A18: Diluted (in dollars per share) | B18: 1.85 | C18: 2.16 | D18: 2.51 | E18: 1.17 | F18: 2.49 | G18: 1.6 | H18: =H15/H21 -> 3.558469 | I18: =I15/I21 -> 3.7534145 | J18: =J15/J21 -> 3.2297108 | K18: 3.73 | M18: 0.95 | N18: 0.78 | O18: 0.9 | P18: =P$15/P21 -> 0.93442318 | R18: 1.16 | S18: 0.83 | T18: 0.87 | U18: =U15/U21 -> 0.90219436 | W18: 0.93 | X18: 0.85 | Y18: 0.79 | Z18: =Z15/Z21 -> 0.66246868 | AB18: 0.94 | AC18: 1.03 | AD18: 0.77
A19: Weighted average common shares outstanding:
A20: Basic (in shares) | B20: =B15/B17 -> 1722.6316 | C20: =C15/C17 -> 1701.3575 | D20: =D15/D17 -> 1656.25 | E20: 1623.8 | F20: 1579.7 | G20: 1558.8 | H20: 1573 | I20: 1578.8 | J20: 1551.6 | K20: 1517.6 | M20: 1561.8 | N20: 1573 | O20: 1578 | P20: 1579 | R20: 1581.9 | S20: 1582.4 | T20: 1579 | U20: 1572 | W20: 1567.1 | X20: 1559 | Y20: 1543.8 | Z20: 1536.5 | AB20: 1528.4 | AC20: 1520.8 | AD20: 1513.2
A21: Diluted (in shares) | B21: =B15/B18 -> 1769.1892 | C21: =C15/C18 -> 1740.7407 | D21: =D15/D18 -> 1689.243 | E21: 1659.1 | F21: 1618.4 | G21: 1591.6 | H21: 1609.4 | I21: 1610.8 | J21: 1569.8 | K21: 1529.7 | M21: 1593.3 | N21: 1609.5 | O21: 1616.9 | P21: 1614.9 | R21: 1619.6 | S21: 1617.4 | T21: 1610.7 | U21: 1595 | W21: 1585.8 | X21: 1572.4 | Y21: 1564.8 | Z21: 1556.3 | AB21: 1543.3 | AC21: 1532.1 | AD21: 1526.5
A23: Ratios
A24: Gross Margin | B24: =B6/B4 -> 0.45969086 | C24: =C6/C4 -> 0.46241043 | D24: =D6/D4 -> 0.44576419 | E24: =E6/E4 -> 0.43838778 | F24: =F6/F4 -> 0.44671115 | G24: =G6/G4 -> 0.43421651 | H24: =H6/H4 -> 0.44820154 | I24: =I6/I4 -> 0.45983729 | ... K24: =K6/K4 -> 0.44560181 | R24: =R6/R4 -> 0.46505552 | S24: =S6/S4 -> 0.45901206 | T24: =T6/T4 -> 0.46610247 | U24: =U6/U4 -> 0.449812 | W24: =W6/W4 -> 0.44257902 | X24: =X6/X4 -> 0.42891476 | Y24: =Y6/Y4 -> 0.43349475 | Z24: =Z6/Z4 -> 0.43625731 | AB24: =AB6/AB4 -> 0.44207435 | AC24: =AC6/AC4 -> 0.44599641 | AD24: =AD6/AD4 -> 0.44750181 | AE24: =AE6/AE4 -> 0.44693003
A25: Total Operating Expense/Revenues | B25: =B9/B4 -> 0.32325741 | C25: =C9/C4 -> 0.32335681 | D25: =D9/D4 -> 0.30751092 | E25: =E9/E4 -> 0.31626233 | F25: =F9/F4 -> 0.32471815 | G25: =G9/G4 -> 0.35093442 | H25: =H9/H4 -> 0.2924469 | I25: =I9/I4 -> 0.31693428 | ... K25: =K9/K4 -> 0.32272887 | R25: =R9/R4 -> 0.29163945 | S25: =S9/S4 -> 0.3309853 | T25: =T9/T4 -> 0.31625425 | U25: =U9/U4 -> 0.32981854 | W25: =W9/W4 -> 0.30897769 | X25: =X9/X4 -> 0.30972587 | Y25: =Y9/Y4 -> 0.31953188 | Z25: =Z9/Z4 -> 0.34105263 | AB25: =AB9/AB4 -> 0.31810805 | AC25: =AC9/AC4 -> 0.30968031 | AD25: =AD9/AD4 -> 0.34001126 | AE25: =AE9/AE4 -> 0.32429002
A26: Operating Margin | B26: =B10/B4 -> 0.13643345 | C26: =C10/C4 -> 0.13905362 | D26: =D10/D4 -> 0.13825328 | E26: =E10/E4 -> 0.12212545 | F26: =F10/F4 -> 0.121993 | G26: =G10/G4 -> 0.08328209 | H26: =H10/H4 -> 0.15575464 | I26: =I10/I4 -> 0.14290302 | ... K26: =K10/K4 -> 0.12287294 | R26: =R10/R4 -> 0.17341607 | S26: =S10/S4 -> 0.12802677 | T26: =T10/T4 -> 0.14984822 | U26: =U10/U4 -> 0.11999346 | W26: =W10/W4 -> 0.13360132 | X26: =X10/X4 -> 0.11918888 | Y26: =Y10/Y4 -> 0.11396287 | Z26: =Z10/Z4 -> 0.095204678 | AB26: =AB10/AB4 -> 0.1239663 | AC26: =AC10/AC4 -> 0.1363161 | AD26: =AD10/AD4 -> 0.10749055 | AE26: =AE10/AE4 -> 0.12264001
A27: Net Margin | B27: =B15/B4 -> 0.10695729 | C27: =C15/C4 -> 0.11613541 | D27: =D15/D4 -> 0.12343523 | E27: =E15/E4 -> 0.053108773 | F27: =F15/F4 -> 0.1029987 | G27: =G15/G4 -> 0.067882255 | H27: =H15/H4 -> 0.12858682 | I27: =I15/I4 -> 0.12943695 | ... K27: =K15/K4 -> 0.11097699 | R27: =R15/R4 -> 0.15300457 | S27: =S15/S4 -> 0.11772475 | T27: =T15/T4 -> 0.12841505 | U27: =U15/U4 -> 0.11762302 | W27: =W15/W4 -> 0.11570899 | X27: =X15/X4 -> 0.099962448 | Y27: =Y15/Y4 -> 0.10008071 | Z27: =Z15/Z4 -> 0.080389864 | AB27: =AB15/AB4 -> 0.1120643 | AC27: =AC15/AC4 -> 0.11786675 | AD27: =AD15/AD4 -> 0.094295599 | AE27: =AE15/AE4 -> 0.11899096
A28: Effective Tax Rate | B28: =B14/B13 -> 0.2216409 | C28: =C14/C13 -> 0.18667532 | D28: =D14/D13 -> 0.13221449 | E28: =E14/E13 -> 0.55306358 | F28: =F14/F13 -> 0.16079983 | G28: =G14/G13 -> 0.12054035 | H28: =H14/H13 -> 0.14021919 | I28: =I14/I13 -> 0.090963765 | ... K28: =K14/K13 -> 0.14925373 | M28: =M14/M13 -> 0.1148688 | N28: =N14/N13 -> 0.1407967 | O28: =O14/O13 -> 0.11430318 | P28: =P14/P13 -> 0.18608414 | R28: =R14/R13 -> 0.11016144 | S28: =S14/S13 -> 0.10926049 | T28: =T14/T13 -> 0.16407186 | U28: =U14/U13 -> -0.047307132 | W28: =W14/W13 -> 0.19693654 | X28: =X14/X13 -> 0.19333333 | Y28: =Y14/Y13 -> 0.16046039 | Z28: =Z14/Z13 -> 0.17255217 | AB28: =AB14/AB13 -> 0.12014563 | AC28: =AC14/AC13 -> 0.17898023 | AD28: =AD14/AD13 -> 0.16524217 | AE28: =AE14/AE13 -> 0.13093859
A30: Growth Rates
A31: Revenues | C31: =(C4-B4)/ABS(B4) -> 0.05800464 | D31: =(D4-C4)/ABS(C4) -> 0.06097109 | E31: =(E4-D4)/ABS(D4) -> 0.059592431 | F31: =(F4-E4)/ABS(E4) -> 0.074731434 | G31: =(G4-F4)/ABS(F4) -> -0.043817266 | H31: =(H4-G4)/ABS(G4) -> 0.1907601 | I31: =(I4-H4)/ABS(H4) -> 0.048767345 | J31: =(J4-I4)/ABS(I4) -> 0.096488975 | K31: =(K4-J4)/ABS(J4) -> 0.0028310912 | R31: =(R4-M4)/ABS(M4) -> 0.15612611 | S31: =(S4-N4)/ABS(N4) -> 0.010139642 | T31: =(T4-O4)/ABS(O4) -> 0.049628271 | U31: =(U4-P4)/ABS(P4) -> -0.0089112119 | W31: =(W4-R4)/ABS(R4) -> 0.035842587 | X31: =(X4-S4)/ABS(S4) -> 0.17240468 | Y31: =(Y4-T4)/ABS(T4) -> 0.13972956 | Z31: =(Z4-U4)/ABS(U4) -> 0.048307994 | AB31: =(AB4-W4)/ABS(W4) -> 0.019862852 | AC31: =(AC4-X4)/ABS(X4) -> 0.0054825385 | AD31: =(AD4-Y4)/ABS(Y4) -> 0.0031476998 | AE31: =(AE4-Z4)/ABS(Z4) -> -0.017076023
A32: Cost of sales | C32: =(C5-B5)/ABS(B5) -> 0.052679327 | D32: =(D5-C5)/ABS(C5) -> 0.093823614 | E32: =(E5-D5)/ABS(D5) -> 0.073694716 | F32: =(F5-E5)/ABS(E5) -> 0.058803385 | G32: =(G5-F5)/ABS(F5) -> -0.022224276 | H32: =(H5-G5)/ABS(G5) -> 0.16132691 | I32: =(I5-H5)/ABS(H5) -> 0.026652018 | J32: =(J5-I5)/ABS(I5) -> 0.1464072 | K32: =(K5-J5)/ABS(J5) -> -0.015557476 | R32: =(R5-M5)/ABS(M5) -> 0.11942594 | S32: =(S5-N5)/ABS(N5) -> -0.039399625 | T32: =(T5-O5)/ABS(O5) -> 0.029443065 | U32: =(U5-P5)/ABS(P5) -> 0.0062789655 | W32: =(W5-R5)/ABS(R5) -> 0.079365079 | X32: =(X5-S5)/ABS(S5) -> 0.23763021 | Y32: =(Y5-T5)/ABS(T5) -> 0.20933839 | Z32: =(Z5-U5)/ABS(U5) -> 0.074134601 | AB32: =(AB5-W5)/ABS(W5) -> 0.020786199 | AC32: =(AC5-X5)/ABS(X5) -> -0.02459232 | AD32: =(AD5-Y5)/ABS(Y5) -> -0.021655506 | AE32: =(AE5-Z5)/ABS(Z5) -> -0.035684647
A33: Gross profit | C33: =(C6-B6)/ABS(B6) -> 0.06426388 | D33: =(D6-C6)/ABS(C6) -> 0.02277737 | E33: =(E6-D6)/ABS(D6) -> 0.042058516 | F33: =(F6-E6)/ABS(E6) -> 0.095136626 | G33: =(G6-F6)/ABS(F6) -> -0.070561978 | H33: =(H6-G6)/ABS(G6) -> 0.22911151 | I33: =(I6-H6)/ABS(H6) -> 0.075994389 | J33: =(J6-I6)/ABS(I6) -> 0.037850924 | K33: =(K6-J6)/ABS(J6) -> 0.02669119 | R33: =(R6-M6)/ABS(M6) -> 0.2014343 | S33: =(S6-N6)/ABS(N6) -> 0.075510625 | T33: =(T6-O6)/ABS(O6) -> 0.073744437 | U33: =(U6-P6)/ABS(P6) -> -0.026878868 | W33: =(W6-R6)/ABS(R6) -> -0.014220506 | X33: =(X6-S6)/ABS(S6) -> 0.095530405 | Y33: =(Y6-T6)/ABS(T6) -> 0.059996053 | Z33: =(Z6-U6)/ABS(U6) -> 0.016718154 | AB33: =(AB6-W6)/ABS(W6) -> 0.018699911 | AC33: =(AC6-X6)/ABS(X6) -> 0.045526178 | AD33: =(AD6-Y6)/ABS(Y6) -> 0.035561348 | AE33: =(AE6-Z6)/ABS(Z6) -> 0.0069705094
A34: Demand creation expense | C34: =(C7-B7)/ABS(B7) -> 0.020230314 | D34: =(D7-C7)/ABS(C7) -> 0.019219036 | E34: =(E7-D7)/ABS(D7) -> 0.070637534 | F34: =(F7-E7)/ABS(E7) -> 0.049203243 | G34: =(G7-F7)/ABS(F7) -> -0.042899014 | H34: =(H7-G7)/ABS(G7) -> -0.1330735 | I34: =(I7-H7)/ABS(H7) -> 0.23635196 | J34: =(J7-I7)/ABS(I7) -> 0.054545455 | K34: =(K7-J7)/ABS(J7) -> 0.055418719 | R34: =(R7-M7)/ABS(M7) -> 0.35598227 | S34: =(S7-N7)/ABS(N7) -> 0.39506173 | T34: =(T7-O7)/ABS(O7) -> 0.20112518 | U34: =(U7-P7)/ABS(P7) -> 0.064192578 | W34: =(W7-R7)/ABS(R7) -> 0.027233115 | X34: =(X7-S7)/ABS(S7) -> 0.083579154 | Y34: =(Y7-T7)/ABS(T7) -> 0.080796253 | Z34: =(Z7-U7)/ABS(U7) -> 0.029217719 | AB34: =(AB7-W7)/ABS(W7) -> 0.13361612 | AC34: =(AC7-X7)/ABS(X7) -> 0.010889292 | AD34: =(AD7-Y7)/ABS(Y7) -> 0.095341278 | AE34: =(AE7-Z7)/ABS(Z7) -> -0.00091575092
A35: Operating overhead expense | C35: =(C8-B8)/ABS(B8) -> 0.076658182 | D35: =(D8-C8)/ABS(C8) -> 0.0043109442 | E35: =(E8-D8)/ABS(D8) -> 0.098587649 | F35: =(F8-E8)/ABS(E8) -> 0.12793043 | G35: =(G8-F8)/ABS(F8) -> 0.065370432 | H35: =(H8-G8)/ABS(G8) -> 0.039542689 | I35: =(I8-H8)/ABS(H8) -> 0.10523661 | J35: =(J8-I8)/ABS(I8) -> 0.12442943 | K35: =(K8-J8)/ABS(J8) -> -0.0021109036 | R35: =(R8-M8)/ABS(M8) -> 0.15491732 | S35: =(S8-N8)/ABS(N8) -> 0.080378251 | T35: =(T8-O8)/ABS(O8) -> 0.10901288 | U35: =(U8-P8)/ABS(P8) -> 0.083424408 | W35: =(W8-R8)/ABS(R8) -> 0.12170309 | X35: =(X8-S8)/ABS(S8) -> 0.10211524 | Y35: =(Y8-T8)/ABS(T8) -> 0.1749226 | Z35: =(Z8-U8)/ABS(U8) -> 0.10356422 | AB35: =(AB8-W8)/ABS(W8) -> 0.023513604 | AC35: =(AC8-X8)/ABS(X8) -> 0.0033090668 | AD35: =(AD8-Y8)/ABS(Y8) -> 0.058959157 | AE35: =(AE8-Z8)/ABS(Z8) -> -0.086837294
A36: Total selling and administrative expense | C36: =(C9-B9)/ABS(B9) -> 0.058329964 | D36: =(D9-C9)/ABS(C9) -> 0.0089788901 | E36: =(E9-D9)/ABS(D9) -> 0.089747231 | F36: =(F9-E9)/ABS(E9) -> 0.10346625 | G36: =(G9-F9)/ABS(F9) -> 0.03338057 | H36: =(H9-G9)/ABS(G9) -> -0.0076946518 | I36: =(I9-H9)/ABS(H9) -> 0.13658349 | J36: =(J9-I9)/ABS(I9) -> 0.10625507 | K36: =(K9-J9)/ABS(J9) -> 0.012151188 | R36: =(R9-M9)/ABS(M9) -> 0.20067227 | S36: =(S9-N9)/ABS(N9) -> 0.15059688 | T36: =(T9-O9)/ABS(O9) -> 0.13054916 | U36: =(U9-P9)/ABS(P9) -> 0.078300374 | W36: =(W9-R9)/ABS(R9) -> 0.097424412 | X36: =(X9-S9)/ABS(S9) -> 0.097100293 | Y36: =(Y9-T9)/ABS(T9) -> 0.15154159 | Z36: =(Z9-U9)/ABS(U9) -> 0.08401487 | AB36: =(AB9-W9)/ABS(W9) -> 0.05 | AC36: =(AC9-X9)/ABS(X9) -> 0.0053346266 | AD36: =(AD9-Y9)/ABS(Y9) -> 0.067441273 | AE36: =(AE9-Z9)/ABS(Z9) -> -0.065386374
A37: Interest expense (income), net | C37: =(C11-B11)/ABS(B11) -> -0.32142857 | D37: =(D11-C11)/ABS(C11) -> 2.1052632 | E37: =(E11-D11)/ABS(D11) -> -0.084745763 | F37: =(F11-E11)/ABS(E11) -> -0.092592593 | G37: =(G11-F11)/ABS(F11) -> 0.81632653 | H37: =(H11-G11)/ABS(G11) -> 1.9438202 | I37: =(I11-H11)/ABS(H11) -> -0.21755725 | J37: =(J11-I11)/ABS(I11) -> -1.0292683 | K37: =(K11-J11)/ABS(J11) -> -25.833333 | R37: =(R11-M11)/ABS(M11) -> -0.12307692 | S37: =(S11-N11)/ABS(N11) -> -0.21428571 | T37: =(T11-O11)/ABS(O11) -> -0.171875 | U37: =(U11-P11)/ABS(P11) -> -0.36507937 | W37: =(W11-R11)/ABS(R11) -> -0.77192982 | X37: =(X11-S11)/ABS(S11) -> -0.70909091 | Y37: =(Y11-T11)/ABS(T11) -> -1.1320755 | Z37: =(Z11-U11)/ABS(U11) -> -1.7 | AB37: =(AB11-W11)/ABS(W11) -> -3.6153846 | AC37: =(AC11-X11)/ABS(X11) -> -2.375 | AD37: =(AD11-Y11)/ABS(Y11) -> -6.4285714 | AE37: =(AE11-Z11)/ABS(Z11) -> -0.89285714
A38: Other (income) expense, net | C38: =(C12-B12)/ABS(B12) -> -1.4137931 | D38: =(D12-C12)/ABS(C12) -> -0.4 | E38: =(E12-D12)/ABS(D12) -> 1.3367347 | F38: =(F12-E12)/ABS(E12) -> -2.1818182 | G38: =(G12-F12)/ABS(F12) -> 2.7820513 | H38: =(H12-G12)/ABS(G12) -> -0.89928058 | I38: =(I12-H12)/ABS(H12) -> -13.928571 | J38: =(J12-I12)/ABS(I12) -> -0.54696133 | K38: =(K12-J12)/ABS(J12) -> 0.18571429 | R38: =(R12-M12)/ABS(M12) -> -1.7857143 | S38: =(S12-N12)/ABS(N12) -> -2.8888889 | T38: =(T12-O12)/ABS(O12) -> -3.2727273 | U38: =(U12-P12)/ABS(P12) -> 14.5 | W38: =(W12-R12)/ABS(R12) -> -2.7435897 | X38: =(X12-S12)/ABS(S12) -> 0.2254902 | Y38: =(Y12-T12)/ABS(T12) -> 0.38297872 | Z38: =(Z12-U12)/ABS(U12) -> -0.94444444 | AB38: =(AB12-W12)/ABS(W12) -> 0.93150685 | AC38: =(AC12-X12)/ABS(X12) -> 0.050632911 | AD38: =(AD12-Y12)/ABS(Y12) -> 0.72413793 | AE38: =(AE12-Z12)/ABS(Z12) -> -43.333333
A39: Income before income taxes | C39: =(C13-B13)/ABS(B13) -> 0.09940547 | D39: =(D13-C13)/ABS(C13) -> 0.056889466 | E39: =(E13-D13)/ABS(D13) -> -0.11481785 | F39: =(F13-E13)/ABS(E13) -> 0.1100578 | G39: =(G13-F13)/ABS(F13) -> -0.39866694 | H39: =(H13-G13)/ABS(G13) -> 1.3072393 | I39: =(I13-H13)/ABS(H13) -> -0.0015012761 | J39: =(J13-I13)/ABS(I13) -> -0.067658999 | K39: =(K13-J13)/ABS(J13) -> 0.080470892 | R39: =(R13-M13)/ABS(M13) -> 0.22798834 | S39: =(S13-N13)/ABS(N13) -> 0.030906593 | T39: =(T13-O13)/ABS(O13) -> 0.020782396 | U39: =(U13-P13)/ABS(P13) -> -0.25889968 | W39: =(W13-R13)/ABS(R13) -> -0.1320038 | X39: =(X13-S13)/ABS(S13) -> 0.099267155 | Y39: =(Y13-T13)/ABS(T13) -> -0.11556886 | Z39: =(Z13-U13)/ABS(U13) -> -0.093158661 | AB39: =(AB13-W13)/ABS(W13) -> -0.098468271 | AC39: =(AC13-X13)/ABS(X13) -> 0.16484848 | AD39: =(AD13-Y13)/ABS(Y13) -> -0.049424509 | AE39: =(AE13-Z13)/ABS(Z13) -> 0.38523274
A40: Income tax expense | C40: =(C14-B14)/ABS(B14) -> -0.074034335 | D40: =(D14-C14)/ABS(C14) -> -0.25144844 | E40: =(E14-D14)/ABS(D14) -> 2.7027864 | F40: =(F14-E14)/ABS(E14) -> -0.67725753 | G40: =(G14-F14)/ABS(F14) -> -0.5492228 | H40: =(H14-G14)/ABS(G14) -> 1.683908 | I40: =(I14-H14)/ABS(H14) -> -0.35224839 | J40: =(J14-I14)/ABS(I14) -> 0.86942149 | K40: =(K14-J14)/ABS(J14) -> -0.1158267 | R40: =(R14-M14)/ABS(M14) -> 0.17766497 | S40: =(S14-N14)/ABS(N14) -> -0.2 | T40: =(T14-O14)/ABS(O14) -> 0.46524064 | U40: =(U14-P14)/ABS(P14) -> -1.1884058 | W40: =(W14-R14)/ABS(R14) -> 0.55172414 | X40: =(X14-S14)/ABS(S14) -> 0.94512195 | Y40: =(Y14-T14)/ABS(T14) -> -0.1350365 | Z40: =(Z14-U14)/ABS(U14) -> 4.3076923 | AB40: =(AB14-W14)/ABS(W14) -> -0.45 | AC40: =(AC14-X14)/ABS(X14) -> 0.078369906 | AD40: =(AD14-Y14)/ABS(Y14) -> -0.021097046 | AE40: =(AE14-Z14)/ABS(Z14) -> 0.051162791
A41: NET INCOME | C41: =(C15-B15)/ABS(B15) -> 0.14879316 | D41: =(D15-C15)/ABS(C15) -> 0.12765957 | E41: =(E15-D15)/ABS(D15) -> -0.54410377 | F41: =(F15-E15)/ABS(E15) -> 1.0843249 | G41: =(G15-F15)/ABS(F15) -> -0.36981881 | H41: =(H15-G15)/ABS(G15) -> 1.2556124 | I41: =(I15-H15)/ABS(H15) -> 0.055701065 | J41: =(J15-I15)/ABS(I15) -> -0.16142904 | K41: =(K15-J15)/ABS(J15) -> 0.12426036 | R41: =(R15-M15)/ABS(M15) -> 0.2345191 | S41: =(S15-N15)/ABS(N15) -> 0.068745004 | T41: =(T15-O15)/ABS(O15) -> -0.03657695 | U41: =(U15-P15)/ABS(P15) -> -0.046388337 | W41: =(W15-R15)/ABS(R15) -> -0.21664888 | X41: =(X15-S15)/ABS(S15) -> -0.0044876589 | Y41: =(Y15-T15)/ABS(T15) -> -0.11174785 | Z41: =(Z15-U15)/ABS(U15) -> -0.28353023 | AB41: =(AB15-W15)/ABS(W15) -> -0.01226158 | AC41: =(AC15-X15)/ABS(X15) -> 0.18557476 | AD41: =(AD15-Y15)/ABS(Y15) -> -0.05483871 | AE41: =(AE15-Z15)/ABS(Z15) -> 0.45489816
A42: Earnings per common share:
A43: Basic (in dollars per share) | C43: =(C17-B17)/ABS(B17) -> 0.16315789 | D43: =(D17-C17)/ABS(C17) -> 0.15837104 | E43: =(E17-D17)/ABS(D17) -> -0.53515625 | F43: =(F17-E17)/ABS(E17) -> 1.1428571 | G43: =(G17-F17)/ABS(F17) -> -0.36078431 | H43: =(H17-G17)/ABS(G17) -> 1.2336281 | I43: =(I17-H17)/ABS(H17) -> 0.051822761 | J43: =(J17-I17)/ABS(I17) -> -0.14672865 | K43: =(K17-J17)/ABS(J17) -> 0.15069349 | R43: =(R17-M17)/ABS(M17) -> 0.21649485 | S43: =(S17-N17)/ABS(N17) -> 0.05 | T43: =(T17-O17)/ABS(O17) -> -0.043478261 | U43: =(U17-P17)/ABS(P17) -> -0.042141974 | W43: =(W17-R17)/ABS(R17) -> -0.20338983 | X43: =(X17-S17)/ABS(S17) -> 0.011904762 | Y43: =(Y17-T17)/ABS(T17) -> -0.090909091 | Z43: =(Z17-U17)/ABS(U17) -> -0.26697658 | AB43: =(AB17-W17)/ABS(W17) -> 0.010638298 | AC43: =(AC17-X17)/ABS(X17) -> 0.22352941 | AD43: =(AD17-Y17)/ABS(Y17) -> -0.0375
A44: Diluted (in dollars per share) | C44: =(C18-B18)/ABS(B18) -> 0.16756757 | D44: =(D18-C18)/ABS(C18) -> 0.16203704 | E44: =(E18-D18)/ABS(D18) -> -0.53386454 | F44: =(F18-E18)/ABS(E18) -> 1.1282051 | G44: =(G18-F18)/ABS(F18) -> -0.35742972 | H44: =(H18-G18)/ABS(G18) -> 1.2240431 | I44: =(I18-H18)/ABS(H18) -> 0.05478352 | J44: =(J18-I18)/ABS(I18) -> -0.13952727 | K44: =(K18-J18)/ABS(J18) -> 0.15490217 | R44: =(R18-M18)/ABS(M18) -> 0.22105263 | S44: =(S18-N18)/ABS(N18) -> 0.064102564 | T44: =(T18-O18)/ABS(O18) -> -0.033333333 | U44: =(U18-P18)/ABS(P18) -> -0.034490611 | W44: =(W18-R18)/ABS(R18) -> -0.19827586 | X44: =(X18-S18)/ABS(S18) -> 0.024096386 | Y44: =(Y18-T18)/ABS(T18) -> -0.091954023 | Z44: =(Z18-U18)/ABS(U18) -> -0.26571401 | AB44: =(AB18-W18)/ABS(W18) -> 0.010752688 | AC44: =(AC18-X18)/ABS(X18) -> 0.21176471 | AD44: =(AD18-Y18)/ABS(Y18) -> -0.025316456
A45: Weighted average common shares outstanding:
A46: Basic (in shares) | C46: =(C20-B20)/ABS(B20) -> -0.012349775 | D46: =(D20-C20)/ABS(C20) -> -0.026512633 | E46: =(E20-D20)/ABS(D20) -> -0.019592453 | F46: =(F20-E20)/ABS(E20) -> -0.027158517 | G46: =(G20-F20)/ABS(F20) -> -0.01323036 | H46: =(H20-G20)/ABS(G20) -> 0.0091095715 | I46: =(I20-H20)/ABS(H20) -> 0.0036872219 | J46: =(J20-I20)/ABS(I20) -> -0.017228275 | K46: =(K20-J20)/ABS(J20) -> -0.021912864 | R46: =(R20-M20)/ABS(M20) -> 0.012869766 | S46: =(S20-N20)/ABS(N20) -> 0.0059758423 | T46: =(T20-O20)/ABS(O20) -> 0.00063371356 | U46: =(U20-P20)/ABS(P20) -> -0.0044331856 | W46: =(W20-R20)/ABS(R20) -> -0.0093558379 | X46: =(X20-S20)/ABS(S20) -> -0.014787664 | Y46: =(Y20-T20)/ABS(T20) -> -0.02229259 | Z46: =(Z20-U20)/ABS(U20) -> -0.022582697 | AB46: =(AB20-W20)/ABS(W20) -> -0.024695297 | AC46: =(AC20-X20)/ABS(X20) -> -0.024502886 | AD46: =(AD20-Y20)/ABS(Y20) -> -0.01982122
A47: Diluted (in shares) | C47: =(C21-B21)/ABS(B21) -> -0.016079936 | D47: =(D21-C21)/ABS(C21) -> -0.029583792 | E47: =(E21-D21)/ABS(D21) -> -0.017844104 | F47: =(F21-E21)/ABS(E21) -> -0.024531372 | G47: =(G21-F21)/ABS(F21) -> -0.016559565 | H47: =(H21-G21)/ABS(G21) -> 0.011183715 | I47: =(I21-H21)/ABS(H21) -> 0.0008698894 | J47: =(J21-I21)/ABS(I21) -> -0.025453191 | K47: =(K21-J21)/ABS(J21) -> -0.025544655 | R47: =(R21-M21)/ABS(M21) -> 0.016506621 | S47: =(S21-N21)/ABS(N21) -> 0.0049083566 | T47: =(T21-O21)/ABS(O21) -> -0.0038344981 | U47: =(U21-P21)/ABS(P21) -> -0.012322744 | W47: =(W21-R21)/ABS(R21) -> -0.02086935 | X47: =(X21-S21)/ABS(S21) -> -0.027822431 | Y47: =(Y21-T21)/ABS(T21) -> -0.028496927 | Z47: =(Z21-U21)/ABS(U21) -> -0.024263323 | AB47: =(AB21-W21)/ABS(W21) -> -0.026800353 | AC47: =(AC21-X21)/ABS(X21) -> -0.025629611 | AD47: =(AD21-Y21)/ABS(Y21) -> -0.024475971

Sheet Statement of Cashflow
A1: Consolidated Statements of Cash Flows - USD ($) $ in Millions | B1: 12 Months Ended
B2: May 31, 2015 | C2: May 31, 2016 | D2: May 31, 2017 | E2: May 31, 2018 | F2: May 31, 2019 | G2: May 31, 2020 | H2: May 31, 2021 | I2: May 31, 2022 | J2: May 31, 2023 | K2: May 31, 2024 E | L2: May 31, 2024
A3: Cash provided (used) by operations:
A4: Net income | B4: 3273 | C4: 3760 | D4: 4240 | E4: 1933 | F4: 4029 | G4: 2539 | H4: 5727 | I4: 6046 | J4: 5070 | K4: ='Valuations & Forecasting'!K45 -> 5475.9 | L4: 5700
A5: Adjustments to reconcile net income to net cash provided (used) by operations:
A6: Depreciation | B6: 606 | C6: 649 | D6: 706 | E6: 747 | F6: 705 | G6: 721 | H6: 744 | I6: 717 | J6: 703 | L6: 796
A7: Deferred income taxes | B7: -113 | C7: -80 | D7: -273 | E7: 647 | F7: 34 | G7: -380 | H7: -385 | I7: -650 | J7: -117 | L7: -497
A8: Stock-based compensation | B8: 191 | C8: 236 | D8: 215 | E8: 218 | F8: 325 | G8: 429 | H8: 611 | I8: 638 | J8: 755 | L8: 804
A9: Amortization, impairment and other | B9: 43 | C9: 13 | D9: 10 | E9: 27 | F9: 15 | G9: 398 | H9: 53 | I9: 123 | J9: 156 | L9: 48
A10: Net foreign currency adjustments | B10: 424 | C10: 98 | D10: -117 | E10: -99 | F10: 233 | G10: 23 | H10: -138 | I10: -26 | J10: -213 | L10: -138
A11: Changes in certain working capital components and other assets and liabilities:
A13: (Increase) decrease in accounts receivable | B13: -216 | C13: 60 | D13: -426 | E13: 187 | F13: -270 | G13: 1239 | H13: -1606 | I13: -504 | J13: 489 | L13: -329
C14: =(C13-B13)/ABS(B13) -> 1.2777778 | D14: =(D13-C13)/ABS(C13) -> -8.1 | E14: =(E13-D13)/ABS(D13) -> 1.4389671 | F14: =(F13-E13)/ABS(E13) -> -2.4438503 | G14: =(G13-F13)/ABS(F13) -> 5.5888889 | H14: =(H13-G13)/ABS(G13) -> -2.2962066 | I14: =(I13-H13)/ABS(H13) -> 0.68617684 | J14: =(J13-I13)/ABS(I13) -> 1.9702381 | L14: =(L13-J13)/ABS(J13) -> -1.6728016
A15: (Increase) decrease in inventories | B15: -621 | C15: -590 | D15: -231 | E15: -255 | F15: -490 | G15: -1854 | H15: 507 | I15: -1676 | J15: -133 | L15: 908
C16: =(C15-B15)/ABS(B15) -> 0.049919485 | D16: =(D15-C15)/ABS(C15) -> 0.60847458 | E16: =(E15-D15)/ABS(D15) -> -0.1038961 | F16: =(F15-E15)/ABS(E15) -> -0.92156863 | G16: =(G15-F15)/ABS(F15) -> -2.7836735 | H16: =(H15-G15)/ABS(G15) -> 1.2734628 | I16: =(I15-H15)/ABS(H15) -> -4.3057199 | J16: =(J15-I15)/ABS(I15) -> 0.92064439 | L16: =(L15-J15)/ABS(J15) -> 7.8270677
A17: (Increase) decrease in prepaid expenses, operating lease right-of-use assets and other current and non-current assets | B17: -144 | C17: -161 | D17: -120 | E17: 35 | F17: -203 | G17: -654 | H17: -182 | I17: -845 | J17: -644 | L17: -260
C18: =(C17-B17)/ABS(B17) -> -0.11805556 | D18: =(D17-C17)/ABS(C17) -> 0.25465839 | E18: =(E17-D17)/ABS(D17) -> 1.2916667 | F18: =(F17-E17)/ABS(E17) -> -6.8 | G18: =(G17-F17)/ABS(F17) -> -2.2216749 | H18: =(H17-G17)/ABS(G17) -> 0.72171254 | I18: =(I17-H17)/ABS(H17) -> -3.6428571 | J18: =(J17-I17)/ABS(I17) -> 0.23786982 | L18: =(L17-J17)/ABS(J17) -> 0.59627329
A19: Increase (decrease) in accounts payable, accrued liabilities, operating lease liabilities and other current and non-current liabilities | B19: 1237 | C19: -889 | D19: -364 | E19: 1515 | F19: 1525 | G19: 24 | H19: 1326 | I19: 1365 | J19: -225 | L19: 397
C20: =(C19-B19)/ABS(B19) -> -1.7186742 | D20: =(D19-C19)/ABS(C19) -> 0.59055118 | E20: =(E19-D19)/ABS(D19) -> 5.1620879 | F20: =(F19-E19)/ABS(E19) -> 0.0066006601 | G20: =(G19-F19)/ABS(F19) -> -0.9842623 | H20: =(H19-G19)/ABS(G19) -> 54.25 | I20: =(I19-H19)/ABS(H19) -> 0.029411765 | J20: =(J19-I19)/ABS(I19) -> -1.1648352 | L20: =(L19-J19)/ABS(J19) -> 2.7644444
A21: Cash provided (used) by operations | B21: 4680 | C21: 3096 | D21: 3640 | E21: 4955 | F21: 5903 | G21: 2485 | H21: 6657 | I21: 5188 | J21: 5841 | L21: 7429
C22: =(C21-B21)/ABS(B21) -> -0.33846154 | D22: =(D21-C21)/ABS(C21) -> 0.17571059 | E22: =(E21-D21)/ABS(D21) -> 0.36126374 | F22: =(F21-E21)/ABS(E21) -> 0.1913219 | G22: =(G21-F21)/ABS(F21) -> -0.57902761 | H22: =(H21-G21)/ABS(G21) -> 1.6788732 | I22: =(I21-H21)/ABS(H21) -> -0.22066997 | J22: =(J21-I21)/ABS(I21) -> 0.12586739 | L22: =(L21-J21)/ABS(J21) -> 0.27187125
A23: Cash provided (used) by investing activities:
A24: Purchases of short-term investments | B24: -4936 | C24: -5367 | D24: -5928 | E24: -4783 | F24: -2937 | G24: -2426 | H24: -9961 | I24: -12913 | J24: -6059 | L24: -4767
A25: Maturities of short-term investments | B25: 3655 | C25: 2924 | D25: 3623 | E25: 3613 | F25: 1715 | G25: 74 | H25: 4236 | I25: 8199 | J25: 3356 | L25: 2269
A26: Sales of short-term investments | B26: 2216 | C26: 2386 | D26: 2423 | E26: 2496 | F26: 2072 | G26: 2379 | H26: 2449 | I26: 3967 | J26: 4184 | L26: 4219
A27: Investments in reverse repurchase agreements | B27: -150 | C27: 150 | D27: 0 | E27: 0 | F27: 0 | G27: 0 | H27: 0 | I27: 0 | J27: 0
A28: Additions to property, plant and equipment | B28: -963 | C28: -1143 | D28: -1105 | E28: -1028 | F28: -1119 | G28: -1086 | H28: -695 | I28: -758 | J28: -969 | L28: -812
A29: Disposals of property, plant and equipment | B29: 3 | C29: 10 | D29: 13 | E29: 0 | F29: 0 | G29: 0 | H29: 0 | I29: 0 | J29: 0
A30: Other investing activities | B30: 0 | C30: 6 | D30: -34 | E30: -22 | F30: 5 | G30: 31 | H30: 171 | I30: -19 | J30: 52 | L30: -15
A31: Cash provided (used) by investing activities | B31: -175 | C31: -1034 | D31: -1008 | E31: 276 | F31: -264 | G31: -1028 | H31: -3800 | I31: -1524 | J31: 564 | L31: 894
A32: Cash provided (used) by financing activities:
A33: Net proceeds from long-term debt issuance | B33: 0 | C33: 981 | D33: 1482 | E33: 0 | F33: 0 | G33: 6134 | H33: 0 | I33: 0 | J33: 0
A34: Long-term debt payments, including current portion | B34: -7 | C34: -106 | D34: -44 | E34: 0 | F34: 0 | G34: 0 | H34: 0 | I34: 0 | J34: 0
A35: Increase (decrease) in notes payable, net | B35: -63 | C35: -67 | D35: 327 | E35: 13 | F35: -325 | G35: 49 | H35: -52 | I35: 15 | J35: -4 | L35: 0
A36: Repayment of borrowings | B36: -19 | C36: -7 | D36: -17 | E36: 0 | F36: 0 | G36: 0 | H36: -197 | I36: 0 | J36: -500 | L36: 0
A37: Proceeds from exercise of stock options and other stock issuances | B37: 514 | C37: 507 | D37: 489 | E37: 733 | F37: 700 | G37: 885 | H37: 1172 | I37: 1151 | J37: 651 | L37: 667
A38: Repurchase of common stock | B38: 218 | C38: 281 | D38: 177 | E38: -4254 | F38: -4286 | G38: -3067 | H38: -608 | I38: -4014 | J38: -5480 | L38: -4250
A39: Dividends — common and preferred | B39: -2534 | C39: -3238 | D39: -3223 | E39: -1243 | F39: -1332 | G39: -1452 | H39: -1638 | I39: -1837 | J39: -2012 | L39: -2169
A40: Other financing activities | B40: -899 | C40: -1022 | D40: -1133 | E40: -84 | F40: -50 | G40: -58 | H40: -136 | I40: -151 | J40: -102 | L40: -136
A41: Cash provided (used) by financing activities | B41: -2790 | C41: -2671 | D41: -1942 | E41: -4835 | F41: -5293 | G41: 2491 | H41: -1459 | I41: -4836 | J41: -7447 | L41: -5888
A42: Effect of exchange rate changes on cash and equivalents | B42: -83 | C42: -105 | D42: -20 | E42: 45 | F42: -129 | G42: -66 | H42: 143 | I42: -143 | J42: -91 | L42: -16
A43: Net increase (decrease) in cash and equivalents | B43: 1632 | C43: -714 | D43: 670 | E43: 441 | F43: 217 | G43: 3882 | H43: 1541 | I43: -1315 | J43: -1133 | L43: 2419
A44: Cash and equivalents, beginning of year | B44: 2220 | C44: 3852 | D44: 3138 | E44: 3808 | F44: 4249 | G44: 4466 | H44: 8348 | I44: 9889 | J44: 8574 | L44: 7441
A45: CASH AND EQUIVALENTS, END OF YEAR | B45: 3852 | C45: 3138 | D45: 3808 | E45: 4249 | F45: 4466 | G45: 8348 | H45: 9889 | I45: 8574 | J45: 7441 | L45: 9860
A46: Cash paid during the year for:
A47: Interest, net of capitalized interest | B47: 53 | C47: 70 | D47: 98 | E47: 125 | F47: 153 | G47: 140 | H47: 293 | I47: 290 | J47: 347 | L47: 381
A48: Income taxes | B48: 1262 | C48: 748 | D48: 703 | E48: 529 | F48: 757 | G48: 1028 | H48: 1177 | I48: 1231 | J48: 1517 | L48: 1299
A49: Non-cash additions to property, plant and equipment | B49: 206 | C49: 252 | D49: 266 | E49: 294 | F49: 160 | G49: 121 | H49: 179 | I49: 160 | J49: 211 | L49: 160
A50: Dividends declared and not paid | B50: 240 | C50: 271 | D50: 300 | E50: 320 | F50: 347 | G50: 385 | H50: 438 | I50: 480 | J50: 524 | L50: 558
A52: Net income | B52: =B4 -> 3273 | C52: =C4 -> 3760 | D52: =D4 -> 4240 | E52: =E4 -> 1933 | F52: =F4 -> 4029 | G52: =G4 -> 2539 | H52: =H4 -> 5727 | I52: =I4 -> 6046 | ... L52: =L4 -> 5700
A53: Depreciation and amort | B53: =B6+B9 -> 649 | C53: =C6+C9 -> 662 | D53: =D6+D9 -> 716 | E53: =E6+E9 -> 774 | F53: =F6+F9 -> 720 | G53: =G6+G9 -> 1119 | H53: =H6+H9 -> 797 | I53: =I6+I9 -> 840 | J53: =J6+J9 -> 859 | K53: 880 | L53: =L6+L9 -> 844
A54: Stock based compensation | B54: =B8 -> 191 | C54: =C8 -> 236 | D54: =D8 -> 215 | E54: =E8 -> 218 | F54: =F8 -> 325 | G54: =G8 -> 429 | H54: =H8 -> 611 | I54: =I8 -> 638 | J54: =J8 -> 755 | K54: 840 | L54: =L8 -> 804
A55: Deferred taxes | B55: =B7 -> -113 | C55: =C7 -> -80 | D55: =D7 -> -273 | E55: =E7 -> 647 | F55: =F7 -> 34 | G55: =G7 -> -380 | H55: =H7 -> -385 | I55: =I7 -> -650 | J55: =J7 -> -117 | K55: 0 | L55: =L7 -> -497
A56: Other | B56: =B10 -> 424 | C56: =C10 -> 98 | D56: =D10 -> -117 | E56: =E10 -> -99 | F56: =F10 -> 233 | G56: =G10 -> 23 | H56: =H10 -> -138 | I56: =I10 -> -26 | ... L56: =L10 -> -138
A57: Working capital, net | B57: =B13+B15+B17+B19 -> 256 | C57: =C13+C15+C17+C19 -> -1580 | D57: =D13+D15+D17+D19 -> -1141 | E57: =E13+E15+E17+E19 -> 1482 | F57: =F13+F15+F17+F19 -> 562 | G57: =G13+G15+G17+G19 -> -1245 | H57: =H13+H15+H17+H19 -> 45 | I57: =I13+I15+I17+I19 -> -1660 | J57: =J13+J15+J17+J19 -> -513 | K57: 300 | L57: =L13+L15+L17+L19 -> 716
A58: Net cash flow from operations | B58: =B52+B53+B54+B55+B56+B57 -> 4680 | C58: =C52+C53+C54+C55+C56+C57 -> 3096 | D58: =D52+D53+D54+D55+D56+D57 -> 3640 | E58: =E52+E53+E54+E55+E56+E57 -> 4955 | F58: =F52+F53+F54+F55+F56+F57 -> 5903 | G58: =G52+G53+G54+G55+G56+G57 -> 2485 | H58: =H52+H53+H54+H55+H56+H57 -> 6657 | I58: =I52+I53+I54+I55+I56+I57 -> 5188 | ... L58: =L52+L53+L54+L55+L56+L57 -> 7429
A59: Capital spending | B59: =B28+B29 -> -960 | C59: =C28+C29 -> -1133 | D59: =D28+D29 -> -1092 | E59: =E28+E29 -> -1028 | F59: =F28+F29 -> -1119 | G59: =G28+G29 -> -1086 | H59: =H28+H29 -> -695 | I59: =I28+I29 -> -758 | J59: =J28+J29 -> -969 | K59: -1080 | L59: =L28+L29 -> -812
A60: Excess cash flow from operations | B60: =B58+B59 -> 3720 | C60: =C58+C59 -> 1963 | D60: =D58+D59 -> 2548 | E60: =E58+E59 -> 3927 | F60: =F58+F59 -> 4784 | G60: =G58+G59 -> 1399 | H60: =H58+H59 -> 5962 | I60: =I58+I59 -> 4430 | ... L60: =L58+L59 -> 6617
A61: Excess cash flow/share | B61: =B60/'Statement of Operations'!B21 -> 2.1026581 | C61: =C60/'Statement of Operations'!C21 -> 1.1276809 | D61: =D60/'Statement of Operations'!D21 -> 1.5083679 | E61: =E60/'Statement of Operations'!E21 -> 2.3669459 | F61: =F60/'Statement of Operations'!F21 -> 2.9560059 | G61: =G60/'Statement of Operations'!G21 -> 0.8789897 | H61: =H60/'Statement of Operations'!H21 -> 3.7044861 | I61: =I60/'Statement of Operations'!I21 -> 2.7501862 | J61: =J60/'Statement of Operations'!J21 -> 3.1035801 | K61: =K60/'Valuations & Forecasting'!K51 -> 4.1784464 | L61: =L60/'Statement of Operations'!K21 -> 4.3256848
A62: Acquisitions, net | B62: =B27 -> -150 | C62: =C27 -> 150 | D62: =D27 -> 0 | E62: =E27 -> 0 | F62: =F27 -> 0 | G62: =G27 -> 0 | H62: =H27 -> 0 | I62: =I27 -> 0 | ... L62: =L27 -> 0
A63: Dividends, net | B63: =B39 -> -2534 | C63: =C39 -> -3238 | D63: =D39 -> -3223 | E63: =E39 -> -1243 | F63: =F39 -> -1332 | G63: =G39 -> -1452 | H63: =H39 -> -1638 | I63: =I39 -> -1837 | J63: =J39 -> -2012 | K63: -2180 | L63: =L39 -> -2169
A64: Debt, net | B64: =B33+B34+B35+B36 -> -89 | C64: =C33+C34+C35+C36 -> 801 | D64: =D33+D34+D35+D36 -> 1748 | E64: =E33+E34+E35+E36 -> 13 | F64: =F33+F34+F35+F36 -> -325 | G64: =G33+G34+G35+G36 -> 6183 | H64: =H33+H34+H35+H36 -> -249 | I64: =I33+I34+I35+I36 -> 15 | ... L64: =L33+L34+L35+L36 -> 0
A65: Change in marketable securities | B65: =B24+B25+B26 -> 935 | C65: =C24+C25+C26 -> -57 | D65: =D24+D25+D26 -> 118 | E65: =E24+E25+E26 -> 1326 | F65: =F24+F25+F26 -> 850 | G65: =G24+G25+G26 -> 27 | H65: =H24+H25+H26 -> -3276 | I65: =I24+I25+I26 -> -747 | J65: =J24+J25+J26 -> 1481 | K65: 700 | L65: =L24+L25+L26 -> 1721
A66: Share repurchases, net | B66: =B37+B38 -> 732 | C66: =C37+C38 -> 788 | D66: =D37+D38 -> 666 | E66: =E37+E38 -> -3521 | F66: =F37+F38 -> -3586 | G66: =G37+G38 -> -2182 | H66: =H37+H38 -> 564 | I66: =I37+I38 -> -2863 | ... L66: =L37+L38 -> -3583
A67: Other | B67: =B42+B40+B30 -> -982 | C67: =C42+C40+C30 -> -1121 | D67: =D42+D40+D30 -> -1187 | E67: =E42+E40+E30 -> -61 | F67: =F42+F40+F30 -> -174 | G67: =G42+G40+G30 -> -93 | H67: =H42+H40+H30 -> 178 | I67: =I42+I40+I30 -> -313 | ... L67: =L42+L40+L30 -> -167
A68: Net change in cash | B68: =B60+B62+B63+B64+B65+B66+B67 -> 1632 | C68: =C60+C62+C63+C64+C65+C66+C67 -> -714 | D68: =D60+D62+D63+D64+D65+D66+D67 -> 670 | E68: =E60+E62+E63+E64+E65+E66+E67 -> 441 | F68: =F60+F62+F63+F64+F65+F66+F67 -> 217 | G68: =G60+G62+G63+G64+G65+G66+G67 -> 3882 | H68: =H60+H62+H63+H64+H65+H66+H67 -> 1541 | I68: =I60+I62+I63+I64+I65+I66+I67 -> -1315 | ... L68: =L60+L62+L63+L64+L65+L66+L67 -> 2419
